Workbook

Sheet Review Summary
A1: Revised cost review
A2: Municipal Building, The Moor, Falmouth | October 2024 Revision A compared with current review position | GBP, VAT excluded
A4: ORIGINAL PRINTED | C4: CURRENT REVIEW | E4: MOVEMENT | G4: PENDING OPTION (DIRECT)
A5: ='Working Calculation'!C21 -> 1971278 | C5: =ROUND('Working Calculation'!E21,0) -> 2039472 | E5: =C5-A5 -> 68194 | G5: ='Review Inputs'!G18 -> 18000
A9: Review position
A11: Item | B11: Original / source | C11: Earlier review | D11: Current review | E11: Movement | F11: Position | G11: Limit treatment | H11: Source
A12: Heating and ASHP | B12: ='Review Inputs'!C9 -> 432000 | C12: ='Review Inputs'!D9 -> 472000 | D12: ='Review Inputs'!E9 -> 458000 | E12: =D12-B12 -> 26000 | F12: Included | G12: Replaces source package within M&E | H12: REV-01
A13: Ventilation | B13: ='Review Inputs'!C10 -> 55000 | C13: - | D13: ='Review Inputs'!E10 -> 55000 | E13: =D13-B13 -> 0 | F13: Included | G13: Unchanged memorandum sum | H13: REV-01
A14: All other elemental works | B14: ='Cost Breakdown'!D22-'Cost Breakdown'!D21 -> 810975 | C14: - | D14: ='Cost Breakdown'!E22-'Cost Breakdown'!E21 -> 810975 | E14: =D14-B14 -> 0 | F14: Included | G14: Unchanged by default; editable | H14: REV-01
A15: Design-development risk | B15: ='Review Inputs'!C28 -> 0.1 | C15: - | D15: ='Review Inputs'!D28 -> 0.12 | E15: =D15-B15 -> 0.02 | F15: Included | G15: % of base cost | H15: REV-02
A16: Asbestos removal | B16: Excluded | C16: - | D16: ='Review Inputs'!D18 -> 18000 | E16: - | F16: ='Review Inputs'!E18 -> Pending | G16: Outside current limit unless Approved | H16: REV-03
A19: Decision view
A21: Current review cost limit | B21: =ROUND('Working Calculation'!E21,0) -> 2039472 | D21: Original full-precision recalculation | E21: ='Working Calculation'!D21 -> 1971277.9 | G21: Price date | H21: 4Q24; inflation to 1Q25
A22: Gross impact if all pending options approved | B22: ='Review Inputs'!H18 -> 22397.76 | D22: Current full-precision calculation | E22: ='Working Calculation'!E21 -> 2039471.6 | G22: VAT | H22: Excluded
A23: Indicative cost limit including pending options | B23: =ROUND('Working Calculation'!F21,0) -> 2061869 | D23: Reconciliation check | E23: =Reconciliation!C16 -> 0 | G23: Estimate status | H23: Guide of probable current cost
A26: Use and limitations
A28: • Edit yellow cells on Review Inputs and Cost Breakdown during the meeting; linked totals and reconciliation update automatically.
A29: • The current limit includes the £458,000 heating/ASHP package and 12% design-development risk. The £18,000 asbestos option is Pending and excluded.
A30: • Provisional sums are memorandum detail already included within elemental costs. The £3,000 M&E balance is held without assigning it to an unsupported category.
A31: • The estimate remains subject to all Revision A notes, qualifications and exclusions. Source values are traceable on Source References.

Sheet Cost Breakdown
A1: Elemental cost breakdown
A2: Original printed elemental analysis alongside the current review position. Current M&E is linked to package inputs.
A4: RTP scope of works
A6: Ref | B6: Element | C6: Original % | D6: Original amount | E6: Current amount | F6: Current % | G6: Movement | H6: Review position | I6: Source | J6: Review note
A7: EL-01 | B7: Grade 2 Listing | C7: 0 | D7: - | E7: - | F7: =IF(AND(ISNUMBER(E7),$E$22<>0),E7/$E$22,0) -> 0 | G7: =IF(AND(ISNUMBER(D7),ISNUMBER(E7)),E7-D7,"-") -> - | H7: Unpriced | I7: SRC-04 | J7: Source dash retained.
A8: EL-02 | B8: Pitched Roof | C8: 0.2929 | D8: 418900 | E8: 418900 | F8: =IF(AND(ISNUMBER(E8),$E$22<>0),E8/$E$22,0) -> 0.28766159 | G8: =IF(AND(ISNUMBER(D8),ISNUMBER(E8)),E8-D8,"-") -> 0 | H8: Included - unchanged | I8: SRC-04 | J8: Current defaults to source amount.
A9: EL-03 | B9: Central Lantern Feature | C9: 0.0067 | D9: 9600 | E9: 9600 | F9: =IF(AND(ISNUMBER(E9),$E$22<>0),E9/$E$22,0) -> 0.0065923879 | G9: =IF(AND(ISNUMBER(D9),ISNUMBER(E9)),E9-D9,"-") -> 0 | H9: Included - unchanged | I9: SRC-04 | J9: Current defaults to source amount.
A10: EL-04 | B10: Rear Roof (refer to Pitched Roof for costs) | C10: 0.0003 | D10: 400 | E10: 400 | F10: =IF(AND(ISNUMBER(E10),$E$22<>0),E10/$E$22,0) -> 0.00027468283 | G10: =IF(AND(ISNUMBER(D10),ISNUMBER(E10)),E10-D10,"-") -> 0 | H10: Included - unchanged | I10: SRC-04 | J10: Source cross-reference retained.
A11: EL-05 | B11: Valley and Parapet Gutters | C11: 0.0117 | D11: 16700 | E11: 16700 | F11: =IF(AND(ISNUMBER(E11),$E$22<>0),E11/$E$22,0) -> 0.011468008 | G11: =IF(AND(ISNUMBER(D11),ISNUMBER(E11)),E11-D11,"-") -> 0 | H11: Included - unchanged | I11: SRC-04 | J11: Current defaults to source amount.
A12: EL-06 | B12: Parapet Walls | C12: 0.0096 | D12: 13800 | E12: 13800 | F12: =IF(AND(ISNUMBER(E12),$E$22<>0),E12/$E$22,0) -> 0.0094765575 | G12: =IF(AND(ISNUMBER(D12),ISNUMBER(E12)),E12-D12,"-") -> 0 | H12: Included - unchanged | I12: SRC-04 | J12: Current defaults to source amount.
A13: EL-07 | B13: Rainwater Goods | C13: 0.0335 | D13: 47950 | E13: 47950 | F13: =IF(AND(ISNUMBER(E13),$E$22<>0),E13/$E$22,0) -> 0.032927604 | G13: =IF(AND(ISNUMBER(D13),ISNUMBER(E13)),E13-D13,"-") -> 0 | H13: Included - unchanged | I13: SRC-04 | J13: Current defaults to source amount.
A14: EL-08 | B14: Masonry | C14: 0.0774 | D14: 110725 | E14: 110725 | F14: =IF(AND(ISNUMBER(E14),$E$22<>0),E14/$E$22,0) -> 0.07603564 | G14: =IF(AND(ISNUMBER(D14),ISNUMBER(E14)),E14-D14,"-") -> 0 | H14: Included - unchanged | I14: SRC-04 | J14: Current defaults to source amount.
A15: EL-09 | B15: Rendered Masonry | C15: 0.005 | D15: 7200 | E15: 7200 | F15: =IF(AND(ISNUMBER(E15),$E$22<>0),E15/$E$22,0) -> 0.0049442909 | G15: =IF(AND(ISNUMBER(D15),ISNUMBER(E15)),E15-D15,"-") -> 0 | H15: Included - unchanged | I15: SRC-04 | J15: Current defaults to source amount.
A16: EL-10 | B16: Windows | C16: 0.0625 | D16: 89450 | E16: 89450 | F16: =IF(AND(ISNUMBER(E16),$E$22<>0),E16/$E$22,0) -> 0.061425947 | G16: =IF(AND(ISNUMBER(D16),ISNUMBER(E16)),E16-D16,"-") -> 0 | H16: Included - unchanged | I16: SRC-04 | J16: Current defaults to source amount.
A17: EL-11 | B17: Rooflights | C17: 0.0113 | D17: 16100 | E17: 16100 | F17: =IF(AND(ISNUMBER(E17),$E$22<>0),E17/$E$22,0) -> 0.011055984 | G17: =IF(AND(ISNUMBER(D17),ISNUMBER(E17)),E17-D17,"-") -> 0 | H17: Included - unchanged | I17: SRC-04 | J17: Spelling normalised; amount unchanged.
A18: EL-12 | B18: Lantern Light and Skylight | C18: 0.0328 | D18: 46950 | E18: 46950 | F18: =IF(AND(ISNUMBER(E18),$E$22<>0),E18/$E$22,0) -> 0.032240897 | G18: =IF(AND(ISNUMBER(D18),ISNUMBER(E18)),E18-D18,"-") -> 0 | H18: Included - unchanged | I18: SRC-04 | J18: Current defaults to source amount.
A19: EL-13 | B19: Doors | C19: 0.0105 | D19: 15000 | E19: 15000 | F19: =IF(AND(ISNUMBER(E19),$E$22<>0),E19/$E$22,0) -> 0.010300606 | G19: =IF(AND(ISNUMBER(D19),ISNUMBER(E19)),E19-D19,"-") -> 0 | H19: Included - unchanged | I19: SRC-04 | J19: Current defaults to source amount.
A20: EL-14 | B20: Walls | C20: 0.0127 | D20: 18200 | E20: 18200 | F20: =IF(AND(ISNUMBER(E20),$E$22<>0),E20/$E$22,0) -> 0.012498069 | G20: =IF(AND(ISNUMBER(D20),ISNUMBER(E20)),E20-D20,"-") -> 0 | H20: Included - unchanged | I20: SRC-04 | J20: Current defaults to source amount.
A21: EL-15 | B21: Mechanical and Electrical Services | C21: 0.433 | D21: 619250 | E21: ='Review Inputs'!E11+'Review Inputs'!E12 -> 645250 | F21: =IF(AND(ISNUMBER(E21),$E$22<>0),E21/$E$22,0) -> 0.44309774 | G21: =IF(AND(ISNUMBER(D21),ISNUMBER(E21)),E21-D21,"-") -> 26000 | H21: Included - revised | I21: SRC-03 / SRC-04 / REV-01 | J21: Source element plus net movement in listed M&E package inputs; residual balance held unchanged.
A22: TOTAL | B22: RTP Scope of Works - Total | C22: =SUM(C7:C21) -> 0.9999 | D22: 1430225 | E22: =SUM(E7:E21) -> 1456225 | F22: =SUM(F7:F21) -> 1 | G22: =E22-D22 -> 26000 | H22: Current elemental total | I22: SRC-04 | J22: Original amount is the printed total; current total excludes unapproved options.
B23: Check: sum of original lines less printed total | D23: =SUM(D7:D21)-D22 -> 0 | J23: Expected £0.

Sheet Review Inputs
A1: Review inputs
A2: Yellow cells are meeting inputs. Current defaults follow the review correspondence dated in the supplied benchmark.
A4: Included M&E package pricing
A6: Ref | B6: Package / memorandum item | C6: Source amount | D6: Earlier review | E6: Current input | F6: Movement | G6: Position | H6: Source | I6: Treatment / qualification
A7: PKG-01 | B7: Electrical power and lighting | C7: 85750 | E7: 85750 | F7: =E7-C7 -> 0 | G7: Included | H7: SRC-03 | I7: Memorandum provisional sum within M&E; unchanged in review.
A8: PKG-02 | B8: Water services | C8: 43500 | E8: 43500 | F8: =E8-C8 -> 0 | G8: Included | H8: SRC-03 | I8: Memorandum provisional sum within M&E; unchanged in review.
A9: PKG-03 | B9: Heating and air-source heat pump | C9: 432000 | D9: 472000 | E9: 458000 | F9: =E9-C9 -> 26000 | G9: Included | H9: SRC-03 / REV-01 | I9: £472,000 earlier review is superseded. Current package replaces £432,000 source allowance.
A10: PKG-04 | B10: Ventilation | C10: 55000 | E10: 55000 | F10: =E10-C10 -> 0 | G10: Included | H10: SRC-03 / REV-01 | I10: Memorandum provisional sum within M&E; correspondence says unchanged.
A11: PKG-SUB | B11: Listed M&E memorandum items subtotal | C11: =SUM(C7:C10) -> 616250 | E11: =SUM(E7:E10) -> 642250 | F11: =E11-C11 -> 26000 | G11: Included | H11: SRC-03 | I11: Subtotal only; these amounts are already included in the elemental M&E total.
A12: PKG-BAL | B12: M&E elemental balance not allocated by source | C12: =619250-C11 -> 3000 | E12: =C12 -> 3000 | F12: =E12-C12 -> 0 | G12: Included - held | H12: SRC-03 / SRC-04 | I12: Difference between the £619,250 element and listed M&E memorandum sums. No allocation is assumed.
A15: Options awaiting decision
A17: Ref | B17: Option | C17: Original treatment | D17: Current price | E17: Decision | F17: Included now | G17: Pending amount | H17: Gross limit impact | I17: Source / treatment
A18: OPT-01 | B18: Asbestos removal | C18: Excluded | D18: 18000 | E18: Pending | F18: =IF(E18="Approved",D18,0) -> 0 | G18: =IF(E18="Pending",D18,0) -> 18000 | H18: =IF(E18="Pending",D18*(1+$D$26)*(1+$D$28)*(1+$D$31),0) -> 22397.76 | I18: SRC-02 / REV-03: outside current limit until approved; price excludes subsequent additions and VAT.
A22: Allowances and additions
A24: Ref | B24: Allowance / addition | C24: Source basis | D24: Current input | E24: Working basis | F24: Source | G24: Qualification
A25: ALL-01 | B25: Main contractor preliminaries | C25: 182800 | D25: 182800 | E25: Fixed amount | F25: SRC-01 | G25: Held unchanged unless edited.
A26: ALL-02 | B26: Main contractor overheads & profit | C26: 0.1 | D26: 0.1 | E26: % of works plus preliminaries | F26: SRC-01 | G26: Original basis retained.
A27: ALL-03 | B27: Project consultants fees | C27: Excluded | D27: Excluded | E27: Excluded | F27: SRC-01 / SRC-02 | G27: No amount included.
A28: ALL-04 | B28: Design-development risk | C28: 0.1 | D28: 0.12 | E28: % of base cost estimate | F28: SRC-01 / REV-02 | G28: Current rate directed by review correspondence.
A29: ALL-05 | B29: Construction risks | C29: - | D29: - | E29: Source dash | F29: SRC-01 | G29: Unpriced source dash retained; no amount included.
A30: ALL-06 | B30: Employer change risks | C30: - | D30: - | E30: Source dash | F30: SRC-01 | G30: Unpriced source dash retained; no amount included.
A31: ALL-07 | B31: Inflation allowance 4Q24 to 1Q25 | C31: 0.01 | D31: 0.01 | E31: % of cost limit before inflation | F31: SRC-01 | G31: Original rate and basis retained.
A32: ALL-08 | B32: VAT | C32: Excluded | D32: Excluded | E32: Excluded | F32: SRC-01 / SRC-02 | G32: Cost limit is VAT excluded.

Sheet Working Calculation
A1: Working calculation
A2: Full-precision calculations are retained. GBP columns display whole pounds; the option scenario includes all currently pending options.
A4: Estimate summary chain
A6: Cost chain | B6: Basis | C6: Original printed | D6: Original recalculated | E6: Current review | F6: Current + pending options | G6: Movement vs recalculated | H6: Source / treatment
A7: Elemental building works | B7: Cost Breakdown | C7: 1430225 | D7: ='Cost Breakdown'!D22 -> 1430225 | E7: ='Cost Breakdown'!E22 -> 1456225 | F7: =E7 -> 1456225 | G7: =IF(AND(ISNUMBER(E7),ISNUMBER(D7)),E7-D7,"-") -> 26000 | H7: SRC-04
A8: Approved / pending options | B8: Decision-controlled | C8: - | D8: 0 | E8: ='Review Inputs'!F18 -> 0 | F8: ='Review Inputs'!F18+'Review Inputs'!G18 -> 18000 | G8: =IF(AND(ISNUMBER(E8),ISNUMBER(D8)),E8-D8,"-") -> 0 | H8: REV-03
A9: Building Works | B9: Elemental works + included options | C9: 1430225 | D9: =D7+D8 -> 1430225 | E9: =E7+E8 -> 1456225 | F9: =F7+F8 -> 1474225 | G9: =IF(AND(ISNUMBER(E9),ISNUMBER(D9)),E9-D9,"-") -> 26000 | H9: SRC-01
A10: Main Contractors Preliminaries | B10: Fixed amount | C10: 182800 | D10: ='Review Inputs'!C25 -> 182800 | E10: ='Review Inputs'!D25 -> 182800 | F10: ='Review Inputs'!D25 -> 182800 | G10: =IF(AND(ISNUMBER(E10),ISNUMBER(D10)),E10-D10,"-") -> 0 | H10: SRC-01
A11: Cost before overheads & profit | B11: Building works + preliminaries | D11: =D9+D10 -> 1613025 | E11: =E9+E10 -> 1639025 | F11: =F9+F10 -> 1657025 | G11: =IF(AND(ISNUMBER(E11),ISNUMBER(D11)),E11-D11,"-") -> 26000 | H11: Calculated
A12: Main Contractors Overheads & Profit | B12: % of works + preliminaries | C12: 161303 | D12: =D11*'Review Inputs'!C26 -> 161302.5 | E12: =E11*'Review Inputs'!D26 -> 163902.5 | F12: =F11*'Review Inputs'!D26 -> 165702.5 | G12: =IF(AND(ISNUMBER(E12),ISNUMBER(D12)),E12-D12,"-") -> 2600 | H12: SRC-01
A13: Building Works Estimate | B13: Cost before OHP + OHP | C13: 1774328 | D13: =D11+D12 -> 1774327.5 | E13: =E11+E12 -> 1802927.5 | F13: =F11+F12 -> 1822727.5 | G13: =IF(AND(ISNUMBER(E13),ISNUMBER(D13)),E13-D13,"-") -> 28600 | H13: SRC-01
A14: Project Consultants Fees | B14: Excluded | C14: Excluded | D14: Excluded | E14: Excluded | F14: Excluded | G14: =IF(AND(ISNUMBER(E14),ISNUMBER(D14)),E14-D14,"-") -> - | H14: SRC-01 / SRC-02
A15: Base Cost Estimate | B15: Building works estimate | C15: 1774328 | D15: =D13 -> 1774327.5 | E15: =E13 -> 1802927.5 | F15: =F13 -> 1822727.5 | G15: =IF(AND(ISNUMBER(E15),ISNUMBER(D15)),E15-D15,"-") -> 28600 | H15: SRC-01
A16: Design Development Risks | B16: % of base cost | C16: 177433 | D16: =D15*'Review Inputs'!C28 -> 177432.75 | E16: =E15*'Review Inputs'!D28 -> 216351.3 | F16: =F15*'Review Inputs'!D28 -> 218727.3 | G16: =IF(AND(ISNUMBER(E16),ISNUMBER(D16)),E16-D16,"-") -> 38918.55 | H16: SRC-01 / REV-02
A17: Construction Risks | B17: Source dash retained | C17: - | D17: - | E17: - | F17: - | G17: =IF(AND(ISNUMBER(E17),ISNUMBER(D17)),E17-D17,"-") -> - | H17: SRC-01
A18: Employer Change Risks | B18: Source dash retained | C18: - | D18: - | E18: - | F18: - | G18: =IF(AND(ISNUMBER(E18),ISNUMBER(D18)),E18-D18,"-") -> - | H18: SRC-01
A19: COST LIMIT (Inflation Excluded) | B19: Base + design risk | C19: 1951760 | D19: =D15+D16 -> 1951760.2 | E19: =E15+E16 -> 2019278.8 | F19: =F15+F16 -> 2041454.8 | G19: =IF(AND(ISNUMBER(E19),ISNUMBER(D19)),E19-D19,"-") -> 67518.55 | H19: SRC-01
A20: Inflation Allowance - 4Q24 to 1Q25 | B20: % of pre-inflation limit | C20: 19518 | D20: =D19*'Review Inputs'!C31 -> 19517.603 | E20: =E19*'Review Inputs'!D31 -> 20192.788 | F20: =F19*'Review Inputs'!D31 -> 20414.548 | G20: =IF(AND(ISNUMBER(E20),ISNUMBER(D20)),E20-D20,"-") -> 675.1855 | H20: SRC-01
A21: COST LIMIT (VAT Excluded) | B21: Pre-inflation limit + inflation | C21: 1971278 | D21: =D19+D20 -> 1971277.9 | E21: =E19+E20 -> 2039471.6 | F21: =F19+F20 -> 2061869.3 | G21: =IF(AND(ISNUMBER(E21),ISNUMBER(D21)),E21-D21,"-") -> 68193.735 | H21: SRC-01 / current review
A23: Precision note | B23: The original printed £1,971,278 reconciles to a full-precision recalculation of | D23: =D21 -> 1971277.9 | E23: Printed less recalculated | F23: =C21-D21 -> 0.1475 | H23: The source summary rounds displayed components; calculations retain underlying precision.

Sheet Reconciliation
A1: Cost-limit reconciliation
A2: Bridge from the original printed VAT-excluded cost limit to the current review position.
A4: Movement bridge
A6: Step | B6: Movement basis | C6: Movement | D6: Running balance | E6: Source / formula | F6: Comment
A7: Original printed cost limit | B7: October 2024 Revision A | C7: ='Working Calculation'!C21 -> 1971278 | D7: =C7 -> 1971278 | E7: SRC-01 | F7: Printed source fact.
A8: Precision adjustment | B8: Move to full-precision original recalculation | C8: ='Working Calculation'!D21-'Working Calculation'!C21 -> -0.1475 | D8: =D7+C8 -> 1971277.9 | E8: Working Calculation | F8: Keeps printed-to-recalculated rounding visible.
A9: Elemental package movement | B9: Current elemental total less original | C9: ='Cost Breakdown'!E22-'Cost Breakdown'!D22 -> 26000 | D9: =D8+C9 -> 1997277.9 | E9: Cost Breakdown | F9: Includes heating/ASHP movement and any meeting edits to elemental/package inputs.
A10: Approved options | B10: Decision-controlled direct works | C10: ='Review Inputs'!F18 -> 0 | D10: =D9+C10 -> 1997277.9 | E10: REV-03 | F10: Pending options remain £0 here.
A11: Preliminaries movement | B11: Current amount less original | C11: ='Review Inputs'!D25-'Review Inputs'!C25 -> 0 | D11: =D10+C11 -> 1997277.9 | E11: Review Inputs | F11: Fixed amount by default.
A12: OHP movement | B12: Current OHP less recalculated original OHP | C12: ='Working Calculation'!E12-'Working Calculation'!D12 -> 2600 | D12: =D11+C12 -> 1999877.9 | E12: Working Calculation | F12: Captures rate, base and option effects.
A13: Design risk movement | B13: Current design risk less recalculated original risk | C13: ='Working Calculation'!E16-'Working Calculation'!D16 -> 38918.55 | D13: =D12+C13 -> 2038796.4 | E13: REV-02 | F13: Current default increases rate from 10% to 12%.
A14: Inflation movement | B14: Current inflation less recalculated original inflation | C14: ='Working Calculation'!E20-'Working Calculation'!D20 -> 675.1855 | D14: =D13+C14 -> 2039471.6 | E14: Working Calculation | F14: Original 1% basis retained by default.
A15: Reconciled current position | B15: Full precision | D15: =D14 -> 2039471.6 | E15: ='Working Calculation'!E21 -> 2039471.6 | F15: Running balance should equal current working calculation.
A16: Reconciliation check | B16: Running balance less current working calculation | C16: =D15-'Working Calculation'!E21 -> 0 | F16: Expected £0.000.
A17: Current review displayed | B17: Rounded to whole pounds | D17: =ROUND(D15,0) -> 2039472 | F17: Workbook presentation basis.
A18: Movement vs original printed | B18: Displayed current less printed source total | C18: =D17-'Working Calculation'!C21 -> 68194 | F18: Headline movement.

Sheet Source References
A1: Source references
A2: Trace register for source amounts, assumptions, exclusions, review directions and workbook treatment.
A4: ID | B4: Source file | C4: Locator | D4: Category | E4: Source fact / qualification | F4: Workbook treatment
A5: SRC-01 | B5: Falmouth_OCE_October2024_RevA.pdf | C5: PDF p2, Summary | D5: Printed summary | E5: Building works £1,430,225; preliminaries £182,800; OHP 10% / £161,303; Building Works Estimate and Base Cost Estimate £1,774,328; design risk 10% / £177,433; inflation-excluded limit £1,951,760; inflation 1% / £19,518; VAT-excluded limit £1,971,278. Consultants fees excluded; construction and employer change risks shown as dashes. | F5: Printed values retained; separate full-precision recalculation shown.
A6: SRC-02 | B6: Falmouth_OCE_October2024_RevA.pdf | C6: PDF p3, Notes / exclusions | D6: Basis and exclusions | E6: Estimate is a guide of probable current cost and should be studied with the Quantity Surveyor. VAT and professional fees are excluded. Asbestos removal is excluded in item r). | F6: Qualifications retained; asbestos shown as a separate option.
A7: SRC-03 | B7: Falmouth_OCE_October2024_RevA.pdf | C7: PDF p4, Basis of Estimate | D7: M&E source amounts | E7: Indicative ZLC Energy heating/ASHP pricing £432,000 excluding VAT. Memorandum provisional sums: electrical £85,750; water £43,500; heating £432,000; ventilation £55,000. These sums are included within elemental costs. | F7: Package movements adjust the £619,250 M&E element by difference; no unsupported allocation is made.
A8: SRC-04 | B8: Falmouth_OCE_October2024_RevA.pdf | C8: PDF p5, Elemental Analysis | D8: Elemental source | E8: Fifteen printed elemental lines total £1,430,225; Mechanical and Electrical Services is £619,250 (43.30%). | F8: All printed amounts and percentages are retained on Cost Breakdown.
A9: REV-01 | B9: review_correspondence.md | C9: Paragraph 2 | D9: Current package review | E9: Earlier heating/ASHP review price £472,000 superseded by current £458,000. Ventilation and all other works unchanged. | F9: Current heating input £458,000; earlier review shown for context only.
A10: REV-02 | B10: review_correspondence.md | C10: Paragraph 3 | D10: Current risk review | E10: Use 12% design-development risk. Other allowance rates and bases remain as original. | F10: Current design risk input 12%; other defaults retained.
A11: REV-03 | B11: review_correspondence.md | C11: Paragraphs 4-5 | D11: Option / price basis | E11: Asbestos-removal option £18,000 awaits decision and is not approved for current limit. Package/option prices are at original price date and exclude VAT and subsequent fee or allowance additions. | F11: Pending by default; approval control adds price before OHP, risk and inflation.
A12: BRF-01 | B12: review_brief.md | C12: All paragraphs | D12: Workpaper convention | E12: Preserve source facts, dashes, exclusions and memorandum treatment; retain precision and show rounding; keep pending options outside current limit; maintain estimate limitations. | F12: Applied across workbook.
A13: BAS-01 | B13: Falmouth_OCE_October2024_RevA.pdf | C13: PDF p3 | D13: Design information | E13: Based purely on pre-planning drawings from RTP Chartered Building Surveyors; no input from another designer for this project type. | F13: Retained as qualification.
A14: BAS-02 | B14: Falmouth_OCE_October2024_RevA.pdf | C14: PDF p3 | D14: Procurement / phasing | E14: Works assumed in a single phase by a local medium-sized bona-fide contractor proficient in this project type. | F14: Retained as qualification.
A15: BAS-03 | B15: Falmouth_OCE_October2024_RevA.pdf | C15: PDF p3 | D15: Programme | E15: Contract duration assumed not to exceed 45 weeks. | F15: Retained as qualification.
... A51: QTE-01 | B51: Falmouth_OCE_October2024_RevA.pdf | C51: PDF p4, Quotations received | D51: Market evidence | E51: References quotations from SSQ Riverstone, Alutec, RM Developments, Storm, Charlestown Joinery and Roofmaker (dates stated in source). | F51: No independent re-pricing performed.
