Workbook

Sheet Valuation Comparison
A1: Amazon Valuation - September 2018
A2: Comparison: Base Case vs. Review Scenario
A4: KEY ASSUMPTIONS
A5: Assumption | B5: Base Case | C5: Review Scenario | D5: Difference
A6: Revenue Growth (Years 1-5) | B6: ='Input sheet'!B23 | C6: ='Input sheet'!B23 | D6: =C6-B6
A7: Terminal Revenue Growth | B7: ='Valuation output'!M2 | C7: ='Valuation output'!AA2 | D7: =C7-B7
A8: Terminal Operating Margin | B8: ='Valuation output'!M4 | C8: ='Valuation output'!AA4 | D8: =C8-B8
A9: Cost of Capital (Initial) | B9: ='Input sheet'!B29 | C9: ='Input sheet'!B29 | D9: =C9-B9
A10: Cost of Capital (Terminal) | B10: ='Valuation output'!M12 | C10: ='Valuation output'!AA12 | D10: =C10-B10
A12: VALUATION RESULTS
A13: Metric | B13: Base Case | C13: Review Scenario | D13: Difference | E13: % Difference
A14: Value of Operating Assets | B14: ='Valuation output'!B24 | C14: ='Valuation output'!P24 | D14: =C14-B14 | E14: =D14/B14
A15: Value of Equity | B15: ='Valuation output'!B29 | C15: ='Valuation output'!P29 | D15: =C15-B15 | E15: =D15/B15
A16: Value per Share | B16: ='Valuation output'!B33 | C16: ='Valuation output'!P33 | D16: =C16-B16 | E16: =D16/B16
A17: Number of Shares | B17: ='Valuation output'!B32 | C17: ='Valuation output'!P32 | D17: =C17-B17
A18: Market Price | B18: ='Valuation output'!B34 | C18: ='Valuation output'!P34 | D18: =C18-B18
A20: EXPLANATION
A21: The review scenario reduces the terminal operating margin target by 2 percentage points
A22: compared to the base case. The linear convergence from the base year margin to the
A23: terminal margin follows the same transition convention as the original model over
A24: the convergence period specified in the input sheet. All other assumptions (growth
A25: rates, cost of capital, reinvestment assumptions) remain identical between the two cases.
A27: The equity value difference reflects the impact of lower profitability on terminal value,
A28: flowing through to reduced cash flows in all forecast periods as margins converge to
A29: the lower target.

Sheet CB_DATA_
A1: Crystal Ball Data
A3: Workbook Variables | B3: Last Var Column | C3: 0
A4: Name:
A5: Value:
A7: Worksheet Data | B7: Last Data Column Used
B8: 3
A10: Sheet Ref
A11: =CB_DATA_!#REF! | B11: ='Input sheet'!#REF! | C11: ='Valuation output'!#REF!
A13: Sheet Guid
A14: 271d6a2b-7a93-4e27-808c-aa1aada6a76d | B14: eb12ad88-c3be-4256-b53f-793e1373a468 | C14: faa3ee01-9bfb-4333-b742-7cca748c6e20
A16: Deleted sheet count
A19: Last row used
A20: 28 | B20: 31 | C20: 31

Sheet Input sheet
A1: Date of valuation | B1: 41882 | C1: Important: Before you run this spreadsheet, go into preferences in Excel and check under Calculation options
A2: Company name | B2: Amazon | C2: There should be a check against the iteration box. If there is not, you will get circular reasoning errors.
A3: Numbers from your base year below ( in consistent units)
B4: This year | C4: Last year
A5: Country of incorporation | B5: United States
A6: Industry (US) | B6: Retail (General)
A7: Industry (Global) | B7: Retail (General) | C7: Last 10K | D7: Years since last 10K
A8: Revenues | B8: 208125 | C8: 177866 | D8: 0.5
A9: Operating income or EBIT | B9: 7385 | C9: 4106 | D9: 0.5
A10: Interest expense | B10: 1239 | C10: 848
A11: Book value of equity | B11: 34995 | C11: 27709
A12: Book value of debt | B12: 27050 | C12: 24473
A13: Do you have R&D expenses to capitalize? | B13: Yes | C13: If you want to capitalize R&D, you have to input the numbers into the R&D worksheet.
A14: Do you have operating lease commitments? | B14: Yes | C14: If you have operating leases, please enter your lease commitments in the lease worksheet below and I will convert to debt
A15: Cash and Marketable Securities | B15: 27050 | C15: 30986
A16: Cross holdings and other non-operating assets | B16: 0 | C16: 0
A17: Minority interests | B17: 0 | C17: 0
A18: Number of shares outstanding = | B18: 497
A19: Current stock price = | B19: 1970.19 | E19: Computed numbers: Here is what your company's numbers look like, relative to industry.
A20: Effective tax rate = | B20: =769/3806 | E20: If you are not working in US dollars, you should add the inflation differential to the industry averages.
A21: Marginal tax rate = | B21: 0.24 | I21: Company | J21: Industry (US data) | K21: Industry (Global data)
A22: The value drivers below: | E22: Revenue growth in the most recent year = | I22: =IF(C8>0,(B8/C8)^(1/D8)-1, "NA") | J22: =VLOOKUP(B6,'Industry Averages(US)'!A2:S95,3) | K22: =VLOOKUP(B7,'Global industry averages'!A2:N95,3)
A23: Compounded annual revenue growth rate over next 5 years = | B23: 0.16 | C23: Growth Lever | E23: Pre-tax operating margin in the most recent year = | I23: ='Valuation output'!B4 | J23: =VLOOKUP(B6,'Industry Averages(US)'!A2:S95,4) | K23: =VLOOKUP(B7,'Global industry averages'!A2:N95,4)
A24: Target pre-tax operating margin (EBIT as % of sales in year 10) = | B24: 0.125 | C24: Profitability Lever | E24: Sales to capital ratio in most recent year = | I24: =B8/(B11+B12-B15) | J24: =VLOOKUP(B6,'Industry Averages(US)'!A2:S95,14) | K24: =VLOOKUP(B7,'Global industry averages'!A2:N95,14)
A25: Year of convergence | B25: 5 | C25: Speed of convergence level | E25: Return on invested capital in most recent year= | I25: ='Valuation output'!B7/'Valuation output'!B39 | J25: =VLOOKUP(B6,'Industry Averages(US)'!A2:S95,5) | K25: =VLOOKUP(B7,'Global industry averages'!A2:N95,5)
A26: Sales to capital ratio (for computing reinvestment) = | B26: =I24 | C26: Efficency of Growth Lever | E26: Standard deviation in stock prices = | J26: =VLOOKUP(B6,'Industry Averages(US)'!A2:S95,10) | K26: =VLOOKUP(B6,'Global industry averages'!A2:Z95,10)
A27: Market numbers | E27: Cost of capital = | J27: =VLOOKUP(B6,'Industry Averages(US)'!A2:S95,13) | K27: =VLOOKUP(B6,'Global industry averages'!A2:Z95,13)
A28: Riskfree rate | B28: 0.03
A29: Initial cost of capital = | B29: 0.0797 | E29: Valuation Output Feedback (for you to use to fine tune your inputs, if you want)
A30: Other inputs | E30: Revenues in year 10, based on your revenue growth = | J30: ='Valuation output'!M3
A31: Do you have employee options outstanding? | B31: No | E31: Pre-tax Operating Income in year 10, based on your operating margin = | J31: ='Valuation output'!M5
A32: Number of options outstanding = | B32: 21.65 | E32: Return on invested capital in year 10, based on your sales/capital ratio = | J32: ='Valuation output'!L40
A33: Average strike price = | B33: 61.13 | E33: Check the Diagnostics worksheet for more details.
A34: Average maturity = | B34: 5.97
A35: Standard deviation on stock price = | B35: 0.3
A37: Default assumptions.
A38: In stable growth, I will assume that your firm will have a cost of capital similar to that of typical mature companies (riskfree rate + 4.5%)
A39: Do you want to override this assumption = | B39: Yes | C39: Mature companies generally see their risk levels approach the average
A40: If yes, enter the cost of capital after year 10 = | B40: 0.075 | C40: Though some sectors, even in stable growth, may have higher risk.
A41: I will assume that your firm will earn a return on capital equal to its cost of capital after year 10. I am assuming that whatever competitive advantages you have today will fade over time.
A42: Do you want to override this assumption = | B42: Yes | C42: Mature companies find it difficult to generate returns that exceed the cost of capital
A43: If yes, enter the return on capital you expect after year 10 | B43: 0.1 | C43: But there are significant exceptions among companies with long-lasting competitive advantages.
A44: I will assume that your firm has no chance of failure over the foreseeable future.
A45: Do you want to override this assumption = | B45: No | C45: Many young, growth companies fail, especially if they have trouble raising cash. Many distressed companies fail, because they have trouble making debt payments.
A46: If yes, enter the probability of failure = | B46: 0.2 | C46: Tough to estimate but a key input.
A47: What do you want to tie your proceeds in failure to? | B47: V | C47: B: Book value of capital, V= Estimated fair value for the company
A48: Enter the distress proceeds as percentage of book or fair value | B48: 0.5 | C48: This can be zero, if the assets will be worth nothing if the firm fails.
A49: I will assume that your effective tax rate will adjust to your marginal tax rate by your terminal year. If you override this assumption, I will leave the tax rate at your effective tax rate.
A50: Do you want to override this assumption = | B50: No
A51: I will assume that you have no losses carried forward from prior years ( NOL) coming into the valuation. If you have a money losing company, you may want to override tis.
A52: Do you want to override this assumption = | B52: No | C52: Check the financial statements.
A53: If yes, enter the NOL that you are carrying over into year 1 | B53: 250 | C53: An NOL will shield your income from taxes, even after you start making money.
A54: I will assume that the growth rate in perpetuity will be equal to the risk free rate. This allows for both valuation consistency and prevents "impossible" growth rates.
A55: Do you want to override this assumption = | B55: No
A56: If yes, enter the growth rate in perpetuity | B56: 0.01 | C56: This can be negative, if you feel the company will decline (and disappear) after growth is done. If you let it exceed the risk free rate, you are on your own in uncharted territory.
A57: I have assumed that none of the cash is trapped (in foreign countries) and that there is no additional tax liability coming due and that cash is a neutral asset.
A58: Do you want to override this assumption | B58: No
A59: If yes, enter trapped cash (if taxes) or entire balance (if mistrust) | B59: 140000 | C59: Cash that is trapped in foreign markets (and subject to additoinal tax) or cash that is being discounted by the market (because of management mistrust)
A60: & Average tax rate of the foreign markets where the cash is trapped | B60: 0.15 | C60: Additional tax rate due on trapped cash or discount being applied to cash balance because of mistrust.

Sheet Valuation output
B1: Base year | C1: 1 | D1: 2 | E1: 3 | F1: 4 | G1: 5 | H1: 6 | I1: 7 | J1: 8 | K1: 9 | L1: 10 | M1: Terminal year | O1: REVIEW SCENARIO | P1: Base year | Q1: 1 | R1: 2 | S1: 3 | T1: 4 | U1: 5 | V1: 6 | W1: 7 | X1: 8 | Y1: 9 | Z1: 10 | AA1: Terminal year
A2: Revenue growth rate | C2: ='Input sheet'!B23 | D2: =C2 | E2: =D2 | F2: =E2 | G2: =F2 | H2: =G2-((G2-$M$2)/5) | I2: =G2-((G2-$M$2)/5)*2 | J2: =G2-((G2-$M$2)/5)*3 | K2: =G2-((G2-$M$2)/5)*4 | L2: =G2-((G2-$M$2)/5)*5 | M2: =IF('Input sheet'!B55="Yes",'Input sheet'!B56,'Input sheet'!B28) | O2: Revenue growth rate | Q2: =C2 | R2: =D2 | S2: =E2 | T2: =F2 | U2: =G2 | V2: =H2 | W2: =I2 | X2: =J2 | ... AA2: =M2
A3: Revenues | B3: ='Input sheet'!B8 | C3: =B3*(1+C2) | D3: =C3*(1+D2) | E3: =D3*(1+E2) | F3: =E3*(1+F2) | G3: =F3*(1+G2) | H3: =G3*(1+H2) | I3: =H3*(1+I2) | J3: =I3*(1+J2) | ... M3: =L3*(1+M2) | O3: Revenues | P3: =B3 | Q3: =P3*(1+Q2) | R3: =Q3*(1+R2) | S3: =R3*(1+S2) | T3: =S3*(1+T2) | U3: =T3*(1+U2) | V3: =U3*(1+V2) | W3: =V3*(1+W2) | X3: =W3*(1+X2) | ... AA3: =Z3*(1+AA2)
A4: EBIT (Operating) margin | B4: =B5/B3 | C4: =IF(C1>'Input sheet'!$B$25,'Input sheet'!$B$24,'Input sheet'!$B$24-(('Input sheet'!$B$24-$B$4)/'Input sheet'!$B$25)*('Input sheet'!$B$25-C1)) | D4: =IF(D1>'Input sheet'!$B$25,'Input sheet'!$B$24,'Input sheet'!$B$24-(('Input sheet'!$B$24-$B$4)/'Input sheet'!$B$25)*('Input sheet'!$B$25-D1)) | E4: =IF(E1>'Input sheet'!$B$25,'Input sheet'!$B$24,'Input sheet'!$B$24-(('Input sheet'!$B$24-$B$4)/'Input sheet'!$B$25)*('Input sheet'!$B$25-E1)) | F4: =IF(F1>'Input sheet'!$B$25,'Input sheet'!$B$24,'Input sheet'!$B$24-(('Input sheet'!$B$24-$B$4)/'Input sheet'!$B$25)*('Input sheet'!$B$25-F1)) | G4: =IF(G1>'Input sheet'!$B$25,'Input sheet'!$B$24,'Input sheet'!$B$24-(('Input sheet'!$B$24-$B$4)/'Input sheet'!$B$25)*('Input sheet'!$B$25-G1)) | H4: =IF(H1>'Input sheet'!$B$25,'Input sheet'!$B$24,'Input sheet'!$B$24-(('Input sheet'!$B$24-$B$4)/'Input sheet'!$B$25)*('Input sheet'!$B$25-H1)) | I4: =IF(I1>'Input sheet'!$B$25,'Input sheet'!$B$24,'Input sheet'!$B$24-(('Input sheet'!$B$24-$B$4)/'Input sheet'!$B$25)*('Input sheet'!$B$25-I1)) | J4: =IF(J1>'Input sheet'!$B$25,'Input sheet'!$B$24,'Input sheet'!$B$24-(('Input sheet'!$B$24-$B$4)/'Input sheet'!$B$25)*('Input sheet'!$B$25-J1)) | ... L4: =IF(L1>'Input sheet'!$B$25,'Input sheet'!$B$24,'Input sheet'!$B$24-(('Input sheet'!$B$24-$B$4)/'Input sheet'!$B$25)*('Input sheet'!$B$25-L1)) | M4: =L4 | O4: EBIT (Operating) margin | P4: =B4 | Q4: =IF(Q1>'Input sheet'!$B$25,'Input sheet'!$B$24-0.02,('Input sheet'!$B$24-0.02)-(('Input sheet'!$B$24-0.02-$P$4)/'Input sheet'!$B$25)*('Input sheet'!$B$25-Q1)) | R4: =IF(R1>'Input sheet'!$B$25,'Input sheet'!$B$24-0.02,('Input sheet'!$B$24-0.02)-(('Input sheet'!$B$24-0.02-$P$4)/'Input sheet'!$B$25)*('Input sheet'!$B$25-R1)) | S4: =IF(S1>'Input sheet'!$B$25,'Input sheet'!$B$24-0.02,('Input sheet'!$B$24-0.02)-(('Input sheet'!$B$24-0.02-$P$4)/'Input sheet'!$B$25)*('Input sheet'!$B$25-S1)) | T4: =IF(T1>'Input sheet'!$B$25,'Input sheet'!$B$24-0.02,('Input sheet'!$B$24-0.02)-(('Input sheet'!$B$24-0.02-$P$4)/'Input sheet'!$B$25)*('Input sheet'!$B$25-T1)) | U4: =IF(U1>'Input sheet'!$B$25,'Input sheet'!$B$24-0.02,('Input sheet'!$B$24-0.02)-(('Input sheet'!$B$24-0.02-$P$4)/'Input sheet'!$B$25)*('Input sheet'!$B$25-U1)) | V4: =IF(V1>'Input sheet'!$B$25,'Input sheet'!$B$24-0.02,('Input sheet'!$B$24-0.02)-(('Input sheet'!$B$24-0.02-$P$4)/'Input sheet'!$B$25)*('Input sheet'!$B$25-V1)) | W4: =IF(W1>'Input sheet'!$B$25,'Input sheet'!$B$24-0.02,('Input sheet'!$B$24-0.02)-(('Input sheet'!$B$24-0.02-$P$4)/'Input sheet'!$B$25)*('Input sheet'!$B$25-W1)) | X4: =IF(X1>'Input sheet'!$B$25,'Input sheet'!$B$24-0.02,('Input sheet'!$B$24-0.02)-(('Input sheet'!$B$24-0.02-$P$4)/'Input sheet'!$B$25)*('Input sheet'!$B$25-X1)) | ... Z4: =IF(Z1>'Input sheet'!$B$25,'Input sheet'!$B$24-0.02,('Input sheet'!$B$24-0.02)-(('Input sheet'!$B$24-0.02-$P$4)/'Input sheet'!$B$25)*('Input sheet'!$B$25-Z1)) | AA4: =Z4
A5: EBIT (Operating income) | B5: =IF('Input sheet'!B14="Yes",IF('Input sheet'!B13="Yes",'Input sheet'!B9+'Operating lease converter'!F32+'R& D converter'!D39,'Input sheet'!B9+'Operating lease converter'!F32),IF('Input sheet'!B13="Yes",'Input sheet'!B9+'R& D converter'!D39,'Input sheet'!B9)) | C5: =C3*C4 | D5: =D3*D4 | E5: =E3*E4 | F5: =F3*F4 | G5: =G3*G4 | H5: =H3*H4 | I5: =I3*I4 | J5: =J3*J4 | ... M5: =M3*M4 | N5: =M5-B5 | O5: EBIT (Operating income) | Q5: =Q3*Q4 | R5: =R3*R4 | S5: =S3*S4 | T5: =T3*T4 | U5: =U3*U4 | V5: =V3*V4 | W5: =W3*W4 | X5: =X3*X4 | ... AA5: =AA3*AA4
A6: Tax rate | B6: ='Input sheet'!B20 | C6: =B6 | D6: =C6 | E6: =D6 | F6: =E6 | G6: =F6 | H6: =G6+($M$6-$G$6)/5 | I6: =H6+($M$6-$G$6)/5 | J6: =I6+($M$6-$G$6)/5 | K6: =J6+($M$6-$G$6)/5 | L6: =K6+($M$6-$G$6)/5 | M6: =IF('Input sheet'!B50="Yes",'Input sheet'!B20,'Input sheet'!B21) | O6: Tax rate | P6: =B6 | Q6: =C6 | R6: =D6 | S6: =E6 | T6: =F6 | U6: =G6 | V6: =H6 | W6: =I6 | ... AA6: =M6
A7: EBIT(1-t) | B7: =IF(B5>0,B5*(1-B6),B5) | C7: =IF(C5>0,MAX(C5*(1-C6)-C10,C5),C5) | D7: =IF(D5>0,MAX(D5*(1-D6)-D10,D5),D5) | E7: =IF(E5>0,MAX(E5*(1-E6)-E10,E5),E5) | F7: =IF(F5>0,MAX(F5*(1-F6)-F10,F5),F5) | G7: =IF(G5>0,MAX(G5*(1-G6)-G10,G5),G5) | H7: =IF(H5>0,MAX(H5*(1-H6)-H10,H5),H5) | I7: =IF(I5>0,MAX(I5*(1-I6)-I10,I5),I5) | J7: =IF(J5>0,MAX(J5*(1-J6)-J10,J5),J5) | ... L7: =IF(L5>0,MAX(L5*(1-L6)-L10,L5),L5) | M7: =M5*(1-M6) | O7: EBIT(1-t) | Q7: =IF(Q5>0,MAX(Q5*(1-Q6)-Q10,Q5),Q5) | R7: =IF(R5>0,MAX(R5*(1-R6)-R10,R5),R5) | S7: =IF(S5>0,MAX(S5*(1-S6)-S10,S5),S5) | T7: =IF(T5>0,MAX(T5*(1-T6)-T10,T5),T5) | U7: =IF(U5>0,MAX(U5*(1-U6)-U10,U5),U5) | V7: =IF(V5>0,MAX(V5*(1-V6)-V10,V5),V5) | W7: =IF(W5>0,MAX(W5*(1-W6)-W10,W5),W5) | X7: =IF(X5>0,MAX(X5*(1-X6)-X10,X5),X5) | ... Z7: =IF(Z5>0,MAX(Z5*(1-Z6)-Z10,Z5),Z5) | AA7: =AA5*(1-AA6)
A8: - Reinvestment | C8: =(C3-B3)/C38 | D8: =(D3-C3)/D38 | E8: =(E3-D3)/E38 | F8: =(F3-E3)/F38 | G8: =(G3-F3)/G38 | H8: =(H3-G3)/H38 | I8: =(I3-H3)/I38 | J8: =(J3-I3)/J38 | ... L8: =(L3-K3)/L38 | M8: =(M3*M2)/M38 | N8: =SUM(C8:M8) | O8: - Reinvestment | Q8: =(Q3-P3)/Q38 | R8: =(R3-Q3)/R38 | S8: =(S3-R3)/S38 | T8: =(T3-S3)/T38 | U8: =(U3-T3)/U38 | V8: =(V3-U3)/V38 | W8: =(W3-V3)/W38 | X8: =(X3-W3)/X38 | ... Z8: =(Z3-Y3)/Z38 | AA8: =(AA3*AA2)/AA38
A9: FCFF | C9: =C7-C8 | D9: =D7-D8 | E9: =E7-E8 | F9: =F7-F8 | G9: =G7-G8 | H9: =H7-H8 | I9: =I7-I8 | J9: =J7-J8 | ... M9: =M7-M8 | O9: FCFF | Q9: =Q7-Q8 | R9: =R7-R8 | S9: =S7-S8 | T9: =T7-T8 | U9: =U7-U8 | V9: =V7-V8 | W9: =W7-W8 | X9: =X7-X8 | ... AA9: =AA7-AA8
A10: NOL | B10: =IF('Input sheet'!B52="Yes",'Input sheet'!B53,0) | C10: =IF(C5>0,MAX(B10-C5*C6,0),B10-C5) | D10: =IF(D5>0,MAX(C10-D5*D6,0),C10-D5) | E10: =IF(E5>0,MAX(D10-E5*E6,0),D10-E5) | F10: =IF(F5>0,MAX(E10-F5*F6,0),E10-F5) | G10: =IF(G5>0,MAX(F10-G5*G6,0),F10-G5) | H10: =IF(H5>0,MAX(G10-H5*H6,0),G10-H5) | I10: =IF(I5>0,MAX(H10-I5*I6,0),H10-I5) | J10: =IF(J5>0,MAX(I10-J5*J6,0),I10-J5) | ... M10: =IF(M5>0,MAX(L10-M5*M6,0),L10-M5) | O10: NOL | P10: =B10 | Q10: =IF(Q5>0,MAX(P10-Q5*Q6,0),P10-Q5) | R10: =IF(R5>0,MAX(Q10-R5*R6,0),Q10-R5) | S10: =IF(S5>0,MAX(R10-S5*S6,0),R10-S5) | T10: =IF(T5>0,MAX(S10-T5*T6,0),S10-T5) | U10: =IF(U5>0,MAX(T10-U5*U6,0),T10-U5) | V10: =IF(V5>0,MAX(U10-V5*V6,0),U10-V5) | W10: =IF(W5>0,MAX(V10-W5*W6,0),V10-W5) | X10: =IF(X5>0,MAX(W10-X5*X6,0),W10-X5) | ... AA10: =IF(AA5>0,MAX(Z10-AA5*AA6,0),Z10-AA5)
A12: Cost of capital | C12: ='Input sheet'!B29 | D12: =C12 | E12: =D12 | F12: =E12 | G12: =F12 | H12: =G12-($G$12-$M$12)/5 | I12: =H12-($G$12-$M$12)/5 | J12: =I12-($G$12-$M$12)/5 | K12: =J12-($G$12-$M$12)/5 | L12: =K12-($G$12-$M$12)/5 | M12: =IF('Input sheet'!B39="Yes",'Input sheet'!B40,'Input sheet'!B28+0.045) | O12: Cost of capital | Q12: =C12 | R12: =D12 | S12: =E12 | T12: =F12 | U12: =G12 | V12: =H12 | W12: =I12 | X12: =J12 | ... AA12: =M12
A13: Cumulated discount factor | C13: =1/(1+C12) | D13: =C13*(1/(1+D12)) | E13: =D13*(1/(1+E12)) | F13: =E13*(1/(1+F12)) | G13: =F13*(1/(1+G12)) | H13: =G13*(1/(1+H12)) | I13: =H13*(1/(1+I12)) | J13: =I13*(1/(1+J12)) | K13: =J13*(1/(1+K12)) | L13: =K13*(1/(1+L12)) | M13: =L13/(1+M12) | O13: Cumulated discount factor | Q13: =1/(1+Q12) | R13: =Q13/(1+R12) | S13: =R13/(1+S12) | T13: =S13/(1+T12) | U13: =T13/(1+U12) | V13: =U13/(1+V12) | W13: =V13/(1+W12) | X13: =W13/(1+X12) | Y13: =X13/(1+Y12) | ... AA13: =Z13/(1+AA12)
A14: PV(FCFF) | C14: =C9*C13 | D14: =D9*D13 | E14: =E9*E13 | F14: =F9*F13 | G14: =G9*G13 | H14: =H9*H13 | I14: =I9*I13 | J14: =J9*J13 | ... M14: =M9*M13 | O14: PV(FCFF) | Q14: =Q9*Q13 | R14: =R9*R13 | S14: =S9*S13 | T14: =T9*T13 | U14: =U9*U13 | V14: =V9*V13 | W14: =W9*W13 | X14: =X9*X13 | ... AA14: =AA9*AA13
A16: Terminal cash flow | M16: =M9 | O16: Terminal cash flow | AA16: =AA9
A17: Terminal cost of capital | M17: =M12 | O17: Terminal cost of capital | AA17: =AA12
A18: Terminal value | M18: =M16/(M17-M2) | O18: Terminal value | AA18: =AA16/(AA17-AA2)
A19: PV(Terminal value) | M19: =M18*M13 | O19: PV(Terminal value) | AA19: =AA18*AA13
A20: PV (CF over next 10 years) | B20: =SUM(C14:L14) | O20: PV (CF over next 10 years) | P20: =SUM(Q14:Z14)
A21: Sum of PV | B21: =B20+M19 | O21: Sum of PV | P21: =P20+AA19
A22: Probability of failure = | B22: =IF('Input sheet'!B45="Yes",'Input sheet'!B46,0) | O22: Probability of failure = | P22: =B22
A23: Proceeds if firm fails = | B23: =IF('Input sheet'!B47="V",B21*'Input sheet'!B48,IF('Input sheet'!B47="BV",'Input sheet'!B11*'Input sheet'!B48,0)) | O23: Proceeds if firm fails = | P23: =IF('Input sheet'!B47="V",P21*'Input sheet'!B48,IF('Input sheet'!B47="BV",'Input sheet'!B11*'Input sheet'!B48,0))
A24: Value of operating assets = | B24: =B21*(1-B22)+B22*B23 | O24: Value of operating assets = | P24: =P21*(1-P22)+P22*P23
A25: - Debt | B25: ='Input sheet'!B12 | O25: - Debt | P25: =B25
A26: - Minority interests | B26: ='Input sheet'!B17 | O26: - Minority interests | P26: =B26
A27: + Cash | B27: =IF('Input sheet'!B58="Yes",'Input sheet'!B15-'Input sheet'!B59,'Input sheet'!B15) | O27: + Cash | P27: =B27
A28: + Non-operating assets | B28: ='Input sheet'!B16 | O28: + Non-operating assets | P28: =B28
A29: Value of equity | B29: =B24-B25-B26+B27+B28 | O29: Value of equity | P29: =P24-P25-P26+P27+P28
A30: - Value of options | B30: =IF('Input sheet'!B31="Yes",'Option value'!H18,0) | O30: - Value of options | P30: =B30
A31: Value of equity in common stock | B31: =B29-B30 | O31: Value of equity in common stock | P31: =P29-P30
A32: Number of shares | B32: ='Input sheet'!B18 | O32: Number of shares | P32: =B32
A33: Estimated value /share | B33: =B31/B32 | O33: Estimated value /share | P33: =P31/P32
A34: Price | B34: ='Input sheet'!B19 | O34: Price | P34: =B34
A35: Price as % of value | B35: =B34/B33 | O35: Price as % of value | P35: =P34/P33
A37: Implied variables | M37: After year 10 | O37: Implied variables
A38: Sales to capital ratio | C38: ='Input sheet'!B26 | D38: =C38 | E38: =C38 | F38: =C38 | G38: =C38 | H38: =C38 | I38: =C38 | J38: =C38 | K38: =C38 | L38: =C38 | M38: =(M12-M2)/M40 | O38: Sales to capital ratio | Q38: =C38 | R38: =D38 | S38: =E38 | T38: =F38 | U38: =G38 | V38: =H38 | W38: =I38 | X38: =J38 | ... Z38: =L38 | AA38: =(AA12-AA2)/AA40
A39: Invested capital | B39: =IF('Input sheet'!B14="Yes",IF('Input sheet'!B13="Yes",'Input sheet'!B11+'Input sheet'!B12-'Input sheet'!B15+'Operating lease converter'!F33+'R& D converter'!D35,'Input sheet'!B11+'Input sheet'!B12-'Input sheet'!B15+'Operating lease converter'!F33),IF('Input sheet'!B13="Yes",'Input sheet'!B11+'Input sheet'!B12-'Input sheet'!B15+'R& D converter'!D35,'Input sheet'!B11+'Input sheet'!B12-'Input sheet'!B15)) | C39: =B39+C8 | D39: =C39+D8 | E39: =D39+E8 | F39: =E39+F8 | G39: =F39+G8 | H39: =G39+H8 | I39: =H39+I8 | J39: =I39+J8 | ... M39: =L39+M8 | O39: Invested capital | P39: =B39 | Q39: =P39+Q8 | R39: =Q39+R8 | S39: =R39+S8 | T39: =S39+T8 | U39: =T39+U8 | V39: =U39+V8 | W39: =V39+W8 | X39: =W39+X8 | ... AA39: =Z39+AA8
A40: ROIC | B40: =B7/B39 | C40: =C7/C39 | D40: =D7/D39 | E40: =E7/E39 | F40: =F7/F39 | G40: =G7/G39 | H40: =H7/H39 | I40: =I7/I39 | ... L40: =L7/L39 | M40: =IF('Input sheet'!B42="Yes",'Input sheet'!B43,M12) | O40: ROIC | Q40: =Q7/Q39 | R40: =R7/R39 | S40: =S7/S39 | T40: =T7/T39 | U40: =U7/U39 | V40: =V7/V39 | W40: =W7/W39 | X40: =X7/X39 | ... Z40: =Z7/Z39 | AA40: =IF('Input sheet'!B42="Yes",'Input sheet'!B43,AA12)

Sheet Stories to Numbers
A1: ='Input sheet'!B2
A2: The Greatest (and most Feared) Disruptive Platform in History
A3: Amazon will complete its metaphorsis from being a retail company to one that can take its competitive advantages - access to capital & willingness to lose money for long periods, while disrupting and changing the status quo - to any business that it targets, giving it the potential for high revenue growth on top of already-large revenues. It will be able to use the pricing power it accumulates in each business it is in, to increase profit margins, partly through economies of scale and partly through higher prices. Its low debt ratio and divergent business mix give it a low cost of capital. | H3: Tell your story about the company. Keep it focuses on the company's businesses and tie it into the three key levers of value: cash flows, growth and risk
A7: The Assumptions
B8: Base year | C8: Years 1-5 | D8: Years 6-10 | F8: After year 10 | G8: Link to story
A9: Revenues (a) | B9: ='Valuation output'!B3 | C9: ='Input sheet'!B23 | D9: =F9 | F9: ='Valuation output'!M2 | G9: Expanding into new businessses | H9: Tie each assumption to the part of your story that relates to it.
A10: Operating margin (b) | B10: ='Valuation output'!B4 | C10: =B10 | D10: =F10 | F10: ='Valuation output'!M4 | G10: Economies of scale and pricing power increase margins
A11: Tax rate | B11: ='Valuation output'!B6 | C11: =B11 | D11: =F11 | F11: ='Valuation output'!M6 | G11: Converging on a global tax rate of 25%
A12: Reinvestment (c ) | C12: Sales to capital ratio = | D12: ='Input sheet'!B26 | E12: RIR = | F12: ='Valuation output'!M2/'Valuation output'!M40 | G12: Big payoffs from investing in technology and content
A13: Return on capital | B13: ='Valuation output'!B40 | C13: Marginal ROIC = | D13: =Diagnostics!B6 | F13: ='Valuation output'!M40 | G13: The last man standing…
A14: Cost of capital (d) | C14: ='Valuation output'!C12 | D14: =F14 | F14: ='Valuation output'!M12 | G14: Low debt & diverse business mix
A15: The Cash Flows
B16: Revenues | C16: Operating Margin | D16: EBIT | E16: EBIT (1-t) | F16: Reinvestment | G16: FCFF | H16: These are the numbers that come from your assumptions. The revenues over time reflect your revenue growth, the operating margins evolve towards your target margin and your tax rate will change, if you have set it to. The reinvestment is estimated using the sales to capital ratio for the first 10 years and based on a reinvestment rate in stable growth (g/ ROC).
A17: 1 | B17: ='Valuation output'!C3 | C17: ='Valuation output'!C4 | D17: =B17*C17 | E17: ='Valuation output'!C7 | F17: ='Valuation output'!C8 | G17: =E17-F17
A18: 2 | B18: ='Valuation output'!D3 | C18: ='Valuation output'!D4 | D18: =B18*C18 | E18: ='Valuation output'!D7 | F18: ='Valuation output'!D8 | G18: =E18-F18
A19: 3 | B19: ='Valuation output'!E3 | C19: ='Valuation output'!E4 | D19: =B19*C19 | E19: ='Valuation output'!E7 | F19: ='Valuation output'!E8 | G19: =E19-F19
A20: 4 | B20: ='Valuation output'!F3 | C20: ='Valuation output'!F4 | D20: =B20*C20 | E20: ='Valuation output'!F7 | F20: ='Valuation output'!F8 | G20: =E20-F20
A21: 5 | B21: ='Valuation output'!G3 | C21: ='Valuation output'!G4 | D21: =B21*C21 | E21: ='Valuation output'!G7 | F21: ='Valuation output'!G8 | G21: =E21-F21
A22: 6 | B22: ='Valuation output'!H3 | C22: ='Valuation output'!H4 | D22: =B22*C22 | E22: ='Valuation output'!H7 | F22: ='Valuation output'!H8 | G22: =E22-F22
A23: 7 | B23: ='Valuation output'!I3 | C23: ='Valuation output'!I4 | D23: =B23*C23 | E23: ='Valuation output'!I7 | F23: ='Valuation output'!I8 | G23: =E23-F23
A24: 8 | B24: ='Valuation output'!J3 | C24: ='Valuation output'!J4 | D24: =B24*C24 | E24: ='Valuation output'!J7 | F24: ='Valuation output'!J8 | G24: =E24-F24
A25: 9 | B25: ='Valuation output'!K3 | C25: ='Valuation output'!K4 | D25: =B25*C25 | E25: ='Valuation output'!K7 | F25: ='Valuation output'!K8 | G25: =E25-F25
A26: 10 | B26: ='Valuation output'!L3 | C26: ='Valuation output'!L4 | D26: =B26*C26 | E26: ='Valuation output'!L7 | F26: ='Valuation output'!L8 | G26: =E26-F26
A27: Terminal year | B27: ='Valuation output'!M3 | C27: ='Valuation output'!M4 | D27: =B27*C27 | E27: ='Valuation output'!M7 | F27: ='Valuation output'!M8 | G27: =E27-F27
A28: The Value
A29: Terminal value | D29: ='Valuation output'!B18 | H29: This is the output from your valuation. It reflects your cash flows being discounted back at the cost of capital to get to your operating asset value, which then gets adjusted for the likelihood that your firm will not make it. We add cash and non-operating assets, subtract out debt and minority interests to get to value of equity.
A30: PV(Terminal value) | D30: ='Valuation output'!B19
A31: PV (CF over next 10 years) | D31: ='Valuation output'!B20
A32: Value of operating assets = | D32: ='Valuation output'!B21
A33: Adjustment for distress | D33: =D32-'Valuation output'!B24 | E33: Probability of failure = | G33: ='Valuation output'!B22
A34: - Debt & Mnority Interests | D34: ='Valuation output'!B25+'Valuation output'!B26
A35: + Cash & Other Non-operating assets | D35: ='Valuation output'!B27+'Valuation output'!B28
A36: Value of equity | D36: =D32-D33-D34+D35
A37: - Value of equity options | D37: ='Valuation output'!B30
A38: Number of shares | D38: ='Valuation output'!B32
A39: Value per share | D39: =(D36-D37)/D38 | E39: Stock was trading at = | G39: ='Input sheet'!B19
J43: =D39/1944

Sheet Summary Sheet
A1: Year | B1: Revenues | C1: Revenue Growth Rate | D1: Pre-Tax Operating Margin | E1: Pre-Tax Operating Income | F1: NOL | G1: Taxes | H1: After-Tax Operating Income
A2: Traling 12 month | B2: ='Valuation output'!B3 | D2: ='Valuation output'!B4 | E2: =B2*D2 | F2: ='Valuation output'!B10 | G2: =E2-H2 | H2: ='Valuation output'!B7
A3: 1 | B3: ='Valuation output'!C3 | C3: ='Valuation output'!C2 | D3: ='Valuation output'!C4 | E3: =B3*D3 | F3: ='Valuation output'!C10 | G3: =E3-H3 | H3: ='Valuation output'!C7
A4: 2 | B4: ='Valuation output'!D3 | C4: =B4/B3-1 | D4: ='Valuation output'!D4 | E4: =B4*D4 | F4: ='Valuation output'!D10 | G4: =E4-H4 | H4: ='Valuation output'!D7
A5: 3 | B5: ='Valuation output'!E3 | C5: =B5/B4-1 | D5: ='Valuation output'!E4 | E5: =B5*D5 | F5: ='Valuation output'!E10 | G5: =E5-H5 | H5: ='Valuation output'!E7
A6: 4 | B6: ='Valuation output'!F3 | C6: =B6/B5-1 | D6: ='Valuation output'!F4 | E6: =B6*D6 | F6: ='Valuation output'!F10 | G6: =E6-H6 | H6: ='Valuation output'!F7
A7: 5 | B7: ='Valuation output'!G3 | C7: =B7/B6-1 | D7: ='Valuation output'!G4 | E7: =B7*D7 | F7: ='Valuation output'!G10 | G7: =E7-H7 | H7: ='Valuation output'!G7
A8: 6 | B8: ='Valuation output'!H3 | C8: =B8/B7-1 | D8: ='Valuation output'!H4 | E8: =B8*D8 | F8: ='Valuation output'!H10 | G8: =E8-H8 | H8: ='Valuation output'!H7
A9: 7 | B9: ='Valuation output'!I3 | C9: =B9/B8-1 | D9: ='Valuation output'!I4 | E9: =B9*D9 | F9: ='Valuation output'!I10 | G9: =E9-H9 | H9: ='Valuation output'!I7
A10: 8 | B10: ='Valuation output'!J3 | C10: =B10/B9-1 | D10: ='Valuation output'!J4 | E10: =B10*D10 | F10: ='Valuation output'!J10 | G10: =E10-H10 | H10: ='Valuation output'!J7
A11: 9 | B11: ='Valuation output'!K3 | C11: =B11/B10-1 | D11: ='Valuation output'!K4 | E11: =B11*D11 | F11: ='Valuation output'!K10 | G11: =E11-H11 | H11: ='Valuation output'!K7
A12: 10 | B12: ='Valuation output'!L3 | C12: =B12/B11-1 | D12: ='Valuation output'!L4 | E12: =B12*D12 | F12: ='Valuation output'!L10 | G12: =E12-H12 | H12: ='Valuation output'!L7
A14: Year | B14: After-Tax Operating Income | C14: Change in Revenues | D14: Sales to Capital | E14: Reinvestment | F14: FCFF | G14: Capital Invested | H14: Implied ROC
A15: =A2 | B15: =H2 | G15: ='Valuation output'!B39 | H15: =B15/G15
A16: =A3 | B16: =H3 | C16: =B3-B2 | D16: ='Valuation output'!C38 | E16: =C16/D16 | F16: =B16-E16 | G16: =G15+E16 | H16: =B16/G16
A17: =A4 | B17: =H4 | C17: =B4-B3 | D17: ='Valuation output'!D38 | E17: =C17/D17 | F17: =B17-E17 | G17: =G16+E17 | H17: =B17/G17
A18: =A5 | B18: =H5 | C18: =B5-B4 | D18: ='Valuation output'!E38 | E18: =C18/D18 | F18: =B18-E18 | G18: =G17+E18 | H18: =B18/G18
A19: =A6 | B19: =H6 | C19: =B6-B5 | D19: ='Valuation output'!F38 | E19: =C19/D19 | F19: =B19-E19 | G19: =G18+E19 | H19: =B19/G19
A20: =A7 | B20: =H7 | C20: =B7-B6 | D20: ='Valuation output'!G38 | E20: =C20/D20 | F20: =B20-E20 | G20: =G19+E20 | H20: =B20/G20
A21: =A8 | B21: =H8 | C21: =B8-B7 | D21: ='Valuation output'!H38 | E21: =C21/D21 | F21: =B21-E21 | G21: =G20+E21 | H21: =B21/G21
A22: =A9 | B22: =H9 | C22: =B9-B8 | D22: ='Valuation output'!I38 | E22: =C22/D22 | F22: =B22-E22 | G22: =G21+E22 | H22: =B22/G22
A23: =A10 | B23: =H10 | C23: =B10-B9 | D23: ='Valuation output'!J38 | E23: =C23/D23 | F23: =B23-E23 | G23: =G22+E23 | H23: =B23/G23
A24: =A11 | B24: =H11 | C24: =B11-B10 | D24: ='Valuation output'!K38 | E24: =C24/D24 | F24: =B24-E24 | G24: =G23+E24 | H24: =B24/G24
A25: =A12 | B25: =H12 | C25: =B12-B11 | D25: ='Valuation output'!L38 | E25: =C25/D25 | F25: =B25-E25 | G25: =G24+E25 | H25: =B25/G25
A27: Year | B27: Beta | C27: Cost of Equity | D27: Pre-Tax Cost of Debt | E27: Tax Savings | F27: After-Tax Cost of Debt | G27: Debt Ratio | H27: Cost of Capital
A28: =A16 | H28: ='Valuation output'!C12
A29: =A17 | H29: ='Valuation output'!D12
A30: =A18 | H30: ='Valuation output'!E12
A31: =A19 | H31: ='Valuation output'!F12
A32: =A20 | H32: ='Valuation output'!G12
A33: =A21 | H33: ='Valuation output'!H12
A34: =A22 | H34: ='Valuation output'!I12
A35: =A23 | H35: ='Valuation output'!J12
A36: =A24 | H36: ='Valuation output'!K12
A37: =A25 | H37: ='Valuation output'!L12
A39: Year | B39: Cost of Capital | C39: Cumulated Cost of Capital | D39: FCFF | E39: Terminal Value | F39: Present Value
A40: =A28 | B40: =H28 | C40: =(1+'Summary Sheet'!B40) | D40: =F16 | F40: =D40/C40
A41: =A29 | B41: =H29 | C41: =C40*(1+B41) | D41: =F17 | F41: =D41/C41
A42: =A30 | B42: =H30 | C42: =C41*(1+B42) | D42: =F18 | F42: =D42/C42
A43: =A31 | B43: =H31 | C43: =C42*(1+B43) | D43: =F19 | F43: =D43/C43
A44: =A32 | B44: =H32 | C44: =C43*(1+B44) | D44: =F20 | F44: =D44/C44
A45: =A33 | B45: =H33 | C45: =C44*(1+B45) | D45: =F21 | F45: =D45/C45
A46: =A34 | B46: =H34 | C46: =C45*(1+B46) | D46: =F22 | F46: =D46/C46
A47: =A35 | B47: =H35 | C47: =C46*(1+B47) | D47: =F23 | F47: =D47/C47
A48: =A36 | B48: =H36 | C48: =C47*(1+B48) | D48: =F24 | F48: =D48/C48
A49: =A37 | B49: =H37 | C49: =C48*(1+B49) | D49: =F25 | E49: ='Valuation output'!B18 | F49: =(D49+E49)/C49
A50: Value of operating assets = | F50: =SUM(F40:F49)

Sheet Option value
A1: Valuing Options or Warrants
A2: Enter the current stock price = | D2: ='Input sheet'!B19
A3: Enter the strike price on the option = | D3: ='Input sheet'!B33
A4: Enter the expiration of the option = | D4: ='Input sheet'!B34
A5: Enter the standard deviation in stock prices = | D5: ='Input sheet'!B35 | E5: (volatility)
A6: Enter the annualized dividend yield on stock = | D6: 0
A7: Enter the treasury bond rate = | D7: ='Input sheet'!B28
A8: Enter the number of warrants (options) outstanding = | D8: ='Input sheet'!B32
A9: Enter the number of shares outstanding = | D9: ='Input sheet'!B18
A11: Do not input any numbers below this line
A12: VALUING WARRANTS WHEN THERE IS DILUTION
A13: Stock Price= | C13: =D2 | D13: # Warrants issued= | F13: =D8
A14: Strike Price= | C14: =D3 | D14: # Shares outstanding= | F14: =D9
A15: Adjusted S = | C15: =(C13*F14+C26*F13)/(F14+F13) | D15: T.Bond rate= | F15: =D7
A16: Adjusted K = | C16: =C14 | D16: Variance= | F16: =D5^2
A17: Expiration (in years) = | C17: =D4 | D17: Annualized dividend yield= | F17: =D6
D18: Div. Adj. interest rate= | F18: =F15-F17
A20: d1 = | B20: =(LN(C15/C16)+(F18+(F16/2))*C17)/(((F16)^(0.5))*(C17^0.5))
A21: N (d1) = | B21: =NORMSDIST(B20)
A23: d2 = | B23: =B20-((F16^0.5)*(C17^(0.5)))
A24: N (d2) = | B24: =NORMSDIST(B23)
A26: Value per option = | C26: =((EXP((0-F17)*C17))*C15*B21-C16*(EXP((0-F15)*C17))*B24)
A27: Value of all options outstanding = | D27: =C26*D8

Sheet Diagnostics
A1: VALUATION DIAGNOSTICS
A2: Invested capital at start of valuation | B2: ='Valuation output'!B39
A3: Invested capital at end of valuation | B3: ='Valuation output'!L39
A4: Change in invested capital over 10 years | B4: =B3-B2
A5: Change in EBIT*(1–t) (after-tax operating income) over 10 years | B5: ='Valuation output'!L5-'Valuation output'!B5
A6: Marginal ROIC over 10 years | B6: =B5/B4
A7: ROIC at end of valuation | B7: ='Valuation output'!L40
A8: Average WACC over the 10 years (compounded) | B8: =(1/'Valuation output'!L13)^(1/10)-1
A9: Your calculated value as a percent of current price | B9: ='Valuation output'!B33/'Valuation output'!B34
B10: =IF(B9="NA","Value is negative. See below",IF(B9>2,"Value seems high. See below",IF(B9<0.5,"Value seems low. See below"," ")))
A11: Inputs | B11: If calculated value is negative or looks too low | C11: If calculated value looks too high
A12: Revenue growth rate (input cell B3) | B12: Increase revenue growth rate | C12: Decrease revenue growth rate
A13: Last period EBIT as % of revenue (Input cell B14) | B13: Increase the target pre-tax operating margin | C13: Decrease the target pre-tax operating margin
A14: Sales to Capital Ratio or reinvestment (Input cell B15) | B14: Decrease the sales/capital ratio | C14: Increase the sales/capital ratio
A15: Return on capital in perpetuity (B30 & B31) | B15: Increase relative to your cost of capital | C15: If higher than your cost of capital, lower towards your cost of capital | D15: T

Sheet R& D converter
A1: R & D Converter
A2: This spreadsheet converts R&D expenses from operating to capital expenses. It makes the appropriate adjustments to operating income, net
A3: income, the book value of assets and the book value of equity.
A5: Inputs
A6: Over how many years do you want to amortize R&D expenses | F6: 2 | G6: ! If in doubt, use the lookup table below
A7: Enter the current year's R&D expense = | F7: 22620 | G7: The maximum allowed is ten years
A8: Enter R& D expenses for past years: the number of years that you will need to enter will be determined by the amortization period
A9: Do not input numbers in the first column (Year). It will get automatically updated based on the input above.
A10: Year | B10: R& D Expenses
A11: -1 | B11: 16085 | C11: ! Year -1 is the year prior to the current year
A12: =IF((0-A11)<$F$6,IF(A11>-1,,A11-1),) | B12: 12540 | C12: ! Year -2 is the two years prior to the current year
A13: =IF((0-A12)<$F$6,IF(A12>-1,,A12-1),)
A14: =IF((0-A13)<$F$6,IF(A13>-1,,A13-1),)
A15: =IF((0-A14)<$F$6,IF(A14>-1,,A14-1),)
A16: =IF((0-A15)<$F$6,IF(A15>-1,,A15-1),)
A17: =IF((0-A16)<$F$6,IF(A16>-1,,A16-1),)
A18: =IF((0-A17)<$F$6,IF(A17>-1,,A17-1),)
A19: =IF((0-A18)<$F$6,IF(A18>-1,,A18-1),)
A20: =IF((0-A19)<$F$6,IF(A19>-1,,A19-1),)
A22: Output
A23: Year | B23: R&D Expense | C23: Unamortized portion | E23: Amortization this year
A24: Current | B24: =F7 | C24: =1 | D24: =B24*C24
A25: =A11 | B25: =B11 | C25: =IF(A25<0,($F$6+A25)/$F$6,0) | D25: =B25*C25 | E25: =IF(A25<0,B25/$F$6,0)
A26: =A12 | B26: =B12 | C26: =IF(A26<0,($F$6+A26)/$F$6,0) | D26: =B26*C26 | E26: =IF(A26<0,B26/$F$6,0)
A27: =A13 | B27: =B13 | C27: =IF(A27<0,($F$6+A27)/$F$6,0) | D27: =B27*C27 | E27: =IF(A27<0,B27/$F$6,0)
A28: =A14 | B28: =B14 | C28: =IF(A28<0,($F$6+A28)/$F$6,0) | D28: =B28*C28 | E28: =IF(A28<0,B28/$F$6,0)
A29: =A15 | B29: =B15 | C29: =IF(A29<0,($F$6+A29)/$F$6,0) | D29: =B29*C29 | E29: =IF(A29<0,B29/$F$6,0)
A30: =A16 | B30: =B16 | C30: =IF(A30<0,($F$6+A30)/$F$6,0) | D30: =B30*C30 | E30: =IF(A30<0,B30/$F$6,0)
A31: =A17 | B31: =B17 | C31: =IF(A31<0,($F$6+A31)/$F$6,0) | D31: =B31*C31 | E31: =IF(A31<0,B31/$F$6,0)
A32: =A18 | B32: =B18 | C32: =IF(A32<0,($F$6+A32)/$F$6,0) | D32: =B32*C32 | E32: =IF(A32<0,B32/$F$6,0)
A33: =A19 | B33: =B19 | C33: =IF(A33<0,($F$6+A33)/$F$6,0) | D33: =B33*C33 | E33: =IF(A33<0,B33/$F$6,0)
A34: =A20 | B34: =B20 | C34: =IF(A34<0,($F$6+A34)/$F$6,0) | D34: =B34*C34 | E34: =IF(A34<0,B34/$F$6,0)
A35: Value of Research Asset = | D35: =SUM(D24:D34) | E35: =SUM(E25:E34)
A37: Amortization of asset for current year = | D37: =E35
A39: Adjustment to Operating Income = | D39: =F7-D37 | E39: ! A positive number indicates an increase in operating income (add to reported EBIT)
A40: Tax Effect of R&D Expensing | D40: =D39*'Input sheet'!B21

Sheet Operating lease converter
A1: Operating Lease Converter
A2: The yellow cells are input cells. Please enter them.
A3: Inputs
A4: Operating lease expense in current year = | E4: 2200
A5: Operating Lease Commitments (From footnote to financials)
A6: Year | B6: Commitment | C6: ! Year 1 is next year, ….
A7: 1 | B7: 2427
A8: 2 | B8: 2376
A9: 3 | B9: 2258
A10: 4 | B10: 2039
A11: 5 | B11: 1813
A12: 6 and beyond | B12: 11935
A14: Output
A15: Pre-tax Cost of Debt = | C15: 0.0413 | D15: ! If you do not have a cost of debt, use the synthetic rating estimator
A18: Number of years embedded in yr 6 estimate = | D18: =IF(B12>0,ROUND(B12/AVERAGE(B7:B11),0),0) | E18: ! I use the average lease expense over the first five years
E19: to estimate the number of years of expenses in yr 6
A20: Converting Operating Leases into debt
A21: Year | B21: Commitment | C21: Present Value
A22: =A7 | B22: =B7 | C22: =B22/(1+$C$15)^A22
A23: =A8 | B23: =B8 | C23: =B23/(1+$C$15)^A23
A24: =A9 | B24: =B9 | C24: =B24/(1+$C$15)^A24
A25: =A10 | B25: =B10 | C25: =B25/(1+$C$15)^A25
A26: =A11 | B26: =B11 | C26: =B26/(1+$C$15)^A26
A27: =A12 | B27: =IF(B12>0,IF(D18>0,B12/D18,B12),0) | C27: =IF(D18>0,(B27*(1-(1+C15)^(-D18))/C15)/(1+$C$15)^5,B27/(1+C15)^6) | D27: ! Commitment beyond year 6 converted into an annuity for ten years
A28: Debt Value of leases = | C28: =SUM(C22:C27)
A30: Restated Financials
A31: Depreciation on Operating Lease Asset = | F31: =C28/(5+D18) | G31: ! I use straight line depreciation
A32: Adjustment to Operating Earnings = | F32: =E4-F31 | G32: ! Add this amount to pre-tax operating income
A33: Adjustment to Total Debt outstanding = | F33: =C28 | G33: ! Add this amount to debt
A34: Adjustment to Depreciation = | F34: =C28/(5+D18)

Sheet Cost of capital worksheet
A1: Estimation of Current Cost of Capital | G1: Operating Countries ERP calculator
A2: Inputs | G2: Country | H2: Revenues | I2: ERP | J2: Weight | K2: Weighted ERP
A3: Equity | G3: United States of America | H3: 120486 | I3: =IF(H3=0,0,VLOOKUP(G3,'Country equity risk premiums'!$A$2:$D$187,4)) | J3: =IF(H3>0,H3/$H$16,) | K3: =IF(J3=0,0,I3*J3) | M3: The last two rows in each of country/region risk premium tables is set aside for your input to provide you with flexibility to enter some numbers directly. For instance, assume that you have a company that breaks its revenues down into three countries and then puts the rest into "Rest of the World". You can enter the "Rest of the World" in one of these two rows and enter an equity risk premium for the rest of the world. The easiest way to do that is to go into the country equity risk premium worksheet and change the GDP for the three countries that you have data for to zero and compute the global weighted average ERP for the remaining countries. With the regional worksheet, you can use the last two rows to enter the data for an individual country (usually the domestic country) that might be broken out though the rest of the revenues are broken down by region. You can look up the ERP for the country in the country ERP worksheet.
A4: Number of Shares outstanding = | B4: ='Input sheet'!B18 | G4: Germany | H4: 16951 | I4: =IF(H4=0,0,VLOOKUP(G4,'Country equity risk premiums'!$A$2:$D$187,4)) | J4: =IF(H4>0,H4/$H$16,) | K4: =IF(J4=0,0,I4*J4)
A5: Current Market Price per share = | B5: ='Input sheet'!B19 | G5: United Kingdom | H5: 11372 | I5: =IF(H5=0,0,VLOOKUP(G5,'Country equity risk premiums'!$A$2:$D$187,4)) | J5: =IF(H5>0,H5/$H$16,) | K5: =IF(J5=0,0,I5*J5)
G6: Japan | H6: 11907 | I6: =IF(H6=0,0,VLOOKUP(G6,'Country equity risk premiums'!$A$2:$D$187,4)) | J6: =IF(H6>0,H6/$H$16,) | K6: =IF(J6=0,0,I6*J6)
A7: Approach for estimating beta | B7: Multibusiness(Global) | I7: =IF(H7=0,0,VLOOKUP(G7,'Country equity risk premiums'!$A$2:$D$187,4)) | J7: =IF(H7>0,H7/$H$16,) | K7: =IF(J7=0,0,I7*J7)
A8: If direct input, enter levered beta (or regression beta) | B8: 1.2 | I8: =IF(H8=0,0,VLOOKUP(G8,'Country equity risk premiums'!$A$2:$D$187,4)) | J8: =IF(H8>0,H8/$H$16,) | K8: =IF(J8=0,0,I8*J8)
A9: Unlevered beta = | B9: =IF(B7="Single Business(US)",VLOOKUP('Input sheet'!B6,'Industry Averages(US)'!A2:G95,7),IF(B7="Multibusiness(US)",K46,IF(B7="Single Business(Global)",VLOOKUP('Input sheet'!B7,'Global industry averages'!A2:G95,7),'Cost of capital worksheet'!K62))) | I9: =IF(H9=0,0,VLOOKUP(G9,'Country equity risk premiums'!$A$2:$D$187,4)) | J9: =IF(H9>0,H9/$H$16,) | K9: =IF(J9=0,0,I9*J9)
A10: Riskfree Rate = | B10: ='Input sheet'!B28 | I10: =IF(H10=0,0,VLOOKUP(G10,'Country equity risk premiums'!$A$2:$D$187,4)) | J10: =IF(H10>0,H10/$H$16,) | K10: =IF(J10=0,0,I10*J10)
A11: What approach do you want to use to input ERP? | B11: Operating countries | I11: =IF(H11=0,0,VLOOKUP(G11,'Country equity risk premiums'!$A$2:$D$187,4)) | J11: =IF(H11>0,H11/$H$16,) | K11: =IF(J11=0,0,I11*J11)
A12: Direct input for ERP (if you choose "will input" | B12: 0.05 | I12: =IF(H12=0,0,VLOOKUP(G12,'Country equity risk premiums'!$A$2:$D$187,4)) | J12: =IF(H12>0,H12/$H$16,) | K12: =IF(J12=0,0,I12*J12)
A13: Equity Risk Premium used in cost of equity = | B13: =IF(B11="Will Input",B12,IF(B11="Country of Incorporation",VLOOKUP('Input sheet'!B5,'Country equity risk premiums'!A2:E187,4),IF(B11="Operating regions",'Cost of capital worksheet'!K30,'Cost of capital worksheet'!K16))) | I13: =IF(H13=0,0,VLOOKUP(G13,'Country equity risk premiums'!$A$2:$D$187,4)) | J13: =IF(H13>0,H13/$H$16,) | K13: =IF(J13=0,0,I13*J13)
J14: =IF(H14>0,H14/$H$16,) | K14: =IF(J14=0,0,I14*J14)
A15: Debt | G15: Rest of the World | H15: 17150 | I15: 0.0621 | J15: =IF(H15>0,H15/$H$16,) | K15: =IF(J15=0,0,I15*J15)
A16: Book Value of Straight Debt = | B16: ='Input sheet'!B12 | G16: Total | H16: =SUM(H3:H15) | J16: =SUM(J3:J15) | K16: =SUM(K3:K15)
A17: Interest Expense on Debt = | B17: ='Input sheet'!B10 | G17: Operating Regions ERP calculator
A18: Average Maturity = | B18: 3 | G18: Region | H18: Revenues | I18: ERP | J18: Weight | K18: Weighted ERP
A19: Approach for estimating pre-tax cost of debt | B19: Synthetic rating | G19: ='Country equity risk premiums'!A191 | H19: 0 | I19: ='Country equity risk premiums'!B191 | J19: =H19/$H$30 | K19: =I19*J19
A20: If direct input, input the pre-tax cost of debt | B20: 0.035 | G20: ='Country equity risk premiums'!A192 | H20: =3159+4281 | I20: ='Country equity risk premiums'!B192 | J20: =H20/$H$30 | K20: =I20*J20
A21: If actual rating, input the rating | B21: Aa2/AA | G21: ='Country equity risk premiums'!A193 | I21: ='Country equity risk premiums'!B193 | J21: =H21/$H$30 | K21: =I21*J21
A22: If synethetic rating, input the type of company | B22: 1 | G22: ='Country equity risk premiums'!A194 | H22: 0 | I22: ='Country equity risk premiums'!B194 | J22: =H22/$H$30 | K22: =I22*J22
A23: Pre-tax Cost of Debt = | B23: =IF(B19="Direct Input",B20,IF(B19="Synthetic Rating",'Synthetic rating'!D13,B10+VLOOKUP('Cost of capital worksheet'!B21,'Synthetic rating'!G39:H53,2))) | G23: ='Country equity risk premiums'!A195 | H23: 0 | I23: ='Country equity risk premiums'!B195 | J23: =H23/$H$30 | K23: =I23*J23
A24: Tax Rate = | B24: ='Input sheet'!B21 | G24: ='Country equity risk premiums'!A196 | I24: ='Country equity risk premiums'!B196 | J24: =H24/$H$30 | K24: =I24*J24
G25: ='Country equity risk premiums'!A197 | H25: 0 | I25: ='Country equity risk premiums'!B197 | J25: =H25/$H$30 | K25: =I25*J25
A26: Book Value of Convertible Debt = | B26: 0 | G26: ='Country equity risk premiums'!A198 | H26: 93864 | I26: ='Country equity risk premiums'!B198 | J26: =H26/$H$30 | K26: =I26*J26
A27: Interest Expense on Convertible = | B27: 0 | G27: ='Country equity risk premiums'!A199 | I27: ='Country equity risk premiums'!B199 | J27: =H27/$H$30 | K27: =I27*J27
A28: Maturity of Convertible Bond = | B28: 0 | J28: =H28/$H$30 | K28: =I28*J28
A29: Market Value of Convertible = | B29: 0 | J29: =H29/$H$30 | K29: =I29*J29
G30: Total | H30: =SUM(H19:H29) | J30: =SUM(J19:J29) | K30: =SUM(K19:K29)
A31: Debt value of operating leases = | B31: =IF('Input sheet'!B14="Yes",'Operating lease converter'!F33,0)
G32: Multi Business (US Industry Averages)
A33: Preferred Stock | G33: Business | H33: Revenues | I33: EV/Sales | J33: Estimated Value | K33: Unlevered Beta
A34: Number of Preferred Shares = | B34: 0 | G34: Advertising | H34: 70 | I34: =IF(G34=0,,VLOOKUP(G34,'Industry Averages(US)'!$A$2:$S$95,15)) | J34: =H34*I34 | K34: =IF(I34=0,0,VLOOKUP(G34,'Industry Averages(US)'!$A$2:$S$95,7))
A35: Current Market Price per Share= | B35: 70 | G35: Computer Services | H35: 30 | I35: =IF(G35=0,,VLOOKUP(G35,'Industry Averages(US)'!$A$2:$S$95,15)) | J35: =H35*I35 | K35: =IF(I35=0,0,VLOOKUP(G35,'Industry Averages(US)'!$A$2:$S$95,7))
A36: Annual Dividend per Share = | B36: 5 | I36: =IF(G36=0,,VLOOKUP(G36,'Industry Averages(US)'!$A$2:$S$95,15)) | J36: =H36*I36 | K36: =IF(I36=0,0,VLOOKUP(G36,'Industry Averages(US)'!$A$2:$S$95,7))
I37: =IF(G37=0,,VLOOKUP(G37,'Industry Averages(US)'!$A$2:$S$95,15)) | J37: =H37*I37 | K37: =IF(I37=0,0,VLOOKUP(G37,'Industry Averages(US)'!$A$2:$S$95,7))
A38: Output | I38: =IF(G38=0,,VLOOKUP(G38,'Industry Averages(US)'!$A$2:$S$95,15)) | J38: =H38*I38 | K38: =IF(I38=0,0,VLOOKUP(G38,'Industry Averages(US)'!$A$2:$S$95,7))
A39: Estimating Market Value of Straight Debt = | C39: =B17*(1-(1+B23)^(-B18))/B23+B16/(1+B23)^B18 | I39: =IF(G39=0,,VLOOKUP(G39,'Industry Averages(US)'!$A$2:$S$95,15)) | J39: =H39*I39 | K39: =IF(I39=0,0,VLOOKUP(G39,'Industry Averages(US)'!$A$2:$S$95,7))
A40: Estimated Value of Straight Debt in Convertible = | C40: =B27*(1-(1+B23)^(-B28))/B23+B26/(1+B23)^B28 | I40: =IF(G40=0,,VLOOKUP(G40,'Industry Averages(US)'!$A$2:$S$95,15)) | J40: =H40*I40 | K40: =IF(I40=0,0,VLOOKUP(G40,'Industry Averages(US)'!$A$2:$S$95,7))
A41: Value of Debt in Operating leases = | C41: =B31 | I41: =IF(G41=0,,VLOOKUP(G41,'Industry Averages(US)'!$A$2:$S$95,15)) | J41: =H41*I41 | K41: =IF(I41=0,0,VLOOKUP(G41,'Industry Averages(US)'!$A$2:$S$95,7))
A42: Estimated Value of Equity in Convertible = | C42: =B29-C40 | I42: =IF(G42=0,,VLOOKUP(G42,'Industry Averages(US)'!$A$2:$S$95,15)) | J42: =H42*I42 | K42: =IF(I42=0,0,VLOOKUP(G42,'Industry Averages(US)'!$A$2:$S$95,7))
A43: Levered Beta for equity = | C43: =IF(B7="Direct Input",B8,B9*(1+(1-B24)*(C46/B46))) | I43: =IF(G43=0,,VLOOKUP(G43,'Industry Averages(US)'!$A$2:$S$95,15)) | J43: =H43*I43 | K43: =IF(I43=0,0,VLOOKUP(G43,'Industry Averages(US)'!$A$2:$S$95,7))
I44: =IF(G44=0,,VLOOKUP(G44,'Industry Averages(US)'!$A$2:$S$95,15)) | J44: =H44*I44 | K44: =IF(I44=0,0,VLOOKUP(G44,'Industry Averages(US)'!$A$2:$S$95,7))
B45: Equity | C45: Debt | D45: Preferred Stock | E45: Capital | I45: =IF(G45=0,,VLOOKUP(G45,'Industry Averages(US)'!$A$2:$S$95,15)) | J45: =H45*I45 | K45: =IF(I45=0,0,VLOOKUP(G45,'Industry Averages(US)'!$A$2:$S$95,7))
A46: Market Value | B46: =B4*B5 | C46: =C39+C40+C41 | D46: =B34*B35 | E46: =SUM(B46:D46) | G46: Company | H46: =SUM(H34:H45) | J46: =SUM(J34:J45) | K46: =K34*(J34/J46)+K35*J35/J46+K36*J36/J46+K37*J37/J46+K38*J38/J46+K39*J39/J46+K40*J40/J46+K41*J41/J46+K42*J42/J46+K43*J43/J46+K44*J44/J46+K45*J45/J46
A47: Weight in Cost of Capital | B47: =B46/$E$46 | C47: =C46/$E$46 | D47: =D46/$E$46 | E47: =SUM(B47:D47)
A48: Cost of Component | B48: =B10+C43*B13 | C48: =B23*(1-B24) | D48: =B36/B35 | E48: =B47*B48+C47*C48+D47*D48 | G48: Multi Business (Global Industry Averages)
G49: Business | H49: Revenues | I49: EV/Sales | J49: Estimated Value | K49: Unlevered Beta
G50: Retail (General) | H50: =108354+5798+31881 | I50: =IF(G50=0,,VLOOKUP(G50,'Global industry averages'!$A$2:$O$95,15)) | J50: =H50*I50 | K50: =IF(G50=0,,VLOOKUP(G50,'Global industry averages'!$A$2:$O$95,7))
G51: Entertainment | H51: =9721 | I51: =IF(G51=0,,VLOOKUP(G51,'Global industry averages'!$A$2:$O$95,15)) | J51: =H51*I51 | K51: =IF(G51=0,,VLOOKUP(G51,'Global industry averages'!$A$2:$O$95,7))
G52: Computer Services | H52: 17459 | I52: =IF(G52=0,,VLOOKUP(G52,'Global industry averages'!$A$2:$O$95,15)) | J52: =H52*I52 | K52: =IF(G52=0,,VLOOKUP(G52,'Global industry averages'!$A$2:$O$95,7))
I53: =IF(G53=0,,VLOOKUP(G53,'Global industry averages'!$A$2:$O$95,15)) | J53: =H53*I53 | K53: =IF(G53=0,,VLOOKUP(G53,'Global industry averages'!$A$2:$O$95,7))
I54: =IF(G54=0,,VLOOKUP(G54,'Global industry averages'!$A$2:$O$95,15)) | J54: =H54*I54 | K54: =IF(G54=0,,VLOOKUP(G54,'Global industry averages'!$A$2:$O$95,7))
I55: =IF(G55=0,,VLOOKUP(G55,'Global industry averages'!$A$2:$O$95,15)) | J55: =H55*I55 | K55: =IF(G55=0,,VLOOKUP(G55,'Global industry averages'!$A$2:$O$95,7))
I56: =IF(G56=0,,VLOOKUP(G56,'Global industry averages'!$A$2:$O$95,15)) | J56: =H56*I56 | K56: =IF(G56=0,,VLOOKUP(G56,'Global industry averages'!$A$2:$O$95,7))
I57: =IF(G57=0,,VLOOKUP(G57,'Global industry averages'!$A$2:$O$95,15)) | J57: =H57*I57 | K57: =IF(G57=0,,VLOOKUP(G57,'Global industry averages'!$A$2:$O$95,7))
I58: =IF(G58=0,,VLOOKUP(G58,'Global industry averages'!$A$2:$O$95,15)) | J58: =H58*I58 | K58: =IF(G58=0,,VLOOKUP(G58,'Global industry averages'!$A$2:$O$95,7))
I59: =IF(G59=0,,VLOOKUP(G59,'Global industry averages'!$A$2:$O$95,15)) | J59: =H59*I59 | K59: =IF(G59=0,,VLOOKUP(G59,'Global industry averages'!$A$2:$O$95,7))
I60: =IF(G60=0,,VLOOKUP(G60,'Global industry averages'!$A$2:$O$95,15)) | J60: =H60*I60 | K60: =IF(G60=0,,VLOOKUP(G60,'Global industry averages'!$A$2:$O$95,7))
I61: =IF(G61=0,,VLOOKUP(G61,'Global industry averages'!$A$2:$O$95,15)) | J61: =H61*I61 | K61: =IF(G61=0,,VLOOKUP(G61,'Global industry averages'!$A$2:$O$95,7))
G62: Company | H62: =SUM(H50:H61) | J62: =SUM(J50:J61) | K62: =K50*(J50/J62)+K51*J51/J62+K52*J52/J62+K53*J53/J62+K54*J54/J62+K55*J55/J62+K56*J56/J62+K57*J57/J62+K58*J58/J62+K59*J59/J62+K60*J60/J62+K61*J61/J62

Sheet Synthetic rating
A1: Inputs for synthetic rating estimation
A2: Please read the special cases worksheet (see below) before you use this spreadsheet.
A3: Before you use this spreadsheet, make sure that the iteration box (under calculation options in excel) is checked.
A4: Enter the type of firm = | C4: ='Cost of capital worksheet'!B22
A5: Enter current Earnings before interest and taxes (EBIT) = | F5: =IF('Input sheet'!B14="Yes",'Input sheet'!B9+'Operating lease converter'!F32,'Input sheet'!B9) | G5: (Add back only long term interest expense for financial firms)
A6: Enter current interest expenses = | F6: =IF('Input sheet'!B14="Yes",'Cost of capital worksheet'!B17+'Operating lease converter'!C28*'Operating lease converter'!C15,'Cost of capital worksheet'!B17) | G6: (Use only long term interest expense for financial firms)
A7: Enter long term risk free rate = | F7: ='Input sheet'!B28
A8: Output
A9: Interest coverage ratio = | D9: =IF(F6=0,1000000,IF(F5<0,-100000,F5/F6))
A10: Estimated Bond Rating = | D10: =IF(C4=1,VLOOKUP(D9,A19:D33,3),(IF(C4=2,VLOOKUP(D9,A38:D52,3),VLOOKUP(D9,F19:I33,3)))) | F10: Note: If you get REF! All over the place, set the operating lease commitment question in cell F5
A11: Estimated Company Default Spread = | D11: =IF(C4=1,VLOOKUP(D9,A19:D33,4),(IF(C4=2,VLOOKUP(D9,A38:D52,4),VLOOKUP(D9,F19:I33,4)))) | F11: to No, and then reset it to Yes. It should work.
A12: Estimated County Default Spread (if any) = | D12: =VLOOKUP('Input sheet'!B5,'Country equity risk premiums'!A2:C187,3)
A13: Estimated Cost of Debt = | D13: =F7+D11+D12
A15: If you want to update the spreads listed below, please visit http://www.bondsonline.com
A16: For large manufacturing firms
A17: If interest coverage ratio is
A18: > | B18: ≤ to | C18: Rating is | D18: Spread is
A19: -100000 | B19: 0.199999 | C19: D2/D | D19: 0.186
A20: 0.2 | B20: 0.649999 | C20: Caa/CCC | D20: 0.1395
A21: 0.65 | B21: 0.799999 | C21: Ca2/CC | D21: 0.1063
A22: 0.8 | B22: 1.249999 | C22: C2/C | D22: 0.0864
A23: 1.25 | B23: 1.499999 | C23: B3/B- | D23: 0.0437
A24: 1.5 | B24: 1.749999 | C24: B2/B | D24: 0.0357
A25: 1.75 | B25: 1.999999 | C25: B1/B+ | D25: 0.0298
A26: 2 | B26: 2.2499999 | C26: Ba2/BB | D26: 0.0238
A27: 2.25 | B27: 2.49999 | C27: Ba1/BB+ | D27: 0.0198
A28: 2.5 | B28: 2.999999 | C28: Baa2/BBB | D28: 0.0127
A29: 3 | B29: 4.249999 | C29: A3/A- | D29: 0.0113
A30: 4.25 | B30: 5.499999 | C30: A2/A | D30: 0.0099
... A33: 8.5 | B33: 100000 | C33: Aaa/AAA | D33: 0.0054
A35: For smaller and riskier firms
A36: If interest coverage ratio is
A37: greater than | B37: ≤ to | C37: Rating is | D37: Spread is
A38: -100000 | B38: 0.499999 | C38: D2/D | D38: 0.186 | G38: Rating is | H38: Spread is
A39: 0.5 | B39: 0.799999 | C39: Caa/CCC | D39: 0.1395 | G39: A1/A+ | H39: 0.01
A40: 0.8 | B40: 1.249999 | C40: Ca2/CC | D40: 0.1063 | G40: A2/A | H40: 0.011
A41: 1.25 | B41: 1.499999 | C41: C2/C | D41: 0.0864 | G41: A3/A- | H41: 0.0125
A42: 1.5 | B42: 1.999999 | C42: B3/B- | D42: 0.0437 | G42: Aa2/AA | H42: 0.008
A43: 2 | B43: 2.499999 | C43: B2/B | D43: 0.0357 | G43: Aaa/AAA | H43: 0.006
A44: 2.5 | B44: 2.999999 | C44: B1/B+ | D44: 0.0298 | G44: B1/B+ | H44: 0.0375
A45: 3 | B45: 3.499999 | C45: Ba2/BB | D45: 0.0238 | G45: B2/B | H45: 0.045
A46: 3.5 | B46: 3.9999999 | C46: Ba1/BB+ | D46: 0.0198 | G46: B3/B- | H46: 0.055
A47: 4 | B47: 4.499999 | C47: Baa2/BBB | D47: 0.0127 | G47: Ba1/BB+ | H47: 0.025
A48: 4.5 | B48: 5.999999 | C48: A3/A- | D48: 0.0113 | G48: Ba2/BB | H48: 0.03
A49: 6 | B49: 7.499999 | C49: A2/A | D49: 0.0099 | G49: Baa2/BBB | H49: 0.016
A50: 7.5 | B50: 9.499999 | C50: A1/A+ | D50: 0.009 | G50: C2/C | H50: 0.105
... A52: 12.5 | B52: 100000 | C52: Aaa/AAA | D52: 0.0054 | G52: Caa/CCC | H52: 0.065
G53: D2/D | H53: 0.14

Sheet Industry Averages(US)
A1: Industry Name | B1: Number of firms | C1: Annual Average Revenue growth - Last 5 years | D1: Pre-tax Operating Margin (Lease & R&D adjusted) | E1: After-tax ROC | F1: Average effective tax rate | G1: Unlevered Beta | H1: Equity (Levered) Beta | I1: Cost of equity | J1: Std deviation in stock prices | K1: Pre-tax cost of debt | L1: Market Debt/Capital | M1: Cost of capital | N1: Sales/Capital | O1: EV/Sales | P1: EV/EBITDA | Q1: EV/EBIT | R1: Price/Book | S1: Trailing PE | T1: Non-cash WC as % of Revenues | U1: Cap Ex as % of Revenues | V1: Net Cap Ex as % of Revenues | W1: Reinvestment Rate | X1: ROE | Y1: Dividend Payout Ratio | Z1: Equity Reinvestment Rate
A2: Advertising | B2: 40 | C2: 0.11766353 | D2: 0.12408515 | E2: 0.77565051 | F2: 0.30392514 | G2: 0.78427897 | H2: 1.1535561 | I2: 0.082700651 | J2: 0.80950932 | K2: 0.0691 | L2: 0.42486145 | M2: 0.069876357 | N2: 6.6765069 | O2: 1.6638697 | P2: 8.3505373 | Q2: 13.149476 | R2: 9.1587623 | S2: 57.180661 | T2: -0.016538856 | U2: 0.023229015 | V2: -0.0026332734 | W2: 0.21519056 | X2: -0.0087986452 | Y2: 0.52845904 | Z2: 0.52845904
A3: Aerospace/Defense | B3: 87 | C3: 0.033537083 | D3: 0.11626118 | E3: 0.37051124 | F3: 0.29150382 | G3: 0.99233232 | H3: 1.082606 | I3: 0.079096385 | J3: 0.49061635 | K3: 0.0391 | L3: 0.15583595 | M3: 0.071401146 | N3: 3.6123522 | O3: 2.0885532 | P3: 13.962257 | Q3: 17.674829 | R3: 6.4263146 | S3: 29.341971 | T3: 0.27710404 | U3: 0.027124933 | V3: 0.020827228 | W3: 0.4016893 | X3: 0.29028585 | Y3: 0.39516823 | Z3: 0.39516823
A4: Air Transport | B4: 17 | C4: 0.0619875 | D4: 0.12840331 | E4: 0.13501065 | F4: 0.37149945 | G4: 0.67328042 | H4: 1.0088835 | I4: 0.075351282 | J4: 0.40200793 | K4: 0.0391 | L4: 0.41520146 | M4: 0.056403446 | N4: 1.3939105 | O4: 1.5580208 | P4: 6.5646386 | Q4: 12.135671 | R4: 3.0618413 | S4: 14.101198 | T4: 0.011868605 | U4: 0.12557975 | V4: 0.08566834 | W4: 1.0167244 | X4: 0.24781682 | Y4: 0.15274743 | Z4: 0.15274743
A5: Apparel | B5: 51 | C5: 0.20665733 | D5: 0.10975583 | E5: 0.14180982 | F5: 0.18584589 | G5: 0.85095727 | H5: 1.0167737 | I5: 0.075752103 | J5: 0.59710824 | K5: 0.0391 | L5: 0.25475946 | M5: 0.064023971 | N5: 1.4407435 | O5: 1.9882822 | P5: 10.973313 | Q5: 17.903533 | R5: 3.5814118 | S5: 34.875996 | T5: 0.2575637 | U5: 0.027043898 | V5: 0.059398572 | W5: 0.61793361 | X5: 0.076234161 | Y5: 0.77532499 | Z5: 0.77532499
A6: Auto & Truck | B6: 18 | C6: 0.22605429 | D6: 0.042080382 | E6: 0.039691311 | F6: 0.27715583 | G6: 0.592262 | H6: 1.1974171 | I6: 0.084928787 | J6: 0.38590283 | K6: 0.0361 | L6: 0.59691746 | M6: 0.050610338 | N6: 1.0215641 | O6: 1.2216369 | P6: 10.615768 | Q6: 30.818883 | R6: 2.0540407 | S6: 17.293466 | T6: -0.020621804 | U6: 0.1169276 | V6: 0.04639462 | W6: 1.4732719 | X6: 0.086358259 | Y6: 0.69488543 | Z6: 0.69488543
A7: Auto Parts | B7: 62 | C7: 0.076424828 | D7: 0.09548248 | E7: 0.23785516 | F7: 0.20110399 | G7: 0.92004456 | H7: 1.0375354 | I7: 0.0768068 | J7: 0.56736904 | K7: 0.0391 | L7: 0.2205866 | M7: 0.066419201 | N7: 2.6880898 | O7: 0.97880002 | P7: 7.5875088 | Q7: 10.690393 | R7: 2.9184201 | S7: 20.029194 | T7: 0.11202404 | U7: 0.045380817 | V7: 0.073866428 | W7: 1.03792 | X7: 0.24139027 | Y7: 0.13853703 | Z7: 0.13853703
A8: Bank (Money Center) | B8: 11 | C8: 0.052188889 | D8: -0.00068663456 | E8: -6.7827396e-05 | F8: 0.28353699 | G8: 0.32250416 | H8: 0.63754545 | I8: 0.056487309 | J8: 0.3337467 | K8: 0.0361 | L8: 0.61128398 | M8: 0.038728709 | N8: 0.13589982 | O8: 8.4502109 | P8: NA | Q8: NA | R8: 1.2438299 | S8: 15.755901 | T8: NA | U8: 0.009147247 | V8: 0.011484866 | W8: NA | X8: 0.099329692 | Y8: 0.24572802 | Z8: 0.24572802
A9: Banks (Regional) | B9: 612 | C9: 0.089641978 | D9: -0.0016135432 | E9: -0.00031426511 | F9: 0.2930678 | G9: 0.38572641 | H9: 0.50171127 | I9: 0.049586932 | J9: 0.32075657 | K9: 0.0361 | L9: 0.36978252 | M9: 0.041395905 | N9: 0.26166276 | O9: 6.2700837 | P9: NA | Q9: NA | R9: 1.5005733 | S9: 23.14689 | T9: NA | U9: 0.044406694 | V9: 0.04757999 | W9: NA | X9: 0.090282785 | Y9: 0.3091185 | Z9: 0.3091185
A10: Beverage (Alcoholic) | B10: 28 | C10: 0.11327273 | D10: 0.23414123 | E10: 0.24322235 | F10: 0.30015704 | G10: 1.1198147 | H10: 1.3261962 | I10: 0.091470766 | J10: 0.50136995 | K10: 0.0391 | L10: 0.20726073 | M10: 0.078671428 | N10: 1.1557147 | O10: 5.0480833 | P10: 17.261492 | Q10: 21.546072 | R10: 4.0050641 | S10: 49.288945 | T10: 0.16509674 | U10: 0.082720791 | V10: 0.67316789 | W10: 3.984283 | X10: 0.25156411 | Y10: 0.20374757 | Z10: 0.20374757
A11: Beverage (Soft) | B11: 35 | C11: 0.094812143 | D11: 0.19326807 | E11: 0.24915365 | F11: 0.26194011 | G11: 0.62680558 | H11: 0.70379615 | I11: 0.059852844 | J11: 0.45334168 | K11: 0.0391 | L11: 0.18739523 | M11: 0.054205343 | N11: 1.3774551 | O11: 4.2021129 | P11: 17.924877 | Q11: 21.727845 | R11: 9.9509384 | S11: 39.43773 | T11: -0.034454493 | U11: 0.046023651 | V11: 0.051108697 | W11: 0.41268111 | X11: 0.28388873 | Y11: 0.84899312 | Z11: 0.84899312
A12: Broadcasting | B12: 27 | C12: 0.081164286 | D12: 0.23454273 | E12: 0.21378655 | F12: 0.2858275 | G12: 0.65097821 | H12: 1.1196445 | I12: 0.08097794 | J12: 0.52300832 | K12: 0.0391 | L12: 0.52868829 | M12: 0.053876353 | N12: 1.1005046 | O12: 2.8336461 | P12: 9.1853991 | Q12: 12.081861 | R12: 7.3378902 | S12: 27.840394 | T12: 0.22956184 | U12: 0.026785462 | V12: 0.054938112 | W12: 0.43574185 | X12: 0.18105355 | Y12: 0.40584288 | Z12: 0.40584288
A13: Brokerage & Investment Banking | B13: 42 | C13: 0.078212609 | D13: 0.0010986436 | E13: 0.00018221573 | F13: 0.28540771 | G13: 0.54417467 | H13: 1.2379533 | I13: 0.086988028 | J13: 0.42480671 | K13: 0.0391 | L13: 0.68742549 | M13: 0.047617776 | N13: 0.19332465 | O13: 6.7457728 | P13: NA | Q13: NA | R13: 1.5583717 | S13: 47.562089 | T13: NA | U13: 0.04081499 | V13: 0.062576786 | W13: 453.97063 | X13: 0.11412665 | Y13: 0.20625382 | Z13: 0.20625382
A14: Building Materials | B14: 39 | C14: 0.12734107 | D14: 0.10326168 | E14: 0.18274341 | F14: 0.30032001 | G14: 0.98593417 | H14: 1.1089115 | I14: 0.080432706 | J14: 0.41014736 | K14: 0.0391 | L14: 0.17666856 | M14: 0.071472659 | N14: 2.3076896 | O14: 1.7781238 | P14: 12.797715 | Q14: 17.224678 | R14: 4.7670485 | S14: 26.552312 | T14: 0.15598884 | U14: 0.029032456 | V14: 0.030570522 | W14: 0.54485796 | X14: 0.23812242 | Y14: 0.15291339 | Z14: 0.15291339
A15: Business & Consumer Services | B15: 169 | C15: 0.051456849 | D15: 0.10525275 | E15: 0.26366136 | F15: 0.30962182 | G15: 1.0067304 | H15: 1.1687212 | I15: 0.083471035 | J15: 0.49449375 | K15: 0.0391 | L15: 0.21529718 | M15: 0.071897728 | N15: 2.8163257 | O15: 1.9431738 | P15: 12.400481 | Q15: 18.292236 | R15: 4.9491192 | S15: 51.595932 | T15: 0.16322114 | U15: 0.024867815 | V15: 0.034798925 | W15: 0.64086754 | X15: 0.1831593 | Y15: 0.2633303 | Z15: 0.2633303
A16: Cable TV | B16: 14 | C16: 0.11788125 | D16: 0.18246762 | E16: 0.12722064 | F16: 0.33563872 | G16: 0.66746834 | H16: 0.9209032 | I16: 0.070881883 | J16: 0.36325755 | K16: 0.0361 | L16: 0.34662154 | M16: 0.055822604 | N16: 0.89651645 | O16: 3.4373538 | P16: 9.6808597 | Q16: 18.262457 | R16: 2.8042665 | S16: 111.31451 | T16: -0.011222086 | U16: 0.12305375 | V16: -0.023988045 | W16: -0.21328263 | X16: 0.11054787 | Y16: 0.33212023 | Z16: 0.33212023
A17: Chemical (Basic) | B17: 38 | C17: 0.016253333 | D17: 0.10936001 | E17: 0.14431255 | F17: 0.23556839 | G17: 0.96489989 | H17: 1.1976211 | I17: 0.084939149 | J17: 0.59390184 | K17: 0.0391 | L17: 0.2921627 | M17: 0.068805005 | N17: 1.4619566 | O17: 1.7593938 | P17: 9.6669982 | Q17: 16.062965 | R17: 3.4676332 | S17: 38.304548 | T17: 0.20269614 | U17: 0.054937422 | V17: 0.031258405 | W17: 0.47816613 | X17: 0.18602096 | Y17: 0.27287812 | Z17: 0.27287812
A18: Chemical (Diversified) | B18: 7 | C18: -0.02543 | D18: 0.12242868 | E18: 0.165906 | F18: 0.22257157 | G18: 1.794686 | H18: 2.033952 | I18: 0.12742476 | J18: 0.68622838 | K18: 0.0466 | L18: 0.21374721 | M18: 0.10775815 | N18: 1.5304583 | O18: 2.899391 | P18: 15.832288 | Q18: 24.092802 | R18: 1.7377402 | S18: 30.215487 | T18: 0.34354391 | U18: 0.059958213 | V18: -0.012108457 | W18: -0.014461805 | X18: 0.14201117 | Y18: 0.58061389 | Z18: 0.58061389
A19: Chemical (Specialty) | B19: 99 | C19: 0.014687059 | D19: 0.13556745 | E19: 0.1674006 | F19: 0.2286681 | G19: 0.94849956 | H19: 1.1145863 | I19: 0.080720984 | J19: 0.59686773 | K19: 0.0391 | L19: 0.22482999 | M19: 0.069253534 | N19: 1.3659769 | O19: 2.7905594 | P19: 13.893471 | Q19: 20.59583 | R19: 4.1536923 | S19: 165.87771 | T19: 0.21485868 | U19: 0.050428111 | V19: 0.10439771 | W19: 1.058397 | X19: 0.16995624 | Y19: 0.39785274 | Z19: 0.39785274
A20: Coal & Related Energy | B20: 30 | C20: -0.040905714 | D20: 0.087114766 | E20: 0.085314376 | F20: 0.048345834 | G20: 1.0423911 | H20: 1.248786 | I20: 0.087538329 | J20: 0.90614735 | K20: 0.0816 | L20: 0.31231195 | M20: 0.079567401 | N20: 1.0312085 | O20: 1.0124232 | P20: 3.9282909 | Q20: 9.2366476 | R20: 2.0262335 | S20: 1276.0219 | T20: 0.04344611 | U20: 0.032597547 | V20: -0.064574555 | W20: -0.49883541 | X20: -6.4638687 | Y20: 0.15728551 | Z20: 0.15728551
A21: Computer Services | B21: 111 | C21: 0.15305093 | D21: 0.083480737 | E21: 0.27960738 | F21: 0.14346588 | G21: 0.94403177 | H21: 1.1013092 | I21: 0.08004651 | J21: 0.48530569 | K21: 0.0391 | L21: 0.23565212 | M21: 0.068186018 | N21: 3.6946039 | O21: 1.3377809 | P21: 11.099666 | Q21: 16.092621 | R21: 4.0372569 | S21: 40.329457 | T21: 0.12648663 | U21: 0.019687815 | V21: 0.01440334 | W21: 0.22996248 | X21: 0.28662241 | Y21: 0.38552173 | Z21: 0.38552173
A22: Computers/Peripherals | B22: 58 | C22: -0.026733333 | D22: 0.20009081 | E22: 0.23859785 | F22: 0.2400921 | G22: 0.92832563 | H22: 1.0096551 | I22: 0.075390478 | J22: 0.61378483 | K22: 0.0391 | L22: 0.15375451 | M22: 0.068367821 | N22: 1.2548328 | O22: 3.0332971 | P22: 12.011415 | Q22: 15.232652 | R22: 5.4205301 | S22: 108.61448 | T22: -0.026207138 | U22: 0.046883851 | V22: 0.019926098 | W22: 0.030424577 | X22: 0.28549481 | Y22: 0.28943953 | Z22: 0.28943953
A23: Construction Supplies | B23: 49 | C23: 0.069450294 | D23: 0.0961771 | E23: 0.10588151 | F23: 0.30820513 | G23: 0.95257769 | H23: 1.1206966 | I23: 0.081031386 | J23: 0.45667986 | K23: 0.0391 | L23: 0.24509215 | M23: 0.068454387 | N23: 1.3322953 | O23: 2.1425436 | P23: 14.508544 | Q23: 22.182858 | R23: 4.2103763 | S23: 41.997047 | T23: 0.15832179 | U23: 0.055692687 | V23: 0.035426738 | W23: 0.67824625 | X23: 0.13232904 | Y23: 0.57629202 | Z23: 0.57629202
A24: Diversified | B24: 24 | C24: 0.028673333 | D24: 0.13006937 | E24: 0.10977638 | F24: 0.24049249 | G24: 1.013544 | H24: 1.1944711 | I24: 0.08477913 | J24: 0.26823043 | K24: 0.0361 | L24: 0.24520856 | M24: 0.070718104 | N24: 0.95944435 | O24: 2.6230194 | P24: 14.685698 | Q24: 20.256102 | R24: 2.0356364 | S24: 25.95998 | T24: 0.14412883 | U24: 0.048417405 | V24: 0.038843876 | W24: 0.4167483 | X24: 0.095888757 | Y24: 0.35252719 | Z24: 0.35252719
A25: Drugs (Biotechnology) | B25: 459 | C25: 0.32284352 | D25: 0.26170414 | E25: 0.11597452 | F25: 0.20664395 | G25: 1.3565309 | H25: 1.4397417 | I25: 0.09723888 | J25: 0.94780627 | K25: 0.0816 | L25: 0.13668677 | M25: 0.092424378 | N25: 0.44897852 | O25: 7.6978721 | P25: 13.051547 | Q25: 24.218972 | R25: 6.2006091 | S25: 69.610535 | T25: 0.14849926 | U25: 0.039386459 | V25: 0.009900259 | W25: 0.098279408 | X25: 0.13445969 | Y25: 0.60255149 | Z25: 0.60255149
... A28: Electrical Equipment | B28: 118 | C28: -0.021368163 | D28: 0.11995039 | E28: 0.21883658 | F28: 0.27798585 | G28: 1.0244696 | H28: 1.0848479 | I28: 0.079210274 | J28: 0.66165257 | K28: 0.0466 | L28: 0.13683395 | M28: 0.073217731 | N28: 1.9207529 | O28: 2.4784693 | P28: 13.977399 | Q28: 19.890726 | R28: 4.3053059 | S28: 23.652056 | T28: 0.19901991 | U28: 0.044312859 | V28: 0.085824036 | W28: 1.0231421 | X28: 0.13542022 | Y28: 0.57587013 | Z28: 0.57587013
A29: Electronics (Consumer & Office) | B29: 24 | C29: -0.00488 | D29: -0.041745545 | E29: -0.055411197 | F29: 0.32278798 | G29: 1.0791544 | H29: 1.0923848 | I29: 0.079593146 | J29: 0.70222244 | K29: 0.0466 | L29: 0.064905326 | M29: 0.076725814 | N29: 1.3944308 | O29: 2.5201706 | P29: 17.172528 | Q29: NA | R29: 7.9107649 | S29: 79.937559 | T29: 0.1975546 | U29: 0.031422358 | V29: -0.0012532992 | W29: NA | X29: -0.2960347 | Y29: 0.0017780749 | Z29: 0.0017780749
A30: Electronics (General) | B30: 167 | C30: 0.068428559 | D30: 0.09809808 | E30: 0.13552539 | F30: 0.25985154 | G30: 0.91332212 | H30: 0.93790062 | I30: 0.071745352 | J30: 0.60247419 | K30: 0.0391 | L30: 0.13021822 | M30: 0.066272364 | N30: 1.502664 | O30: 2.1188319 | P30: 13.163295 | Q30: 21.93201 | R30: 3.0440889 | S30: 182.29978 | T30: 0.18576293 | U30: 0.0469788 | V30: 0.077241952 | W30: 1.2201645 | X30: 0.11298555 | Y30: 0.20224852 | Z30: 0.20224852
A31: Engineering/Construction | B31: 49 | C31: 0.096434333 | D31: 0.042794154 | E31: 0.18434869 | F31: 0.30555208 | G31: 1.1280527 | H31: 1.270317 | I31: 0.088632102 | J31: 0.53019913 | K31: 0.0391 | L31: 0.2290832 | M31: 0.075135413 | N31: 4.9740445 | O31: 0.69480009 | P31: 9.9208191 | Q31: 16.11336 | R31: 2.07738 | S31: 33.839981 | T31: 0.15065427 | U31: 0.016176327 | V31: 0.013082673 | W31: 0.61052349 | X31: 0.077080741 | Y31: 0.16894439 | Z31: 0.16894439
A32: Entertainment | B32: 90 | C32: 0.033348636 | D32: 0.20721251 | E32: 0.3110816 | F32: 0.29214109 | G32: 0.95716683 | H32: 1.1517724 | I32: 0.082610039 | J32: 0.54936934 | K32: 0.0391 | L32: 0.25228095 | M32: 0.06926588 | N32: 1.5877529 | O32: 2.8738858 | P32: 10.584347 | Q32: 13.807929 | R32: 3.0506231 | S32: 70.065609 | T32: 0.10586516 | U32: 0.04343329 | V32: 0.042730804 | W32: 0.85177455 | X32: 0.18985279 | Y32: 0.29810125 | Z32: 0.29810125
A33: Environmental & Waste Services | B33: 87 | C33: 0.15919613 | D33: 0.12538693 | E33: 0.21281667 | F33: 0.35708021 | G33: 0.69977482 | H33: 0.87699722 | I33: 0.068651459 | J33: 0.65736793 | K33: 0.0466 | L33: 0.25853847 | M33: 0.060058814 | N33: 1.7763237 | O33: 2.6252537 | P33: 11.833229 | Q33: 20.798909 | R33: 4.0984723 | S33: 132.15099 | T33: 0.10128195 | U33: 0.070820022 | V33: 0.023358351 | W33: 0.28487948 | X33: 0.094698445 | Y33: 0.71145395 | Z33: 0.71145395
A34: Farming/Agriculture | B34: 34 | C34: 0.13077176 | D34: 0.04501038 | E34: 0.071386552 | F34: 0.27685178 | G34: 0.55737082 | H34: 0.74491013 | I34: 0.061941435 | J34: 0.4256799 | K34: 0.0391 | L34: 0.35706003 | M34: 0.05043502 | N34: 1.7179416 | O34: 1.0199035 | P34: 13.8183 | Q34: 22.601545 | R34: 2.4208635 | S34: 23.276807 | T34: 0.10285891 | U34: 0.033244731 | V34: 0.023777334 | W34: 1.0696274 | X34: 0.1209508 | Y34: 0.40751986 | Z34: 0.40751986
A35: Financial Svcs. (Non-bank & Insurance) | B35: 264 | C35: 0.10352006 | D35: 0.073867873 | E35: 0.0020540101 | F35: 0.33105596 | G35: 0.07028908 | H35: 0.60687177 | I35: 0.054929086 | J35: 0.36633352 | K35: 0.0361 | L35: 0.91167542 | M35: 0.029864315 | N35: 0.034589818 | O35: 31.180551 | P35: NA | Q35: NA | R35: 2.2045008 | S35: 31.991934 | T35: NA | U35: 0.071181358 | V35: 0.11691986 | W35: 2.1631272 | X35: -0.0028691188 | Y35: 0.1529496 | Z35: 0.1529496
A36: Food Processing | B36: 87 | C36: 0.041166429 | D36: 0.142114 | E36: 0.19710222 | F36: 0.28578164 | G36: 0.55631902 | H36: 0.67576568 | I36: 0.058428897 | J36: 0.41184293 | K36: 0.0391 | L36: 0.23557441 | M36: 0.051664873 | N36: 1.6341833 | O36: 2.4165275 | P36: 13.379213 | Q36: 16.915703 | R36: 2.8778619 | S36: 100.84708 | T36: 0.073180421 | U36: 0.036791625 | V36: 0.069987015 | W36: 0.68649983 | X36: 0.11540232 | Y36: 0.58833931 | Z36: 0.58833931
A37: Food Wholesalers | B37: 15 | C37: 0.08865 | D37: 0.029779207 | E37: 0.1996332 | F37: 0.33715279 | G37: 1.4147585 | H37: 1.7856129 | I37: 0.11480914 | J37: 0.55419287 | K37: 0.0391 | L37: 0.27251059 | M37: 0.091620356 | N37: 7.6101447 | O37: 0.5292923 | P37: 11.625092 | Q37: 17.757236 | R37: 4.9959001 | S37: 25.876544 | T37: 0.064230469 | U37: 0.011011693 | V37: 0.0042873032 | W37: 0.3520739 | X37: 0.16644472 | Y37: 0.46220798 | Z37: 0.46220798
A38: Furn/Home Furnishings | B38: 31 | C38: 0.099548 | D38: 0.094798903 | E38: 0.17560866 | F38: 0.23323141 | G38: 0.67368657 | H38: 0.79009286 | I38: 0.064236717 | J38: 0.51258555 | K38: 0.0391 | L38: 0.21791684 | M38: 0.056714071 | N38: 2.1166071 | O38: 1.4095205 | P38: 10.376679 | Q38: 14.894159 | R38: 2.9801264 | S38: 90.857391 | T38: 0.1287084 | U38: 0.04215871 | V38: 0.036439922 | W38: 0.59896225 | X38: 0.1761982 | Y38: 0.23269695 | Z38: 0.23269695
A39: Green & Renewable Energy | B39: 22 | C39: -0.04735 | D39: 0.11730528 | E39: 0.019364212 | F39: 0.18073548 | G39: 0.72015965 | H39: 1.2016165 | I39: 0.08514212 | J39: 0.60288075 | K39: 0.0391 | L39: 0.49552829 | M39: 0.057676909 | N39: 0.16916645 | O39: 8.4015473 | P39: 15.129489 | Q39: 69.091053 | R39: 1.2079388 | S39: 192.48759 | T39: 0.096719334 | U39: 0.18674926 | V39: 0.13072925 | W39: 1.6079035 | X39: 0.0065591137 | Y39: 7.356862 | Z39: 7.356862
A40: Healthcare Products | B40: 251 | C40: 0.10539388 | D40: 0.15982684 | E40: 0.16298502 | F40: 0.15835806 | G40: 0.88508347 | H40: 0.94128674 | I40: 0.071917366 | J40: 0.66920738 | K40: 0.0466 | L40: 0.14590611 | M40: 0.066591594 | N40: 1.0688797 | O40: 4.7925885 | P40: 18.965463 | Q40: 30.350965 | R40: 4.0441064 | S40: 91.798885 | T40: 0.22925003 | U40: 0.047494364 | V40: 0.16309959 | W40: 1.3058968 | X40: 0.095091155 | Y40: 0.3691474 | Z40: 0.3691474
A41: Healthcare Support Services | B41: 115 | C41: 0.16545429 | D41: 0.046698396 | E41: 0.50539654 | F41: 0.31920641 | G41: 0.82382035 | H41: 0.89753851 | I41: 0.069694956 | J41: 0.57442505 | K41: 0.0391 | L41: 0.19889333 | M41: 0.061743408 | N41: 12.543451 | O41: 0.62400188 | P41: 10.719757 | Q41: 13.273015 | R41: 3.1946219 | S41: 41.189689 | T41: -0.061509763 | U41: 0.0069979055 | V41: 0.014545809 | W41: 0.55966593 | X41: 0.17400256 | Y41: 0.18636773 | Z41: 0.18636773
A42: Heathcare Information and Technology | B42: 112 | C42: 0.066784118 | D42: 0.14339763 | E42: 0.15732767 | F42: 0.1754741 | G42: 0.88370801 | H42: 0.97915624 | I42: 0.073841137 | J42: 0.58636122 | K42: 0.0391 | L42: 0.16174197 | M42: 0.06670425 | N42: 1.163768 | O42: 4.9468644 | P42: 20.511045 | Q42: 35.153541 | R42: 4.0486422 | S42: 69.026288 | T42: 0.23130937 | U42: 0.042274508 | V42: 0.12093859 | W42: 1.2166591 | X42: 0.10795782 | Y42: 0.09318579 | Z42: 0.09318579
A43: Homebuilding | B43: 32 | C43: 0.22908571 | D43: 0.10106891 | E43: 0.093081965 | F43: 0.33619497 | G43: 0.89482816 | H43: 1.1083665 | I43: 0.080405016 | J43: 0.44699654 | K43: 0.0391 | L43: 0.2839287 | M43: 0.066012949 | N43: 1.2095705 | O43: 1.4887747 | P43: 13.781556 | Q43: 14.720094 | R43: 2.0655773 | S43: 24.372311 | T43: 0.78804785 | U43: 0.0052834794 | V43: 0.013483112 | W43: 0.70681499 | X43: 0.12485575 | Y43: 0.08355432 | Z43: 0.08355432
A44: Hospitals/Healthcare Facilities | B44: 35 | C44: 0.0818755 | D44: 0.088087688 | E44: 0.11836938 | F44: 0.31059733 | G44: 0.51228544 | H44: 1.1785352 | I44: 0.083969588 | J44: 0.60628194 | K44: 0.0391 | L44: 0.63835382 | M44: 0.049336603 | N44: 1.5026057 | O44: 1.3236785 | P44: 8.2376182 | Q44: 14.973507 | R44: 3.81796 | S44: 19.772562 | T44: 0.12327429 | U44: 0.051007628 | V44: 0.025638742 | W44: 1.1041297 | X44: 0.082109099 | Y44: 0.24140641 | Z44: 0.24140641
A45: Hotel/Gaming | B45: 70 | C45: 0.078601951 | D45: 0.19589531 | E45: 0.11330146 | F45: 0.20303232 | G45: 0.74415946 | H45: 0.93865277 | I45: 0.071783561 | J45: 0.45513832 | K45: 0.0391 | L45: 0.28523666 | M45: 0.05978435 | N45: 0.67261691 | O45: 4.1531114 | P45: 13.365907 | Q45: 21.099932 | R45: 4.5102396 | S45: 54.561463 | T45: -0.01446804 | U45: 0.085059692 | V45: 0.01429466 | W45: 0.09412295 | X45: 0.12942558 | Y45: 0.63063727 | Z45: 0.63063727
A46: Household Products | B46: 131 | C46: 0.073411091 | D46: 0.18298293 | E46: 0.29517901 | F46: 0.25471792 | G46: 0.87926933 | H46: 0.996213 | I46: 0.07470762 | J46: 0.56296915 | K46: 0.0391 | L46: 0.17374447 | M46: 0.066890575 | N46: 1.740794 | O46: 3.2987169 | P46: 14.188402 | Q46: 18.038864 | R46: 5.0945435 | S46: 48.589875 | T46: 0.10464759 | U46: 0.044214397 | V46: 0.037366099 | W46: 0.28080267 | X46: 0.2925373 | Y46: 0.4961505 | Z46: 0.4961505
A47: Information Services | B47: 61 | C47: 0.069383846 | D47: 0.25403076 | E47: 0.33510939 | F47: 0.32555267 | G47: 0.82102604 | H47: 0.88160296 | I47: 0.068885431 | J47: 0.41348623 | K47: 0.0391 | L47: 0.13575475 | M47: 0.063567994 | N47: 1.567618 | O47: 6.0330412 | P47: 18.741071 | Q47: 23.457131 | R47: 7.6315684 | S47: 34.305331 | T47: -0.051458973 | U47: 0.032661635 | V47: 0.011075998 | W47: 0.13569632 | X47: 0.20909125 | Y47: 0.2725727 | Z47: 0.2725727
... A50: Insurance (Prop/Cas.) | B50: 50 | C50: 0.068166829 | D50: 0.092964764 | E50: 0.08321458 | F50: 0.28290693 | G50: 0.72774299 | H50: 0.83840033 | I50: 0.066690737 | J50: 0.34652799 | K50: 0.0361 | L50: 0.20902503 | M50: 0.058485514 | N50: 1.0983336 | O50: 1.5215393 | P50: 11.913079 | Q50: 15.355944 | R50: 1.6981079 | S50: 49.68774 | T50: -0.36666228 | U50: 0.0086098316 | V50: 0.005722111 | W50: 0.16365715 | X50: 0.072896982 | Y50: 0.42648134 | Z50: 0.42648134
A51: Investments & Asset Management | B51: 165 | C51: 0.078606316 | D51: 0.19979115 | E51: 0.098879893 | F51: 0.24209612 | G51: 0.86690938 | H51: 0.98742883 | I51: 0.074261384 | J51: 0.40996093 | K51: 0.0391 | L51: 0.29616694 | M51: 0.061068514 | N51: 0.53963057 | O51: 4.9637962 | P51: 21.41869 | Q51: 24.314162 | R51: 2.1193805 | S51: 158.40592 | T51: NA | U51: 0.031099148 | V51: 0.035739012 | W51: 0.36901569 | X51: 0.1375442 | Y51: 0.36325454 | Z51: 0.36325454
A52: Machinery | B52: 126 | C52: 0.018409494 | D52: 0.13681817 | E52: 0.25888143 | F52: 0.26161361 | G52: 1.0376808 | H52: 1.1493211 | I52: 0.082485513 | J52: 0.4317096 | K52: 0.0391 | L52: 0.16489704 | M52: 0.073783976 | N52: 2.1994667 | O52: 2.6543183 | P52: 14.8484 | Q52: 19.489632 | R52: 4.4945297 | S52: 32.743346 | T52: 0.22983739 | U52: 0.02673809 | V52: 0.10378821 | W52: 1.1247558 | X52: 0.19082547 | Y52: 0.30098344 | Z52: 0.30098344
A53: Metals & Mining | B53: 102 | C53: 0.14721846 | D53: 0.17929902 | E53: 0.1434493 | F53: 0.42304589 | G53: 0.96016218 | H53: 1.1032091 | I53: 0.080143024 | J53: 0.8232808 | K53: 0.0691 | L53: 0.23394949 | M53: 0.073679696 | N53: 0.81357246 | O53: 2.5390062 | P53: 8.81437 | Q53: 13.938117 | R53: 2.9329223 | S53: 52.109038 | T53: 0.15300839 | U53: 0.081138875 | V53: -0.0010898064 | W53: 0.25875404 | X53: 0.10777864 | Y53: 0.1857217 | Z53: 0.1857217
A54: Office Equipment & Services | B54: 24 | C54: 0.042641333 | D54: 0.085960257 | E54: 0.17715975 | F54: 0.34663679 | G54: 1.0984143 | H54: 1.3734419 | I54: 0.093870849 | J54: 0.49658829 | K54: 0.0391 | L54: 0.34057576 | M54: 0.072021263 | N54: 2.5224766 | O54: 1.0215806 | P54: 8.3703979 | Q54: 11.930065 | R54: 3.1235005 | S54: 35.376266 | T54: 0.082130702 | U54: 0.028914487 | V54: 0.031044349 | W54: 0.40661209 | X54: 0.087016981 | Y54: 0.82360221 | Z54: 0.82360221
A55: Oil/Gas (Integrated) | B55: 5 | C55: -0.12333333 | D55: 0.029283377 | E55: 0.02151427 | F55: 0.18219717 | G55: 1.250764 | H55: 1.3724 | I55: 0.09381792 | J55: 0.20212921 | K55: 0.0311 | L55: 0.13264555 | M55: 0.084508601 | N55: 0.82546242 | O55: 2.0661784 | P55: 12.946499 | Q55: 70.355412 | R55: 1.8126956 | S55: 55.942502 | T55: 0.042146542 | U55: 0.098087059 | V55: -0.027795972 | W55: -0.9281323 | X55: 0.059026827 | Y55: 1.1621366 | Z55: 1.1621366
A56: Oil/Gas (Production and Exploration) | B56: 311 | C56: -0.017194194 | D56: 0.0023290825 | E56: 0.00086135625 | F56: 0.051612811 | G56: 1.0036901 | H56: 1.258732 | I56: 0.088043586 | J56: 0.78882535 | K56: 0.0691 | L56: 0.29533303 | M56: 0.077551117 | N56: 0.37902125 | O56: 4.328661 | P56: 10.55504 | Q56: NA | R56: 1.9337817 | S56: 126.14508 | T56: -0.017514996 | U56: 0.53968386 | V56: 0.22033928 | W56: NA | X56: -0.048665361 | Y56: 0.0082698454 | Z56: 0.0082698454
A57: Oil/Gas Distribution | B57: 16 | C57: 0.138885 | D57: 0.17796226 | E57: 0.061284012 | F57: 0.25778061 | G57: 0.71646756 | H57: 1.2064832 | I57: 0.085389347 | J57: 0.62786695 | K57: 0.0391 | L57: 0.48301044 | M57: 0.058498539 | N57: 0.36186963 | O57: 4.5196657 | P57: 14.577435 | Q57: 25.295508 | R57: 1.627297 | S57: 43.873606 | T57: 0.042389607 | U57: 0.23557719 | V57: 0.12979706 | W57: 0.98647692 | X57: 0.019724466 | Y57: 3.1026852 | Z57: 3.1026852
A58: Oilfield Svcs/Equip. | B58: 130 | C58: -0.049305 | D58: 0.031994485 | E58: 0.064161071 | F58: 0.29403 | G58: 1.0558983 | H58: 1.2272059 | I58: 0.086442062 | J58: 0.73286392 | K58: 0.0466 | L58: 0.23652026 | M58: 0.074373364 | N58: 2.1180278 | O58: 1.0150834 | P58: 12.145857 | Q58: 30.032057 | R58: 1.6364966 | S58: 131.00464 | T58: 0.097703008 | U58: 0.035382019 | V58: 0.01154529 | W58: 0.72525884 | X58: 0.019709504 | Y58: 2.4226705 | Z58: 2.4226705
A59: Packaging & Container | B59: 25 | C59: 0.016736111 | D59: 0.10003902 | E59: 0.14576129 | F59: 0.27456065 | G59: 0.55106848 | H59: 0.73852582 | I59: 0.061617112 | J59: 0.27674734 | K59: 0.0361 | L59: 0.33432742 | M59: 0.050189429 | N59: 1.8769868 | O59: 1.6493482 | P59: 10.298289 | Q59: 16.464158 | R59: 3.8815434 | S59: 26.437476 | T59: 0.10409736 | U59: 0.050747146 | V59: 0.064852135 | W59: 0.89332831 | X59: 0.20537745 | Y59: 0.39590227 | Z59: 0.39590227
A60: Paper/Forest Products | B60: 21 | C60: 0.072335333 | D60: 0.054387086 | E60: 0.084788149 | F60: 0.22855481 | G60: 0.9775302 | H60: 1.1990846 | I60: 0.085013499 | J60: 0.56813633 | K60: 0.0391 | L60: 0.28575484 | M60: 0.069211971 | N60: 1.8162155 | O60: 0.97029118 | P60: 8.8980282 | Q60: 17.712073 | R60: 1.8896378 | S60: 75.088352 | T60: 0.13986954 | U60: 0.043267024 | V60: 0.014999147 | W60: 0.4284968 | X60: 0.061475007 | Y60: 0.46742274 | Z60: 0.46742274
A61: Power | B61: 61 | C61: 0.077802745 | D61: 0.17915189 | E61: 0.064259134 | F61: 0.1717112 | G61: 0.32493566 | H61: 0.50452295 | I61: 0.049729766 | J61: 0.31226008 | K61: 0.0361 | L61: 0.4329841 | M61: 0.04007692 | N61: 0.45023554 | O61: 3.5101806 | P61: 10.545868 | Q61: 19.564906 | R61: 1.8759351 | S61: 25.953938 | T61: 0.073165133 | U61: 0.26960628 | V61: 0.18479321 | W61: 1.3671426 | X61: 0.15545721 | Y61: 0.45741917 | Z61: 0.45741917
A62: Precious Metals | B62: 111 | C62: -0.05543 | D62: 0.17387841 | E62: 0.075340895 | F62: 0.35618618 | G62: 0.94639981 | H62: 0.96314967 | I62: 0.073028003 | J62: 0.91351577 | K62: 0.0816 | L62: 0.15145728 | M62: 0.071360155 | N62: 0.44283974 | O62: 3.2402286 | P62: 8.3786583 | Q62: 18.141072 | R62: 1.4930716 | S62: 36.158048 | T62: 0.13556524 | U62: 0.18217023 | V62: 0.010835478 | W62: 0.22252686 | X62: 0.018869167 | Y62: 0.63784911 | Z62: 0.63784911
A63: Publishing & Newspapers | B63: 41 | C63: -0.016509524 | D63: 0.074283132 | E63: 0.13482426 | F63: 0.30887758 | G63: 0.82623364 | H63: 1.018991 | I63: 0.075864741 | J63: 0.54141232 | K63: 0.0391 | L63: 0.30792155 | M63: 0.06165455 | N63: 2.0608689 | O63: 1.042684 | P63: 8.0228421 | Q63: 13.853666 | R63: 1.7588532 | S63: 69.166306 | T63: 0.11337882 | U63: 0.02601757 | V63: 0.0063302353 | W63: 0.10540501 | X63: -0.025097024 | Y63: 0.006274239 | Z63: 0.006274239
A64: R.E.I.T. | B64: 244 | C64: 0.15015941 | D64: 0.2230772 | E64: 0.030797432 | F64: 0.022347848 | G64: 0.42133592 | H64: 0.65925715 | I64: 0.057590263 | J64: 0.32140323 | K64: 0.0361 | L64: 0.43978544 | M64: 0.044328857 | N64: 0.14081607 | O64: 11.475026 | P64: 20.788928 | Q64: 46.796567 | R64: 2.0537288 | S64: 42.503025 | T64: 0.4635282 | U64: 0.032267028 | V64: -0.08394078 | W64: -0.35980163 | X64: 0.095369802 | Y64: 1.0486875 | Z64: 1.0486875
A65: Real Estate (Development) | B65: 20 | C65: 0.13901667 | D65: 0.11585584 | E65: 0.022716325 | F65: 0.35932382 | G65: 0.61355811 | H65: 0.749504 | I65: 0.062174803 | J65: 0.44266157 | K65: 0.0391 | L65: 0.31177717 | M65: 0.052054889 | N65: 0.20814717 | O65: 7.4210404 | P65: 28.916007 | Q65: 63.21559 | R65: 1.5996176 | S65: 38.106621 | T65: 0.65059021 | U65: 0.035464988 | V65: -0.051113458 | W65: 0.069910033 | X65: 0.046152039 | Y65: 0 | Z65: 0
A66: Real Estate (General/Diversified) | B66: 10 | C66: 0.3099 | D66: 0.14635992 | E66: 0.043150303 | F66: 0.26414455 | G66: 0.73331097 | H66: 0.74512978 | I66: 0.061952593 | J66: 0.41067832 | K66: 0.0391 | L66: 0.19096768 | M66: 0.055796445 | N66: 0.33798513 | O66: 6.2003245 | P66: 11.961761 | Q66: 29.067518 | R66: 1.2498473 | S66: 28.474322 | T66: 1.9748408 | U66: 0.019527417 | V66: -0.11849742 | W66: -2.1650425 | X66: 0.041671641 | Y66: 0.27909109 | Z66: 0.27909109
A67: Real Estate (Operations & Services) | B67: 60 | C67: 0.0018947368 | D67: 0.075849938 | E67: 0.11048525 | F67: 0.2825908 | G67: 0.80185642 | H67: 1.0225767 | I67: 0.076046895 | J67: 0.54014341 | K67: 0.0391 | L67: 0.31840191 | M67: 0.061295049 | N67: 1.5969085 | O67: 1.9870561 | P67: 14.07909 | Q67: 24.607681 | R67: 3.062181 | S67: 75.202582 | T67: 0.14996609 | U67: 0.015147385 | V67: -0.012796065 | W67: 0.036015614 | X67: 0.15059168 | Y67: 0.098994122 | Z67: 0.098994122
A68: Recreation | B68: 70 | C68: 0.0086319355 | D68: 0.11092741 | E68: 0.14588172 | F68: 0.47660955 | G68: 0.72607339 | H68: 0.84953387 | I68: 0.06725632 | J68: 0.50849782 | K68: 0.0391 | L68: 0.22831139 | M68: 0.058685438 | N68: 1.4613204 | O68: 2.0175763 | P68: 11.678995 | Q68: 18.393647 | R68: 4.118141 | S68: 21.935351 | T68: 0.19927337 | U68: 0.048532282 | V68: 0.038970475 | W68: 0.50389728 | X68: 0.052604952 | Y68: 2.00828 | Z68: 2.00828
... A95: Utility (Water) | B95: 23 | C95: 0.037748667 | D95: 0.28274574 | E95: 0.088563273 | F95: 0.32858539 | G95: 0.26742846 | H95: 0.342384 | I95: 0.041493107 | J95: 0.34496 | K95: 0.0361 | L95: 0.27609368 | M95: 0.037612029 | N95: 0.36896912 | O95: 6.4756686 | P95: 15.212629 | Q95: 22.563482 | R95: 3.3258605 | S95: 137.58221 | T95: 0.098886703 | U95: 0.34650066 | V95: 0.26068326 | W95: 1.5721436 | X95: 0.1362786 | Y95: 0.58233539 | Z95: 0.42942631

Sheet Global industry averages
A1: Industry Name | B1: Number of firms | C1: Annual Average Revenue growth - Last 5 years | D1: Pre-tax Operating Margin (Lease & R&D adjusted) | E1: After-tax ROC | F1: Average effective tax rate | G1: Unlevered Beta | H1: Equity (Levered) Beta | I1: Cost of equity | J1: Std deviation in stock prices | K1: Pre-tax cost of debt | L1: Market Debt/Capital | M1: Cost of capital | N1: Sales/Capital | O1: EV/Sales | P1: EV/EBITDA | Q1: EV/EBIT | R1: Price/Book | S1: Trailing PE | T1: Non-cash WC as % of Revenues | U1: Cap Ex as % of Revenues | V1: Net Cap Ex as % of Revenues | W1: Reinvestment Rate | X1: ROE | Y1: Dividend Payout Ratio | Z1: Equity Reinvestment Rate
A2: Advertising | B2: 258 | C2: 0.068148 | D2: 0.10552838 | E2: 0.35906419 | F2: 0.26619805 | G2: 0.96915594 | H2: 1.150971 | I2: 0.095460202 | J2: 0.45740446 | K2: 0.0491 | L2: 0.27889407 | M2: 0.079157859 | N2: 4.1563609 | O2: 1.5682618 | P2: 9.4816699 | Q2: 14.688738 | R2: 2.4907997 | S2: 57.778507 | T2: -0.035576837 | U2: 0.019845363 | V2: 0.017136143 | W2: 0.3497764 | X2: 0.12618373 | Y2: 0.54535802 | Z2: 0.54535802
A3: Aerospace/Defense | B3: 229 | C3: 0.079251103 | D3: 0.087505455 | E3: 0.20436455 | F3: 0.27412094 | G3: 1.0545917 | H3: 1.1415626 | I3: 0.094876884 | J3: 0.42291217 | K3: 0.0491 | L3: 0.17238241 | M3: 0.084901077 | N3: 2.6610778 | O3: 1.8130889 | P3: 14.505506 | Q3: 20.224597 | R3: 5.0083109 | S3: 44.54813 | T3: 0.25729665 | U3: 0.033346548 | V3: 0.017268883 | W3: 0.60034034 | X3: 0.21952562 | Y3: 0.42284944 | Z3: 0.42284944
A4: Air Transport | B4: 155 | C4: 0.068464444 | D4: 0.099095239 | E4: 0.088686709 | F4: 0.26080344 | G4: 0.63607803 | H4: 0.92515756 | I4: 0.081459769 | J4: 0.32685984 | K4: 0.0461 | L4: 0.42266588 | M4: 0.061715271 | N4: 1.075933 | O4: 1.6897989 | P4: 7.5578614 | Q4: 16.947626 | R4: 2.4336983 | S4: 37.307296 | T4: -0.026815977 | U4: 0.1226138 | V4: 0.066255141 | W4: 0.92538842 | X4: 0.17245442 | Y4: 0.32465799 | Z4: 0.32465799
A5: Apparel | B5: 1160 | C5: 0.026880476 | D5: 0.11078462 | E5: 0.14032785 | F5: 0.2585432 | G5: 0.8259888 | H5: 0.90026869 | I5: 0.079916659 | J5: 0.37064485 | K5: 0.0461 | L5: 0.17942384 | M5: 0.071811888 | N5: 1.5126181 | O5: 2.0436683 | P5: 12.023683 | Q5: 18.101187 | R5: 2.9918805 | S5: 66.702896 | T5: 0.22982015 | U5: 0.0397396 | V5: 0.02538109 | W5: 0.39704121 | X5: 0.11549743 | Y5: 0.50252352 | Z5: 0.50252352
A6: Auto & Truck | B6: 133 | C6: 0.058233333 | D6: 0.062915599 | E6: 0.065108421 | F6: 0.25483446 | G6: 1.0306651 | H6: 1.4985615 | I6: 0.11701081 | J6: 0.30813856 | K6: 0.0461 | L6: 0.45842651 | M6: 0.079298244 | N6: 1.2036233 | O6: 0.98324608 | P6: 9.3676333 | Q6: 16.161514 | R6: 1.3858432 | S6: 133.26447 | T6: 0.017401924 | U6: 0.069970775 | V6: 0.039734797 | W6: 0.99951265 | X6: 0.12548054 | Y6: 0.33928519 | Z6: 0.33928519
A7: Auto Parts | B7: 687 | C7: 0.060309302 | D7: 0.078528883 | E7: 0.12286934 | F7: 0.2351582 | G7: 1.1992463 | H7: 1.2623702 | I7: 0.10236695 | J7: 0.34653859 | K7: 0.0461 | L7: 0.17788205 | M7: 0.090338323 | N7: 1.8992772 | O7: 0.99948297 | P7: 8.2908229 | Q7: 13.05519 | R7: 1.9436536 | S7: 33.368551 | T7: 0.11244747 | U7: 0.057561203 | V7: 0.050249841 | W7: 1.0459829 | X7: 0.13700721 | Y7: 0.24861722 | Z7: 0.24861722
A8: Bank (Money Center) | B8: 615 | C8: 0.086579774 | D8: 0.00098588969 | E8: 9.5295722e-05 | F8: 0.22488695 | G8: 0.49500311 | H8: 1.0048783 | I8: 0.086402457 | J8: 0.24497459 | K8: 0.0411 | L8: 0.69733496 | M8: 0.047752397 | N8: 0.12160459 | O8: 8.510355 | P8: NA | Q8: NA | R8: 1.0790237 | S8: 19.882789 | T8: NA | U8: 0.041336505 | V8: 0.026838012 | W8: 34.531437 | X8: 0.10261047 | Y8: 0.35788115 | Z8: 0.35788115
A9: Banks (Regional) | B9: 853 | C9: 0.0785587 | D9: -0.00081818644 | E9: -0.00014827374 | F9: 0.26440562 | G9: 0.45192001 | H9: 0.61694931 | I9: 0.062350857 | J9: 0.30943093 | K9: 0.0461 | L9: 0.56315274 | M9: 0.046804864 | N9: 0.24072099 | O9: 5.7534905 | P9: NA | Q9: NA | R9: 1.1230876 | S9: 22.778537 | T9: NA | U9: 0.042096419 | V9: 0.04710834 | W9: NA | X9: 0.084628801 | Y9: 0.31289442 | Z9: 0.31289442
A10: Beverage (Alcoholic) | B10: 222 | C10: 0.031269687 | D10: 0.20922246 | E10: 0.14188638 | F10: 0.26752737 | G10: 0.66891167 | H10: 0.75730182 | I10: 0.071052713 | J10: 0.29647424 | K10: 0.0461 | L10: 0.18628751 | M10: 0.064289146 | N10: 0.83630455 | O10: 4.4001572 | P10: 16.532287 | Q10: 20.90878 | R10: 3.7049393 | S10: 45.659756 | T10: 0.092418439 | U10: 0.041958046 | V10: 0.051513518 | W10: 0.2608349 | X10: 0.17141244 | Y10: 0.62585568 | Z10: 0.62585568
A11: Beverage (Soft) | B11: 101 | C11: 0.046103833 | D11: 0.15391971 | E11: 0.2038157 | F11: 0.27053136 | G11: 0.57134634 | H11: 0.64022674 | I11: 0.063794058 | J11: 0.32789652 | K11: 0.0461 | L11: 0.19027698 | M11: 0.058266799 | N11: 1.5345339 | O11: 3.1865531 | P11: 16.076227 | Q11: 20.69919 | R11: 6.2319731 | S11: 176.04766 | T11: -0.010067559 | U11: 0.045547609 | V11: 0.035518753 | W11: 0.37386917 | X11: 0.2187408 | Y11: 0.76568454 | Z11: 0.76568454
A12: Broadcasting | B12: 139 | C12: 0.064979018 | D12: 0.17029172 | E12: 0.15449699 | F12: 0.2731255 | G12: 0.8026873 | H12: 1.0667256 | I12: 0.09023699 | J12: 0.3789217 | K12: 0.0461 | L12: 0.36183491 | M12: 0.070158257 | N12: 1.1063599 | O12: 2.3594864 | P12: 10.040724 | Q12: 13.816238 | R12: 2.6380226 | S12: 95.780301 | T12: 0.16043389 | U12: 0.038794605 | V12: 0.030778932 | W12: 0.3462136 | X12: 0.10159708 | Y12: 0.51011227 | Z12: 0.51011227
A13: Brokerage & Investment Banking | B13: 555 | C13: 0.13294546 | D13: 0.0029983085 | E13: 0.00043680418 | F13: 0.25317286 | G13: 0.49683671 | H13: 1.0703812 | I13: 0.090463634 | J13: 0.37224704 | K13: 0.0461 | L13: 0.66317081 | M13: 0.05351304 | N13: 0.17131056 | O13: 7.6287291 | P13: NA | Q13: NA | R13: 1.4898152 | S13: 45.716822 | T13: NA | U13: 0.037731132 | V13: 0.032445927 | W13: 191.5654 | X13: 0.09970439 | Y13: 0.4620237 | Z13: 0.4620237
A14: Building Materials | B14: 432 | C14: 0.059001497 | D14: 0.093186176 | E14: 0.12581037 | F14: 0.26031505 | G14: 0.84404433 | H14: 0.95040426 | I14: 0.083025064 | J14: 0.34167971 | K14: 0.0461 | L14: 0.2052143 | M14: 0.073117422 | N14: 1.6716053 | O14: 1.504962 | P14: 10.93107 | Q14: 15.980734 | R14: 2.3528632 | S14: 30.40905 | T14: 0.17628124 | U14: 0.040283911 | V14: 0.033097286 | W14: 0.62984994 | X14: 0.11458642 | Y14: 0.31637689 | Z14: 0.31637689
A15: Business & Consumer Services | B15: 834 | C15: 0.08914312 | D15: 0.088787678 | E15: 0.22145328 | F15: 0.27709194 | G15: 0.88390547 | H15: 0.99132838 | I15: 0.085562359 | J15: 0.4049824 | K15: 0.0491 | L15: 0.19658973 | M15: 0.07601681 | N15: 3.0692261 | O15: 1.7618176 | P15: 12.975929 | Q15: 18.865212 | R15: 4.3161518 | S15: 59.600363 | T15: 0.099552022 | U15: 0.024008215 | V15: 0.021515146 | W15: 0.48585221 | X15: 0.16656372 | Y15: 0.49379207 | Z15: 0.49379207
A16: Cable TV | B16: 65 | C16: 0.078983556 | D16: 0.16334448 | E16: 0.12055066 | F16: 0.28001122 | G16: 0.82568757 | H16: 1.1500852 | I16: 0.095405279 | J16: 0.35168283 | K16: 0.0461 | L16: 0.36387603 | M16: 0.073332665 | N16: 0.84300119 | O16: 3.7082116 | P16: 10.733565 | Q16: 22.184723 | R16: 3.2223414 | S16: 53.351008 | T16: -0.013369507 | U16: 0.12938772 | V16: -0.025669674 | W16: -0.19464982 | X16: 0.10261876 | Y16: 0.35725026 | Z16: 0.35725026
A17: Chemical (Basic) | B17: 787 | C17: 0.062841446 | D17: 0.10691971 | E17: 0.11066769 | F17: 0.18667288 | G17: 1.0368797 | H17: 1.1356958 | I17: 0.09451314 | J17: 0.34364401 | K17: 0.0461 | L17: 0.20424319 | M17: 0.082306021 | N17: 1.2520658 | O17: 1.5419246 | P17: 9.5304668 | Q17: 14.136599 | R17: 1.9341191 | S17: 38.07524 | T17: 0.14161492 | U17: 0.057901905 | V17: 0.03742665 | W17: 0.66024152 | X17: 0.14364334 | Y17: 0.39949114 | Z17: 0.39949114
A18: Chemical (Diversified) | B18: 75 | C18: 0.041228438 | D18: 0.11204207 | E18: 0.11914755 | F18: 0.22741452 | G18: 1.314727 | H18: 1.5026692 | I18: 0.11726549 | J18: 0.33753716 | K18: 0.0461 | L18: 0.23017738 | M18: 0.098271272 | N18: 1.3119843 | O18: 1.7862969 | P18: 10.21687 | Q18: 16.025098 | R18: 1.77318 | S18: 22.344379 | T18: 0.22056907 | U18: 0.071636915 | V18: 0.040019683 | W18: 0.58598891 | X18: 0.14102541 | Y18: 0.41524539 | Z18: 0.41524539
A19: Chemical (Specialty) | B19: 770 | C19: 0.058134971 | D19: 0.11327955 | E19: 0.12157757 | F19: 0.22583226 | G19: 1.0643537 | H19: 1.1747598 | I19: 0.09693511 | J19: 0.39157476 | K19: 0.0461 | L19: 0.18466391 | M19: 0.085450947 | N19: 1.2836358 | O19: 2.1829315 | P19: 12.881227 | Q19: 19.092624 | R19: 2.9595758 | S19: 49.746109 | T19: 0.15661743 | U19: 0.059262189 | V19: 0.058164133 | W19: 0.79806228 | X19: 0.13564521 | Y19: 0.41845979 | Z19: 0.41845979
A20: Coal & Related Energy | B20: 254 | C20: -0.011700992 | D20: 0.17227149 | E20: 0.14155741 | F20: 0.21803096 | G20: 1.10575 | H20: 1.2469816 | I20: 0.10141286 | J20: 0.58189185 | K20: 0.0491 | L20: 0.28004581 | M20: 0.083376175 | N20: 0.89761508 | O20: 1.7041685 | P20: 6.4333254 | Q20: 9.4707041 | R20: 1.4569318 | S20: 122.67183 | T20: 0.012762734 | U20: 0.075098629 | V20: 0.024490877 | W20: 0.1180266 | X20: 0.1493409 | Y20: 0.72355498 | Z20: 0.72355498
A21: Computer Services | B21: 931 | C21: 0.08190236 | D21: 0.07569469 | E21: 0.20736079 | F21: 0.20770227 | G21: 1.0135858 | H21: 1.0836705 | I21: 0.091287571 | J21: 0.39256792 | K21: 0.0461 | L21: 0.15802567 | M21: 0.082352483 | N21: 3.3085029 | O21: 1.2899418 | P21: 12.148974 | Q21: 16.80237 | R21: 3.4523466 | S21: 49.110763 | T21: 0.14323778 | U21: 0.018155785 | V21: 0.019285386 | W21: 0.47557409 | X21: 0.18959146 | Y21: 0.3640588 | Z21: 0.3640588
A22: Computers/Peripherals | B22: 331 | C22: 0.019933731 | D22: 0.12454521 | E22: 0.16607756 | F22: 0.23969355 | G22: 1.2105562 | H22: 1.2703873 | I22: 0.10286401 | J22: 0.37998546 | K22: 0.0461 | L22: 0.15641309 | M22: 0.092209395 | N22: 1.5220738 | O22: 1.6608867 | P22: 9.4533224 | Q22: 13.297444 | R22: 2.8857014 | S22: 61.584346 | T22: 0.054791769 | U22: 0.067349109 | V22: 0.067142809 | W22: 0.84658109 | X22: 0.18860771 | Y22: 0.28122039 | Z22: 0.28122039
A23: Construction Supplies | B23: 763 | C23: 0.054673396 | D23: 0.087659503 | E23: 0.085513603 | F23: 0.23776082 | G23: 1.0592816 | H23: 1.2554766 | I23: 0.10193955 | J23: 0.34652782 | K23: 0.0461 | L23: 0.29201157 | M23: 0.08231813 | N23: 1.167562 | O23: 1.6762826 | P23: 11.852787 | Q23: 18.869566 | R23: 1.9283566 | S23: 45.864065 | T23: 0.13318283 | U23: 0.046017675 | V23: 0.035128628 | W23: 0.75837516 | X23: 0.10165602 | Y23: 0.46284033 | Z23: 0.46284033
A24: Diversified | B24: 349 | C24: 0.055677482 | D24: 0.13065175 | E24: 0.10795917 | F24: 0.21526038 | G24: 0.75801351 | H24: 1.0028101 | I24: 0.086274225 | J24: 0.27076427 | K24: 0.0461 | L24: 0.37272439 | M24: 0.067068239 | N24: 0.97556851 | O24: 1.688909 | P24: 9.520922 | Q24: 12.738058 | R24: 1.2419928 | S24: 27.209151 | T24: -0.13702415 | U24: 0.049101278 | V24: 0.041181976 | W24: 0.46973494 | X24: 0.098389828 | Y24: 0.30936947 | Z24: 0.30936947
A25: Drugs (Biotechnology) | B25: 952 | C25: 0.22894977 | D25: 0.23086929 | E25: 0.10263414 | F25: 0.20060542 | G25: 1.3126218 | H25: 1.3839374 | I25: 0.10990412 | J25: 0.73158538 | K25: 0.0566 | L25: 0.12713561 | M25: 0.10135492 | N25: 0.45463899 | O25: 7.9333897 | P25: 14.771544 | Q25: 29.356825 | R25: 5.5298306 | S25: 298.16188 | T25: 0.19155626 | U25: 0.048442559 | V25: 0.042278322 | W25: 0.42184703 | X25: 0.089325745 | Y25: 0.67920704 | Z25: 0.67920704
... A34: Farming/Agriculture | B34: 412 | C34: 0.098678209 | D34: 0.056576996 | E34: 0.069277602 | F34: 0.2359126 | G34: 0.69377848 | H34: 0.89297752 | I34: 0.079464606 | J34: 0.34478895 | K34: 0.0461 | L34: 0.33375395 | M34: 0.064539451 | N34: 1.4133423 | O34: 1.1962792 | P34: 13.072775 | Q34: 20.676359 | R34: 1.9266081 | S34: 51.721075 | T34: 0.14962038 | U34: 0.044727444 | V34: 0.026265033 | W34: 0.86770008 | X34: 0.10325978 | Y34: 0.37536595 | Z34: 0.37536595
A35: Financial Svcs. (Non-bank & Insurance) | B35: 1030 | C35: 0.15422724 | D35: 0.075319879 | E35: 0.0040056146 | F35: 0.23833539 | G35: 0.15451673 | H35: 0.82153056 | I35: 0.075034894 | J35: 0.35975775 | K35: 0.0461 | L35: 0.86428902 | M35: 0.040213274 | N35: 0.064822495 | O35: 16.26326 | P35: 148.8931 | Q35: NA | R35: 1.4647869 | S35: 125.58747 | T35: NA | U35: 0.072664348 | V35: 0.10179956 | W35: 2.0594356 | X35: 0.20806048 | Y35: 0.22777488 | Z35: 0.22777488
A36: Food Processing | B36: 1270 | C36: 0.07048174 | D36: 0.0908205 | E36: 0.1398993 | F36: 0.25263434 | G36: 0.71579535 | H36: 0.81145831 | I36: 0.074410415 | J36: 0.33814143 | K36: 0.0461 | L36: 0.19902637 | M36: 0.066516065 | N36: 1.8505349 | O36: 1.6893593 | P36: 13.014761 | Q36: 18.414349 | R36: 2.7746218 | S36: 45.324205 | T36: 0.10516464 | U36: 0.043342695 | V36: 0.047397084 | W36: 0.7307323 | X36: 0.12153582 | Y36: 0.51948816 | Z36: 0.51948816
A37: Food Wholesalers | B37: 148 | C37: 0.14294788 | D37: 0.027067222 | E37: 0.12400116 | F37: 0.28418668 | G37: 0.6220549 | H37: 0.83599654 | I37: 0.075931786 | J37: 0.33439175 | K37: 0.0461 | L37: 0.37286172 | M37: 0.060575022 | N37: 5.6051001 | O37: 0.46103731 | P37: 10.426627 | Q37: 16.923604 | R37: 1.9398316 | S37: 62.931947 | T37: 0.047379144 | U37: 0.014744315 | V37: 0.0083061734 | W37: 0.27980282 | X37: 0.1053544 | Y37: 0.47431948 | Z37: 0.47431948
A38: Furn/Home Furnishings | B38: 316 | C38: 0.069436681 | D38: 0.082028773 | E38: 0.19261615 | F38: 0.18029652 | G38: 0.93378537 | H38: 0.9623883 | I38: 0.083768074 | J38: 0.33398846 | K38: 0.0461 | L38: 0.17683584 | M38: 0.075099139 | N38: 2.8061741 | O38: 1.4083416 | P38: 11.946024 | Q38: 17.283952 | R38: 2.8403088 | S38: 58.122269 | T38: 0.080483993 | U38: 0.033801953 | V38: 0.060377212 | W38: 0.8619883 | X38: 0.20831533 | Y38: 0.40513929 | Z38: 0.40513929
A39: Green & Renewable Energy | B39: 181 | C39: 0.092931325 | D39: 0.35860917 | E39: 0.074601523 | F39: 0.1745338 | G39: 0.75692622 | H39: 1.1532019 | I39: 0.095598517 | J39: 0.38077028 | K39: 0.0461 | L39: 0.43565934 | M39: 0.069087362 | N39: 0.23219697 | O39: 7.3693795 | P39: 11.714658 | Q39: 20.349804 | R39: 1.6482534 | S39: 90.272413 | T39: -0.065779938 | U39: 0.30266328 | V39: 0.10858288 | W39: 0.46268433 | X39: 0.10119998 | Y39: 0.90617978 | Z39: 0.90617978
A40: Healthcare Products | B40: 696 | C40: 0.11558816 | D40: 0.15379877 | E40: 0.15290816 | F40: 0.17178643 | G40: 1.002876 | H40: 1.0654171 | I40: 0.090155861 | J40: 0.49924052 | K40: 0.0491 | L40: 0.13878614 | M40: 0.08277949 | N40: 1.0764192 | O40: 4.0954084 | P40: 17.2053 | Q40: 26.706785 | R40: 3.6683101 | S40: 63.82264 | T40: 0.24777779 | U40: 0.046944498 | V40: 0.093296508 | W40: 0.85658237 | X40: 0.10693927 | Y40: 0.39859501 | Z40: 0.39859501
A41: Healthcare Support Services | B41: 355 | C41: 0.15546896 | D41: 0.048484759 | E41: 0.35179233 | F41: 0.30692402 | G41: 0.87129942 | H41: 0.96165592 | I41: 0.083722667 | J41: 0.42386232 | K41: 0.0491 | L41: 0.20926034 | M41: 0.073946862 | N41: 8.769724 | O41: 0.69061482 | P41: 10.972641 | Q41: 14.07955 | R41: 2.8979128 | S41: 84.723024 | T41: -0.018492769 | U41: 0.0098100741 | V41: 0.019673114 | W41: 0.67729169 | X41: 0.14756031 | Y41: 0.25671207 | Z41: 0.25671207
A42: Heathcare Information and Technology | B42: 339 | C42: 0.10740044 | D42: 0.13443547 | E42: 0.15181851 | F42: 0.19103583 | G42: 0.98161344 | H42: 1.0494313 | I42: 0.089164738 | J42: 0.50375336 | K42: 0.0491 | L42: 0.13254843 | M42: 0.082251268 | N42: 1.2182514 | O42: 5.0505018 | P42: 21.646145 | Q42: 37.422665 | R42: 4.4253187 | S42: 124.87695 | T42: 0.19611999 | U42: 0.051486475 | V42: 0.10676236 | W42: 1.2174825 | X42: 0.10068193 | Y42: 0.16981129 | Z42: 0.16981129
A43: Homebuilding | B43: 171 | C43: 0.087730325 | D43: 0.095126571 | E43: 0.095429849 | F43: 0.28282489 | G43: 0.92999919 | H43: 1.1016582 | I43: 0.092402807 | J43: 0.38660009 | K43: 0.0461 | L43: 0.28210407 | M43: 0.076137466 | N43: 1.281648 | O43: 1.3387559 | P43: 10.285106 | Q43: 13.487834 | R43: 1.8605681 | S43: 17.63385 | T43: 0.61977344 | U43: 0.0093982576 | V43: 0.013238244 | W43: 0.519276 | X43: 0.1244796 | Y43: 0.23035656 | Z43: 0.23035656
A44: Hospitals/Healthcare Facilities | B44: 198 | C44: 0.084660984 | D44: 0.082482171 | E44: 0.083770217 | F44: 0.25253569 | G44: 0.57742348 | H44: 0.90346766 | I44: 0.080114995 | J44: 0.37722668 | K44: 0.0461 | L44: 0.44694044 | M44: 0.059837564 | N44: 1.2124575 | O44: 1.9052755 | P44: 11.254809 | Q44: 22.984653 | R44: 3.107303 | S44: 45.747418 | T44: 0.077966366 | U44: 0.061837849 | V44: 0.04424678 | W44: 1.2787702 | X44: 0.10176821 | Y44: 0.46446485 | Z44: 0.46446485
A45: Hotel/Gaming | B45: 658 | C45: 0.14181577 | D45: 0.13635386 | E45: 0.091536947 | F45: 0.17332319 | G45: 0.82742905 | H45: 0.98355788 | I45: 0.085080588 | J45: 0.35258839 | K45: 0.0461 | L45: 0.26198534 | M45: 0.071893551 | N45: 0.77897469 | O45: 3.1409588 | P45: 13.228745 | Q45: 22.75106 | R45: 2.6807235 | S45: 152.97033 | T45: -0.024489798 | U45: 0.089040179 | V45: 0.032524672 | W45: 0.28251033 | X45: 0.095240491 | Y45: 0.55861898 | Z45: 0.55861898
A46: Household Products | B46: 531 | C46: 0.089879794 | D46: 0.15741545 | E46: 0.28525341 | F46: 0.27032516 | G46: 0.91165924 | H46: 0.98004145 | I46: 0.08486257 | J46: 0.39931656 | K46: 0.0461 | L46: 0.12990315 | M46: 0.078352214 | N46: 2.1258959 | O46: 3.0707119 | P46: 16.235449 | Q46: 19.500688 | R46: 5.4082642 | S46: 61.998946 | T46: 0.070155916 | U46: 0.03943607 | V46: 0.085448532 | W46: 0.77351882 | X46: 0.25254019 | Y46: 0.48712037 | Z46: 0.48712037
A47: Information Services | B47: 193 | C47: 0.12530554 | D47: 0.24079706 | E47: 0.31475102 | F47: 0.31355401 | G47: 1.2339628 | H47: 1.3163519 | I47: 0.10571382 | J47: 0.40662845 | K47: 0.0491 | L47: 0.13353934 | M47: 0.096538711 | N47: 1.5754565 | O47: 5.6441259 | P47: 18.343822 | Q47: 23.200277 | R47: 7.1386166 | S47: 43.910179 | T47: -0.027375445 | U47: 0.032072164 | V47: 0.013826922 | W47: 0.14377269 | X47: 0.20973428 | Y47: 0.28052686 | Z47: 0.28052686
... A50: Insurance (Prop/Cas.) | B50: 225 | C50: 0.069751059 | D50: 0.081985199 | E50: 0.092394595 | F50: 0.23227637 | G50: 0.6394355 | H50: 0.69606139 | I50: 0.067255806 | J50: 0.30647297 | K50: 0.0461 | L50: 0.20987145 | M50: 0.060432836 | N50: 1.3580986 | O50: 1.127973 | P50: 11.109653 | Q50: 13.263333 | R50: 1.389075 | S50: 27.507668 | T50: -0.36198392 | U50: 0.0058511962 | V50: 0.0053800039 | W50: 0.29532331 | X50: 0.08333837 | Y50: 0.40358402 | Z50: 0.40358402
A51: Investments & Asset Management | B51: 1065 | C51: 0.12686074 | D51: 0.19267936 | E51: 0.070469285 | F51: 0.20628335 | G51: 0.6568246 | H51: 0.88246294 | I51: 0.078812702 | J51: 0.38367017 | K51: 0.0461 | L51: 0.41746259 | M51: 0.060416323 | N51: 0.39771446 | O51: 5.0136803 | P51: 21.354503 | Q51: 23.858191 | R51: 1.6062734 | S51: 158.42114 | T51: NA | U51: 0.021898341 | V51: 0.068433339 | W51: 0.52730496 | X51: 0.12235952 | Y51: 0.37734118 | Z51: 0.37734118
A52: Machinery | B52: 1309 | C52: 0.03835241 | D52: 0.099451593 | E52: 0.13032343 | F52: 0.2561092 | G52: 1.1266532 | H52: 1.1700063 | I52: 0.096640391 | J52: 0.35439353 | K52: 0.0461 | L52: 0.1403249 | M52: 0.087955006 | N52: 1.6036319 | O52: 2.0153924 | P52: 14.23467 | Q52: 20.065107 | R52: 3.0133481 | S52: 43.760528 | T52: 0.24753405 | U52: 0.036587872 | V52: 0.045369465 | W52: 0.84245295 | X52: 0.12215779 | Y52: 0.38935573 | Z52: 0.38935573
A53: Metals & Mining | B53: 1594 | C53: 0.025022937 | D53: 0.12464585 | E53: 0.11856069 | F53: 0.32623321 | G53: 1.3338429 | H53: 1.551813 | I53: 0.12031241 | J53: 0.73249456 | K53: 0.0566 | L53: 0.25597321 | M53: 0.10043532 | N53: 0.99654385 | O53: 1.8200144 | P53: 8.6170266 | Q53: 14.089198 | R53: 1.8937144 | S53: 57.416138 | T53: 0.091252803 | U53: 0.070604224 | V53: 0.021764576 | W53: 0.47681873 | X53: 0.099348586 | Y53: 0.44123251 | Z53: 0.44123251
A54: Office Equipment & Services | B54: 157 | C54: 0.025704701 | D54: 0.085545189 | E54: 0.1385447 | F54: 0.2959695 | G54: 0.85376703 | H54: 0.95412823 | I54: 0.08325595 | J54: 0.38171384 | K54: 0.0461 | L54: 0.24152537 | M54: 0.071539463 | N54: 1.9783391 | O54: 1.246267 | P54: 9.122535 | Q54: 14.486342 | R54: 2.5657293 | S54: 49.871056 | T54: 0.12308547 | U54: 0.036514779 | V54: 0.028863196 | W54: 0.4689996 | X54: 0.081089502 | Y54: 0.55902951 | Z54: 0.55902951
A55: Oil/Gas (Integrated) | B55: 48 | C55: -0.028293421 | D55: 0.056770904 | E55: 0.046263227 | F55: 0.28708411 | G55: 1.2203418 | H55: 1.4640062 | I55: 0.11486839 | J55: 0.27869868 | K55: 0.0461 | L55: 0.27417789 | M55: 0.09290048 | N55: 1.0474058 | O55: 1.156537 | P55: 7.1623905 | Q55: 20.311558 | R55: 1.1689839 | S55: 42.684005 | T55: 0.0255437 | U55: 0.092847515 | V55: 0.0091667376 | W55: 0.32439813 | X55: 0.062169886 | Y55: 0.67452401 | Z55: 0.67452401
A56: Oil/Gas (Production and Exploration) | B56: 928 | C56: -0.0011101856 | D56: 0.080964145 | E56: 0.028733407 | F56: 0.1812468 | G56: 1.3269818 | H56: 1.6667318 | I56: 0.12743737 | J56: 0.70828672 | K56: 0.0566 | L56: 0.3037628 | M56: 0.10168499 | N56: 0.36764812 | O56: 3.8696633 | P56: 8.4739247 | Q56: 46.405017 | R56: 1.5248632 | S56: 84.75786 | T56: 0.01100571 | U56: 0.4229843 | V56: 0.15608132 | W56: 3.27985 | X56: -0.0067846667 | Y56: 0.0055704694 | Z56: 0.0055704694
A57: Oil/Gas Distribution | B57: 143 | C57: 0.10205873 | D57: 0.12914271 | E57: 0.064145369 | F57: 0.24372102 | G57: 1.0805147 | H57: 1.6810482 | I57: 0.12832499 | J57: 0.39862498 | K57: 0.0461 | L57: 0.44414103 | M57: 0.086762528 | N57: 0.56985296 | O57: 2.965672 | P57: 13.448069 | Q57: 22.534098 | R57: 1.5627869 | S57: 29.934183 | T57: 0.022887865 | U57: 0.16416177 | V57: 0.094852533 | W57: 1.0535173 | X57: 0.069786332 | Y57: 1.1211855 | Z57: 1.1211855
A58: Oilfield Svcs/Equip. | B58: 524 | C58: -0.034584337 | D58: 0.052932496 | E58: 0.091455154 | F58: 0.26130845 | G58: 1.172196 | H58: 1.4182456 | I58: 0.11203123 | J58: 0.47418001 | K58: 0.0491 | L58: 0.28001167 | M58: 0.091023476 | N58: 1.9276791 | O58: 0.94930038 | P58: 9.5167379 | Q58: 17.158521 | R58: 1.7355193 | S58: 51.706499 | T58: 0.064612428 | U58: 0.03544678 | V58: 0.011931196 | W58: 0.6432954 | X58: 0.070089025 | Y58: 0.74533229 | Z58: 0.74533229
A59: Packaging & Container | B59: 390 | C59: 0.057597075 | D59: 0.090549876 | E59: 0.12043092 | F59: 0.25269683 | G59: 0.61983804 | H59: 0.78632057 | I59: 0.072851875 | J59: 0.32264137 | K59: 0.0461 | L59: 0.30486582 | M59: 0.061234565 | N59: 1.6379719 | O59: 1.5255253 | P59: 10.247697 | Q59: 16.754819 | R59: 2.7454483 | S59: 27.28228 | T59: 0.13147946 | U59: 0.057791599 | V59: 0.065004037 | W59: 1.0697223 | X59: 0.14594679 | Y59: 0.41630542 | Z59: 0.41630542
A60: Paper/Forest Products | B60: 295 | C60: 0.033273975 | D60: 0.088547891 | E60: 0.077432715 | F60: 0.22124068 | G60: 0.80493435 | H60: 1.0378924 | I60: 0.088449327 | J60: 0.36006107 | K60: 0.0461 | L60: 0.32910241 | M60: 0.070775291 | N60: 1.0321484 | O60: 1.4248195 | P60: 9.2532579 | Q60: 15.862809 | R60: 1.6143218 | S60: 297.11262 | T60: 0.1803948 | U60: 0.070619945 | V60: 0.03963469 | W60: 0.62124449 | X60: 0.093193486 | Y60: 0.41970483 | Z60: 0.41970483
A61: Power | B61: 563 | C61: 0.061279032 | D61: 0.12101678 | E61: 0.063544358 | F61: 0.20261505 | G61: 0.57713574 | H61: 0.9285693 | I61: 0.081671297 | J61: 0.28370384 | K61: 0.0461 | L61: 0.47369004 | M61: 0.059443047 | N61: 0.64527035 | O61: 2.1434533 | P61: 9.3734108 | Q61: 17.650278 | R61: 1.3504947 | S61: 31.320709 | T61: 0.012225448 | U61: 0.1559626 | V61: 0.087433225 | W61: 1.0071466 | X61: 0.10565345 | Y61: 0.54591221 | Z61: 0.54591221
A62: Precious Metals | B62: 961 | C62: 0.057864978 | D62: 0.12243869 | E62: 0.078303319 | F62: 0.27550448 | G62: 1.2235515 | H62: 1.3329101 | I62: 0.10674043 | J62: 0.86964896 | K62: 0.0791 | L62: 0.18395375 | M62: 0.09807202 | N62: 0.66320372 | O62: 2.7038671 | P62: 8.5215576 | Q62: 20.471299 | R62: 1.7045241 | S62: 39.297046 | T62: 0.13055828 | U62: 0.18964264 | V62: 0.096871934 | W62: 1.2958906 | X62: 0.042936373 | Y62: 0.71466998 | Z62: 0.71466998
A63: Publishing & Newspapers | B63: 371 | C63: -0.0029573643 | D63: 0.071671058 | E63: 0.10054601 | F63: 0.24121291 | G63: 0.89627883 | H63: 0.97585724 | I63: 0.084603149 | J63: 0.39437486 | K63: 0.0461 | L63: 0.22125659 | M63: 0.073571831 | N63: 1.6498584 | O63: 1.2932484 | P63: 9.9387588 | Q63: 17.345755 | R63: 1.7051446 | S63: 79.450689 | T63: 0.11070495 | U63: 0.030193389 | V63: 0.020068148 | W63: 0.38103727 | X63: 0.0085935533 | Y63: 4.7140496 | Z63: 4.7140496
... A95: Utility (Water) | B95: 103 | C95: 0.10277746 | D95: 0.26649783 | E95: 0.08262244 | F95: 0.23132571 | G95: 0.80811062 | H95: 1.0937241 | I95: 0.091910895 | J95: 0.31872655 | K95: 0.0461 | L95: 0.36321003 | M95: 0.071147876 | N95: 0.37302466 | O95: 4.9835089 | P95: 12.698447 | Q95: 18.562866 | R95: 1.9406849 | S95: 42.018219 | T95: 0.049034099 | U95: 0.20698375 | V95: 0.12039038 | W95: 0.95649969 | X95: 0.11231241 | Y95: 0.5493142 | Z95: 0.44264679

Sheet Country equity risk premiums
A1: Country | B1: Moody's rating | C1: Adj. Default Spread | D1: Equity Risk Premium | E1: Country Risk Premium | F1: Corporate Tax Rate | G1: Region
A2: Abu Dhabi | B2: Aa2 | C2: 0.0050876317 | D2: 0.056520148 | E2: 0.0057201482 | F2: 0 | G2: Middle East
A3: Albania | B3: B1 | C3: 0.046158695 | D3: 0.10269734 | E3: 0.051897345 | F3: 0.15 | G3: Eastern Europe & Russia
A4: Algeria | B4: NA | C4: 0.0667 | D4: 0.12579243 | E4: 0.074992435 | F4: 0.26 | G4: Africa
A5: Andorra (Principality of) | B5: Baa2 | C5: 0.019518005 | D5: 0.072744569 | E5: 0.021944569 | F5: 0 | G5: Western Europe
A6: Angola | B6: B2 | C6: 0.05642646 | D6: 0.11424164 | E6: 0.063441644 | F6: 0.3 | G6: Africa
A7: Anguilla | B7: NA | C7: 0.056135951 | D7: 0.11391502 | E7: 0.063115016 | F7: 0.24024843 | G7: Caribbean
A8: Antigua & Barbuda | B8: NA | C8: 0.0561 | D8: 0.1139 | E8: 0.0631 | F8: 0.2402 | G8: Caribbean
A9: Argentina | B9: B2 | C9: 0.05642646 | D9: 0.11424164 | E9: 0.063441644 | F9: 0.35 | G9: Central and South America
A10: Armenia | B10: B1 | C10: 0.046158695 | D10: 0.10269734 | E10: 0.051897345 | F10: 0.2 | G10: Eastern Europe & Russia
A11: Aruba | B11: Baa1 | C11: 0.016372924 | D11: 0.069208477 | E11: 0.018408477 | F11: 0 | G11: Caribbean
A12: Australia | B12: Aaa | C12: 0 | D12: 0.0508 | E12: 0 | F12: 0.3 | G12: Australia & New Zealand
A13: Austria | B13: Aa1 | C13: 0.0040701053 | D13: 0.055376119 | E13: 0.0045761186 | F13: 0.25 | G13: Western Europe
... A187: Zimbabwe | B187: NA | C187: 0.0923 | D187: 0.15457514 | E187: 0.10377514 | F187: 0.25 | G187: Africa
B190: ERP | C190: Default Spread | D190: Tax rate
A191: Africa & Mid East | B191: 0.081097357 | C191: 0.026947168 | D191: 0.23255991
A192: Australia, NZ & Canada | B192: 0.050821324 | C192: 1.8965754e-05 | D192: 0.28027735
A193: Latin America & Caribbean | B193: 0.087504941 | C193: 0.020003294 | D193: 0.2715
A194: Japan | B194: 0.05891221 | C194: 0.0072151867 | D194: 0.3564
A195: US | B195: 0.0508 | C195: 0 | D195: 0.4
A196: Europe | B196: 0.06005813 | C196: 0.0082343943 | D196: 0.3
A197: Emerging Markets | B197: 0.07141001 | C197: 0.0092733401 | D197: 0.25
A198: Small Asia (No India, China & Japan) | B198: 0.069263798 | C198: 0.0078425318 | D198: 0.2
A199: North America | B199: 0.0508 | C199: 0 | D199: 0.265
A201: Global | B201: 0.0621 | C201: 0.01 | D201: 0.3

Sheet Trailing 12 month
B1: Last 10K | C1: First X months: Last year | D1: First X months: Current year | E1: Trailing 12 month
A2: Revenues | B2: 215639 | C2: 75872 | D2: 78351 | E2: =B2-C2+D2
A3: R&D expense | B3: 10045 | C3: 2404 | D3: 2871 | E3: =B3-C3+D3
A4: Operating income or EBIT | B4: 60024 | C4: 24171 | D4: 23359 | E4: =B4-C4+D4
A5: Interest expenses | B5: 1456 | C5: 276 | D5: 525 | E5: =B5-C5+D5
A6: Book value of equity | B6: 128249 | D6: 132390
A7: Book value of debt | B7: =75427+8105+3500 | D7: =10493+3499+73557
A8: Do you have operating lease commitments?
A9: Cash and cross holdings | B9: =20484+46671+170430 | D9: =16371+44081+184638
A10: Non-operating assets | B10: 0 | D10: 0
A11: Minority interests | B11: 0 | D11: 0
A12: Number of shares outstanding =
A13: Current stock price =
A14: Effective tax rate = | B14: =15885/61372 | C14: =6392/24416 | D14: =6289/24180
A15: Marginal tax rate =
A16: Lease commitments
A17: Year 1 | B17: 929 | D17: NA
A18: Year 2 | B18: 919 | C18: Copy into operating lease worksheet | D18: NA
A19: Year 3 | B19: 915 | D19: NA
A20: Year 4 | B20: 889 | D20: NA
A21: Year 5 | B21: 836 | D21: NA
A22: Beyond year 5 | B22: 3139 | D22: NA
A25: Current year's lease expense | B25: 939
D29: 75872
D30: 2404
D31: 24171
D32: 276

Sheet Answer keys
A1: Yes/No | B1: Book or Market Value | C1: ERP choices | D1: Cost of debt | E1: Synthetic rating | F1: Beta
A2: Yes | B2: B | C2: Will input | D2: Direct input | E2: 1 | F2: Direct input
A3: No | B3: V | C3: Country of incorporation | D3: Synthetic rating | E3: 2 | F3: Single Business(US)
C4: Operating countries | D4: Actual rating | F4: Single Business(Global)
C5: Operating regions | F5: Multibusiness(US)
F6: Multibusiness(Global)

Sheet Historical financing basis
A1: Historical financing basis
A3: This reconstruction fixes the historical lease financing rate at the unique self-consistent rating/lease solution from the original September 2018 model.
A5: Historical pre-tax lease financing rate | B5: 0.0413
A7: The original lease commitments, rating bands, lease present-value formulas and operating-earnings adjustments remain available in their source worksheets.
A9: This rate is a fixed historical input for the growth, operating-margin and discount-rate review. Future forecast, cash-flow and valuation outputs remain calculation work.
A11: Source: Aswath Damodaran, AmazonSept18.xlsx, September 2018. Project construction adjustment; the untouched original is retained separately.
