Workbook

Sheet Readme
A1: Long Term Growth Model (LTGM) Spreadsheet
A2: V4.42
A3: 44546
A4: Spreadsheet developed by Steven Pennings, Leonardo Garrido and Jorge Luis Guzman
F5: (with guidance from Norman Loayza and input from Rishabh Sinha)
A6: DECMG, World Bank
A8: Comments and suggestions welcome, please email Steven Pennings (spennings@worldbank.org) or LTGM@worldbank.org
A9: The spreadsheet updated regularly, please check back LTGM website (below) for the last version:
A10: http://www.worldbank.org/LTGM
A11: Based on the model by Hevia and Loayza (2012) "Savings and Growth in Egypt" Middle East Development Journal 4 (1)
A12: Thanks to Vinaya Swaroop for project overview and Diego Barrot for assistance with data
A14: See the pdf "Long Term Growth Model V4_3" for a list of model equations, and an explanation of the drivers of growth in the LTGM.
A15: System Requirements: | C15: if using Excel 2010 or later all features work as planned*
C16: if using earlier versions of Excel, dropdown menus are not supported; but there is an easy fix - see instruction (7) below
C17: There are no macros in this spreadsheet
A18: New in v4 - poverty extension. Now users can see the implications of growth fundamentals for poverty rates. See Model description Section 5 for a description
A20: 1) General Instructions
A21: Worksheet "InputDataA_GeneralAssumptions" controls most simulation parameters and assumptions that affect all three models
A22: Choose your country from the drop down menu at the top left of "InputDataA_GeneralAssumptions" (select the cell first).
A23: Data from that country will automatically be populated, but you can specify most of the parameters yourself if you choose (see Worksheet "GraphsA" figures of general assumptions).
A24: Worksheet "InputDataB_ModelSpecAssumptions" controls model-specific parameters
A25: If you want to calculate growth for a given investment-to-GDP profile, use Model 1
A26: If you want to calculate required investment to achieve a target growth path, use Model 2
A27: If you want to calculate growth for a given savings-to-GDP profile, use Model 3
A28: (This this last case also requires some assumption on external balance, described below)
A29: See Worksheet "GrapshB" for graphs of model-specific inputs and outputs
A30: Color coding: | B30: Yellow= can edit | D30: Grey=not active (don’t edit) | G30: Red = formulas/populated data (don't edit)
A32: 2) Entering General Parameter Assumptions (use InputDataA_GeneralAssumptions)
A33: In most cases you can choose "automatic" or "manual" version of each series from a drop-down menu
A34: - if automatic, select a target value and the year it is achieved and the spreadsheet automatically generates a smooth path to get there
A35: - if manual, you must type the values manually into the ""Manual" [user defined year by year]" yellow cells to the right in InputDataA and InputDataB (they become yellow when you select manual from the drop down menu)
A36: Model 1, 2 and 3 uses the same general parameters as each other; Model 1s, 2s and 3s uses the same general parameters as each other("s" is for scenarios - see below)
A37: The parameters which actually go into the calculations are listed in "Summary of Inputs based on User's choice" in the Model 1(s), Model 2(s) and Model 3(s) spreadsheets
A39: 3) Entering Model 1-, Model 2- or Model 3-specific parameters - Use InputDataB sheet
A40: For Model 1, choose either "automated" or "manual" values for a path of I/Y (as above), these will not affect Model 2 or 3
A41: For Model 2, choose between the types of growth target: a GDP per capita growth target, a headline GDP growth target, a GDP per capita levels target (does not affect Model 1 or 3)
A42: - Then choose between "automated" or "manual" values for a path of the growth target. If automatic, you also need to choose an end date as above and the model generates a smooth path
A43: - If choose "manual" then you need to enter the values corresponding to the type of growth target in InputDataB on the RHS row 13 and 19. Eg 5000 (for a GDP per capita levels target) or 0.06 (for a growth target)
A44: - The model automatically interprets the "type" of these numbers, and converts them to an implied GDP per capita growth target the Model 2 and Model 2s sheets
... A69: Scenarios allows you to easily compare two outputs given different assumptions in the "GraphsA" and "GraphsB" worksheet
B70: For example, to calculate growth rates given the same investment profile but different TFP growth assumptions, use Model 1 for one (baseline) TFP assumption, and Model 1s (scenario) for the alternative TFP assumption.
A72: Model 1, 2, 3 apply to the "baseline". Model 1s, 2s, 3s apply to the "scenarios". Automatic and Manual (from the drop-down menu) apply to both Baseline and Scenario
A73: - this means if you set a series to manual, you need to manually type in those values into "User defined, year by year" yellow cells in worksheet "InputDataA_ GeneralAssumptions" or "InputDataB_ModelSpecAssumptions" for both baseline and scenario
A74: These switch to yellow (user able to edit) when you chose manual from the dropdown menu.
A76: 7) Instruction specfic for pre-Excel 2010 versions
A77: In pre-2010 versions of Excel the dropdown menus don't work. But this is easy to fix by manually typing the values instead (making sure spelling is exact). Worksheet: InputDataA_ GeneralAssumptions
A78: Country Name InputDataA_ GeneralAssumptions B3)
A79: - lookup your country name in data>Cells B23+ edit the cell and copy the text of the country name in the edit bar at the top of the screen (DO NOT copy the cell, just the text - you will need unhide the "data" worksheet)
A80: - edit InputDataA_ GeneralAssumptions>B3, and paste the name of county text into the edit bar at the top of the screen
A81: - alternatively, just Type the Country name into InputDataA_ GeneralAssumptions>B3, making sure that the Country name is spelt correctly
A82: Automatic vs Manual (Inputdata: Various Cells)
A83: - Type "Automatic" or "Manual" (without quotes) to run that series in Automatic or Manual mode
A84: External balance
... A89: * in testing, occationally conditonal formatting would only update when one changed to a different tab.

Sheet InputDataA_GeneralAssumptions
B1: General Assumptions and Parameters for all Sub-models | G1: Key | AN1: ="35 hidden columns for years "&AN19+1&" to "&AN19+35&" -->"
B2: Country (World Bank Name): | G2: Fields in yellow are for the user to edit | H2: Field in grey are inactive (do not edit)
B3: Zambia | C3: <-- Select from list | G3: Initial data/generated output, user is NOT able to edit | H3: Interpolated data
G4: Note: If choosing "manual" from the drop down menu for universal parameters (grey), please enter values for that series by hand in the yellow field "User defined, year by year" on right
B6: Initial and Final years | C6: units
B7: Initial year for estimation--> | C7: (YYYY) | D7: 2019
B8: Final year for estimation --> | C8: (YYYY) | D8: 2050
B10: Parameters | C10: =""&DataSummary!D142&" for "&B3&"" | D10: =DataSummary!N4 | E10: =DataSummary!N5 | H10: =""&DataSummary!D191&"" | I10: =DataSummary!N4 | J10: =DataSummary!N5
B11: Depreciation rate, user defined --> | C11: (e.g. 0.07) | D11: 0.049 | E11: 0.049 | G11: Initial K/Y ratio (user defined) --> | H11: (e.g. 0.40) | I11: 2.42 | J11: 2.42
B12: Depreciation rate, pre-loaded based on | C12: PWT 8.1 | D12: =IF(ISNUMBER(DataSummary!B142)=TRUE(),DataSummary!B142,".") | G12: Initial K/Y ratio, (pre-loaded) --> | H12: MFMOD | I12: =IF(ISNUMBER(DataSummary!B191)=TRUE(),DataSummary!B191,".")
B13: Depreciation rate is / are (if cells D11:E11 are blank, uses D12): --> | C13: (e.g. 0.07) | D13: =IF(ISBLANK(D11)=TRUE(),D12,D11) | E13: =IF(ISBLANK(E11)=TRUE(),D12,E11) | G13: Initial is (if cell I11:J11 is blank uses pre-loaded) --> | H13: (e.g. 0.40) | I13: =IF(ISBLANK(I11)=TRUE(),I12,I11) | J13: =IF(ISBLANK(J11)=TRUE(),I12,J11)
B14: Labor Shares, user defined --> | C14: =""&DataSummary!D161&" for "&B3&"" | D14: 0.618 | E14: 0.618 | G14: Initial GDP per capita (user defined) --> | H14: (Unit defined by user)
B15: ="Labor Shares, pre-loaded (Based on "&DataSummary!D161&")" | C15: Default (PWT 8.1 / GTAP / Interpolated) | D15: =IF(ISNUMBER(DataSummary!B161)=TRUE(),DataSummary!B161,".") | G15: ="Initial GDP per capita, "&DataSummary!D286&", pre-loaded -->" | H15: WDI 2019 | I15: =IF(ISNUMBER(DataSummary!B286)=TRUE(),DataSummary!B286,".")
B16: Labor Share is / are (if cells D14:E14 are blank, uses D15): --> | C16: (e.g. 0.40) | D16: =IF(ISBLANK(D14)=TRUE(),D15,D14) | E16: =IF(ISBLANK(E14)=TRUE(),D15,E14) | G16: Initial is: (if cell I14:J14 is blank uses pre-loaded) --> | H16: =IF(ISBLANK(I14)=TRUE(),H15,H14) | I16: =IF(ISBLANK(I14)=TRUE(),I15,I14) | J16: =IF(ISBLANK(J14)=TRUE(),I15,J14)
B18: Assumptions
B19: Human Capital (HK) (applies to all models) | C19: =""&DataSummary!D182&"" | D19: =DataSummary!N4 | E19: =DataSummary!N5 | F19: =D24 | G19: Human Capital Index Annual Growth Rate | H19: Chart | I19: =InputDataA_GeneralAssumptions!$D$7 | J19: =I19+1 | K19: =J19+1 | L19: =K19+1 | M19: =L19+1 | N19: =M19+1 | O19: =N19+1 | P19: =O19+1 | Q19: =P19+1 | ... BW19: =BV19+1
B20: Initial Human Capital Index annual growth rate (user defined) --> | C20: (e.g. 0.01) | D20: 0.006 | E20: 0.006 | F20: =DataSummary!N4 | G20: "Manual" [user defined year by year] | H20: (e.g. 0.02) | I20: =I21 | J20: 0.01 | K20: 0.01 | L20: 0.01 | M20: 0.01 | N20: 0.01 | O20: 0.01 | P20: 0.01 | Q20: 0.01 | R20: 0.01 | S20: 0.01 | T20: 0.01 | U20: 0.01 | V20: 0.01 | W20: 0.01 | X20: 0.01 | Y20: 0.01 | Z20: 0.01 | AA20: 0.01 | AB20: 0.01 | AC20: 0.01 | AD20: 0.01 | AE20: 0.01 | AF20: 0.01 | AG20: 0.01 | AH20: 0.01 | AI20: 0.01 | AJ20: 0.01 | AK20: 0.01 | AL20: 0.01 | AM20: 0.01 | AN20: 0.01 | AO20: 0.01 | AP20: 0.01 | AQ20: 0.01 | AR20: 0.01 | AS20: 0.01 | AT20: =AS20 | AU20: =AT20 | AV20: =AU20 | AW20: =AV20 | AX20: =AW20 | AY20: =AX20 | AZ20: =AY20 | BA20: =AZ20 | ... BW20: =BV20
B21: Initial Human Capital Index, pre-loaded based on | C21: PWT 9.1 15yr avg | D21: =IF(ISNUMBER(DataSummary!B182)=TRUE(),DataSummary!B182,".") | G21: "Automatic" [reach target by year] | H21: =H20 | I21: =InputDataA_GeneralAssumptions!D22 | J21: =IF(J19>InputDataA_GeneralAssumptions!$D$26,InputDataA_GeneralAssumptions!$D$25,I21+(InputDataA_GeneralAssumptions!$D$25-$I$21)/(InputDataA_GeneralAssumptions!$D$26-InputDataA_GeneralAssumptions!$D$7)) | K21: =IF(K19>InputDataA_GeneralAssumptions!$D$26,InputDataA_GeneralAssumptions!$D$25,J21+(InputDataA_GeneralAssumptions!$D$25-$I$21)/(InputDataA_GeneralAssumptions!$D$26-InputDataA_GeneralAssumptions!$D$7)) | L21: =IF(L19>InputDataA_GeneralAssumptions!$D$26,InputDataA_GeneralAssumptions!$D$25,K21+(InputDataA_GeneralAssumptions!$D$25-$I$21)/(InputDataA_GeneralAssumptions!$D$26-InputDataA_GeneralAssumptions!$D$7)) | M21: =IF(M19>InputDataA_GeneralAssumptions!$D$26,InputDataA_GeneralAssumptions!$D$25,L21+(InputDataA_GeneralAssumptions!$D$25-$I$21)/(InputDataA_GeneralAssumptions!$D$26-InputDataA_GeneralAssumptions!$D$7)) | N21: =IF(N19>InputDataA_GeneralAssumptions!$D$26,InputDataA_GeneralAssumptions!$D$25,M21+(InputDataA_GeneralAssumptions!$D$25-$I$21)/(InputDataA_GeneralAssumptions!$D$26-InputDataA_GeneralAssumptions!$D$7)) | O21: =IF(O19>InputDataA_GeneralAssumptions!$D$26,InputDataA_GeneralAssumptions!$D$25,N21+(InputDataA_GeneralAssumptions!$D$25-$I$21)/(InputDataA_GeneralAssumptions!$D$26-InputDataA_GeneralAssumptions!$D$7)) | P21: =IF(P19>InputDataA_GeneralAssumptions!$D$26,InputDataA_GeneralAssumptions!$D$25,O21+(InputDataA_GeneralAssumptions!$D$25-$I$21)/(InputDataA_GeneralAssumptions!$D$26-InputDataA_GeneralAssumptions!$D$7)) | Q21: =IF(Q19>InputDataA_GeneralAssumptions!$D$26,InputDataA_GeneralAssumptions!$D$25,P21+(InputDataA_GeneralAssumptions!$D$25-$I$21)/(InputDataA_GeneralAssumptions!$D$26-InputDataA_GeneralAssumptions!$D$7)) | ... BW21: =IF(BW19>InputDataA_GeneralAssumptions!$D$26,InputDataA_GeneralAssumptions!$D$25,BV21+(InputDataA_GeneralAssumptions!$D$25-$I$21)/(InputDataA_GeneralAssumptions!$D$26-InputDataA_GeneralAssumptions!$D$7))
B22: Initial is: (if cell D20:E20 -yellow- is blank uses pre-loaded) --> | C22: (e.g. 0.01) | D22: =IF(ISBLANK(D20)=TRUE(),D21,D20) | E22: =IF(ISBLANK(E20)=TRUE(),D21,E20) | G22: Used in "baseline" simulation | H22: =H21 | I22: =IF(VLOOKUP(InputDataA_GeneralAssumptions!$D$24,DataSummary!$A$110:$B$112,2,FALSE())=1,InputDataA_GeneralAssumptions!I20,InputDataA_GeneralAssumptions!I21) | J22: =IF(VLOOKUP(InputDataA_GeneralAssumptions!$D$24,DataSummary!$A$110:$B$112,2,FALSE())=1,InputDataA_GeneralAssumptions!J20,InputDataA_GeneralAssumptions!J21) | K22: =IF(VLOOKUP(InputDataA_GeneralAssumptions!$D$24,DataSummary!$A$110:$B$112,2,FALSE())=1,InputDataA_GeneralAssumptions!K20,InputDataA_GeneralAssumptions!K21) | L22: =IF(VLOOKUP(InputDataA_GeneralAssumptions!$D$24,DataSummary!$A$110:$B$112,2,FALSE())=1,InputDataA_GeneralAssumptions!L20,InputDataA_GeneralAssumptions!L21) | M22: =IF(VLOOKUP(InputDataA_GeneralAssumptions!$D$24,DataSummary!$A$110:$B$112,2,FALSE())=1,InputDataA_GeneralAssumptions!M20,InputDataA_GeneralAssumptions!M21) | N22: =IF(VLOOKUP(InputDataA_GeneralAssumptions!$D$24,DataSummary!$A$110:$B$112,2,FALSE())=1,InputDataA_GeneralAssumptions!N20,InputDataA_GeneralAssumptions!N21) | O22: =IF(VLOOKUP(InputDataA_GeneralAssumptions!$D$24,DataSummary!$A$110:$B$112,2,FALSE())=1,InputDataA_GeneralAssumptions!O20,InputDataA_GeneralAssumptions!O21) | P22: =IF(VLOOKUP(InputDataA_GeneralAssumptions!$D$24,DataSummary!$A$110:$B$112,2,FALSE())=1,InputDataA_GeneralAssumptions!P20,InputDataA_GeneralAssumptions!P21) | ... BW22: =IF(VLOOKUP(InputDataA_GeneralAssumptions!$D$24,DataSummary!$A$110:$B$112,2,FALSE())=1,InputDataA_GeneralAssumptions!BW20,InputDataA_GeneralAssumptions!BW21)
B24: Choice for future growth rate of HK: | C24: Select from list --> | D24: Automatic | F24: =DataSummary!N5 | G24: "Manual" [user defined year by year] | H24: (e.g. 0.02) | I24: =I25 | J24: 0.01 | K24: 0.01 | L24: 0.01 | M24: 0.01 | N24: 0.01 | O24: 0.01 | P24: 0.01 | Q24: 0.01 | R24: 0.01 | S24: 0.01 | T24: 0.01 | U24: 0.01 | V24: 0.01 | W24: 0.01 | X24: 0.01 | Y24: 0.01 | Z24: 0.01 | AA24: 0.01 | AB24: 0.01 | AC24: 0.01 | AD24: 0.01 | AE24: 0.01 | AF24: 0.01 | AG24: 0.01 | AH24: 0.01 | AI24: 0.01 | AJ24: 0.01 | AK24: 0.01 | AL24: 0.01 | AM24: 0.01 | AN24: 0.01 | AO24: 0.01 | AP24: 0.01 | AQ24: 0.01 | AR24: 0.01 | AS24: 0.01 | AT24: 0.01 | AU24: 0.01 | AV24: 0.01 | AW24: 0.01 | AX24: 0.01 | AY24: 0.01 | AZ24: 0.01 | BA24: 0.01 | BB24: 0.01 | BC24: 0.01 | BD24: 0.01 | BE24: 0.01 | BF24: 0.01 | BG24: 0.01 | BH24: 0.01 | BI24: 0.01 | BJ24: 0.01 | BK24: 0.01 | BL24: 0.01 | BM24: 0.01 | BN24: 0.01 | BO24: 0.01 | BP24: 0.01 | BQ24: 0.01 | BR24: 0.01 | BS24: 0.01 | BT24: 0.01 | BU24: 0.01 | BV24: 0.01 | BW24: 0.01
B25: Target Human Capital Index annual growth rate --> | C25: (e.g. 0.01) | D25: =D22 | E25: =E22 | G25: "Automatic" [reach target by year] | H25: =H24 | I25: =InputDataA_GeneralAssumptions!E22 | J25: =IF(J19>InputDataA_GeneralAssumptions!$E$26,InputDataA_GeneralAssumptions!$E$25,I25+(InputDataA_GeneralAssumptions!$E$25-$I$25)/(InputDataA_GeneralAssumptions!$E$26-InputDataA_GeneralAssumptions!$D$7)) | K25: =IF(K19>InputDataA_GeneralAssumptions!$E$26,InputDataA_GeneralAssumptions!$E$25,J25+(InputDataA_GeneralAssumptions!$E$25-$I$25)/(InputDataA_GeneralAssumptions!$E$26-InputDataA_GeneralAssumptions!$D$7)) | L25: =IF(L19>InputDataA_GeneralAssumptions!$E$26,InputDataA_GeneralAssumptions!$E$25,K25+(InputDataA_GeneralAssumptions!$E$25-$I$25)/(InputDataA_GeneralAssumptions!$E$26-InputDataA_GeneralAssumptions!$D$7)) | M25: =IF(M19>InputDataA_GeneralAssumptions!$E$26,InputDataA_GeneralAssumptions!$E$25,L25+(InputDataA_GeneralAssumptions!$E$25-$I$25)/(InputDataA_GeneralAssumptions!$E$26-InputDataA_GeneralAssumptions!$D$7)) | N25: =IF(N19>InputDataA_GeneralAssumptions!$E$26,InputDataA_GeneralAssumptions!$E$25,M25+(InputDataA_GeneralAssumptions!$E$25-$I$25)/(InputDataA_GeneralAssumptions!$E$26-InputDataA_GeneralAssumptions!$D$7)) | O25: =IF(O19>InputDataA_GeneralAssumptions!$E$26,InputDataA_GeneralAssumptions!$E$25,N25+(InputDataA_GeneralAssumptions!$E$25-$I$25)/(InputDataA_GeneralAssumptions!$E$26-InputDataA_GeneralAssumptions!$D$7)) | P25: =IF(P19>InputDataA_GeneralAssumptions!$E$26,InputDataA_GeneralAssumptions!$E$25,O25+(InputDataA_GeneralAssumptions!$E$25-$I$25)/(InputDataA_GeneralAssumptions!$E$26-InputDataA_GeneralAssumptions!$D$7)) | Q25: =IF(Q19>InputDataA_GeneralAssumptions!$E$26,InputDataA_GeneralAssumptions!$E$25,P25+(InputDataA_GeneralAssumptions!$E$25-$I$25)/(InputDataA_GeneralAssumptions!$E$26-InputDataA_GeneralAssumptions!$D$7)) | ... BW25: =IF(BW19>InputDataA_GeneralAssumptions!$E$26,InputDataA_GeneralAssumptions!$E$25,BV25+(InputDataA_GeneralAssumptions!$E$25-$I$25)/(InputDataA_GeneralAssumptions!$E$26-InputDataA_GeneralAssumptions!$D$7))
B26: Reach Target HK annual growth rate by year --> | C26: (YYYY) | D26: 2030 | E26: =D26 | G26: Used in "scenario" simulation | H26: =H25 | I26: =IF(VLOOKUP(InputDataA_GeneralAssumptions!$D$24,DataSummary!$A$110:$B$112,2,FALSE())=1,InputDataA_GeneralAssumptions!I24,InputDataA_GeneralAssumptions!I25) | J26: =IF(VLOOKUP(InputDataA_GeneralAssumptions!$D$24,DataSummary!$A$110:$B$112,2,FALSE())=1,InputDataA_GeneralAssumptions!J24,InputDataA_GeneralAssumptions!J25) | K26: =IF(VLOOKUP(InputDataA_GeneralAssumptions!$D$24,DataSummary!$A$110:$B$112,2,FALSE())=1,InputDataA_GeneralAssumptions!K24,InputDataA_GeneralAssumptions!K25) | L26: =IF(VLOOKUP(InputDataA_GeneralAssumptions!$D$24,DataSummary!$A$110:$B$112,2,FALSE())=1,InputDataA_GeneralAssumptions!L24,InputDataA_GeneralAssumptions!L25) | M26: =IF(VLOOKUP(InputDataA_GeneralAssumptions!$D$24,DataSummary!$A$110:$B$112,2,FALSE())=1,InputDataA_GeneralAssumptions!M24,InputDataA_GeneralAssumptions!M25) | N26: =IF(VLOOKUP(InputDataA_GeneralAssumptions!$D$24,DataSummary!$A$110:$B$112,2,FALSE())=1,InputDataA_GeneralAssumptions!N24,InputDataA_GeneralAssumptions!N25) | O26: =IF(VLOOKUP(InputDataA_GeneralAssumptions!$D$24,DataSummary!$A$110:$B$112,2,FALSE())=1,InputDataA_GeneralAssumptions!O24,InputDataA_GeneralAssumptions!O25) | P26: =IF(VLOOKUP(InputDataA_GeneralAssumptions!$D$24,DataSummary!$A$110:$B$112,2,FALSE())=1,InputDataA_GeneralAssumptions!P24,InputDataA_GeneralAssumptions!P25) | ... BW26: =IF(VLOOKUP(InputDataA_GeneralAssumptions!$D$24,DataSummary!$A$110:$B$112,2,FALSE())=1,InputDataA_GeneralAssumptions!BW24,InputDataA_GeneralAssumptions!BW25)
B28: Total Factor Productivity (TFP) (applies to all models) | C28: =""&DataSummary!D211&"" | D28: =DataSummary!N4 | E28: =DataSummary!N5 | F28: =D33 | G28: Total Factor Productivity Annual Growth Rate | H28: Chart | I28: =InputDataA_GeneralAssumptions!$D$7 | J28: =I28+1 | K28: =J28+1 | L28: =K28+1 | M28: =L28+1 | N28: =M28+1 | O28: =N28+1 | P28: =O28+1 | Q28: =P28+1 | ... BW28: =BV28+1
B29: Initial TFP annual growth rate (user defined) --> | C29: (e.g. 0.01) | D29: 0.01 | E29: 0.01 | F29: =DataSummary!N4 | G29: "Manual" [user defined year by year] | H29: (e.g. 0.02) | I29: =I30 | J29: 0.01 | K29: 0.01 | L29: 0.01 | M29: 0.01 | N29: 0.01 | O29: 0.01 | P29: 0.01 | Q29: 0.01 | R29: 0.01 | S29: 0.01 | T29: 0.01 | U29: 0.01 | V29: 0.01 | W29: 0.01 | X29: 0.01 | Y29: 0.01 | Z29: 0.01 | AA29: 0.01 | AB29: 0.01 | AC29: 0.01 | AD29: 0.01 | AE29: 0.01 | AF29: 0.01 | AG29: 0.01 | AH29: 0.01 | AI29: 0.01 | AJ29: 0.01 | AK29: 0.01 | AL29: 0.01 | AM29: 0.01 | AN29: 0.01 | AO29: 0.01 | AP29: 0.01 | AQ29: 0.01 | AR29: 0.01 | AS29: 0.01 | AT29: =AS29 | AU29: =AT29 | AV29: =AU29 | AW29: =AV29 | AX29: =AW29 | AY29: =AX29 | AZ29: =AY29 | BA29: =AZ29 | ... BW29: =BV29
B30: ="Initial TFP based on " | C30: PWT 9.1 15yr avg | D30: =IF(ISNUMBER(DataSummary!B211)=TRUE(),DataSummary!B211,".") | G30: "Automatic" [reach target by year] | H30: =H29 | I30: =InputDataA_GeneralAssumptions!D31 | J30: =IF(J28>InputDataA_GeneralAssumptions!$D$35,InputDataA_GeneralAssumptions!$D$34,I30+(InputDataA_GeneralAssumptions!$D$34-$I$30)/(InputDataA_GeneralAssumptions!$D$35-InputDataA_GeneralAssumptions!$D$7)) | K30: =IF(K28>InputDataA_GeneralAssumptions!$D$35,InputDataA_GeneralAssumptions!$D$34,J30+(InputDataA_GeneralAssumptions!$D$34-$I$30)/(InputDataA_GeneralAssumptions!$D$35-InputDataA_GeneralAssumptions!$D$7)) | L30: =IF(L28>InputDataA_GeneralAssumptions!$D$35,InputDataA_GeneralAssumptions!$D$34,K30+(InputDataA_GeneralAssumptions!$D$34-$I$30)/(InputDataA_GeneralAssumptions!$D$35-InputDataA_GeneralAssumptions!$D$7)) | M30: =IF(M28>InputDataA_GeneralAssumptions!$D$35,InputDataA_GeneralAssumptions!$D$34,L30+(InputDataA_GeneralAssumptions!$D$34-$I$30)/(InputDataA_GeneralAssumptions!$D$35-InputDataA_GeneralAssumptions!$D$7)) | N30: =IF(N28>InputDataA_GeneralAssumptions!$D$35,InputDataA_GeneralAssumptions!$D$34,M30+(InputDataA_GeneralAssumptions!$D$34-$I$30)/(InputDataA_GeneralAssumptions!$D$35-InputDataA_GeneralAssumptions!$D$7)) | O30: =IF(O28>InputDataA_GeneralAssumptions!$D$35,InputDataA_GeneralAssumptions!$D$34,N30+(InputDataA_GeneralAssumptions!$D$34-$I$30)/(InputDataA_GeneralAssumptions!$D$35-InputDataA_GeneralAssumptions!$D$7)) | P30: =IF(P28>InputDataA_GeneralAssumptions!$D$35,InputDataA_GeneralAssumptions!$D$34,O30+(InputDataA_GeneralAssumptions!$D$34-$I$30)/(InputDataA_GeneralAssumptions!$D$35-InputDataA_GeneralAssumptions!$D$7)) | Q30: =IF(Q28>InputDataA_GeneralAssumptions!$D$35,InputDataA_GeneralAssumptions!$D$34,P30+(InputDataA_GeneralAssumptions!$D$34-$I$30)/(InputDataA_GeneralAssumptions!$D$35-InputDataA_GeneralAssumptions!$D$7)) | ... BW30: =IF(BW28>InputDataA_GeneralAssumptions!$D$35,InputDataA_GeneralAssumptions!$D$34,BV30+(InputDataA_GeneralAssumptions!$D$34-$I$30)/(InputDataA_GeneralAssumptions!$D$35-InputDataA_GeneralAssumptions!$D$7))
B31: Initial is: (if cell D29:E29 -yellow- is blank uses pre-loaded) --> | C31: (e.g. 0.01) | D31: =IF(ISBLANK(D29)=TRUE(),D30,D29) | E31: =IF(ISBLANK(E29)=TRUE(),D30,E29) | G31: Used in "baseline" simulation | H31: =H30 | I31: =IF(VLOOKUP(InputDataA_GeneralAssumptions!$D$33,DataSummary!$A$110:$B$112,2,FALSE())=1,InputDataA_GeneralAssumptions!I29,InputDataA_GeneralAssumptions!I30) | J31: =IF(VLOOKUP(InputDataA_GeneralAssumptions!$D$33,DataSummary!$A$110:$B$112,2,FALSE())=1,InputDataA_GeneralAssumptions!J29,InputDataA_GeneralAssumptions!J30) | K31: =IF(VLOOKUP(InputDataA_GeneralAssumptions!$D$33,DataSummary!$A$110:$B$112,2,FALSE())=1,InputDataA_GeneralAssumptions!K29,InputDataA_GeneralAssumptions!K30) | L31: =IF(VLOOKUP(InputDataA_GeneralAssumptions!$D$33,DataSummary!$A$110:$B$112,2,FALSE())=1,InputDataA_GeneralAssumptions!L29,InputDataA_GeneralAssumptions!L30) | M31: =IF(VLOOKUP(InputDataA_GeneralAssumptions!$D$33,DataSummary!$A$110:$B$112,2,FALSE())=1,InputDataA_GeneralAssumptions!M29,InputDataA_GeneralAssumptions!M30) | N31: =IF(VLOOKUP(InputDataA_GeneralAssumptions!$D$33,DataSummary!$A$110:$B$112,2,FALSE())=1,InputDataA_GeneralAssumptions!N29,InputDataA_GeneralAssumptions!N30) | O31: =IF(VLOOKUP(InputDataA_GeneralAssumptions!$D$33,DataSummary!$A$110:$B$112,2,FALSE())=1,InputDataA_GeneralAssumptions!O29,InputDataA_GeneralAssumptions!O30) | P31: =IF(VLOOKUP(InputDataA_GeneralAssumptions!$D$33,DataSummary!$A$110:$B$112,2,FALSE())=1,InputDataA_GeneralAssumptions!P29,InputDataA_GeneralAssumptions!P30) | ... BW31: =IF(VLOOKUP(InputDataA_GeneralAssumptions!$D$33,DataSummary!$A$110:$B$112,2,FALSE())=1,InputDataA_GeneralAssumptions!BW29,InputDataA_GeneralAssumptions!BW30)
B33: Choice for future growth rate of TFP: | C33: Select from list --> | D33: Automatic | F33: =DataSummary!N5 | G33: "Manual" [user defined year by year] | H33: (e.g. 0.02) | I33: =I34 | J33: 0.01 | K33: 0.01 | L33: 0.01 | M33: 0.01 | N33: 0.01 | O33: 0.01 | P33: 0.01 | Q33: 0.01 | R33: 0.01 | S33: 0.01 | T33: 0.01 | U33: 0.01 | V33: 0.01 | W33: 0.01 | X33: 0.01 | Y33: 0.01 | Z33: 0.01 | AA33: 0.01 | AB33: 0.01 | AC33: 0.01 | AD33: 0.01 | AE33: 0.01 | AF33: 0.01 | AG33: 0.01 | AH33: 0.01 | AI33: 0.01 | AJ33: 0.01 | AK33: 0.01 | AL33: 0.01 | AM33: 0.01 | AN33: 0.01 | AO33: 0.01 | AP33: 0.01 | AQ33: 0.01 | AR33: 0.01 | AS33: 0.01 | AT33: 0.01 | AU33: 0.01 | AV33: 0.01 | AW33: 0.01 | AX33: 0.01 | AY33: 0.01 | AZ33: 0.01 | BA33: 0.01 | BB33: 0.01 | BC33: 0.01 | BD33: 0.01 | BE33: 0.01 | BF33: 0.01 | BG33: 0.01 | BH33: 0.01 | BI33: 0.01 | BJ33: 0.01 | BK33: 0.01 | BL33: 0.01 | BM33: 0.01 | BN33: 0.01 | BO33: 0.01 | BP33: 0.01 | BQ33: 0.01 | BR33: 0.01 | BS33: 0.01 | BT33: 0.01 | BU33: 0.01 | BV33: 0.01 | BW33: 0.01
B34: Target TFP annual growth rate --> | C34: (e.g. 0.01) | D34: =D31 | E34: =D34 | G34: "Automatic" [reach target by year] | H34: =H33 | I34: =InputDataA_GeneralAssumptions!E31 | J34: =IF(J28>InputDataA_GeneralAssumptions!$E$35,InputDataA_GeneralAssumptions!$E$34,I34+(InputDataA_GeneralAssumptions!$E$34-InputDataA_GeneralAssumptions!$I$34)/(InputDataA_GeneralAssumptions!$E$35-InputDataA_GeneralAssumptions!$D$7)) | K34: =IF(K28>InputDataA_GeneralAssumptions!$E$35,InputDataA_GeneralAssumptions!$E$34,J34+(InputDataA_GeneralAssumptions!$E$34-InputDataA_GeneralAssumptions!$I$34)/(InputDataA_GeneralAssumptions!$E$35-InputDataA_GeneralAssumptions!$D$7)) | L34: =IF(L28>InputDataA_GeneralAssumptions!$E$35,InputDataA_GeneralAssumptions!$E$34,K34+(InputDataA_GeneralAssumptions!$E$34-InputDataA_GeneralAssumptions!$I$34)/(InputDataA_GeneralAssumptions!$E$35-InputDataA_GeneralAssumptions!$D$7)) | M34: =IF(M28>InputDataA_GeneralAssumptions!$E$35,InputDataA_GeneralAssumptions!$E$34,L34+(InputDataA_GeneralAssumptions!$E$34-InputDataA_GeneralAssumptions!$I$34)/(InputDataA_GeneralAssumptions!$E$35-InputDataA_GeneralAssumptions!$D$7)) | N34: =IF(N28>InputDataA_GeneralAssumptions!$E$35,InputDataA_GeneralAssumptions!$E$34,M34+(InputDataA_GeneralAssumptions!$E$34-InputDataA_GeneralAssumptions!$I$34)/(InputDataA_GeneralAssumptions!$E$35-InputDataA_GeneralAssumptions!$D$7)) | O34: =IF(O28>InputDataA_GeneralAssumptions!$E$35,InputDataA_GeneralAssumptions!$E$34,N34+(InputDataA_GeneralAssumptions!$E$34-InputDataA_GeneralAssumptions!$I$34)/(InputDataA_GeneralAssumptions!$E$35-InputDataA_GeneralAssumptions!$D$7)) | P34: =IF(P28>InputDataA_GeneralAssumptions!$E$35,InputDataA_GeneralAssumptions!$E$34,O34+(InputDataA_GeneralAssumptions!$E$34-InputDataA_GeneralAssumptions!$I$34)/(InputDataA_GeneralAssumptions!$E$35-InputDataA_GeneralAssumptions!$D$7)) | Q34: =IF(Q28>InputDataA_GeneralAssumptions!$E$35,InputDataA_GeneralAssumptions!$E$34,P34+(InputDataA_GeneralAssumptions!$E$34-InputDataA_GeneralAssumptions!$I$34)/(InputDataA_GeneralAssumptions!$E$35-InputDataA_GeneralAssumptions!$D$7)) | ... BW34: =IF(BW28>InputDataA_GeneralAssumptions!$E$35,InputDataA_GeneralAssumptions!$E$34,BV34+(InputDataA_GeneralAssumptions!$E$34-InputDataA_GeneralAssumptions!$I$34)/(InputDataA_GeneralAssumptions!$E$35-InputDataA_GeneralAssumptions!$D$7))
B35: Reach target TFP annual growth rate by year --> | C35: (YYYY) | D35: 2030 | E35: =D35 | G35: Used in "scenario" simulation | H35: =H34 | I35: =IF(VLOOKUP(InputDataA_GeneralAssumptions!$D$33,DataSummary!$A$110:$B$112,2,FALSE())=1,InputDataA_GeneralAssumptions!I33,InputDataA_GeneralAssumptions!I34) | J35: =IF(VLOOKUP(InputDataA_GeneralAssumptions!$D$33,DataSummary!$A$110:$B$112,2,FALSE())=1,InputDataA_GeneralAssumptions!J33,InputDataA_GeneralAssumptions!J34) | K35: =IF(VLOOKUP(InputDataA_GeneralAssumptions!$D$33,DataSummary!$A$110:$B$112,2,FALSE())=1,InputDataA_GeneralAssumptions!K33,InputDataA_GeneralAssumptions!K34) | L35: =IF(VLOOKUP(InputDataA_GeneralAssumptions!$D$33,DataSummary!$A$110:$B$112,2,FALSE())=1,InputDataA_GeneralAssumptions!L33,InputDataA_GeneralAssumptions!L34) | M35: =IF(VLOOKUP(InputDataA_GeneralAssumptions!$D$33,DataSummary!$A$110:$B$112,2,FALSE())=1,InputDataA_GeneralAssumptions!M33,InputDataA_GeneralAssumptions!M34) | N35: =IF(VLOOKUP(InputDataA_GeneralAssumptions!$D$33,DataSummary!$A$110:$B$112,2,FALSE())=1,InputDataA_GeneralAssumptions!N33,InputDataA_GeneralAssumptions!N34) | O35: =IF(VLOOKUP(InputDataA_GeneralAssumptions!$D$33,DataSummary!$A$110:$B$112,2,FALSE())=1,InputDataA_GeneralAssumptions!O33,InputDataA_GeneralAssumptions!O34) | P35: =IF(VLOOKUP(InputDataA_GeneralAssumptions!$D$33,DataSummary!$A$110:$B$112,2,FALSE())=1,InputDataA_GeneralAssumptions!P33,InputDataA_GeneralAssumptions!P34) | ... BW35: =IF(VLOOKUP(InputDataA_GeneralAssumptions!$D$33,DataSummary!$A$110:$B$112,2,FALSE())=1,InputDataA_GeneralAssumptions!BW33,InputDataA_GeneralAssumptions!BW34)
B38: Labor Market Participation | F38: =D39 | G38: Participation rate, male | H38: Chart | I38: =InputDataA_GeneralAssumptions!$D$7 | J38: =I38+1 | K38: =J38+1 | L38: =K38+1 | M38: =L38+1 | N38: =M38+1 | O38: =N38+1 | P38: =O38+1 | Q38: =P38+1 | ... BW38: =BV38+1
B39: Choice for Future Labor Participation: | C39: Select from list --> | D39: Automatic | F39: =DataSummary!N4 | G39: "Manual" [user defined year by year] | H39: (e.g. 0.40) | I39: =I40 | J39: 0.86728206 | K39: 0.86753571 | L39: 0.86782619 | M39: 0.86815595 | N39: 0.86852709 | O39: 0.86894124 | P39: 0.86939952 | Q39: 0.86990245 | R39: 0.87044993 | S39: 0.8710412 | T39: 0.87167486 | U39: 0.87234885 | V39: 0.87306054 | W39: 0.87380676 | X39: 0.87458387 | Y39: 0.87538787 | Z39: 0.87621445 | AA39: 0.87705914 | AB39: 0.87791734 | AC39: 0.87878448 | AD39: 0.87965603 | AE39: 0.88052764 | AF39: 0.88139516 | AG39: 0.88225471 | AH39: 0.88310273 | AI39: 0.88393598 | AJ39: 0.88475159 | AK39: 0.88554707 | AL39: 0.88632025 | AM39: 0.88706938 | AN39: 0.887793 | AO39: 0.88849002 | AP39: 0.88915962 | AQ39: 0.8898013 | AR39: 0.89041477 | AS39: 0.891 | AT39: =AS39 | AU39: =AT39 | AV39: =AU39 | AW39: =AV39 | AX39: =AW39 | AY39: =AX39 | AZ39: =AY39 | BA39: =AZ39 | ... BW39: =BV39
B40: Initial participation rate --> | C40: (e.g. 0.40) | D40: =IF(ISNUMBER(DataSummary!D35)=TRUE(),DataSummary!D35,".") | G40: "Automatic" [reach target by year] | H40: =H39 | I40: =InputDataA_GeneralAssumptions!D44 | J40: =IF(J38>InputDataA_GeneralAssumptions!$D$47,InputDataA_GeneralAssumptions!$D$46,I40+(InputDataA_GeneralAssumptions!$D$46-$I$40)/(InputDataA_GeneralAssumptions!$D$47-InputDataA_GeneralAssumptions!$D$7)) | K40: =IF(K38>InputDataA_GeneralAssumptions!$D$47,InputDataA_GeneralAssumptions!$D$46,J40+(InputDataA_GeneralAssumptions!$D$46-$I$40)/(InputDataA_GeneralAssumptions!$D$47-InputDataA_GeneralAssumptions!$D$7)) | L40: =IF(L38>InputDataA_GeneralAssumptions!$D$47,InputDataA_GeneralAssumptions!$D$46,K40+(InputDataA_GeneralAssumptions!$D$46-$I$40)/(InputDataA_GeneralAssumptions!$D$47-InputDataA_GeneralAssumptions!$D$7)) | M40: =IF(M38>InputDataA_GeneralAssumptions!$D$47,InputDataA_GeneralAssumptions!$D$46,L40+(InputDataA_GeneralAssumptions!$D$46-$I$40)/(InputDataA_GeneralAssumptions!$D$47-InputDataA_GeneralAssumptions!$D$7)) | N40: =IF(N38>InputDataA_GeneralAssumptions!$D$47,InputDataA_GeneralAssumptions!$D$46,M40+(InputDataA_GeneralAssumptions!$D$46-$I$40)/(InputDataA_GeneralAssumptions!$D$47-InputDataA_GeneralAssumptions!$D$7)) | O40: =IF(O38>InputDataA_GeneralAssumptions!$D$47,InputDataA_GeneralAssumptions!$D$46,N40+(InputDataA_GeneralAssumptions!$D$46-$I$40)/(InputDataA_GeneralAssumptions!$D$47-InputDataA_GeneralAssumptions!$D$7)) | P40: =IF(P38>InputDataA_GeneralAssumptions!$D$47,InputDataA_GeneralAssumptions!$D$46,O40+(InputDataA_GeneralAssumptions!$D$46-$I$40)/(InputDataA_GeneralAssumptions!$D$47-InputDataA_GeneralAssumptions!$D$7)) | Q40: =IF(Q38>InputDataA_GeneralAssumptions!$D$47,InputDataA_GeneralAssumptions!$D$46,P40+(InputDataA_GeneralAssumptions!$D$46-$I$40)/(InputDataA_GeneralAssumptions!$D$47-InputDataA_GeneralAssumptions!$D$7)) | ... BW40: =IF(BW38>InputDataA_GeneralAssumptions!$D$47,InputDataA_GeneralAssumptions!$D$46,BV40+(InputDataA_GeneralAssumptions!$D$46-$I$40)/(InputDataA_GeneralAssumptions!$D$47-InputDataA_GeneralAssumptions!$D$7))
B41: Participation rate, male | G41: Used in "baseline" simulation | H41: (e.g. 0.40) | I41: =IF(VLOOKUP(InputDataA_GeneralAssumptions!$D$39,DataSummary!$A$110:$B$112,2,FALSE())=1,InputDataA_GeneralAssumptions!I39,InputDataA_GeneralAssumptions!I40) | J41: =IF(VLOOKUP(InputDataA_GeneralAssumptions!$D$39,DataSummary!$A$110:$B$112,2,FALSE())=1,InputDataA_GeneralAssumptions!J39,InputDataA_GeneralAssumptions!J40) | K41: =IF(VLOOKUP(InputDataA_GeneralAssumptions!$D$39,DataSummary!$A$110:$B$112,2,FALSE())=1,InputDataA_GeneralAssumptions!K39,InputDataA_GeneralAssumptions!K40) | L41: =IF(VLOOKUP(InputDataA_GeneralAssumptions!$D$39,DataSummary!$A$110:$B$112,2,FALSE())=1,InputDataA_GeneralAssumptions!L39,InputDataA_GeneralAssumptions!L40) | M41: =IF(VLOOKUP(InputDataA_GeneralAssumptions!$D$39,DataSummary!$A$110:$B$112,2,FALSE())=1,InputDataA_GeneralAssumptions!M39,InputDataA_GeneralAssumptions!M40) | N41: =IF(VLOOKUP(InputDataA_GeneralAssumptions!$D$39,DataSummary!$A$110:$B$112,2,FALSE())=1,InputDataA_GeneralAssumptions!N39,InputDataA_GeneralAssumptions!N40) | O41: =IF(VLOOKUP(InputDataA_GeneralAssumptions!$D$39,DataSummary!$A$110:$B$112,2,FALSE())=1,InputDataA_GeneralAssumptions!O39,InputDataA_GeneralAssumptions!O40) | P41: =IF(VLOOKUP(InputDataA_GeneralAssumptions!$D$39,DataSummary!$A$110:$B$112,2,FALSE())=1,InputDataA_GeneralAssumptions!P39,InputDataA_GeneralAssumptions!P40) | ... BW41: =IF(VLOOKUP(InputDataA_GeneralAssumptions!$D$39,DataSummary!$A$110:$B$112,2,FALSE())=1,InputDataA_GeneralAssumptions!BW39,InputDataA_GeneralAssumptions!BW40)
B42: Initial participation rate, male (user defined) --> | C42: (e.g. 0.40)
B43: ="Init partic rate male, pre-loaded (Avail. "&D7&") -->" | C43: (e.g. 0.40) | D43: =IF(ISNUMBER(DataSummary!D36)=TRUE(),DataSummary!D36,".") | F43: =DataSummary!N5 | G43: "Manual" [user defined year by year] | H43: (e.g. 0.40) | I43: =I44 | J43: 0.86728206 | K43: 0.86753571 | L43: 0.86782619 | M43: 0.86815595 | N43: 0.86852709 | O43: 0.86894124 | P43: 0.86939952 | Q43: 0.86990245 | R43: 0.87044993 | S43: 0.8710412 | T43: 0.87167486 | U43: 0.87234885 | V43: 0.87306054 | W43: 0.87380676 | X43: 0.87458387 | Y43: 0.87538787 | Z43: 0.87621445 | AA43: 0.87705914 | AB43: 0.87791734 | AC43: 0.87878448 | AD43: 0.87965603 | AE43: 0.88052764 | AF43: 0.88139516 | AG43: 0.88225471 | AH43: 0.88310273 | AI43: 0.88393598 | AJ43: 0.88475159 | AK43: 0.88554707 | AL43: 0.88632025 | AM43: 0.88706938 | AN43: 0.887793 | AO43: 0.88849002 | AP43: 0.88915962 | AQ43: 0.8898013 | AR43: 0.89041477 | AS43: 0.891 | AT43: 0.891 | AU43: 0.891 | AV43: 0.891 | AW43: 0.891 | AX43: 0.891 | AY43: 0.891 | AZ43: 0.891 | BA43: 0.891 | BB43: 0.891 | BC43: 0.891 | BD43: 0.891 | BE43: 0.891 | BF43: 0.891 | BG43: 0.891 | BH43: 0.891 | BI43: 0.891 | BJ43: 0.891 | BK43: 0.891 | BL43: 0.891 | BM43: 0.891 | BN43: 0.891 | BO43: 0.891 | BP43: 0.891 | BQ43: 0.891 | BR43: 0.891 | BS43: 0.891 | BT43: 0.891 | BU43: 0.891 | BV43: 0.891 | BW43: 0.891
B44: Initial is: (if cell D42:E42 -yellow- is blank uses pre-loaded) --> | C44: (e.g. 0.40) | D44: =IF(ISBLANK(D42)=TRUE(),D43,D42) | E44: =IF(ISBLANK(E42)=TRUE(),D43,E42) | G44: "Automatic" [reach target by year] | H44: (e.g. 0.40) | I44: =InputDataA_GeneralAssumptions!E44 | J44: =IF(J38>InputDataA_GeneralAssumptions!$E$47,InputDataA_GeneralAssumptions!$E$46,I44+(InputDataA_GeneralAssumptions!$E$46-$I$44)/(InputDataA_GeneralAssumptions!$E$47-InputDataA_GeneralAssumptions!$D$7)) | K44: =IF(K38>InputDataA_GeneralAssumptions!$E$47,InputDataA_GeneralAssumptions!$E$46,J44+(InputDataA_GeneralAssumptions!$E$46-$I$44)/(InputDataA_GeneralAssumptions!$E$47-InputDataA_GeneralAssumptions!$D$7)) | L44: =IF(L38>InputDataA_GeneralAssumptions!$E$47,InputDataA_GeneralAssumptions!$E$46,K44+(InputDataA_GeneralAssumptions!$E$46-$I$44)/(InputDataA_GeneralAssumptions!$E$47-InputDataA_GeneralAssumptions!$D$7)) | M44: =IF(M38>InputDataA_GeneralAssumptions!$E$47,InputDataA_GeneralAssumptions!$E$46,L44+(InputDataA_GeneralAssumptions!$E$46-$I$44)/(InputDataA_GeneralAssumptions!$E$47-InputDataA_GeneralAssumptions!$D$7)) | N44: =IF(N38>InputDataA_GeneralAssumptions!$E$47,InputDataA_GeneralAssumptions!$E$46,M44+(InputDataA_GeneralAssumptions!$E$46-$I$44)/(InputDataA_GeneralAssumptions!$E$47-InputDataA_GeneralAssumptions!$D$7)) | O44: =IF(O38>InputDataA_GeneralAssumptions!$E$47,InputDataA_GeneralAssumptions!$E$46,N44+(InputDataA_GeneralAssumptions!$E$46-$I$44)/(InputDataA_GeneralAssumptions!$E$47-InputDataA_GeneralAssumptions!$D$7)) | P44: =IF(P38>InputDataA_GeneralAssumptions!$E$47,InputDataA_GeneralAssumptions!$E$46,O44+(InputDataA_GeneralAssumptions!$E$46-$I$44)/(InputDataA_GeneralAssumptions!$E$47-InputDataA_GeneralAssumptions!$D$7)) | Q44: =IF(Q38>InputDataA_GeneralAssumptions!$E$47,InputDataA_GeneralAssumptions!$E$46,P44+(InputDataA_GeneralAssumptions!$E$46-$I$44)/(InputDataA_GeneralAssumptions!$E$47-InputDataA_GeneralAssumptions!$D$7)) | ... BW44: =IF(BW38>InputDataA_GeneralAssumptions!$E$47,InputDataA_GeneralAssumptions!$E$46,BV44+(InputDataA_GeneralAssumptions!$E$46-$I$44)/(InputDataA_GeneralAssumptions!$E$47-InputDataA_GeneralAssumptions!$D$7))
G45: Used in "scenario" simulation | H45: (e.g. 0.40) | I45: =IF(VLOOKUP(InputDataA_GeneralAssumptions!$D$39,DataSummary!$A$110:$B$112,2,FALSE())=1,InputDataA_GeneralAssumptions!I43,InputDataA_GeneralAssumptions!I44) | J45: =IF(VLOOKUP(InputDataA_GeneralAssumptions!$D$39,DataSummary!$A$110:$B$112,2,FALSE())=1,InputDataA_GeneralAssumptions!J43,InputDataA_GeneralAssumptions!J44) | K45: =IF(VLOOKUP(InputDataA_GeneralAssumptions!$D$39,DataSummary!$A$110:$B$112,2,FALSE())=1,InputDataA_GeneralAssumptions!K43,InputDataA_GeneralAssumptions!K44) | L45: =IF(VLOOKUP(InputDataA_GeneralAssumptions!$D$39,DataSummary!$A$110:$B$112,2,FALSE())=1,InputDataA_GeneralAssumptions!L43,InputDataA_GeneralAssumptions!L44) | M45: =IF(VLOOKUP(InputDataA_GeneralAssumptions!$D$39,DataSummary!$A$110:$B$112,2,FALSE())=1,InputDataA_GeneralAssumptions!M43,InputDataA_GeneralAssumptions!M44) | N45: =IF(VLOOKUP(InputDataA_GeneralAssumptions!$D$39,DataSummary!$A$110:$B$112,2,FALSE())=1,InputDataA_GeneralAssumptions!N43,InputDataA_GeneralAssumptions!N44) | O45: =IF(VLOOKUP(InputDataA_GeneralAssumptions!$D$39,DataSummary!$A$110:$B$112,2,FALSE())=1,InputDataA_GeneralAssumptions!O43,InputDataA_GeneralAssumptions!O44) | P45: =IF(VLOOKUP(InputDataA_GeneralAssumptions!$D$39,DataSummary!$A$110:$B$112,2,FALSE())=1,InputDataA_GeneralAssumptions!P43,InputDataA_GeneralAssumptions!P44) | ... BW45: =IF(VLOOKUP(InputDataA_GeneralAssumptions!$D$39,DataSummary!$A$110:$B$112,2,FALSE())=1,InputDataA_GeneralAssumptions!BW43,InputDataA_GeneralAssumptions!BW44)
B46: Target participation rate, male --> | C46: (e.g. 0.40) | D46: =D44 | E46: =E44
B47: Reach target Participation Rate Male by year --> | C47: (YYYY) | D47: 2030 | E47: 2030 | G47: Participation rate, female | H47: Chart | I47: =InputDataA_GeneralAssumptions!$D$7 | J47: =I47+1 | K47: =J47+1 | L47: =K47+1 | M47: =L47+1 | N47: =M47+1 | O47: =N47+1 | P47: =O47+1 | Q47: =P47+1 | ... BW47: =BV47+1
F48: =DataSummary!N4 | G48: "Manual" [user defined year by year] | H48: (e.g. 0.40) | I48: =I49 | J48: 0.61435265 | K48: 0.61725912 | L48: 0.62085306 | M48: 0.6251849 | N48: 0.63027769 | O48: 0.63612271 | P48: 0.64267805 | Q48: 0.64987035 | R48: 0.65759959 | S48: 0.66574585 | T48: 0.67417742 | U48: 0.68275899 | V48: 0.69135918 | W48: 0.69985674 | X48: 0.70814506 | Y48: 0.71613494 | Z48: 0.72375576 | AA48: 0.73095535 | AB48: 0.73769873 | AC48: 0.74396634 | AD48: 0.74975179 | AE48: 0.75505949 | AF48: 0.75990237 | AG48: 0.76429978 | AH48: 0.76827556 | AI48: 0.77185648 | AJ48: 0.77507092 | AK48: 0.77794784 | AL48: 0.78051593 | AM48: 0.78280305 | AN48: 0.7848358 | AO48: 0.78663923 | AP48: 0.7882367 | AQ48: 0.78964977 | AR48: 0.7908982 | AS48: 0.792 | AT48: =AS48 | AU48: =AT48 | AV48: =AU48 | AW48: =AV48 | AX48: =AW48 | AY48: =AX48 | AZ48: =AY48 | BA48: =AZ48 | ... BW48: =BV48
G49: "Automatic" [reach target by year] | H49: =H48 | I49: =InputDataA_GeneralAssumptions!D53 | J49: =IF(J47>InputDataA_GeneralAssumptions!$D$56,InputDataA_GeneralAssumptions!$D$55,I49+(InputDataA_GeneralAssumptions!$D$55-$I$49)/(InputDataA_GeneralAssumptions!$D$56-InputDataA_GeneralAssumptions!$D$7)) | K49: =IF(K47>InputDataA_GeneralAssumptions!$D$56,InputDataA_GeneralAssumptions!$D$55,J49+(InputDataA_GeneralAssumptions!$D$55-$I$49)/(InputDataA_GeneralAssumptions!$D$56-InputDataA_GeneralAssumptions!$D$7)) | L49: =IF(L47>InputDataA_GeneralAssumptions!$D$56,InputDataA_GeneralAssumptions!$D$55,K49+(InputDataA_GeneralAssumptions!$D$55-$I$49)/(InputDataA_GeneralAssumptions!$D$56-InputDataA_GeneralAssumptions!$D$7)) | M49: =IF(M47>InputDataA_GeneralAssumptions!$D$56,InputDataA_GeneralAssumptions!$D$55,L49+(InputDataA_GeneralAssumptions!$D$55-$I$49)/(InputDataA_GeneralAssumptions!$D$56-InputDataA_GeneralAssumptions!$D$7)) | N49: =IF(N47>InputDataA_GeneralAssumptions!$D$56,InputDataA_GeneralAssumptions!$D$55,M49+(InputDataA_GeneralAssumptions!$D$55-$I$49)/(InputDataA_GeneralAssumptions!$D$56-InputDataA_GeneralAssumptions!$D$7)) | O49: =IF(O47>InputDataA_GeneralAssumptions!$D$56,InputDataA_GeneralAssumptions!$D$55,N49+(InputDataA_GeneralAssumptions!$D$55-$I$49)/(InputDataA_GeneralAssumptions!$D$56-InputDataA_GeneralAssumptions!$D$7)) | P49: =IF(P47>InputDataA_GeneralAssumptions!$D$56,InputDataA_GeneralAssumptions!$D$55,O49+(InputDataA_GeneralAssumptions!$D$55-$I$49)/(InputDataA_GeneralAssumptions!$D$56-InputDataA_GeneralAssumptions!$D$7)) | Q49: =IF(Q47>InputDataA_GeneralAssumptions!$D$56,InputDataA_GeneralAssumptions!$D$55,P49+(InputDataA_GeneralAssumptions!$D$55-$I$49)/(InputDataA_GeneralAssumptions!$D$56-InputDataA_GeneralAssumptions!$D$7)) | ... BW49: =IF(BW47>InputDataA_GeneralAssumptions!$D$56,InputDataA_GeneralAssumptions!$D$55,BV49+(InputDataA_GeneralAssumptions!$D$55-$I$49)/(InputDataA_GeneralAssumptions!$D$56-InputDataA_GeneralAssumptions!$D$7))
B50: Participation rate, female | G50: Used in "baseline" simulation | H50: =H49 | I50: =IF(VLOOKUP(InputDataA_GeneralAssumptions!$D$39,DataSummary!$A$110:$B$112,2,FALSE())=1,InputDataA_GeneralAssumptions!I48,InputDataA_GeneralAssumptions!I49) | J50: =IF(VLOOKUP(InputDataA_GeneralAssumptions!$D$39,DataSummary!$A$110:$B$112,2,FALSE())=1,InputDataA_GeneralAssumptions!J48,InputDataA_GeneralAssumptions!J49) | K50: =IF(VLOOKUP(InputDataA_GeneralAssumptions!$D$39,DataSummary!$A$110:$B$112,2,FALSE())=1,InputDataA_GeneralAssumptions!K48,InputDataA_GeneralAssumptions!K49) | L50: =IF(VLOOKUP(InputDataA_GeneralAssumptions!$D$39,DataSummary!$A$110:$B$112,2,FALSE())=1,InputDataA_GeneralAssumptions!L48,InputDataA_GeneralAssumptions!L49) | M50: =IF(VLOOKUP(InputDataA_GeneralAssumptions!$D$39,DataSummary!$A$110:$B$112,2,FALSE())=1,InputDataA_GeneralAssumptions!M48,InputDataA_GeneralAssumptions!M49) | N50: =IF(VLOOKUP(InputDataA_GeneralAssumptions!$D$39,DataSummary!$A$110:$B$112,2,FALSE())=1,InputDataA_GeneralAssumptions!N48,InputDataA_GeneralAssumptions!N49) | O50: =IF(VLOOKUP(InputDataA_GeneralAssumptions!$D$39,DataSummary!$A$110:$B$112,2,FALSE())=1,InputDataA_GeneralAssumptions!O48,InputDataA_GeneralAssumptions!O49) | P50: =IF(VLOOKUP(InputDataA_GeneralAssumptions!$D$39,DataSummary!$A$110:$B$112,2,FALSE())=1,InputDataA_GeneralAssumptions!P48,InputDataA_GeneralAssumptions!P49) | ... BW50: =IF(VLOOKUP(InputDataA_GeneralAssumptions!$D$39,DataSummary!$A$110:$B$112,2,FALSE())=1,InputDataA_GeneralAssumptions!BW48,InputDataA_GeneralAssumptions!BW49)
B51: Initial participation rate, female (user defined) --> | C51: (e.g. 0.40)
B52: ="Init Partic rate female, pre-loaded(Avail. until "&D7&") -->" | C52: (e.g. 0.40) | D52: =IF(ISNUMBER(DataSummary!D37)=TRUE(),DataSummary!D37,".") | F52: =DataSummary!N5 | G52: "Manual" [user defined year by year] | H52: (e.g. 0.40) | I52: =I53 | J52: 0.61435265 | K52: 0.61725912 | L52: 0.62085306 | M52: 0.6251849 | N52: 0.63027769 | O52: 0.63612271 | P52: 0.64267805 | Q52: 0.64987035 | R52: 0.65759959 | S52: 0.66574585 | T52: 0.67417742 | U52: 0.68275899 | V52: 0.69135918 | W52: 0.69985674 | X52: 0.70814506 | Y52: 0.71613494 | Z52: 0.72375576 | AA52: 0.73095535 | AB52: 0.73769873 | AC52: 0.74396634 | AD52: 0.74975179 | AE52: 0.75505949 | AF52: 0.75990237 | AG52: 0.76429978 | AH52: 0.76827556 | AI52: 0.77185648 | AJ52: 0.77507092 | AK52: 0.77794784 | AL52: 0.78051593 | AM52: 0.78280305 | AN52: 0.7848358 | AO52: 0.78663923 | AP52: 0.7882367 | AQ52: 0.78964977 | AR52: 0.7908982 | AS52: 0.792 | AT52: 0.792 | AU52: 0.792 | AV52: 0.792 | AW52: 0.792 | AX52: 0.792 | AY52: 0.792 | AZ52: 0.792 | BA52: 0.792 | BB52: 0.792 | BC52: 0.792 | BD52: 0.792 | BE52: 0.792 | BF52: 0.792 | BG52: 0.792 | BH52: 0.792 | BI52: 0.792 | BJ52: 0.792 | BK52: 0.792 | BL52: 0.792 | BM52: 0.792 | BN52: 0.792 | BO52: 0.792 | BP52: 0.792 | BQ52: 0.792 | BR52: 0.792 | BS52: 0.792 | BT52: 0.792 | BU52: 0.792 | BV52: 0.792 | BW52: 0.792
B53: Initial is: (if cell D51:E51 -yellow- is blank uses pre-loaded) --> | C53: (e.g. 0.40) | D53: =IF(ISBLANK(D51)=TRUE(),D52,D51) | E53: =IF(ISBLANK(E51)=TRUE(),D52,E51) | G53: "Automatic" [reach target by year] | H53: (e.g. 0.40) | I53: =InputDataA_GeneralAssumptions!E53 | J53: =IF(J47>InputDataA_GeneralAssumptions!$E$56,InputDataA_GeneralAssumptions!$E$55,I53+(InputDataA_GeneralAssumptions!$E$55-$I$53)/(InputDataA_GeneralAssumptions!$E$56-InputDataA_GeneralAssumptions!$D$7)) | K53: =IF(K47>InputDataA_GeneralAssumptions!$E$56,InputDataA_GeneralAssumptions!$E$55,J53+(InputDataA_GeneralAssumptions!$E$55-$I$53)/(InputDataA_GeneralAssumptions!$E$56-InputDataA_GeneralAssumptions!$D$7)) | L53: =IF(L47>InputDataA_GeneralAssumptions!$E$56,InputDataA_GeneralAssumptions!$E$55,K53+(InputDataA_GeneralAssumptions!$E$55-$I$53)/(InputDataA_GeneralAssumptions!$E$56-InputDataA_GeneralAssumptions!$D$7)) | M53: =IF(M47>InputDataA_GeneralAssumptions!$E$56,InputDataA_GeneralAssumptions!$E$55,L53+(InputDataA_GeneralAssumptions!$E$55-$I$53)/(InputDataA_GeneralAssumptions!$E$56-InputDataA_GeneralAssumptions!$D$7)) | N53: =IF(N47>InputDataA_GeneralAssumptions!$E$56,InputDataA_GeneralAssumptions!$E$55,M53+(InputDataA_GeneralAssumptions!$E$55-$I$53)/(InputDataA_GeneralAssumptions!$E$56-InputDataA_GeneralAssumptions!$D$7)) | O53: =IF(O47>InputDataA_GeneralAssumptions!$E$56,InputDataA_GeneralAssumptions!$E$55,N53+(InputDataA_GeneralAssumptions!$E$55-$I$53)/(InputDataA_GeneralAssumptions!$E$56-InputDataA_GeneralAssumptions!$D$7)) | P53: =IF(P47>InputDataA_GeneralAssumptions!$E$56,InputDataA_GeneralAssumptions!$E$55,O53+(InputDataA_GeneralAssumptions!$E$55-$I$53)/(InputDataA_GeneralAssumptions!$E$56-InputDataA_GeneralAssumptions!$D$7)) | Q53: =IF(Q47>InputDataA_GeneralAssumptions!$E$56,InputDataA_GeneralAssumptions!$E$55,P53+(InputDataA_GeneralAssumptions!$E$55-$I$53)/(InputDataA_GeneralAssumptions!$E$56-InputDataA_GeneralAssumptions!$D$7)) | ... BW53: =IF(BW47>InputDataA_GeneralAssumptions!$E$56,InputDataA_GeneralAssumptions!$E$55,BV53+(InputDataA_GeneralAssumptions!$E$55-$I$53)/(InputDataA_GeneralAssumptions!$E$56-InputDataA_GeneralAssumptions!$D$7))
G54: Used in "scenario" simulation | H54: (e.g. 0.40) | I54: =IF(VLOOKUP(InputDataA_GeneralAssumptions!$D$39,DataSummary!$A$110:$B$112,2,FALSE())=1,InputDataA_GeneralAssumptions!I52,InputDataA_GeneralAssumptions!I53) | J54: =IF(VLOOKUP(InputDataA_GeneralAssumptions!$D$39,DataSummary!$A$110:$B$112,2,FALSE())=1,InputDataA_GeneralAssumptions!J52,InputDataA_GeneralAssumptions!J53) | K54: =IF(VLOOKUP(InputDataA_GeneralAssumptions!$D$39,DataSummary!$A$110:$B$112,2,FALSE())=1,InputDataA_GeneralAssumptions!K52,InputDataA_GeneralAssumptions!K53) | L54: =IF(VLOOKUP(InputDataA_GeneralAssumptions!$D$39,DataSummary!$A$110:$B$112,2,FALSE())=1,InputDataA_GeneralAssumptions!L52,InputDataA_GeneralAssumptions!L53) | M54: =IF(VLOOKUP(InputDataA_GeneralAssumptions!$D$39,DataSummary!$A$110:$B$112,2,FALSE())=1,InputDataA_GeneralAssumptions!M52,InputDataA_GeneralAssumptions!M53) | N54: =IF(VLOOKUP(InputDataA_GeneralAssumptions!$D$39,DataSummary!$A$110:$B$112,2,FALSE())=1,InputDataA_GeneralAssumptions!N52,InputDataA_GeneralAssumptions!N53) | O54: =IF(VLOOKUP(InputDataA_GeneralAssumptions!$D$39,DataSummary!$A$110:$B$112,2,FALSE())=1,InputDataA_GeneralAssumptions!O52,InputDataA_GeneralAssumptions!O53) | P54: =IF(VLOOKUP(InputDataA_GeneralAssumptions!$D$39,DataSummary!$A$110:$B$112,2,FALSE())=1,InputDataA_GeneralAssumptions!P52,InputDataA_GeneralAssumptions!P53) | ... BW54: =IF(VLOOKUP(InputDataA_GeneralAssumptions!$D$39,DataSummary!$A$110:$B$112,2,FALSE())=1,InputDataA_GeneralAssumptions!BW52,InputDataA_GeneralAssumptions!BW53)
B55: Target participation rate, female --> | C55: (e.g. 0.40) | D55: =D53 | E55: =E53 | H55: Chart
B56: Reach target Participation Rate Female by year --> | C56: (YYYY) | D56: 2030 | E56: =D56 | F56: =DataSummary!N4 | G56: Labor force participation rate, Total | H56: (e.g. 0.7) | I56: =I41*I103+I50*(1-I103) | J56: =J41*J103+J50*(1-J103) | K56: =K41*K103+K50*(1-K103) | L56: =L41*L103+L50*(1-L103) | M56: =M41*M103+M50*(1-M103) | N56: =N41*N103+N50*(1-N103) | O56: =O41*O103+O50*(1-O103) | P56: =P41*P103+P50*(1-P103) | ... BW56: =BW41*BW103+BW50*(1-BW103)
F57: =DataSummary!N5 | G57: Labor force participation rate, Total | H57: (e.g. 0.7) | I57: =I45*I107+I54*(1-I107) | J57: =J45*J107+J54*(1-J107) | K57: =K45*K107+K54*(1-K107) | L57: =L45*L107+L54*(1-L107) | M57: =M45*M107+M54*(1-M107) | N57: =N45*N107+N54*(1-N107) | O57: =O45*O107+O54*(1-O107) | P57: =P45*P107+P54*(1-P107) | ... BW57: =BW45*BW107+BW54*(1-BW107)
B59: External Balance (applies to all models) | D59: =DataSummary!N4 | E59: =DataSummary!N5
B60: User Defines External Sector Constraint | C60: Select from list --> | D60: CAB
C61: =VLOOKUP(D60,DataSummary!A116:D117,4,FALSE())
B62: (User should choose path for CAB/Y plus CAB/Y=0 for countries with closed capital accounts) | H62: Chart | I62: =InputDataA_GeneralAssumptions!$D$7 | J62: =I62+1 | K62: =J62+1 | L62: =K62+1 | M62: =L62+1 | N62: =M62+1 | O62: =N62+1 | P62: =O62+1 | Q62: =P62+1 | ... BW62: =BV62+1
B63: IF path for CAB / Y is chosen: | F63: =D68 | G63: Current Account Balance | H63: =IF(VLOOKUP(InputDataA_GeneralAssumptions!$D$60,DataSummary!A116:B117,2,FALSE())=1,"This data is utilized, based on User's choice","This data is NOT utilized, based on User's choice")
B64: Initial CAB Ratio (CAB/Y) (user defined) --> | C64: (e.g. 0.02) | F64: =DataSummary!N4 | G64: "Manual" [user defined year by year] | H64: =InputDataA_GeneralAssumptions!H29 | I64: =I65 | J64: -0.0070715672 | K64: -0.0086001294 | L64: -0.010128692 | M64: -0.011657254 | N64: -0.013185816 | O64: -0.014714378 | P64: -0.01624294 | Q64: -0.017771503 | R64: -0.019300065 | S64: -0.020828627 | T64: -0.022357189 | U64: -0.023885751 | V64: -0.025414313 | W64: -0.026942876 | X64: -0.028471438 | Y64: -0.03 | Z64: -0.03 | AA64: -0.03 | AB64: -0.03 | AC64: -0.03 | AD64: -0.03 | AE64: -0.03 | AF64: -0.03 | AG64: -0.03 | AH64: -0.03 | AI64: -0.03 | AJ64: -0.03 | AK64: -0.03 | AL64: -0.03 | AM64: -0.03 | AN64: -0.03 | AO64: -0.03 | AP64: -0.03 | AQ64: -0.03 | AR64: -0.03 | AS64: -0.03 | AT64: =AS64 | AU64: =AT64 | AV64: =AU64 | AW64: =AV64 | AX64: =AW64 | AY64: =AX64 | AZ64: =AY64 | BA64: =AZ64 | ... BW64: =BV64
B65: Initial CAB/GDP, pre-loaded | C65: WDI 15yr ave | D65: =IF(ISNUMBER(DataSummary!B226)=TRUE(),DataSummary!B226,".") | G65: "Automatic" [reach target by year] | H65: =H64 | I65: =InputDataA_GeneralAssumptions!$D$66 | J65: =IF(J62>InputDataA_GeneralAssumptions!$D$70,InputDataA_GeneralAssumptions!$D$69,I65+(InputDataA_GeneralAssumptions!$D$69-$I$65)/(InputDataA_GeneralAssumptions!$D$70-InputDataA_GeneralAssumptions!$D$7)) | K65: =IF(K62>InputDataA_GeneralAssumptions!$D$70,InputDataA_GeneralAssumptions!$D$69,J65+(InputDataA_GeneralAssumptions!$D$69-$I$65)/(InputDataA_GeneralAssumptions!$D$70-InputDataA_GeneralAssumptions!$D$7)) | L65: =IF(L62>InputDataA_GeneralAssumptions!$D$70,InputDataA_GeneralAssumptions!$D$69,K65+(InputDataA_GeneralAssumptions!$D$69-$I$65)/(InputDataA_GeneralAssumptions!$D$70-InputDataA_GeneralAssumptions!$D$7)) | M65: =IF(M62>InputDataA_GeneralAssumptions!$D$70,InputDataA_GeneralAssumptions!$D$69,L65+(InputDataA_GeneralAssumptions!$D$69-$I$65)/(InputDataA_GeneralAssumptions!$D$70-InputDataA_GeneralAssumptions!$D$7)) | N65: =IF(N62>InputDataA_GeneralAssumptions!$D$70,InputDataA_GeneralAssumptions!$D$69,M65+(InputDataA_GeneralAssumptions!$D$69-$I$65)/(InputDataA_GeneralAssumptions!$D$70-InputDataA_GeneralAssumptions!$D$7)) | O65: =IF(O62>InputDataA_GeneralAssumptions!$D$70,InputDataA_GeneralAssumptions!$D$69,N65+(InputDataA_GeneralAssumptions!$D$69-$I$65)/(InputDataA_GeneralAssumptions!$D$70-InputDataA_GeneralAssumptions!$D$7)) | P65: =IF(P62>InputDataA_GeneralAssumptions!$D$70,InputDataA_GeneralAssumptions!$D$69,O65+(InputDataA_GeneralAssumptions!$D$69-$I$65)/(InputDataA_GeneralAssumptions!$D$70-InputDataA_GeneralAssumptions!$D$7)) | Q65: =IF(Q62>InputDataA_GeneralAssumptions!$D$70,InputDataA_GeneralAssumptions!$D$69,P65+(InputDataA_GeneralAssumptions!$D$69-$I$65)/(InputDataA_GeneralAssumptions!$D$70-InputDataA_GeneralAssumptions!$D$7)) | ... BW65: =IF(BW62>InputDataA_GeneralAssumptions!$D$70,InputDataA_GeneralAssumptions!$D$69,BV65+(InputDataA_GeneralAssumptions!$D$69-$I$65)/(InputDataA_GeneralAssumptions!$D$70-InputDataA_GeneralAssumptions!$D$7))
B66: Initial is: (if cell D64:E64 -yellow- is blank uses pre-loaded) --> | C66: (e.g. 0.02) | D66: =IF(ISBLANK(D64)=TRUE(),D65,D64) | E66: =IF(ISBLANK(E64)=TRUE(),D65,E64) | G66: Used in "baseline" simulation | H66: (e.g. 0.02) | I66: =IF(AND(VLOOKUP(InputDataA_GeneralAssumptions!$D$60,DataSummary!$A$116:$B$117,2,FALSE())=1,VLOOKUP(InputDataA_GeneralAssumptions!$D$68,DataSummary!$A$111:$B$112,2,FALSE())=2),InputDataA_GeneralAssumptions!I$65, IF(AND(VLOOKUP(InputDataA_GeneralAssumptions!$D$60,DataSummary!$A$116:$B$117,2,FALSE())=1,VLOOKUP(InputDataA_GeneralAssumptions!$D$68,DataSummary!$A$111:$B$112,2,FALSE())=1), InputDataA_GeneralAssumptions!I$64,"Not an input")) | J66: =IF(AND(VLOOKUP(InputDataA_GeneralAssumptions!$D$60,DataSummary!$A$116:$B$117,2,FALSE())=1,VLOOKUP(InputDataA_GeneralAssumptions!$D$68,DataSummary!$A$111:$B$112,2,FALSE())=2),InputDataA_GeneralAssumptions!J$65, IF(AND(VLOOKUP(InputDataA_GeneralAssumptions!$D$60,DataSummary!$A$116:$B$117,2,FALSE())=1,VLOOKUP(InputDataA_GeneralAssumptions!$D$68,DataSummary!$A$111:$B$112,2,FALSE())=1), InputDataA_GeneralAssumptions!J$64,"Not an input")) | K66: =IF(AND(VLOOKUP(InputDataA_GeneralAssumptions!$D$60,DataSummary!$A$116:$B$117,2,FALSE())=1,VLOOKUP(InputDataA_GeneralAssumptions!$D$68,DataSummary!$A$111:$B$112,2,FALSE())=2),InputDataA_GeneralAssumptions!K$65, IF(AND(VLOOKUP(InputDataA_GeneralAssumptions!$D$60,DataSummary!$A$116:$B$117,2,FALSE())=1,VLOOKUP(InputDataA_GeneralAssumptions!$D$68,DataSummary!$A$111:$B$112,2,FALSE())=1), InputDataA_GeneralAssumptions!K$64,"Not an input")) | L66: =IF(AND(VLOOKUP(InputDataA_GeneralAssumptions!$D$60,DataSummary!$A$116:$B$117,2,FALSE())=1,VLOOKUP(InputDataA_GeneralAssumptions!$D$68,DataSummary!$A$111:$B$112,2,FALSE())=2),InputDataA_GeneralAssumptions!L$65, IF(AND(VLOOKUP(InputDataA_GeneralAssumptions!$D$60,DataSummary!$A$116:$B$117,2,FALSE())=1,VLOOKUP(InputDataA_GeneralAssumptions!$D$68,DataSummary!$A$111:$B$112,2,FALSE())=1), InputDataA_GeneralAssumptions!L$64,"Not an input")) | M66: =IF(AND(VLOOKUP(InputDataA_GeneralAssumptions!$D$60,DataSummary!$A$116:$B$117,2,FALSE())=1,VLOOKUP(InputDataA_GeneralAssumptions!$D$68,DataSummary!$A$111:$B$112,2,FALSE())=2),InputDataA_GeneralAssumptions!M$65, IF(AND(VLOOKUP(InputDataA_GeneralAssumptions!$D$60,DataSummary!$A$116:$B$117,2,FALSE())=1,VLOOKUP(InputDataA_GeneralAssumptions!$D$68,DataSummary!$A$111:$B$112,2,FALSE())=1), InputDataA_GeneralAssumptions!M$64,"Not an input")) | N66: =IF(AND(VLOOKUP(InputDataA_GeneralAssumptions!$D$60,DataSummary!$A$116:$B$117,2,FALSE())=1,VLOOKUP(InputDataA_GeneralAssumptions!$D$68,DataSummary!$A$111:$B$112,2,FALSE())=2),InputDataA_GeneralAssumptions!N$65, IF(AND(VLOOKUP(InputDataA_GeneralAssumptions!$D$60,DataSummary!$A$116:$B$117,2,FALSE())=1,VLOOKUP(InputDataA_GeneralAssumptions!$D$68,DataSummary!$A$111:$B$112,2,FALSE())=1), InputDataA_GeneralAssumptions!N$64,"Not an input")) | O66: =IF(AND(VLOOKUP(InputDataA_GeneralAssumptions!$D$60,DataSummary!$A$116:$B$117,2,FALSE())=1,VLOOKUP(InputDataA_GeneralAssumptions!$D$68,DataSummary!$A$111:$B$112,2,FALSE())=2),InputDataA_GeneralAssumptions!O$65, IF(AND(VLOOKUP(InputDataA_GeneralAssumptions!$D$60,DataSummary!$A$116:$B$117,2,FALSE())=1,VLOOKUP(InputDataA_GeneralAssumptions!$D$68,DataSummary!$A$111:$B$112,2,FALSE())=1), InputDataA_GeneralAssumptions!O$64,"Not an input")) | P66: =IF(AND(VLOOKUP(InputDataA_GeneralAssumptions!$D$60,DataSummary!$A$116:$B$117,2,FALSE())=1,VLOOKUP(InputDataA_GeneralAssumptions!$D$68,DataSummary!$A$111:$B$112,2,FALSE())=2),InputDataA_GeneralAssumptions!P$65, IF(AND(VLOOKUP(InputDataA_GeneralAssumptions!$D$60,DataSummary!$A$116:$B$117,2,FALSE())=1,VLOOKUP(InputDataA_GeneralAssumptions!$D$68,DataSummary!$A$111:$B$112,2,FALSE())=1), InputDataA_GeneralAssumptions!P$64,"Not an input")) | ... BW66: =IF(AND(VLOOKUP(InputDataA_GeneralAssumptions!$D$60,DataSummary!$A$116:$B$117,2,FALSE())=1,VLOOKUP(InputDataA_GeneralAssumptions!$D$68,DataSummary!$A$111:$B$112,2,FALSE())=2),InputDataA_GeneralAssumptions!BW$65, IF(AND(VLOOKUP(InputDataA_GeneralAssumptions!$D$60,DataSummary!$A$116:$B$117,2,FALSE())=1,VLOOKUP(InputDataA_GeneralAssumptions!$D$68,DataSummary!$A$111:$B$112,2,FALSE())=1), InputDataA_GeneralAssumptions!BW$64,"Not an input"))
B68: Choice for future Current Account Balance: | C68: Select from list --> | D68: Automatic | F68: =DataSummary!N5 | G68: "Manual" [user defined year by year] | H68: (e.g. 0.02) | I68: =I69 | J68: -0.0070715672 | K68: -0.0086001294 | L68: -0.010128692 | M68: -0.011657254 | N68: -0.013185816 | O68: -0.014714378 | P68: -0.01624294 | Q68: -0.017771503 | R68: -0.019300065 | S68: -0.020828627 | T68: -0.022357189 | U68: -0.023885751 | V68: -0.025414313 | W68: -0.026942876 | X68: -0.028471438 | Y68: -0.03 | Z68: -0.03 | AA68: -0.03 | AB68: -0.03 | AC68: -0.03 | AD68: -0.03 | AE68: -0.03 | AF68: -0.03 | AG68: -0.03 | AH68: -0.03 | AI68: -0.03 | AJ68: -0.03 | AK68: -0.03 | AL68: -0.03 | AM68: -0.03 | AN68: -0.03 | AO68: -0.03 | AP68: -0.03 | AQ68: -0.03 | AR68: -0.03 | AS68: -0.03 | AT68: -0.03 | AU68: -0.03 | AV68: -0.03 | AW68: -0.03 | AX68: -0.03 | AY68: -0.03 | AZ68: -0.03 | BA68: -0.03 | BB68: -0.03 | BC68: -0.03 | BD68: -0.03 | BE68: -0.03 | BF68: -0.03 | BG68: -0.03 | BH68: -0.03 | BI68: -0.03 | BJ68: -0.03 | BK68: -0.03 | BL68: -0.03 | BM68: -0.03 | BN68: -0.03 | BO68: -0.03 | BP68: -0.03 | BQ68: -0.03 | BR68: -0.03 | BS68: -0.03 | BT68: -0.03 | BU68: -0.03 | BV68: -0.03 | BW68: -0.03
B69: Target CAB Ratio (CAB/Y) --> | C69: (e.g. 0.02) | D69: =D66 | E69: =D69 | G69: "Automatic" [reach target by year] | H69: (e.g. 0.02) | I69: =InputDataA_GeneralAssumptions!$E$66 | J69: =IF(J62>InputDataA_GeneralAssumptions!$E$70,InputDataA_GeneralAssumptions!$E$69,I69+(InputDataA_GeneralAssumptions!$E$69-$I$69)/(InputDataA_GeneralAssumptions!$E$70-InputDataA_GeneralAssumptions!$D$7)) | K69: =IF(K62>InputDataA_GeneralAssumptions!$E$70,InputDataA_GeneralAssumptions!$E$69,J69+(InputDataA_GeneralAssumptions!$E$69-$I$69)/(InputDataA_GeneralAssumptions!$E$70-InputDataA_GeneralAssumptions!$D$7)) | L69: =IF(L62>InputDataA_GeneralAssumptions!$E$70,InputDataA_GeneralAssumptions!$E$69,K69+(InputDataA_GeneralAssumptions!$E$69-$I$69)/(InputDataA_GeneralAssumptions!$E$70-InputDataA_GeneralAssumptions!$D$7)) | M69: =IF(M62>InputDataA_GeneralAssumptions!$E$70,InputDataA_GeneralAssumptions!$E$69,L69+(InputDataA_GeneralAssumptions!$E$69-$I$69)/(InputDataA_GeneralAssumptions!$E$70-InputDataA_GeneralAssumptions!$D$7)) | N69: =IF(N62>InputDataA_GeneralAssumptions!$E$70,InputDataA_GeneralAssumptions!$E$69,M69+(InputDataA_GeneralAssumptions!$E$69-$I$69)/(InputDataA_GeneralAssumptions!$E$70-InputDataA_GeneralAssumptions!$D$7)) | O69: =IF(O62>InputDataA_GeneralAssumptions!$E$70,InputDataA_GeneralAssumptions!$E$69,N69+(InputDataA_GeneralAssumptions!$E$69-$I$69)/(InputDataA_GeneralAssumptions!$E$70-InputDataA_GeneralAssumptions!$D$7)) | P69: =IF(P62>InputDataA_GeneralAssumptions!$E$70,InputDataA_GeneralAssumptions!$E$69,O69+(InputDataA_GeneralAssumptions!$E$69-$I$69)/(InputDataA_GeneralAssumptions!$E$70-InputDataA_GeneralAssumptions!$D$7)) | Q69: =IF(Q62>InputDataA_GeneralAssumptions!$E$70,InputDataA_GeneralAssumptions!$E$69,P69+(InputDataA_GeneralAssumptions!$E$69-$I$69)/(InputDataA_GeneralAssumptions!$E$70-InputDataA_GeneralAssumptions!$D$7)) | ... BW69: =IF(BW62>InputDataA_GeneralAssumptions!$E$70,InputDataA_GeneralAssumptions!$E$69,BV69+(InputDataA_GeneralAssumptions!$E$69-$I$69)/(InputDataA_GeneralAssumptions!$E$70-InputDataA_GeneralAssumptions!$D$7))
B70: Reach target CAB/Y rate by year --> | C70: (YYYY) | D70: 2030 | E70: =D70 | G70: Used in "scenario" simulation | H70: (e.g. 0.02) | I70: =IF(AND(VLOOKUP(InputDataA_GeneralAssumptions!$D$60,DataSummary!$A$116:$B$117,2,FALSE())=1,VLOOKUP(InputDataA_GeneralAssumptions!$D$68,DataSummary!$A$111:$B$112,2,FALSE())=2),InputDataA_GeneralAssumptions!I$69, IF(AND(VLOOKUP(InputDataA_GeneralAssumptions!$D$60,DataSummary!$A$116:$B$117,2,FALSE())=1,VLOOKUP(InputDataA_GeneralAssumptions!$D$68,DataSummary!$A$111:$B$112,2,FALSE())=1), InputDataA_GeneralAssumptions!I$68,"Not an input")) | J70: =IF(AND(VLOOKUP(InputDataA_GeneralAssumptions!$D$60,DataSummary!$A$116:$B$117,2,FALSE())=1,VLOOKUP(InputDataA_GeneralAssumptions!$D$68,DataSummary!$A$111:$B$112,2,FALSE())=2),InputDataA_GeneralAssumptions!J$69, IF(AND(VLOOKUP(InputDataA_GeneralAssumptions!$D$60,DataSummary!$A$116:$B$117,2,FALSE())=1,VLOOKUP(InputDataA_GeneralAssumptions!$D$68,DataSummary!$A$111:$B$112,2,FALSE())=1), InputDataA_GeneralAssumptions!J$68,"Not an input")) | K70: =IF(AND(VLOOKUP(InputDataA_GeneralAssumptions!$D$60,DataSummary!$A$116:$B$117,2,FALSE())=1,VLOOKUP(InputDataA_GeneralAssumptions!$D$68,DataSummary!$A$111:$B$112,2,FALSE())=2),InputDataA_GeneralAssumptions!K$69, IF(AND(VLOOKUP(InputDataA_GeneralAssumptions!$D$60,DataSummary!$A$116:$B$117,2,FALSE())=1,VLOOKUP(InputDataA_GeneralAssumptions!$D$68,DataSummary!$A$111:$B$112,2,FALSE())=1), InputDataA_GeneralAssumptions!K$68,"Not an input")) | L70: =IF(AND(VLOOKUP(InputDataA_GeneralAssumptions!$D$60,DataSummary!$A$116:$B$117,2,FALSE())=1,VLOOKUP(InputDataA_GeneralAssumptions!$D$68,DataSummary!$A$111:$B$112,2,FALSE())=2),InputDataA_GeneralAssumptions!L$69, IF(AND(VLOOKUP(InputDataA_GeneralAssumptions!$D$60,DataSummary!$A$116:$B$117,2,FALSE())=1,VLOOKUP(InputDataA_GeneralAssumptions!$D$68,DataSummary!$A$111:$B$112,2,FALSE())=1), InputDataA_GeneralAssumptions!L$68,"Not an input")) | M70: =IF(AND(VLOOKUP(InputDataA_GeneralAssumptions!$D$60,DataSummary!$A$116:$B$117,2,FALSE())=1,VLOOKUP(InputDataA_GeneralAssumptions!$D$68,DataSummary!$A$111:$B$112,2,FALSE())=2),InputDataA_GeneralAssumptions!M$69, IF(AND(VLOOKUP(InputDataA_GeneralAssumptions!$D$60,DataSummary!$A$116:$B$117,2,FALSE())=1,VLOOKUP(InputDataA_GeneralAssumptions!$D$68,DataSummary!$A$111:$B$112,2,FALSE())=1), InputDataA_GeneralAssumptions!M$68,"Not an input")) | N70: =IF(AND(VLOOKUP(InputDataA_GeneralAssumptions!$D$60,DataSummary!$A$116:$B$117,2,FALSE())=1,VLOOKUP(InputDataA_GeneralAssumptions!$D$68,DataSummary!$A$111:$B$112,2,FALSE())=2),InputDataA_GeneralAssumptions!N$69, IF(AND(VLOOKUP(InputDataA_GeneralAssumptions!$D$60,DataSummary!$A$116:$B$117,2,FALSE())=1,VLOOKUP(InputDataA_GeneralAssumptions!$D$68,DataSummary!$A$111:$B$112,2,FALSE())=1), InputDataA_GeneralAssumptions!N$68,"Not an input")) | O70: =IF(AND(VLOOKUP(InputDataA_GeneralAssumptions!$D$60,DataSummary!$A$116:$B$117,2,FALSE())=1,VLOOKUP(InputDataA_GeneralAssumptions!$D$68,DataSummary!$A$111:$B$112,2,FALSE())=2),InputDataA_GeneralAssumptions!O$69, IF(AND(VLOOKUP(InputDataA_GeneralAssumptions!$D$60,DataSummary!$A$116:$B$117,2,FALSE())=1,VLOOKUP(InputDataA_GeneralAssumptions!$D$68,DataSummary!$A$111:$B$112,2,FALSE())=1), InputDataA_GeneralAssumptions!O$68,"Not an input")) | P70: =IF(AND(VLOOKUP(InputDataA_GeneralAssumptions!$D$60,DataSummary!$A$116:$B$117,2,FALSE())=1,VLOOKUP(InputDataA_GeneralAssumptions!$D$68,DataSummary!$A$111:$B$112,2,FALSE())=2),InputDataA_GeneralAssumptions!P$69, IF(AND(VLOOKUP(InputDataA_GeneralAssumptions!$D$60,DataSummary!$A$116:$B$117,2,FALSE())=1,VLOOKUP(InputDataA_GeneralAssumptions!$D$68,DataSummary!$A$111:$B$112,2,FALSE())=1), InputDataA_GeneralAssumptions!P$68,"Not an input")) | ... BW70: =IF(AND(VLOOKUP(InputDataA_GeneralAssumptions!$D$60,DataSummary!$A$116:$B$117,2,FALSE())=1,VLOOKUP(InputDataA_GeneralAssumptions!$D$68,DataSummary!$A$111:$B$112,2,FALSE())=2),InputDataA_GeneralAssumptions!BW$69, IF(AND(VLOOKUP(InputDataA_GeneralAssumptions!$D$60,DataSummary!$A$116:$B$117,2,FALSE())=1,VLOOKUP(InputDataA_GeneralAssumptions!$D$68,DataSummary!$A$111:$B$112,2,FALSE())=1), InputDataA_GeneralAssumptions!BW$68,"Not an input"))
B72: IF external debt constraint is chosen: | H72: Chart | I72: =InputDataA_GeneralAssumptions!$D$7 | J72: =I72+1 | K72: =J72+1 | L72: =K72+1 | M72: =L72+1 | N72: =M72+1 | O72: =N72+1 | P72: =O72+1 | Q72: =P72+1 | ... BW72: =BV72+1
B73: Initial External Debt to GDP ratio (user defined) --> | C73: (e.g. 0.40) | F73: =D76 | G73: Debt Ratio to GDP (end of period) | H73: =IF(VLOOKUP(InputDataA_GeneralAssumptions!$D$60,DataSummary!A116:B117,2,FALSE())=2,"This data is utilized, based on User's choice","This data is NOT utilized, based on User's choice")
B74: Init. External Debt to GDP ratio, pre-loaded --> | C74: (e.g. 0.40) | D74: =IF(ISNUMBER(DataSummary!D40)=TRUE(),DataSummary!D40,".") | F74: =DataSummary!N4 | G74: "Manual" [user defined year by year] | H74: (e.g. 0.40) | I74: =I75 | J74: =J75 | K74: =K75 | L74: =L75 | M74: =M75 | N74: =N75 | O74: =O75 | P74: =P75 | ... AN74: =AN75 | AO74: 0.6 | AP74: 0.6 | AQ74: 0.6 | AR74: 0.6 | AS74: 0.6 | AT74: =AS74 | AU74: =AT74 | AV74: =AU74 | AW74: =AV74 | AX74: =AW74 | AY74: =AX74 | AZ74: =AY74 | BA74: =AZ74 | ... BW74: =BV74
B75: Initial is (if cell D73:E73 is blank uses pre-loaded) --> | C75: (e.g. 0.40) | D75: =IF(ISBLANK(D73)=TRUE(),D74,D73) | E75: =IF(ISBLANK(E73)=TRUE(),D74,E73) | G75: "Automatic" [reach target by year] | H75: =H74 | I75: =InputDataA_GeneralAssumptions!D75 | J75: =InputDataA_GeneralAssumptions!$D$75+(InputDataA_GeneralAssumptions!$D$78-InputDataA_GeneralAssumptions!$D$75)/(1+EXP(-DataSummary!$K$97*(J$72-$I$72)))^(1/DataSummary!$H$97) | K75: =InputDataA_GeneralAssumptions!$D$75+(InputDataA_GeneralAssumptions!$D$78-InputDataA_GeneralAssumptions!$D$75)/(1+EXP(-DataSummary!$K$97*(K$72-$I$72)))^(1/DataSummary!$H$97) | L75: =InputDataA_GeneralAssumptions!$D$75+(InputDataA_GeneralAssumptions!$D$78-InputDataA_GeneralAssumptions!$D$75)/(1+EXP(-DataSummary!$K$97*(L$72-$I$72)))^(1/DataSummary!$H$97) | M75: =InputDataA_GeneralAssumptions!$D$75+(InputDataA_GeneralAssumptions!$D$78-InputDataA_GeneralAssumptions!$D$75)/(1+EXP(-DataSummary!$K$97*(M$72-$I$72)))^(1/DataSummary!$H$97) | N75: =InputDataA_GeneralAssumptions!$D$75+(InputDataA_GeneralAssumptions!$D$78-InputDataA_GeneralAssumptions!$D$75)/(1+EXP(-DataSummary!$K$97*(N$72-$I$72)))^(1/DataSummary!$H$97) | O75: =InputDataA_GeneralAssumptions!$D$75+(InputDataA_GeneralAssumptions!$D$78-InputDataA_GeneralAssumptions!$D$75)/(1+EXP(-DataSummary!$K$97*(O$72-$I$72)))^(1/DataSummary!$H$97) | P75: =InputDataA_GeneralAssumptions!$D$75+(InputDataA_GeneralAssumptions!$D$78-InputDataA_GeneralAssumptions!$D$75)/(1+EXP(-DataSummary!$K$97*(P$72-$I$72)))^(1/DataSummary!$H$97) | Q75: =InputDataA_GeneralAssumptions!$D$75+(InputDataA_GeneralAssumptions!$D$78-InputDataA_GeneralAssumptions!$D$75)/(1+EXP(-DataSummary!$K$97*(Q$72-$I$72)))^(1/DataSummary!$H$97) | ... BW75: =InputDataA_GeneralAssumptions!$D$75+(InputDataA_GeneralAssumptions!$D$78-InputDataA_GeneralAssumptions!$D$75)/(1+EXP(-DataSummary!$K$97*(BW$72-$I$72)))^(1/DataSummary!$H$97)
B76: Choice for future Ratio of External Debt to GDP: | C76: Select from list --> | D76: Automatic | G76: Used in "baseline" simulation | H76: (e.g. 0.40) | I76: =IF(AND(VLOOKUP(InputDataA_GeneralAssumptions!$D$60,DataSummary!$A$116:$B$117,2,FALSE())=2,VLOOKUP(InputDataA_GeneralAssumptions!$D$76,DataSummary!$A$111:$B$112,2,FALSE())=2),InputDataA_GeneralAssumptions!I$75, IF(AND(VLOOKUP(InputDataA_GeneralAssumptions!$D$60,DataSummary!$A$116:$B$117,2,FALSE())=2,VLOOKUP(InputDataA_GeneralAssumptions!$D$76,DataSummary!$A$111:$B$112,2,FALSE())=1), InputDataA_GeneralAssumptions!I$74,"Not an input")) | J76: =IF(AND(VLOOKUP(InputDataA_GeneralAssumptions!$D$60,DataSummary!$A$116:$B$117,2,FALSE())=2,VLOOKUP(InputDataA_GeneralAssumptions!$D$76,DataSummary!$A$111:$B$112,2,FALSE())=2),InputDataA_GeneralAssumptions!J$75, IF(AND(VLOOKUP(InputDataA_GeneralAssumptions!$D$60,DataSummary!$A$116:$B$117,2,FALSE())=2,VLOOKUP(InputDataA_GeneralAssumptions!$D$76,DataSummary!$A$111:$B$112,2,FALSE())=1), InputDataA_GeneralAssumptions!J$74,"Not an input")) | K76: =IF(AND(VLOOKUP(InputDataA_GeneralAssumptions!$D$60,DataSummary!$A$116:$B$117,2,FALSE())=2,VLOOKUP(InputDataA_GeneralAssumptions!$D$76,DataSummary!$A$111:$B$112,2,FALSE())=2),InputDataA_GeneralAssumptions!K$75, IF(AND(VLOOKUP(InputDataA_GeneralAssumptions!$D$60,DataSummary!$A$116:$B$117,2,FALSE())=2,VLOOKUP(InputDataA_GeneralAssumptions!$D$76,DataSummary!$A$111:$B$112,2,FALSE())=1), InputDataA_GeneralAssumptions!K$74,"Not an input")) | L76: =IF(AND(VLOOKUP(InputDataA_GeneralAssumptions!$D$60,DataSummary!$A$116:$B$117,2,FALSE())=2,VLOOKUP(InputDataA_GeneralAssumptions!$D$76,DataSummary!$A$111:$B$112,2,FALSE())=2),InputDataA_GeneralAssumptions!L$75, IF(AND(VLOOKUP(InputDataA_GeneralAssumptions!$D$60,DataSummary!$A$116:$B$117,2,FALSE())=2,VLOOKUP(InputDataA_GeneralAssumptions!$D$76,DataSummary!$A$111:$B$112,2,FALSE())=1), InputDataA_GeneralAssumptions!L$74,"Not an input")) | M76: =IF(AND(VLOOKUP(InputDataA_GeneralAssumptions!$D$60,DataSummary!$A$116:$B$117,2,FALSE())=2,VLOOKUP(InputDataA_GeneralAssumptions!$D$76,DataSummary!$A$111:$B$112,2,FALSE())=2),InputDataA_GeneralAssumptions!M$75, IF(AND(VLOOKUP(InputDataA_GeneralAssumptions!$D$60,DataSummary!$A$116:$B$117,2,FALSE())=2,VLOOKUP(InputDataA_GeneralAssumptions!$D$76,DataSummary!$A$111:$B$112,2,FALSE())=1), InputDataA_GeneralAssumptions!M$74,"Not an input")) | N76: =IF(AND(VLOOKUP(InputDataA_GeneralAssumptions!$D$60,DataSummary!$A$116:$B$117,2,FALSE())=2,VLOOKUP(InputDataA_GeneralAssumptions!$D$76,DataSummary!$A$111:$B$112,2,FALSE())=2),InputDataA_GeneralAssumptions!N$75, IF(AND(VLOOKUP(InputDataA_GeneralAssumptions!$D$60,DataSummary!$A$116:$B$117,2,FALSE())=2,VLOOKUP(InputDataA_GeneralAssumptions!$D$76,DataSummary!$A$111:$B$112,2,FALSE())=1), InputDataA_GeneralAssumptions!N$74,"Not an input")) | O76: =IF(AND(VLOOKUP(InputDataA_GeneralAssumptions!$D$60,DataSummary!$A$116:$B$117,2,FALSE())=2,VLOOKUP(InputDataA_GeneralAssumptions!$D$76,DataSummary!$A$111:$B$112,2,FALSE())=2),InputDataA_GeneralAssumptions!O$75, IF(AND(VLOOKUP(InputDataA_GeneralAssumptions!$D$60,DataSummary!$A$116:$B$117,2,FALSE())=2,VLOOKUP(InputDataA_GeneralAssumptions!$D$76,DataSummary!$A$111:$B$112,2,FALSE())=1), InputDataA_GeneralAssumptions!O$74,"Not an input")) | P76: =IF(AND(VLOOKUP(InputDataA_GeneralAssumptions!$D$60,DataSummary!$A$116:$B$117,2,FALSE())=2,VLOOKUP(InputDataA_GeneralAssumptions!$D$76,DataSummary!$A$111:$B$112,2,FALSE())=2),InputDataA_GeneralAssumptions!P$75, IF(AND(VLOOKUP(InputDataA_GeneralAssumptions!$D$60,DataSummary!$A$116:$B$117,2,FALSE())=2,VLOOKUP(InputDataA_GeneralAssumptions!$D$76,DataSummary!$A$111:$B$112,2,FALSE())=1), InputDataA_GeneralAssumptions!P$74,"Not an input")) | ... BW76: =IF(AND(VLOOKUP(InputDataA_GeneralAssumptions!$D$60,DataSummary!$A$116:$B$117,2,FALSE())=2,VLOOKUP(InputDataA_GeneralAssumptions!$D$76,DataSummary!$A$111:$B$112,2,FALSE())=2),InputDataA_GeneralAssumptions!BW$75, IF(AND(VLOOKUP(InputDataA_GeneralAssumptions!$D$60,DataSummary!$A$116:$B$117,2,FALSE())=2,VLOOKUP(InputDataA_GeneralAssumptions!$D$76,DataSummary!$A$111:$B$112,2,FALSE())=1), InputDataA_GeneralAssumptions!BW$74,"Not an input"))
B78: Limit (External Debt)/GDP --> | C78: (e.g. 0.40) | D78: =D75 | E78: =D78 | F78: =DataSummary!N5 | G78: "Manual" [user defined year by year] | H78: (e.g. 0.40) | I78: =I79 | J78: =J79 | K78: =K79 | L78: =L79 | M78: =M79 | N78: =N79 | O78: =O79 | P78: =P79 | ... AN78: =AN79 | AO78: 0.6 | AP78: 0.6 | AQ78: 0.6 | AR78: 0.6 | AS78: 0.6 | AT78: 0.6 | AU78: 0.6 | AV78: 0.6 | AW78: 0.6 | AX78: 0.6 | AY78: 0.6 | AZ78: 0.6 | BA78: 0.6 | BB78: 0.6 | BC78: 0.6 | BD78: 0.6 | BE78: 0.6 | BF78: 0.6 | BG78: 0.6 | BH78: 0.6 | BI78: 0.6 | BJ78: 0.6 | BK78: 0.6 | BL78: 0.6 | BM78: 0.6 | BN78: 0.6 | BO78: 0.6 | BP78: 0.6 | BQ78: 0.6 | BR78: 0.6 | BS78: 0.6 | BT78: 0.6 | BU78: 0.6 | BV78: 0.6 | BW78: 0.6
B79: Reach target External Debt/Y rate by year --> | C79: (YYYY) | D79: 2030 | E79: 2030 | G79: "Automatic" [reach target by year] | H79: =H78 | I79: =InputDataA_GeneralAssumptions!E75 | J79: =InputDataA_GeneralAssumptions!$D$75+(InputDataA_GeneralAssumptions!$E$78-InputDataA_GeneralAssumptions!$D$75)/(1+EXP(-DataSummary!$K$97*(J$72-$I$72)))^(1/DataSummary!$H$97) | K79: =InputDataA_GeneralAssumptions!$D$75+(InputDataA_GeneralAssumptions!$E$78-InputDataA_GeneralAssumptions!$D$75)/(1+EXP(-DataSummary!$K$97*(K$72-$I$72)))^(1/DataSummary!$H$97) | L79: =InputDataA_GeneralAssumptions!$D$75+(InputDataA_GeneralAssumptions!$E$78-InputDataA_GeneralAssumptions!$D$75)/(1+EXP(-DataSummary!$K$97*(L$72-$I$72)))^(1/DataSummary!$H$97) | M79: =InputDataA_GeneralAssumptions!$D$75+(InputDataA_GeneralAssumptions!$E$78-InputDataA_GeneralAssumptions!$D$75)/(1+EXP(-DataSummary!$K$97*(M$72-$I$72)))^(1/DataSummary!$H$97) | N79: =InputDataA_GeneralAssumptions!$D$75+(InputDataA_GeneralAssumptions!$E$78-InputDataA_GeneralAssumptions!$D$75)/(1+EXP(-DataSummary!$K$97*(N$72-$I$72)))^(1/DataSummary!$H$97) | O79: =InputDataA_GeneralAssumptions!$D$75+(InputDataA_GeneralAssumptions!$E$78-InputDataA_GeneralAssumptions!$D$75)/(1+EXP(-DataSummary!$K$97*(O$72-$I$72)))^(1/DataSummary!$H$97) | P79: =InputDataA_GeneralAssumptions!$D$75+(InputDataA_GeneralAssumptions!$E$78-InputDataA_GeneralAssumptions!$D$75)/(1+EXP(-DataSummary!$K$97*(P$72-$I$72)))^(1/DataSummary!$H$97) | Q79: =InputDataA_GeneralAssumptions!$D$75+(InputDataA_GeneralAssumptions!$E$78-InputDataA_GeneralAssumptions!$D$75)/(1+EXP(-DataSummary!$K$97*(Q$72-$I$72)))^(1/DataSummary!$H$97) | ... BW79: =InputDataA_GeneralAssumptions!$D$75+(InputDataA_GeneralAssumptions!$E$78-InputDataA_GeneralAssumptions!$D$75)/(1+EXP(-DataSummary!$K$97*(BW$72-$I$72)))^(1/DataSummary!$H$97)
G80: Used in "scenario" simulation | H80: (e.g. 0.40) | I80: =IF(AND(VLOOKUP(InputDataA_GeneralAssumptions!$D$60,DataSummary!$A$116:$B$117,2,FALSE())=2,VLOOKUP(InputDataA_GeneralAssumptions!$D$76,DataSummary!$A$111:$B$112,2,FALSE())=2),InputDataA_GeneralAssumptions!I$79, IF(AND(VLOOKUP(InputDataA_GeneralAssumptions!$D$60,DataSummary!$A$116:$B$117,2,FALSE())=2,VLOOKUP(InputDataA_GeneralAssumptions!$D$76,DataSummary!$A$111:$B$112,2,FALSE())=1), InputDataA_GeneralAssumptions!I$78,"Not an input")) | J80: =IF(AND(VLOOKUP(InputDataA_GeneralAssumptions!$D$60,DataSummary!$A$116:$B$117,2,FALSE())=2,VLOOKUP(InputDataA_GeneralAssumptions!$D$76,DataSummary!$A$111:$B$112,2,FALSE())=2),InputDataA_GeneralAssumptions!J$79, IF(AND(VLOOKUP(InputDataA_GeneralAssumptions!$D$60,DataSummary!$A$116:$B$117,2,FALSE())=2,VLOOKUP(InputDataA_GeneralAssumptions!$D$76,DataSummary!$A$111:$B$112,2,FALSE())=1), InputDataA_GeneralAssumptions!J$78,"Not an input")) | K80: =IF(AND(VLOOKUP(InputDataA_GeneralAssumptions!$D$60,DataSummary!$A$116:$B$117,2,FALSE())=2,VLOOKUP(InputDataA_GeneralAssumptions!$D$76,DataSummary!$A$111:$B$112,2,FALSE())=2),InputDataA_GeneralAssumptions!K$79, IF(AND(VLOOKUP(InputDataA_GeneralAssumptions!$D$60,DataSummary!$A$116:$B$117,2,FALSE())=2,VLOOKUP(InputDataA_GeneralAssumptions!$D$76,DataSummary!$A$111:$B$112,2,FALSE())=1), InputDataA_GeneralAssumptions!K$78,"Not an input")) | L80: =IF(AND(VLOOKUP(InputDataA_GeneralAssumptions!$D$60,DataSummary!$A$116:$B$117,2,FALSE())=2,VLOOKUP(InputDataA_GeneralAssumptions!$D$76,DataSummary!$A$111:$B$112,2,FALSE())=2),InputDataA_GeneralAssumptions!L$79, IF(AND(VLOOKUP(InputDataA_GeneralAssumptions!$D$60,DataSummary!$A$116:$B$117,2,FALSE())=2,VLOOKUP(InputDataA_GeneralAssumptions!$D$76,DataSummary!$A$111:$B$112,2,FALSE())=1), InputDataA_GeneralAssumptions!L$78,"Not an input")) | M80: =IF(AND(VLOOKUP(InputDataA_GeneralAssumptions!$D$60,DataSummary!$A$116:$B$117,2,FALSE())=2,VLOOKUP(InputDataA_GeneralAssumptions!$D$76,DataSummary!$A$111:$B$112,2,FALSE())=2),InputDataA_GeneralAssumptions!M$79, IF(AND(VLOOKUP(InputDataA_GeneralAssumptions!$D$60,DataSummary!$A$116:$B$117,2,FALSE())=2,VLOOKUP(InputDataA_GeneralAssumptions!$D$76,DataSummary!$A$111:$B$112,2,FALSE())=1), InputDataA_GeneralAssumptions!M$78,"Not an input")) | N80: =IF(AND(VLOOKUP(InputDataA_GeneralAssumptions!$D$60,DataSummary!$A$116:$B$117,2,FALSE())=2,VLOOKUP(InputDataA_GeneralAssumptions!$D$76,DataSummary!$A$111:$B$112,2,FALSE())=2),InputDataA_GeneralAssumptions!N$79, IF(AND(VLOOKUP(InputDataA_GeneralAssumptions!$D$60,DataSummary!$A$116:$B$117,2,FALSE())=2,VLOOKUP(InputDataA_GeneralAssumptions!$D$76,DataSummary!$A$111:$B$112,2,FALSE())=1), InputDataA_GeneralAssumptions!N$78,"Not an input")) | O80: =IF(AND(VLOOKUP(InputDataA_GeneralAssumptions!$D$60,DataSummary!$A$116:$B$117,2,FALSE())=2,VLOOKUP(InputDataA_GeneralAssumptions!$D$76,DataSummary!$A$111:$B$112,2,FALSE())=2),InputDataA_GeneralAssumptions!O$79, IF(AND(VLOOKUP(InputDataA_GeneralAssumptions!$D$60,DataSummary!$A$116:$B$117,2,FALSE())=2,VLOOKUP(InputDataA_GeneralAssumptions!$D$76,DataSummary!$A$111:$B$112,2,FALSE())=1), InputDataA_GeneralAssumptions!O$78,"Not an input")) | P80: =IF(AND(VLOOKUP(InputDataA_GeneralAssumptions!$D$60,DataSummary!$A$116:$B$117,2,FALSE())=2,VLOOKUP(InputDataA_GeneralAssumptions!$D$76,DataSummary!$A$111:$B$112,2,FALSE())=2),InputDataA_GeneralAssumptions!P$79, IF(AND(VLOOKUP(InputDataA_GeneralAssumptions!$D$60,DataSummary!$A$116:$B$117,2,FALSE())=2,VLOOKUP(InputDataA_GeneralAssumptions!$D$76,DataSummary!$A$111:$B$112,2,FALSE())=1), InputDataA_GeneralAssumptions!P$78,"Not an input")) | ... BW80: =IF(AND(VLOOKUP(InputDataA_GeneralAssumptions!$D$60,DataSummary!$A$116:$B$117,2,FALSE())=2,VLOOKUP(InputDataA_GeneralAssumptions!$D$76,DataSummary!$A$111:$B$112,2,FALSE())=2),InputDataA_GeneralAssumptions!BW$79, IF(AND(VLOOKUP(InputDataA_GeneralAssumptions!$D$60,DataSummary!$A$116:$B$117,2,FALSE())=2,VLOOKUP(InputDataA_GeneralAssumptions!$D$76,DataSummary!$A$111:$B$112,2,FALSE())=1), InputDataA_GeneralAssumptions!BW$78,"Not an input"))
B82: Net Foreign Direct Investment Ratio to GDP | F82: =D87 | G82: Net Foreign Direct Investment Ratio to GDP | H82: Chart | I82: =InputDataA_GeneralAssumptions!$D$7 | J82: =I82+1 | K82: =J82+1 | L82: =K82+1 | M82: =L82+1 | N82: =M82+1 | O82: =N82+1 | P82: =O82+1 | Q82: =P82+1 | ... BW82: =BV82+1
B83: Initial Net FDI/GDP (Net Inflow) (user defined) --> | C83: (e.g. 0.03) | F83: =DataSummary!N4 | G83: "Manual" [user defined year by year] | H83: (e.g. 0.40) | I83: =I84 | J83: 0.012279458 | K83: 0.01258828 | L83: 0.012897101 | M83: 0.013205923 | N83: 0.013514745 | O83: 0.013823567 | P83: 0.014132388 | Q83: 0.01444121 | R83: 0.014750032 | S83: 0.015058853 | T83: 0.015367675 | U83: 0.015676497 | V83: 0.015985318 | W83: 0.01629414 | X83: 0.016602962 | Y83: 0.016911783 | Z83: 0.017220605 | AA83: 0.017529427 | AB83: 0.017838248 | AC83: 0.01814707 | AD83: 0.018455892 | AE83: 0.018764713 | AF83: 0.019073535 | AG83: 0.019382357 | AH83: 0.019691178 | AI83: 0.02 | AJ83: 0.02 | AK83: 0.02 | AL83: 0.02 | AM83: 0.02 | AN83: 0.02 | AO83: 0.02 | AP83: 0.02 | AQ83: 0.02 | AR83: 0.02 | AS83: 0.02 | AT83: =AS83 | AU83: =AT83 | AV83: =AU83 | AW83: =AV83 | AX83: =AW83 | AY83: =AX83 | AZ83: =AY83 | BA83: =AZ83 | ... BW83: =BV83
B84: Initial FDI ratio to GDP, pre-loaded --> | C84: 2019 | D84: =IF(ISNUMBER(DataSummary!B240)=TRUE(),DataSummary!B240,".") | G84: "Automatic" [reach target by year] | H84: (e.g. 0.40) | I84: =D85 | J84: =IF(J82>InputDataA_GeneralAssumptions!$D$89,InputDataA_GeneralAssumptions!$D$88,I84+(InputDataA_GeneralAssumptions!$D$88-$I84)/(InputDataA_GeneralAssumptions!$D$89-InputDataA_GeneralAssumptions!$D$7)) | K84: =IF(K82>InputDataA_GeneralAssumptions!$D$89,InputDataA_GeneralAssumptions!$D$88,J84+(InputDataA_GeneralAssumptions!$D$88-$I84)/(InputDataA_GeneralAssumptions!$D$89-InputDataA_GeneralAssumptions!$D$7)) | L84: =IF(L82>InputDataA_GeneralAssumptions!$D$89,InputDataA_GeneralAssumptions!$D$88,K84+(InputDataA_GeneralAssumptions!$D$88-$I84)/(InputDataA_GeneralAssumptions!$D$89-InputDataA_GeneralAssumptions!$D$7)) | M84: =IF(M82>InputDataA_GeneralAssumptions!$D$89,InputDataA_GeneralAssumptions!$D$88,L84+(InputDataA_GeneralAssumptions!$D$88-$I84)/(InputDataA_GeneralAssumptions!$D$89-InputDataA_GeneralAssumptions!$D$7)) | N84: =IF(N82>InputDataA_GeneralAssumptions!$D$89,InputDataA_GeneralAssumptions!$D$88,M84+(InputDataA_GeneralAssumptions!$D$88-$I84)/(InputDataA_GeneralAssumptions!$D$89-InputDataA_GeneralAssumptions!$D$7)) | O84: =IF(O82>InputDataA_GeneralAssumptions!$D$89,InputDataA_GeneralAssumptions!$D$88,N84+(InputDataA_GeneralAssumptions!$D$88-$I84)/(InputDataA_GeneralAssumptions!$D$89-InputDataA_GeneralAssumptions!$D$7)) | P84: =IF(P82>InputDataA_GeneralAssumptions!$D$89,InputDataA_GeneralAssumptions!$D$88,O84+(InputDataA_GeneralAssumptions!$D$88-$I84)/(InputDataA_GeneralAssumptions!$D$89-InputDataA_GeneralAssumptions!$D$7)) | Q84: =IF(Q82>InputDataA_GeneralAssumptions!$D$89,InputDataA_GeneralAssumptions!$D$88,P84+(InputDataA_GeneralAssumptions!$D$88-$I84)/(InputDataA_GeneralAssumptions!$D$89-InputDataA_GeneralAssumptions!$D$7)) | ... BW84: =IF(BW82>InputDataA_GeneralAssumptions!$D$89,InputDataA_GeneralAssumptions!$D$88,BV84+(InputDataA_GeneralAssumptions!$D$88-$I84)/(InputDataA_GeneralAssumptions!$D$89-InputDataA_GeneralAssumptions!$D$7))
B85: Initial FDI/Y is (if cell D83:E83 is blank uses pre-loaded) --> | C85: (e.g. 0.03) | D85: =IF(ISBLANK(D83)=TRUE(),D84,D83) | E85: =IF(ISBLANK(E83)=TRUE(),D84,E83) | G85: Used in "baseline" simulation | H85: (e.g. 0.40) | I85: =IF(VLOOKUP(InputDataA_GeneralAssumptions!$D$87,DataSummary!$A$111:$B$112,2,FALSE())=1,I83,I84) | J85: =IF(VLOOKUP(InputDataA_GeneralAssumptions!$D$87,DataSummary!$A$111:$B$112,2,FALSE())=1,J83,J84) | K85: =IF(VLOOKUP(InputDataA_GeneralAssumptions!$D$87,DataSummary!$A$111:$B$112,2,FALSE())=1,K83,K84) | L85: =IF(VLOOKUP(InputDataA_GeneralAssumptions!$D$87,DataSummary!$A$111:$B$112,2,FALSE())=1,L83,L84) | M85: =IF(VLOOKUP(InputDataA_GeneralAssumptions!$D$87,DataSummary!$A$111:$B$112,2,FALSE())=1,M83,M84) | N85: =IF(VLOOKUP(InputDataA_GeneralAssumptions!$D$87,DataSummary!$A$111:$B$112,2,FALSE())=1,N83,N84) | O85: =IF(VLOOKUP(InputDataA_GeneralAssumptions!$D$87,DataSummary!$A$111:$B$112,2,FALSE())=1,O83,O84) | P85: =IF(VLOOKUP(InputDataA_GeneralAssumptions!$D$87,DataSummary!$A$111:$B$112,2,FALSE())=1,P83,P84) | ... BW85: =IF(VLOOKUP(InputDataA_GeneralAssumptions!$D$87,DataSummary!$A$111:$B$112,2,FALSE())=1,BW83,BW84)
B87: Choice for future FDI Ratio to GDP: | C87: Select from list --> | D87: Automatic | F87: =DataSummary!N5 | G87: "Manual" [user defined year by year] | H87: (e.g. 0.40) | I87: =I88 | J87: 0.012279458 | K87: 0.01258828 | L87: 0.012897101 | M87: 0.013205923 | N87: 0.013514745 | O87: 0.013823567 | P87: 0.014132388 | Q87: 0.01444121 | R87: 0.014750032 | S87: 0.015058853 | T87: 0.015367675 | U87: 0.015676497 | V87: 0.015985318 | W87: 0.01629414 | X87: 0.016602962 | Y87: 0.016911783 | Z87: 0.017220605 | AA87: 0.017529427 | AB87: 0.017838248 | AC87: 0.01814707 | AD87: 0.018455892 | AE87: 0.018764713 | AF87: 0.019073535 | AG87: 0.019382357 | AH87: 0.019691178 | AI87: 0.02 | AJ87: 0.02 | AK87: 0.02 | AL87: 0.02 | AM87: 0.02 | AN87: 0.02 | AO87: 0.02 | AP87: 0.02 | AQ87: 0.02 | AR87: 0.02 | AS87: 0.02 | AT87: 0.02 | AU87: 0.02 | AV87: 0.02 | AW87: 0.02 | AX87: 0.02 | AY87: 0.02 | AZ87: 0.02 | BA87: 0.02 | BB87: 0.02 | BC87: 0.02 | BD87: 0.02 | BE87: 0.02 | BF87: 0.02 | BG87: 0.02 | BH87: 0.02 | BI87: 0.02 | BJ87: 0.02 | BK87: 0.02 | BL87: 0.02 | BM87: 0.02 | BN87: 0.02 | BO87: 0.02 | BP87: 0.02 | BQ87: 0.02 | BR87: 0.02 | BS87: 0.02 | BT87: 0.02 | BU87: 0.02 | BV87: 0.02 | BW87: 0.02
B88: Target FDI / GDP --> | C88: (e.g. 0.03) | D88: =D85 | E88: =E85 | G88: "Automatic" [reach target by year] | H88: (e.g. 0.40) | I88: =InputDataA_GeneralAssumptions!E85 | J88: =IF(J82>InputDataA_GeneralAssumptions!$E$89,InputDataA_GeneralAssumptions!$E$88,I88+(InputDataA_GeneralAssumptions!$E$88-$I88)/(InputDataA_GeneralAssumptions!$E$89-InputDataA_GeneralAssumptions!$D$7)) | K88: =IF(K82>InputDataA_GeneralAssumptions!$E$89,InputDataA_GeneralAssumptions!$E$88,J88+(InputDataA_GeneralAssumptions!$E$88-$I88)/(InputDataA_GeneralAssumptions!$E$89-InputDataA_GeneralAssumptions!$D$7)) | L88: =IF(L82>InputDataA_GeneralAssumptions!$E$89,InputDataA_GeneralAssumptions!$E$88,K88+(InputDataA_GeneralAssumptions!$E$88-$I88)/(InputDataA_GeneralAssumptions!$E$89-InputDataA_GeneralAssumptions!$D$7)) | M88: =IF(M82>InputDataA_GeneralAssumptions!$E$89,InputDataA_GeneralAssumptions!$E$88,L88+(InputDataA_GeneralAssumptions!$E$88-$I88)/(InputDataA_GeneralAssumptions!$E$89-InputDataA_GeneralAssumptions!$D$7)) | N88: =IF(N82>InputDataA_GeneralAssumptions!$E$89,InputDataA_GeneralAssumptions!$E$88,M88+(InputDataA_GeneralAssumptions!$E$88-$I88)/(InputDataA_GeneralAssumptions!$E$89-InputDataA_GeneralAssumptions!$D$7)) | O88: =IF(O82>InputDataA_GeneralAssumptions!$E$89,InputDataA_GeneralAssumptions!$E$88,N88+(InputDataA_GeneralAssumptions!$E$88-$I88)/(InputDataA_GeneralAssumptions!$E$89-InputDataA_GeneralAssumptions!$D$7)) | P88: =IF(P82>InputDataA_GeneralAssumptions!$E$89,InputDataA_GeneralAssumptions!$E$88,O88+(InputDataA_GeneralAssumptions!$E$88-$I88)/(InputDataA_GeneralAssumptions!$E$89-InputDataA_GeneralAssumptions!$D$7)) | Q88: =IF(Q82>InputDataA_GeneralAssumptions!$E$89,InputDataA_GeneralAssumptions!$E$88,P88+(InputDataA_GeneralAssumptions!$E$88-$I88)/(InputDataA_GeneralAssumptions!$E$89-InputDataA_GeneralAssumptions!$D$7)) | ... BW88: =IF(BW82>InputDataA_GeneralAssumptions!$E$89,InputDataA_GeneralAssumptions!$E$88,BV88+(InputDataA_GeneralAssumptions!$E$88-$I88)/(InputDataA_GeneralAssumptions!$E$89-InputDataA_GeneralAssumptions!$D$7))
B89: Reach target FDI/GDP by year --> | C89: (YYYY) | D89: 2030 | E89: 2030 | G89: Used in "scenario" simulation | H89: (e.g. 0.40) | I89: =IF(VLOOKUP(InputDataA_GeneralAssumptions!$D$87,DataSummary!$A$111:$B$112,2,FALSE())=1,I87,I88) | J89: =IF(VLOOKUP(InputDataA_GeneralAssumptions!$D$87,DataSummary!$A$111:$B$112,2,FALSE())=1,J87,J88) | K89: =IF(VLOOKUP(InputDataA_GeneralAssumptions!$D$87,DataSummary!$A$111:$B$112,2,FALSE())=1,K87,K88) | L89: =IF(VLOOKUP(InputDataA_GeneralAssumptions!$D$87,DataSummary!$A$111:$B$112,2,FALSE())=1,L87,L88) | M89: =IF(VLOOKUP(InputDataA_GeneralAssumptions!$D$87,DataSummary!$A$111:$B$112,2,FALSE())=1,M87,M88) | N89: =IF(VLOOKUP(InputDataA_GeneralAssumptions!$D$87,DataSummary!$A$111:$B$112,2,FALSE())=1,N87,N88) | O89: =IF(VLOOKUP(InputDataA_GeneralAssumptions!$D$87,DataSummary!$A$111:$B$112,2,FALSE())=1,O87,O88) | P89: =IF(VLOOKUP(InputDataA_GeneralAssumptions!$D$87,DataSummary!$A$111:$B$112,2,FALSE())=1,P87,P88) | ... BW89: =IF(VLOOKUP(InputDataA_GeneralAssumptions!$D$87,DataSummary!$A$111:$B$112,2,FALSE())=1,BW87,BW88)
B91: Demographics | C91: =DataSummary!K44 | D91: =DataSummary!N4 | E91: =DataSummary!N5 | F91: =D92 | G91: Total Population Annual Growth Rate | H91: Chart | I91: =InputDataA_GeneralAssumptions!$D$7 | J91: =I91+1 | K91: =J91+1 | L91: =K91+1 | M91: =L91+1 | N91: =M91+1 | O91: =N91+1 | P91: =O91+1 | Q91: =P91+1 | ... BW91: =BV91+1
D92: Automatic | F92: =DataSummary!N4 | G92: "Manual" [user defined year by year] | H92: (e.g. 0.40) | I92: =I93 | J92: 0.03 | K92: 0.024315038 | L92: 0.024167885 | M92: 0.023975479 | N92: 0.02390618 | O92: 0.023868642 | P92: 0.02374247 | Q92: 0.023650327 | R92: 0.023551807 | S92: 0.023411005 | T92: 0.023231783 | U92: 0.02308737 | V92: 0.022940776 | W92: 0.022792307 | X92: 0.022642246 | Y92: 0.022522666 | Z92: 0.022368789 | AA92: 0.022214107 | AB92: 0.022118362 | AC92: 0.021989224 | AD92: 0.021858079 | AE92: 0.021753075 | AF92: 0.021644785 | AG92: 0.021506813 | AH92: 0.021394011 | AI92: 0.021227563 | AJ92: 0.021112281 | AK92: 0.02094588 | AL92: 0.020804772 | AM92: 0.020616371 | AN92: 0.020476949 | AO92: 0.020314904 | AP92: 0.020132145 | AQ92: 0.019952184 | AR92: 0.019796284 | AS92: 0.01964185 | AT92: =AS92 | AU92: =AT92 | AV92: =AU92 | AW92: =AV92 | AX92: =AW92 | AY92: =AX92 | AZ92: =AY92 | BA92: =AZ92 | ... BW92: =BV92
B93: Automated: Initial population annual growth rate --> | C93: (e.g. 0.01) | D93: =IF(ISNUMBER(DataSummary!D42)=TRUE(),DataSummary!D42,".") | G93: "Automatic" [reach target by year] | H93: (e.g. 0.40) | I93: =IF(ISNUMBER(DataSummary!F81),DataSummary!F81,"#N/A") | J93: =IF(ISNUMBER(DataSummary!G81),DataSummary!G81,"#N/A") | K93: =IF(ISNUMBER(DataSummary!H81),DataSummary!H81,"#N/A") | L93: =IF(ISNUMBER(DataSummary!I81),DataSummary!I81,"#N/A") | M93: =IF(ISNUMBER(DataSummary!J81),DataSummary!J81,"#N/A") | N93: =IF(ISNUMBER(DataSummary!K81),DataSummary!K81,"#N/A") | O93: =IF(ISNUMBER(DataSummary!L81),DataSummary!L81,"#N/A") | P93: =IF(ISNUMBER(DataSummary!M81),DataSummary!M81,"#N/A") | ... AP93: =IF(ISNUMBER(DataSummary!AM81),DataSummary!AM81,"#N/A") | AQ93: =AP93 | AR93: =AQ93 | AS93: =AR93 | AT93: =AS93 | AU93: =AT93 | AV93: =AU93 | AW93: =AV93 | AX93: =AW93 | ... BW93: =BV93
B94: ="Automated: Population growth rate by "&DataSummary!AK79&" -->" | C94: (e.g. 0.01) | D94: =IF(ISNUMBER(DataSummary!D43)=TRUE(),DataSummary!D43,".") | G94: Used in "baseline" simulation | H94: =H93 | I94: =IF(VLOOKUP(InputDataA_GeneralAssumptions!$D$92,DataSummary!$A$111:$B$112,2,FALSE())=1,I92,I93) | J94: =IF(VLOOKUP(InputDataA_GeneralAssumptions!$D$92,DataSummary!$A$111:$B$112,2,FALSE())=1,J92,J93) | K94: =IF(VLOOKUP(InputDataA_GeneralAssumptions!$D$92,DataSummary!$A$111:$B$112,2,FALSE())=1,K92,K93) | L94: =IF(VLOOKUP(InputDataA_GeneralAssumptions!$D$92,DataSummary!$A$111:$B$112,2,FALSE())=1,L92,L93) | M94: =IF(VLOOKUP(InputDataA_GeneralAssumptions!$D$92,DataSummary!$A$111:$B$112,2,FALSE())=1,M92,M93) | N94: =IF(VLOOKUP(InputDataA_GeneralAssumptions!$D$92,DataSummary!$A$111:$B$112,2,FALSE())=1,N92,N93) | O94: =IF(VLOOKUP(InputDataA_GeneralAssumptions!$D$92,DataSummary!$A$111:$B$112,2,FALSE())=1,O92,O93) | P94: =IF(VLOOKUP(InputDataA_GeneralAssumptions!$D$92,DataSummary!$A$111:$B$112,2,FALSE())=1,P92,P93) | ... BW94: =IF(VLOOKUP(InputDataA_GeneralAssumptions!$D$92,DataSummary!$A$111:$B$112,2,FALSE())=1,BW92,BW93)
F96: =DataSummary!N5 | G96: "Manual" [user defined year by year] | H96: (e.g. 0.02) | I96: =I97 | J96: 0.03 | K96: 0.024315038 | L96: 0.024167885 | M96: 0.023975479 | N96: 0.02390618 | O96: 0.023868642 | P96: 0.02374247 | Q96: 0.023650327 | R96: 0.023551807 | S96: 0.023411005 | T96: 0.023231783 | U96: 0.02308737 | V96: 0.022940776 | W96: 0.022792307 | X96: 0.022642246 | Y96: 0.022522666 | Z96: 0.022368789 | AA96: 0.022214107 | AB96: 0.022118362 | AC96: 0.021989224 | AD96: 0.021858079 | AE96: 0.021753075 | AF96: 0.021644785 | AG96: 0.021506813 | AH96: 0.021394011 | AI96: 0.021227563 | AJ96: 0.021112281 | AK96: 0.02094588 | AL96: 0.020804772 | AM96: 0.020616371 | AN96: 0.020476949 | AO96: 0.020314904 | AP96: 0.020132145 | AQ96: 0.019952184 | AR96: 0.019796284 | AS96: 0.01964185 | AT96: 0.01964185 | AU96: 0.01964185 | AV96: 0.01964185 | AW96: 0.01964185 | AX96: 0.01964185 | AY96: 0.01964185 | AZ96: 0.01964185 | BA96: 0.01964185 | BB96: 0.01964185 | BC96: 0.01964185 | BD96: 0.01964185 | BE96: 0.01964185 | BF96: 0.01964185 | BG96: 0.01964185 | BH96: 0.01964185 | BI96: 0.01964185 | BJ96: 0.01964185 | BK96: 0.01964185 | BL96: 0.01964185 | BM96: 0.01964185 | BN96: 0.01964185 | BO96: 0.01964185 | BP96: 0.01964185 | BQ96: 0.01964185 | BR96: 0.01964185 | BS96: 0.01964185 | BT96: 0.01964185 | BU96: 0.01964185 | BV96: 0.01964185 | BW96: 0.01964185
G97: "Automatic" [reach target by year] | H97: (e.g. 0.02) | I97: =IF(ISNUMBER(DataSummary!F81),DataSummary!F81,"#N/A") | J97: =IF(ISNUMBER(DataSummary!G81),DataSummary!G81,"#N/A") | K97: =IF(ISNUMBER(DataSummary!H81),DataSummary!H81,"#N/A") | L97: =IF(ISNUMBER(DataSummary!I81),DataSummary!I81,"#N/A") | M97: =IF(ISNUMBER(DataSummary!J81),DataSummary!J81,"#N/A") | N97: =IF(ISNUMBER(DataSummary!K81),DataSummary!K81,"#N/A") | O97: =IF(ISNUMBER(DataSummary!L81),DataSummary!L81,"#N/A") | P97: =IF(ISNUMBER(DataSummary!M81),DataSummary!M81,"#N/A") | ... AP97: =IF(ISNUMBER(DataSummary!AM81),DataSummary!AM81,"#N/A") | AQ97: =AP97 | AR97: =AQ97 | AS97: =AR97 | AT97: =AS97 | AU97: =AT97 | AV97: =AU97 | AW97: =AV97 | AX97: =AW97 | ... BW97: =BV97
G98: Used in "scenario" simulation | H98: =H97 | I98: =IF(VLOOKUP(InputDataA_GeneralAssumptions!$D$92,DataSummary!$A$111:$B$112,2,FALSE())=1,I96,I97) | J98: =IF(VLOOKUP(InputDataA_GeneralAssumptions!$D$92,DataSummary!$A$111:$B$112,2,FALSE())=1,J96,J97) | K98: =IF(VLOOKUP(InputDataA_GeneralAssumptions!$D$92,DataSummary!$A$111:$B$112,2,FALSE())=1,K96,K97) | L98: =IF(VLOOKUP(InputDataA_GeneralAssumptions!$D$92,DataSummary!$A$111:$B$112,2,FALSE())=1,L96,L97) | M98: =IF(VLOOKUP(InputDataA_GeneralAssumptions!$D$92,DataSummary!$A$111:$B$112,2,FALSE())=1,M96,M97) | N98: =IF(VLOOKUP(InputDataA_GeneralAssumptions!$D$92,DataSummary!$A$111:$B$112,2,FALSE())=1,N96,N97) | O98: =IF(VLOOKUP(InputDataA_GeneralAssumptions!$D$92,DataSummary!$A$111:$B$112,2,FALSE())=1,O96,O97) | P98: =IF(VLOOKUP(InputDataA_GeneralAssumptions!$D$92,DataSummary!$A$111:$B$112,2,FALSE())=1,P96,P97) | ... BW98: =IF(VLOOKUP(InputDataA_GeneralAssumptions!$D$92,DataSummary!$A$111:$B$112,2,FALSE())=1,BW96,BW97)
H99: Chart
G100: Share of male population in total population (usually 0.5) | H100: =I100-1 | I100: =InputDataA_GeneralAssumptions!$D$7 | J100: =I100+1 | K100: =J100+1 | L100: =K100+1 | M100: =L100+1 | N100: =M100+1 | O100: =N100+1 | P100: =O100+1 | Q100: =P100+1 | ... BW100: =BV100+1
F101: =DataSummary!N4 | G101: "Manual" [user defined year by year] | H101: (e.g. 0.40) | I101: =I102 | J101: 0.50665821 | K101: 0.50675527 | L101: 0.50676901 | M101: 0.50673226 | N101: 0.5067173 | O101: 0.50662649 | P101: 0.5066577 | Q101: 0.50671764 | R101: 0.50668761 | S101: 0.50668447 | T101: 0.50664159 | U101: 0.50658693 | V101: 0.50650654 | W101: 0.50637539 | X101: 0.50623874 | Y101: 0.50608408 | Z101: 0.50594655 | AA101: 0.50581697 | AB101: 0.50562772 | AC101: 0.50544133 | AD101: 0.50525214 | AE101: 0.50508362 | AF101: 0.50487335 | AG101: 0.50466984 | AH101: 0.50441842 | AI101: 0.50420209 | AJ101: 0.50402267 | AK101: 0.50384895 | AL101: 0.50366837 | AM101: 0.50347925 | AN101: 0.50328032 | AO101: 0.5031225 | AP101: 0.50297902 | AQ101: 0.50282913 | AR101: 0.50266623 | AS101: 0.50249368 | AT101: =AS101 | AU101: =AT101 | AV101: =AU101 | AW101: =AV101 | AX101: =AW101 | AY101: =AX101 | AZ101: =AY101 | BA101: =AZ101 | ... BW101: =BV101
G102: "Automatic" [reach target by year] | H102: (e.g. 0.40) | I102: =IF(ISNUMBER(DataSummary!F82),DataSummary!F82,"N/A") | J102: =IF(ISNUMBER(DataSummary!G82),DataSummary!G82,"N/A") | K102: =IF(ISNUMBER(DataSummary!H82),DataSummary!H82,"N/A") | L102: =IF(ISNUMBER(DataSummary!I82),DataSummary!I82,"N/A") | M102: =IF(ISNUMBER(DataSummary!J82),DataSummary!J82,"N/A") | N102: =IF(ISNUMBER(DataSummary!K82),DataSummary!K82,"N/A") | O102: =IF(ISNUMBER(DataSummary!L82),DataSummary!L82,"N/A") | P102: =IF(ISNUMBER(DataSummary!M82),DataSummary!M82,"N/A") | ... AP102: =IF(ISNUMBER(DataSummary!AM82),DataSummary!AM82,"N/A") | AQ102: =AP102 | AR102: =AQ102 | AS102: =AR102 | AT102: =AS102 | AU102: =AT102 | AV102: =AU102 | AW102: =AV102 | AX102: =AW102 | ... BW102: =BV102
G103: Used in "baseline" simulation | H103: (e.g. 0.40) | I103: =IF(VLOOKUP(InputDataA_GeneralAssumptions!$D$92,DataSummary!$A$111:$B$112,2,FALSE())=1,I101,I102) | J103: =IF(VLOOKUP(InputDataA_GeneralAssumptions!$D$92,DataSummary!$A$111:$B$112,2,FALSE())=1,J101,J102) | K103: =IF(VLOOKUP(InputDataA_GeneralAssumptions!$D$92,DataSummary!$A$111:$B$112,2,FALSE())=1,K101,K102) | L103: =IF(VLOOKUP(InputDataA_GeneralAssumptions!$D$92,DataSummary!$A$111:$B$112,2,FALSE())=1,L101,L102) | M103: =IF(VLOOKUP(InputDataA_GeneralAssumptions!$D$92,DataSummary!$A$111:$B$112,2,FALSE())=1,M101,M102) | N103: =IF(VLOOKUP(InputDataA_GeneralAssumptions!$D$92,DataSummary!$A$111:$B$112,2,FALSE())=1,N101,N102) | O103: =IF(VLOOKUP(InputDataA_GeneralAssumptions!$D$92,DataSummary!$A$111:$B$112,2,FALSE())=1,O101,O102) | P103: =IF(VLOOKUP(InputDataA_GeneralAssumptions!$D$92,DataSummary!$A$111:$B$112,2,FALSE())=1,P101,P102) | ... BW103: =IF(VLOOKUP(InputDataA_GeneralAssumptions!$D$92,DataSummary!$A$111:$B$112,2,FALSE())=1,BW101,BW102)
F105: =DataSummary!N5 | G105: "Manual" [user defined year by year] | H105: (e.g. 0.40) | I105: =I106 | J105: 0.50665821 | K105: 0.9 | L105: 0.50676901 | M105: 0.50673226 | N105: 0.5067173 | O105: 0.50662649 | P105: 0.5066577 | Q105: 0.50671764 | R105: 0.50668761 | S105: 0.50668447 | T105: 0.50664159 | U105: 0.50658693 | V105: 0.50650654 | W105: 0.50637539 | X105: 0.50623874 | Y105: 0.50608408 | Z105: 0.50594655 | AA105: 0.50581697 | AB105: 0.50562772 | AC105: 0.50544133 | AD105: 0.50525214 | AE105: 0.50508362 | AF105: 0.50487335 | AG105: 0.50466984 | AH105: 0.50441842 | AI105: 0.50420209 | AJ105: 0.50402267 | AK105: 0.50384895 | AL105: 0.50366837 | AM105: 0.50347925 | AN105: 0.50328032 | AO105: 0.5031225 | AP105: 0.50297902 | AQ105: 0.50282913 | AR105: 0.50266623 | AS105: 0.50249368 | AT105: 0.50249368 | AU105: 0.50249368 | AV105: 0.50249368 | AW105: 0.50249368 | AX105: 0.50249368 | AY105: 0.50249368 | AZ105: 0.50249368 | BA105: 0.50249368 | BB105: 0.50249368 | BC105: 0.50249368 | BD105: 0.50249368 | BE105: 0.50249368 | BF105: 0.50249368 | BG105: 0.50249368 | BH105: 0.50249368 | BI105: 0.50249368 | BJ105: 0.50249368 | BK105: 0.50249368 | BL105: 0.50249368 | BM105: 0.50249368 | BN105: 0.50249368 | BO105: 0.50249368 | BP105: 0.50249368 | BQ105: 0.50249368 | BR105: 0.50249368 | BS105: 0.50249368 | BT105: 0.50249368 | BU105: 0.50249368 | BV105: 0.50249368 | BW105: 0.50249368
G106: "Automatic" [reach target by year] | H106: (e.g. 0.40) | I106: =IF(ISNUMBER(DataSummary!F82),DataSummary!F82,"#N/A") | J106: =IF(ISNUMBER(DataSummary!G82),DataSummary!G82,"#N/A") | K106: =IF(ISNUMBER(DataSummary!H82),DataSummary!H82,"#N/A") | L106: =IF(ISNUMBER(DataSummary!I82),DataSummary!I82,"#N/A") | M106: =IF(ISNUMBER(DataSummary!J82),DataSummary!J82,"#N/A") | N106: =IF(ISNUMBER(DataSummary!K82),DataSummary!K82,"#N/A") | O106: =IF(ISNUMBER(DataSummary!L82),DataSummary!L82,"#N/A") | P106: =IF(ISNUMBER(DataSummary!M82),DataSummary!M82,"#N/A") | ... AP106: =IF(ISNUMBER(DataSummary!AM82),DataSummary!AM82,"#N/A") | AQ106: =AP106 | AR106: =AQ106 | AS106: =AR106 | AT106: =AS106 | AU106: =AT106 | AV106: =AU106 | AW106: =AV106 | AX106: =AW106 | ... BW106: =BV106
G107: Used in "scenario" simulation | H107: (e.g. 0.40) | I107: =IF(VLOOKUP(InputDataA_GeneralAssumptions!$D$92,DataSummary!$A$111:$B$112,2,FALSE())=1,I105,I106) | J107: =IF(VLOOKUP(InputDataA_GeneralAssumptions!$D$92,DataSummary!$A$111:$B$112,2,FALSE())=1,J105,J106) | K107: =IF(VLOOKUP(InputDataA_GeneralAssumptions!$D$92,DataSummary!$A$111:$B$112,2,FALSE())=1,K105,K106) | L107: =IF(VLOOKUP(InputDataA_GeneralAssumptions!$D$92,DataSummary!$A$111:$B$112,2,FALSE())=1,L105,L106) | M107: =IF(VLOOKUP(InputDataA_GeneralAssumptions!$D$92,DataSummary!$A$111:$B$112,2,FALSE())=1,M105,M106) | N107: =IF(VLOOKUP(InputDataA_GeneralAssumptions!$D$92,DataSummary!$A$111:$B$112,2,FALSE())=1,N105,N106) | O107: =IF(VLOOKUP(InputDataA_GeneralAssumptions!$D$92,DataSummary!$A$111:$B$112,2,FALSE())=1,O105,O106) | P107: =IF(VLOOKUP(InputDataA_GeneralAssumptions!$D$92,DataSummary!$A$111:$B$112,2,FALSE())=1,P105,P106) | ... BW107: =IF(VLOOKUP(InputDataA_GeneralAssumptions!$D$92,DataSummary!$A$111:$B$112,2,FALSE())=1,BW105,BW106)
H108: Chart
B109: Working Age to Total Population Ratio --> | C109: (e.g. 15-64, 15-60, 20-64) | D109: WATP ratio 15-64 | G109: Working age population to total population ratio | H109: =I109-1 | I109: =InputDataA_GeneralAssumptions!$D$7 | J109: =I109+1 | K109: =J109+1 | L109: =K109+1 | M109: =L109+1 | N109: =M109+1 | O109: =N109+1 | P109: =O109+1 | Q109: =P109+1 | ... BW109: =BV109+1
F110: =DataSummary!N4 | G110: "Manual" [user defined year by year] | H110: (e.g. 0.40) | I110: =I111 | J110: 0.542 | K110: =K111 | L110: =L111 | M110: =M111 | N110: =N111 | O110: =O111 | P110: =P111 | Q110: =Q111 | R110: =R111 | ... AS110: =AS111 | AT110: =AS110 | AU110: =AT110 | AV110: =AU110 | AW110: =AV110 | AX110: =AW110 | AY110: =AX110 | AZ110: =AY110 | BA110: =AZ110 | ... BW110: =BV110
G111: "Automatic" [reach target by year] | H111: (e.g. 0.40) | I111: =IF(ISNUMBER(DataSummary!G105),DataSummary!G105,"#N/A") | J111: =IF(ISNUMBER(DataSummary!H105),DataSummary!H105,"#N/A") | K111: =IF(ISNUMBER(DataSummary!I105),DataSummary!I105,"#N/A") | L111: =IF(ISNUMBER(DataSummary!J105),DataSummary!J105,"#N/A") | M111: =IF(ISNUMBER(DataSummary!K105),DataSummary!K105,"#N/A") | N111: =IF(ISNUMBER(DataSummary!L105),DataSummary!L105,"#N/A") | O111: =IF(ISNUMBER(DataSummary!M105),DataSummary!M105,"#N/A") | P111: =IF(ISNUMBER(DataSummary!N105),DataSummary!N105,"#N/A") | ... AN111: =IF(ISNUMBER(DataSummary!AL105),DataSummary!AL105,"#N/A") | AO111: =IF(ISNUMBER(DataSummary!AL83),DataSummary!AL83,"#N/A") | AP111: =IF(ISNUMBER(DataSummary!AM83),DataSummary!AM83,"#N/A") | AQ111: =AP111 | AR111: =AQ111 | AS111: =AR111 | AT111: =AS111 | AU111: =AT111 | AV111: =AU111 | AW111: =AV111 | AX111: =AW111 | ... BW111: =BV111
G112: Used in "baseline" simulation | H112: (e.g. 0.40) | I112: =IF(VLOOKUP(InputDataA_GeneralAssumptions!$D$92,DataSummary!$A$111:$B$112,2,FALSE())=1,InputDataA_GeneralAssumptions!I110,InputDataA_GeneralAssumptions!I111) | J112: =IF(VLOOKUP(InputDataA_GeneralAssumptions!$D$92,DataSummary!$A$111:$B$112,2,FALSE())=1,InputDataA_GeneralAssumptions!J110,InputDataA_GeneralAssumptions!J111) | K112: =IF(VLOOKUP(InputDataA_GeneralAssumptions!$D$92,DataSummary!$A$111:$B$112,2,FALSE())=1,InputDataA_GeneralAssumptions!K110,InputDataA_GeneralAssumptions!K111) | L112: =IF(VLOOKUP(InputDataA_GeneralAssumptions!$D$92,DataSummary!$A$111:$B$112,2,FALSE())=1,InputDataA_GeneralAssumptions!L110,InputDataA_GeneralAssumptions!L111) | M112: =IF(VLOOKUP(InputDataA_GeneralAssumptions!$D$92,DataSummary!$A$111:$B$112,2,FALSE())=1,InputDataA_GeneralAssumptions!M110,InputDataA_GeneralAssumptions!M111) | N112: =IF(VLOOKUP(InputDataA_GeneralAssumptions!$D$92,DataSummary!$A$111:$B$112,2,FALSE())=1,InputDataA_GeneralAssumptions!N110,InputDataA_GeneralAssumptions!N111) | O112: =IF(VLOOKUP(InputDataA_GeneralAssumptions!$D$92,DataSummary!$A$111:$B$112,2,FALSE())=1,InputDataA_GeneralAssumptions!O110,InputDataA_GeneralAssumptions!O111) | P112: =IF(VLOOKUP(InputDataA_GeneralAssumptions!$D$92,DataSummary!$A$111:$B$112,2,FALSE())=1,InputDataA_GeneralAssumptions!P110,InputDataA_GeneralAssumptions!P111) | ... BW112: =IF(VLOOKUP(InputDataA_GeneralAssumptions!$D$92,DataSummary!$A$111:$B$112,2,FALSE())=1,InputDataA_GeneralAssumptions!BW110,InputDataA_GeneralAssumptions!BW111)
G113: Growth Working age to total population ratio | H113: =H112 | I113: =IF(ISNUMBER(DataSummary!B105),DataSummary!B105,"#N/A") | J113: =J112/I112-1 | K113: =K112/J112-1 | L113: =L112/K112-1 | M113: =M112/L112-1 | N113: =N112/M112-1 | O113: =O112/N112-1 | P113: =P112/O112-1 | Q113: =Q112/P112-1 | ... BW113: =BW112/BV112-1
F115: =DataSummary!N5 | G115: "Manual" [user defined year by year] | H115: (e.g. 0.40) | I115: =I116 | J115: 0.5117638 | K115: 0.51381996 | L115: 0.51588225 | M115: 0.51588225 | N115: 0.52056429 | O115: 0.52340636 | P115: 0.52578557 | Q115: 0.52861067 | R115: 0.5316658 | S115: 0.53467442 | T115: 0.53751065 | U115: 0.54009798 | V115: 0.54255954 | W115: 0.54493929 | X115: 0.547339 | Y115: 0.54979891 | Z115: 0.55193953 | AA115: 0.55417397 | AB115: 0.55644848 | AC115: 0.55868225 | AD115: 0.56083162 | AE115: 0.56262548 | AF115: 0.56442234 | AG115: 0.56620325 | AH115: 0.56795145 | AI115: 0.56965638 | AJ115: 0.57109157 | AK115: 0.57252522 | AL115: 0.57397709 | AM115: 0.57547473 | AN115: 0.57702481 | AO115: 0.57843546 | AP115: 0.57992506 | AQ115: 0.58146443 | AR115: 0.58301607 | AS115: 0.58455611 | AT115: 0.58455611 | AU115: 0.58455611 | AV115: 0.58455611 | AW115: 0.58455611 | AX115: 0.58455611 | AY115: 0.58455611 | AZ115: 0.58455611 | BA115: 0.58455611 | BB115: 0.58455611 | BC115: 0.58455611 | BD115: 0.58455611 | BE115: 0.58455611 | BF115: 0.58455611 | BG115: 0.58455611 | BH115: 0.58455611 | BI115: 0.58455611 | BJ115: 0.58455611 | BK115: 0.58455611 | BL115: 0.58455611 | BM115: 0.58455611 | BN115: 0.58455611 | BO115: 0.58455611 | BP115: 0.58455611 | BQ115: 0.58455611 | BR115: 0.58455611 | BS115: 0.58455611 | BT115: 0.58455611 | BU115: 0.58455611 | BV115: 0.58455611 | BW115: 0.58455611
G116: "Automatic" [reach target by year] | H116: =H115 | I116: =IF(ISNUMBER(DataSummary!G105),DataSummary!G105,"#N/A") | J116: =IF(ISNUMBER(DataSummary!H105),DataSummary!H105,"#N/A") | K116: =IF(ISNUMBER(DataSummary!I105),DataSummary!I105,"#N/A") | L116: =IF(ISNUMBER(DataSummary!J105),DataSummary!J105,"#N/A") | M116: =IF(ISNUMBER(DataSummary!K105),DataSummary!K105,"#N/A") | N116: =IF(ISNUMBER(DataSummary!L105),DataSummary!L105,"#N/A") | O116: =IF(ISNUMBER(DataSummary!M105),DataSummary!M105,"#N/A") | P116: =IF(ISNUMBER(DataSummary!N105),DataSummary!N105,"#N/A") | ... AN116: =IF(ISNUMBER(DataSummary!AL105),DataSummary!AL105,"#N/A") | AO116: =IF(ISNUMBER(DataSummary!AL83),DataSummary!AL83,"#N/A") | AP116: =IF(ISNUMBER(DataSummary!AM83),DataSummary!AM83,"#N/A") | AQ116: =AP116 | AR116: =AQ116 | AS116: =AR116 | AT116: =AS116 | AU116: =AT116 | AV116: =AU116 | AW116: =AV116 | AX116: =AW116 | ... BW116: =BV116
G117: Used in "scenario" simulation | H117: (e.g. 0.40) | I117: =IF(VLOOKUP(InputDataA_GeneralAssumptions!$D$92,DataSummary!$A$111:$B$112,2,FALSE())=1,I115,I116) | J117: =IF(VLOOKUP(InputDataA_GeneralAssumptions!$D$92,DataSummary!$A$111:$B$112,2,FALSE())=1,J115,J116) | K117: =IF(VLOOKUP(InputDataA_GeneralAssumptions!$D$92,DataSummary!$A$111:$B$112,2,FALSE())=1,K115,K116) | L117: =IF(VLOOKUP(InputDataA_GeneralAssumptions!$D$92,DataSummary!$A$111:$B$112,2,FALSE())=1,L115,L116) | M117: =IF(VLOOKUP(InputDataA_GeneralAssumptions!$D$92,DataSummary!$A$111:$B$112,2,FALSE())=1,M115,M116) | N117: =IF(VLOOKUP(InputDataA_GeneralAssumptions!$D$92,DataSummary!$A$111:$B$112,2,FALSE())=1,N115,N116) | O117: =IF(VLOOKUP(InputDataA_GeneralAssumptions!$D$92,DataSummary!$A$111:$B$112,2,FALSE())=1,O115,O116) | P117: =IF(VLOOKUP(InputDataA_GeneralAssumptions!$D$92,DataSummary!$A$111:$B$112,2,FALSE())=1,P115,P116) | ... BW117: =IF(VLOOKUP(InputDataA_GeneralAssumptions!$D$92,DataSummary!$A$111:$B$112,2,FALSE())=1,BW115,BW116)
G118: Growth Working age to total population ratio | H118: =H117 | I118: =IF(ISNUMBER(DataSummary!B105),DataSummary!B105,"#N/A") | J118: =J117/I117-1 | K118: =K117/J117-1 | L118: =L117/K117-1 | M118: =M117/L117-1 | N118: =N117/M117-1 | O118: =O117/N117-1 | P118: =P117/O117-1 | Q118: =Q117/P117-1 | ... BW118: =BW117/BV117-1
...

Sheet GraphsA
B1: Graphs of assumptons which affect all model
A3: Main growth drivers (Human Capital and TFP)
F18: Back | O18: Back
A19: Labor force Participation Rate (by Gender)
G34: Back | O34: Back | W34: Back
A35: External balance variables (either CAB or debt & FDI are active)
G50: Back | O50: Back | W50: Back
A51: Demographic variables
G66: Back | O66: Back | W66: Back | AD66: Back
B67: Poverty and Income Distribution

Sheet InputDataB_ModelSpecAssumptions
B1: Assumption Specific to Model 1, Model 2 or Model 3 | AN1: ="35 hidden columns for years "&AO3&" to "&BW3&" -->"
B3: Model 1: Calculating growth implied by investment | C3: =DataSummary!D278 | D3: =DataSummary!N4 | E3: =DataSummary!N5 | F3: =D8 | G3: Investment to GDP Ratio | H3: Chart | I3: =InputDataA_GeneralAssumptions!$D$7 | J3: =I3+1 | K3: =J3+1 | L3: =K3+1 | M3: =L3+1 | N3: =M3+1 | O3: =N3+1 | P3: =O3+1 | Q3: =P3+1 | ... BW3: =BV3+1
B4: Initial Investment Ratio (I/Y) (User defined) --> | C4: (e.g. 0.40) | D4: 0.31 | E4: 0.31 | F4: =DataSummary!N4 | G4: "Manual" [user defined year by year] | H4: (e.g. 0.40) | I4: =I5 | J4: 0.25 | K4: 0.25 | L4: 0.25 | M4: 0.25 | N4: 0.25 | O4: 0.25 | P4: 0.25 | Q4: 0.25 | R4: 0.25 | S4: 0.25 | T4: 0.25 | U4: 0.25 | V4: 0.25 | W4: 0.25 | X4: 0.25 | Y4: 0.25 | Z4: 0.25 | AA4: 0.25 | AB4: 0.25 | AC4: 0.25 | AD4: 0.25 | AE4: 0.25 | AF4: 0.25 | AG4: 0.25 | AH4: 0.25 | AI4: 0.25 | AJ4: 0.25 | AK4: 0.25 | AL4: 0.25 | AM4: 0.25 | AN4: 0.25 | AO4: 0.25 | AP4: 0.25 | AQ4: 0.25 | AR4: 0.25 | AS4: 0.25 | AT4: =AS4 | AU4: =AT4 | AV4: =AU4 | AW4: =AV4 | AX4: =AW4 | AY4: =AX4 | AZ4: =AY4 | BA4: =AZ4 | ... BW4: =BV4
B5: ="Initial Investment Ratio, pre-loaded from "&DataSummary!D278&" -->" | C5: WDI 2019 | D5: =IF(ISNUMBER(IF(InputDataA_GeneralAssumptions!D7>202020,".",DataSummary!B278))=TRUE(),IF(InputDataA_GeneralAssumptions!D7>2020,".",DataSummary!B278),".") | G5: "Automatic" [reach target by year] | H5: =H4 | I5: =D6 | J5: =IF(Submodel1!F4>InputDataB_ModelSpecAssumptions!$D$10,InputDataB_ModelSpecAssumptions!$D$9,I5+(InputDataB_ModelSpecAssumptions!$D$9-$I$5)/(InputDataB_ModelSpecAssumptions!$D$10-InputDataA_GeneralAssumptions!$D$7)) | K5: =IF(Submodel1!G4>InputDataB_ModelSpecAssumptions!$D$10,InputDataB_ModelSpecAssumptions!$D$9,J5+(InputDataB_ModelSpecAssumptions!$D$9-$I$5)/(InputDataB_ModelSpecAssumptions!$D$10-InputDataA_GeneralAssumptions!$D$7)) | L5: =IF(Submodel1!H4>InputDataB_ModelSpecAssumptions!$D$10,InputDataB_ModelSpecAssumptions!$D$9,K5+(InputDataB_ModelSpecAssumptions!$D$9-$I$5)/(InputDataB_ModelSpecAssumptions!$D$10-InputDataA_GeneralAssumptions!$D$7)) | M5: =IF(Submodel1!I4>InputDataB_ModelSpecAssumptions!$D$10,InputDataB_ModelSpecAssumptions!$D$9,L5+(InputDataB_ModelSpecAssumptions!$D$9-$I$5)/(InputDataB_ModelSpecAssumptions!$D$10-InputDataA_GeneralAssumptions!$D$7)) | N5: =IF(Submodel1!J4>InputDataB_ModelSpecAssumptions!$D$10,InputDataB_ModelSpecAssumptions!$D$9,M5+(InputDataB_ModelSpecAssumptions!$D$9-$I$5)/(InputDataB_ModelSpecAssumptions!$D$10-InputDataA_GeneralAssumptions!$D$7)) | O5: =IF(Submodel1!K4>InputDataB_ModelSpecAssumptions!$D$10,InputDataB_ModelSpecAssumptions!$D$9,N5+(InputDataB_ModelSpecAssumptions!$D$9-$I$5)/(InputDataB_ModelSpecAssumptions!$D$10-InputDataA_GeneralAssumptions!$D$7)) | P5: =IF(Submodel1!L4>InputDataB_ModelSpecAssumptions!$D$10,InputDataB_ModelSpecAssumptions!$D$9,O5+(InputDataB_ModelSpecAssumptions!$D$9-$I$5)/(InputDataB_ModelSpecAssumptions!$D$10-InputDataA_GeneralAssumptions!$D$7)) | Q5: =IF(Submodel1!M4>InputDataB_ModelSpecAssumptions!$D$10,InputDataB_ModelSpecAssumptions!$D$9,P5+(InputDataB_ModelSpecAssumptions!$D$9-$I$5)/(InputDataB_ModelSpecAssumptions!$D$10-InputDataA_GeneralAssumptions!$D$7)) | ... BW5: =IF(Submodel1!BS4>InputDataB_ModelSpecAssumptions!$D$10,InputDataB_ModelSpecAssumptions!$D$9,BV5+(InputDataB_ModelSpecAssumptions!$D$9-$I$5)/(InputDataB_ModelSpecAssumptions!$D$10-InputDataA_GeneralAssumptions!$D$7))
B6: Initial is: (if cell D4:E4 -yellow- is blank uses pre-loaded) --> | C6: (e.g. 0.40) | D6: =IF(ISBLANK(D4)=TRUE(),D5,D4) | E6: =IF(ISBLANK(E4)=TRUE(),D5,E4) | G6: Used in "baseline" simulation | H6: (e.g. 0.40) | I6: =IF(VLOOKUP(InputDataB_ModelSpecAssumptions!$D$8,DataSummary!$A$111:$B$112,2,FALSE())=1,InputDataB_ModelSpecAssumptions!I4,InputDataB_ModelSpecAssumptions!I5) | J6: =IF(VLOOKUP(InputDataB_ModelSpecAssumptions!$D$8,DataSummary!$A$111:$B$112,2,FALSE())=1,InputDataB_ModelSpecAssumptions!J4,InputDataB_ModelSpecAssumptions!J5) | K6: =IF(VLOOKUP(InputDataB_ModelSpecAssumptions!$D$8,DataSummary!$A$111:$B$112,2,FALSE())=1,InputDataB_ModelSpecAssumptions!K4,InputDataB_ModelSpecAssumptions!K5) | L6: =IF(VLOOKUP(InputDataB_ModelSpecAssumptions!$D$8,DataSummary!$A$111:$B$112,2,FALSE())=1,InputDataB_ModelSpecAssumptions!L4,InputDataB_ModelSpecAssumptions!L5) | M6: =IF(VLOOKUP(InputDataB_ModelSpecAssumptions!$D$8,DataSummary!$A$111:$B$112,2,FALSE())=1,InputDataB_ModelSpecAssumptions!M4,InputDataB_ModelSpecAssumptions!M5) | N6: =IF(VLOOKUP(InputDataB_ModelSpecAssumptions!$D$8,DataSummary!$A$111:$B$112,2,FALSE())=1,InputDataB_ModelSpecAssumptions!N4,InputDataB_ModelSpecAssumptions!N5) | O6: =IF(VLOOKUP(InputDataB_ModelSpecAssumptions!$D$8,DataSummary!$A$111:$B$112,2,FALSE())=1,InputDataB_ModelSpecAssumptions!O4,InputDataB_ModelSpecAssumptions!O5) | P6: =IF(VLOOKUP(InputDataB_ModelSpecAssumptions!$D$8,DataSummary!$A$111:$B$112,2,FALSE())=1,InputDataB_ModelSpecAssumptions!P4,InputDataB_ModelSpecAssumptions!P5) | ... BW6: =IF(VLOOKUP(InputDataB_ModelSpecAssumptions!$D$8,DataSummary!$A$111:$B$112,2,FALSE())=1,InputDataB_ModelSpecAssumptions!BW4,InputDataB_ModelSpecAssumptions!BW5)
B8: Choice for future Capital Formation: | C8: Select from list --> | D8: Automatic | F8: =DataSummary!N5 | G8: "Manual" [user defined year by year] | H8: (e.g. 0.40) | I8: =I9 | J8: 0.25 | K8: 0.25 | L8: 0.25 | M8: 0.25 | N8: 0.25 | O8: 0.25 | P8: 0.25 | Q8: 0.25 | R8: 0.25 | S8: 0.25 | T8: 0.25 | U8: 0.25 | V8: 0.25 | W8: 0.25 | X8: 0.25 | Y8: 0.25 | Z8: 0.25 | AA8: 0.25 | AB8: 0.25 | AC8: 0.25 | AD8: 0.25 | AE8: 0.25 | AF8: 0.25 | AG8: 0.25 | AH8: 0.25 | AI8: 0.25 | AJ8: 0.25 | AK8: 0.25 | AL8: 0.25 | AM8: 0.25 | AN8: 0.25 | AO8: 0.25 | AP8: 0.25 | AQ8: 0.25 | AR8: 0.25 | AS8: 0.25 | AT8: 0.25 | AU8: 0.25 | AV8: 0.25 | AW8: 0.25 | AX8: 0.25 | AY8: 0.25 | AZ8: 0.25 | BA8: 0.25 | BB8: 0.25 | BC8: 0.25 | BD8: 0.25 | BE8: 0.25 | BF8: 0.25 | BG8: 0.25 | BH8: 0.25 | BI8: 0.25 | BJ8: 0.25 | BK8: 0.25 | BL8: 0.25 | BM8: 0.25 | BN8: 0.25 | BO8: 0.25 | BP8: 0.25 | BQ8: 0.25 | BR8: 0.25 | BS8: 0.25 | BT8: 0.25 | BU8: 0.25 | BV8: 0.25 | BW8: 0.25
B9: Target Investment Ratio (I/Y) --> | C9: (e.g. 0.40) | D9: 0.31 | E9: 0.24 | G9: "Automatic" [reach target by year] | H9: (e.g. 0.40) | I9: =E6 | J9: =IF(Submodel1s!F4>InputDataB_ModelSpecAssumptions!$E$10,InputDataB_ModelSpecAssumptions!$E$9,I9+(InputDataB_ModelSpecAssumptions!$E$9-$I$9)/(InputDataB_ModelSpecAssumptions!$E$10-InputDataA_GeneralAssumptions!$D$7)) | K9: =IF(Submodel1s!G4>InputDataB_ModelSpecAssumptions!$E$10,InputDataB_ModelSpecAssumptions!$E$9,J9+(InputDataB_ModelSpecAssumptions!$E$9-$I$9)/(InputDataB_ModelSpecAssumptions!$E$10-InputDataA_GeneralAssumptions!$D$7)) | L9: =IF(Submodel1s!H4>InputDataB_ModelSpecAssumptions!$E$10,InputDataB_ModelSpecAssumptions!$E$9,K9+(InputDataB_ModelSpecAssumptions!$E$9-$I$9)/(InputDataB_ModelSpecAssumptions!$E$10-InputDataA_GeneralAssumptions!$D$7)) | M9: =IF(Submodel1s!I4>InputDataB_ModelSpecAssumptions!$E$10,InputDataB_ModelSpecAssumptions!$E$9,L9+(InputDataB_ModelSpecAssumptions!$E$9-$I$9)/(InputDataB_ModelSpecAssumptions!$E$10-InputDataA_GeneralAssumptions!$D$7)) | N9: =IF(Submodel1s!J4>InputDataB_ModelSpecAssumptions!$E$10,InputDataB_ModelSpecAssumptions!$E$9,M9+(InputDataB_ModelSpecAssumptions!$E$9-$I$9)/(InputDataB_ModelSpecAssumptions!$E$10-InputDataA_GeneralAssumptions!$D$7)) | O9: =IF(Submodel1s!K4>InputDataB_ModelSpecAssumptions!$E$10,InputDataB_ModelSpecAssumptions!$E$9,N9+(InputDataB_ModelSpecAssumptions!$E$9-$I$9)/(InputDataB_ModelSpecAssumptions!$E$10-InputDataA_GeneralAssumptions!$D$7)) | P9: =IF(Submodel1s!L4>InputDataB_ModelSpecAssumptions!$E$10,InputDataB_ModelSpecAssumptions!$E$9,O9+(InputDataB_ModelSpecAssumptions!$E$9-$I$9)/(InputDataB_ModelSpecAssumptions!$E$10-InputDataA_GeneralAssumptions!$D$7)) | Q9: =IF(Submodel1s!M4>InputDataB_ModelSpecAssumptions!$E$10,InputDataB_ModelSpecAssumptions!$E$9,P9+(InputDataB_ModelSpecAssumptions!$E$9-$I$9)/(InputDataB_ModelSpecAssumptions!$E$10-InputDataA_GeneralAssumptions!$D$7)) | ... BW9: =IF(Submodel1s!BS4>InputDataB_ModelSpecAssumptions!$E$10,InputDataB_ModelSpecAssumptions!$E$9,BV9+(InputDataB_ModelSpecAssumptions!$E$9-$I$9)/(InputDataB_ModelSpecAssumptions!$E$10-InputDataA_GeneralAssumptions!$D$7))
B10: Reach target I/Y rate by year --> | C10: (YYYY) | D10: 2025 | E10: 2025 | G10: Used in "scenario" simulation | H10: (e.g. 0.40) | I10: =IF(VLOOKUP(InputDataB_ModelSpecAssumptions!$D$8,DataSummary!$A$111:$B$112,2,FALSE())=1,InputDataB_ModelSpecAssumptions!I8,InputDataB_ModelSpecAssumptions!I9) | J10: =IF(VLOOKUP(InputDataB_ModelSpecAssumptions!$D$8,DataSummary!$A$111:$B$112,2,FALSE())=1,InputDataB_ModelSpecAssumptions!J8,InputDataB_ModelSpecAssumptions!J9) | K10: =IF(VLOOKUP(InputDataB_ModelSpecAssumptions!$D$8,DataSummary!$A$111:$B$112,2,FALSE())=1,InputDataB_ModelSpecAssumptions!K8,InputDataB_ModelSpecAssumptions!K9) | L10: =IF(VLOOKUP(InputDataB_ModelSpecAssumptions!$D$8,DataSummary!$A$111:$B$112,2,FALSE())=1,InputDataB_ModelSpecAssumptions!L8,InputDataB_ModelSpecAssumptions!L9) | M10: =IF(VLOOKUP(InputDataB_ModelSpecAssumptions!$D$8,DataSummary!$A$111:$B$112,2,FALSE())=1,InputDataB_ModelSpecAssumptions!M8,InputDataB_ModelSpecAssumptions!M9) | N10: =IF(VLOOKUP(InputDataB_ModelSpecAssumptions!$D$8,DataSummary!$A$111:$B$112,2,FALSE())=1,InputDataB_ModelSpecAssumptions!N8,InputDataB_ModelSpecAssumptions!N9) | O10: =IF(VLOOKUP(InputDataB_ModelSpecAssumptions!$D$8,DataSummary!$A$111:$B$112,2,FALSE())=1,InputDataB_ModelSpecAssumptions!O8,InputDataB_ModelSpecAssumptions!O9) | P10: =IF(VLOOKUP(InputDataB_ModelSpecAssumptions!$D$8,DataSummary!$A$111:$B$112,2,FALSE())=1,InputDataB_ModelSpecAssumptions!P8,InputDataB_ModelSpecAssumptions!P9) | ... BW10: =IF(VLOOKUP(InputDataB_ModelSpecAssumptions!$D$8,DataSummary!$A$111:$B$112,2,FALSE())=1,InputDataB_ModelSpecAssumptions!BW8,InputDataB_ModelSpecAssumptions!BW9)
B12: Model 2: Calculating Investment Ratio to Achieve Output Target | F12: =D21 | G12: =VLOOKUP(InputDataB_ModelSpecAssumptions!D20,DataSummary!A122:C125,3,FALSE()) | H12: Chart | I12: =InputDataA_GeneralAssumptions!$D$7 | J12: =I12+1 | K12: =J12+1 | L12: =K12+1 | M12: =L12+1 | N12: =M12+1 | O12: =N12+1 | P12: =O12+1 | Q12: =P12+1 | ... BW12: =BV12+1
B13: Initial Value of user defined Output Target --> | C13: =C22 | F13: =DataSummary!N4 | G13: "Manual" [user defined year by year] | H13: (e.g. 0.40) | I13: =I14 | J13: =I13 | K13: =J13 | L13: =K13 | M13: =L13 | N13: =M13 | O13: =N13 | P13: =O13 | Q13: =P13 | ... BW13: =BV13
B14: ="Pre-loaded initial value of user-defined Output Target from:" | C14: WDI | D14: =DataSummary!E134 | G14: "Automatic" [reach target by year] | H14: =H13 | I14: =D15 | J14: =IF(VLOOKUP(InputDataB_ModelSpecAssumptions!$D$20,DataSummary!$A$122:$B$125,2,FALSE())=3,J17,IF(J12>=InputDataB_ModelSpecAssumptions!$D$23,InputDataB_ModelSpecAssumptions!$D$22,I14+(InputDataB_ModelSpecAssumptions!$D$22-$I$14)/(InputDataB_ModelSpecAssumptions!$D$23-InputDataA_GeneralAssumptions!$D$7))) | K14: =IF(VLOOKUP(InputDataB_ModelSpecAssumptions!$D$20,DataSummary!$A$122:$B$125,2,FALSE())=3,K17,IF(K12>=InputDataB_ModelSpecAssumptions!$D$23,InputDataB_ModelSpecAssumptions!$D$22,J14+(InputDataB_ModelSpecAssumptions!$D$22-$I$14)/(InputDataB_ModelSpecAssumptions!$D$23-InputDataA_GeneralAssumptions!$D$7))) | L14: =IF(VLOOKUP(InputDataB_ModelSpecAssumptions!$D$20,DataSummary!$A$122:$B$125,2,FALSE())=3,L17,IF(L12>=InputDataB_ModelSpecAssumptions!$D$23,InputDataB_ModelSpecAssumptions!$D$22,K14+(InputDataB_ModelSpecAssumptions!$D$22-$I$14)/(InputDataB_ModelSpecAssumptions!$D$23-InputDataA_GeneralAssumptions!$D$7))) | M14: =IF(VLOOKUP(InputDataB_ModelSpecAssumptions!$D$20,DataSummary!$A$122:$B$125,2,FALSE())=3,M17,IF(M12>=InputDataB_ModelSpecAssumptions!$D$23,InputDataB_ModelSpecAssumptions!$D$22,L14+(InputDataB_ModelSpecAssumptions!$D$22-$I$14)/(InputDataB_ModelSpecAssumptions!$D$23-InputDataA_GeneralAssumptions!$D$7))) | N14: =IF(VLOOKUP(InputDataB_ModelSpecAssumptions!$D$20,DataSummary!$A$122:$B$125,2,FALSE())=3,N17,IF(N12>=InputDataB_ModelSpecAssumptions!$D$23,InputDataB_ModelSpecAssumptions!$D$22,M14+(InputDataB_ModelSpecAssumptions!$D$22-$I$14)/(InputDataB_ModelSpecAssumptions!$D$23-InputDataA_GeneralAssumptions!$D$7))) | O14: =IF(VLOOKUP(InputDataB_ModelSpecAssumptions!$D$20,DataSummary!$A$122:$B$125,2,FALSE())=3,O17,IF(O12>=InputDataB_ModelSpecAssumptions!$D$23,InputDataB_ModelSpecAssumptions!$D$22,N14+(InputDataB_ModelSpecAssumptions!$D$22-$I$14)/(InputDataB_ModelSpecAssumptions!$D$23-InputDataA_GeneralAssumptions!$D$7))) | P14: =IF(VLOOKUP(InputDataB_ModelSpecAssumptions!$D$20,DataSummary!$A$122:$B$125,2,FALSE())=3,P17,IF(P12>=InputDataB_ModelSpecAssumptions!$D$23,InputDataB_ModelSpecAssumptions!$D$22,O14+(InputDataB_ModelSpecAssumptions!$D$22-$I$14)/(InputDataB_ModelSpecAssumptions!$D$23-InputDataA_GeneralAssumptions!$D$7))) | Q14: =IF(VLOOKUP(InputDataB_ModelSpecAssumptions!$D$20,DataSummary!$A$122:$B$125,2,FALSE())=3,Q17,IF(Q12>=InputDataB_ModelSpecAssumptions!$D$23,InputDataB_ModelSpecAssumptions!$D$22,P14+(InputDataB_ModelSpecAssumptions!$D$22-$I$14)/(InputDataB_ModelSpecAssumptions!$D$23-InputDataA_GeneralAssumptions!$D$7))) | ... BW14: =IF(VLOOKUP(InputDataB_ModelSpecAssumptions!$D$20,DataSummary!$A$122:$B$125,2,FALSE())=3,BW17,IF(BW12>=InputDataB_ModelSpecAssumptions!$D$23,InputDataB_ModelSpecAssumptions!$D$22,BV14+(InputDataB_ModelSpecAssumptions!$D$22-$I$14)/(InputDataB_ModelSpecAssumptions!$D$23-InputDataA_GeneralAssumptions!$D$7)))
B15: Initial is (if cell D13:E13 -yellow- is blank uses pre-loaded)--> | C15: =IF(DataSummary!B133=1,"(e.g. 0.01)",IF(DataSummary!B133=2,"(e.g. 0.01)","Real US$")) | D15: =IF(ISBLANK(D13)=TRUE(),D14,D13) | E15: =IF(ISBLANK(E13)=TRUE(),D14,E13) | G15: Used in "baseline" simulation | H15: (e.g. 0.40) | I15: =IF(VLOOKUP(InputDataB_ModelSpecAssumptions!$D$21,DataSummary!$A$111:$B$112,2,FALSE())=1,InputDataB_ModelSpecAssumptions!I13,InputDataB_ModelSpecAssumptions!I14) | J15: =IF(VLOOKUP(InputDataB_ModelSpecAssumptions!$D$21,DataSummary!$A$111:$B$112,2,FALSE())=1,InputDataB_ModelSpecAssumptions!J13,InputDataB_ModelSpecAssumptions!J14) | K15: =IF(VLOOKUP(InputDataB_ModelSpecAssumptions!$D$21,DataSummary!$A$111:$B$112,2,FALSE())=1,InputDataB_ModelSpecAssumptions!K13,InputDataB_ModelSpecAssumptions!K14) | L15: =IF(VLOOKUP(InputDataB_ModelSpecAssumptions!$D$21,DataSummary!$A$111:$B$112,2,FALSE())=1,InputDataB_ModelSpecAssumptions!L13,InputDataB_ModelSpecAssumptions!L14) | M15: =IF(VLOOKUP(InputDataB_ModelSpecAssumptions!$D$21,DataSummary!$A$111:$B$112,2,FALSE())=1,InputDataB_ModelSpecAssumptions!M13,InputDataB_ModelSpecAssumptions!M14) | N15: =IF(VLOOKUP(InputDataB_ModelSpecAssumptions!$D$21,DataSummary!$A$111:$B$112,2,FALSE())=1,InputDataB_ModelSpecAssumptions!N13,InputDataB_ModelSpecAssumptions!N14) | O15: =IF(VLOOKUP(InputDataB_ModelSpecAssumptions!$D$21,DataSummary!$A$111:$B$112,2,FALSE())=1,InputDataB_ModelSpecAssumptions!O13,InputDataB_ModelSpecAssumptions!O14) | P15: =IF(VLOOKUP(InputDataB_ModelSpecAssumptions!$D$21,DataSummary!$A$111:$B$112,2,FALSE())=1,InputDataB_ModelSpecAssumptions!P13,InputDataB_ModelSpecAssumptions!P14) | ... BW15: =IF(VLOOKUP(InputDataB_ModelSpecAssumptions!$D$21,DataSummary!$A$111:$B$112,2,FALSE())=1,InputDataB_ModelSpecAssumptions!BW13,InputDataB_ModelSpecAssumptions!BW14)
B16: Growth rate average (historical or target)* | C16: 15yr avg | D16: =(InputDataB_ModelSpecAssumptions!D22/InputDataB_ModelSpecAssumptions!D15)^(1/(InputDataB_ModelSpecAssumptions!D23-InputDataA_GeneralAssumptions!D7))-1 | E16: =(InputDataB_ModelSpecAssumptions!E22/InputDataB_ModelSpecAssumptions!E15)^(1/(InputDataB_ModelSpecAssumptions!E23-InputDataA_GeneralAssumptions!D7))-1
I17: =InputDataB_ModelSpecAssumptions!D15 | J17: =IF(J12>=InputDataB_ModelSpecAssumptions!$D$23,InputDataB_ModelSpecAssumptions!$D$22,I14*(1+$D$16)) | K17: =IF(K12>=InputDataB_ModelSpecAssumptions!$D$23,InputDataB_ModelSpecAssumptions!$D$22,J14*(1+$D$16)) | L17: =IF(L12>=InputDataB_ModelSpecAssumptions!$D$23,InputDataB_ModelSpecAssumptions!$D$22,K14*(1+$D$16)) | M17: =IF(M12>=InputDataB_ModelSpecAssumptions!$D$23,InputDataB_ModelSpecAssumptions!$D$22,L14*(1+$D$16)) | N17: =IF(N12>=InputDataB_ModelSpecAssumptions!$D$23,InputDataB_ModelSpecAssumptions!$D$22,M14*(1+$D$16)) | O17: =IF(O12>=InputDataB_ModelSpecAssumptions!$D$23,InputDataB_ModelSpecAssumptions!$D$22,N14*(1+$D$16)) | P17: =IF(P12>=InputDataB_ModelSpecAssumptions!$D$23,InputDataB_ModelSpecAssumptions!$D$22,O14*(1+$D$16)) | Q17: =IF(Q12>=InputDataB_ModelSpecAssumptions!$D$23,InputDataB_ModelSpecAssumptions!$D$22,P14*(1+$D$16)) | ... BW17: =IF(BW12>=InputDataB_ModelSpecAssumptions!$D$23,InputDataB_ModelSpecAssumptions!$D$22,BV14*(1+$D$16))
I18: =InputDataB_ModelSpecAssumptions!E15 | J18: =IF(J12>=InputDataB_ModelSpecAssumptions!$E$23,InputDataB_ModelSpecAssumptions!$E$22,I20*(1+$E$16)) | K18: =IF(K12>=InputDataB_ModelSpecAssumptions!$E$23,InputDataB_ModelSpecAssumptions!$E$22,J20*(1+$E$16)) | L18: =IF(L12>=InputDataB_ModelSpecAssumptions!$E$23,InputDataB_ModelSpecAssumptions!$E$22,K20*(1+$E$16)) | M18: =IF(M12>=InputDataB_ModelSpecAssumptions!$E$23,InputDataB_ModelSpecAssumptions!$E$22,L20*(1+$E$16)) | N18: =IF(N12>=InputDataB_ModelSpecAssumptions!$E$23,InputDataB_ModelSpecAssumptions!$E$22,M20*(1+$E$16)) | O18: =IF(O12>=InputDataB_ModelSpecAssumptions!$E$23,InputDataB_ModelSpecAssumptions!$E$22,N20*(1+$E$16)) | P18: =IF(P12>=InputDataB_ModelSpecAssumptions!$E$23,InputDataB_ModelSpecAssumptions!$E$22,O20*(1+$E$16)) | Q18: =IF(Q12>=InputDataB_ModelSpecAssumptions!$E$23,InputDataB_ModelSpecAssumptions!$E$22,P20*(1+$E$16)) | ... BW18: =IF(BW12>=InputDataB_ModelSpecAssumptions!$E$23,InputDataB_ModelSpecAssumptions!$E$22,BV20*(1+$E$16))
B19: *Only applies to growth rates, not GDP PC levels | C19: ="Most recent year is "&DataSummary!Q129 | D19: =VLOOKUP(D20,DataSummary!A122:C125,3,FALSE()) | F19: =DataSummary!N5 | G19: "Manual" [user defined year by year] | H19: (e.g. 0.40) | I19: =I20 | J19: =I19 | K19: =J19 | L19: =K19 | M19: =L19 | N19: =M19 | O19: =N19 | P19: =O19 | Q19: =P19 | ... BW19: =BV19
B20: ="Select Output Target Variable, period "&InputDataA_GeneralAssumptions!D7&"-"&InputDataA_GeneralAssumptions!D8&":" | C20: Select from list --> | D20: GDP Growth | G20: "Automatic" [reach target by year] | H20: (e.g. 0.40) | I20: =E15 | J20: =IF(VLOOKUP(InputDataB_ModelSpecAssumptions!$D$20,DataSummary!$A$122:$B$125,2,FALSE())=3,J18,IF(J12>=InputDataB_ModelSpecAssumptions!$E$23,InputDataB_ModelSpecAssumptions!$E$22,I20+(InputDataB_ModelSpecAssumptions!$E$22-$I$20)/(InputDataB_ModelSpecAssumptions!$E$23-InputDataA_GeneralAssumptions!$D$7))) | K20: =IF(VLOOKUP(InputDataB_ModelSpecAssumptions!$D$20,DataSummary!$A$122:$B$125,2,FALSE())=3,K18,IF(K12>=InputDataB_ModelSpecAssumptions!$E$23,InputDataB_ModelSpecAssumptions!$E$22,J20+(InputDataB_ModelSpecAssumptions!$E$22-$I$20)/(InputDataB_ModelSpecAssumptions!$E$23-InputDataA_GeneralAssumptions!$D$7))) | L20: =IF(VLOOKUP(InputDataB_ModelSpecAssumptions!$D$20,DataSummary!$A$122:$B$125,2,FALSE())=3,L18,IF(L12>=InputDataB_ModelSpecAssumptions!$E$23,InputDataB_ModelSpecAssumptions!$E$22,K20+(InputDataB_ModelSpecAssumptions!$E$22-$I$20)/(InputDataB_ModelSpecAssumptions!$E$23-InputDataA_GeneralAssumptions!$D$7))) | M20: =IF(VLOOKUP(InputDataB_ModelSpecAssumptions!$D$20,DataSummary!$A$122:$B$125,2,FALSE())=3,M18,IF(M12>=InputDataB_ModelSpecAssumptions!$E$23,InputDataB_ModelSpecAssumptions!$E$22,L20+(InputDataB_ModelSpecAssumptions!$E$22-$I$20)/(InputDataB_ModelSpecAssumptions!$E$23-InputDataA_GeneralAssumptions!$D$7))) | N20: =IF(VLOOKUP(InputDataB_ModelSpecAssumptions!$D$20,DataSummary!$A$122:$B$125,2,FALSE())=3,N18,IF(N12>=InputDataB_ModelSpecAssumptions!$E$23,InputDataB_ModelSpecAssumptions!$E$22,M20+(InputDataB_ModelSpecAssumptions!$E$22-$I$20)/(InputDataB_ModelSpecAssumptions!$E$23-InputDataA_GeneralAssumptions!$D$7))) | O20: =IF(VLOOKUP(InputDataB_ModelSpecAssumptions!$D$20,DataSummary!$A$122:$B$125,2,FALSE())=3,O18,IF(O12>=InputDataB_ModelSpecAssumptions!$E$23,InputDataB_ModelSpecAssumptions!$E$22,N20+(InputDataB_ModelSpecAssumptions!$E$22-$I$20)/(InputDataB_ModelSpecAssumptions!$E$23-InputDataA_GeneralAssumptions!$D$7))) | P20: =IF(VLOOKUP(InputDataB_ModelSpecAssumptions!$D$20,DataSummary!$A$122:$B$125,2,FALSE())=3,P18,IF(P12>=InputDataB_ModelSpecAssumptions!$E$23,InputDataB_ModelSpecAssumptions!$E$22,O20+(InputDataB_ModelSpecAssumptions!$E$22-$I$20)/(InputDataB_ModelSpecAssumptions!$E$23-InputDataA_GeneralAssumptions!$D$7))) | Q20: =IF(VLOOKUP(InputDataB_ModelSpecAssumptions!$D$20,DataSummary!$A$122:$B$125,2,FALSE())=3,Q18,IF(Q12>=InputDataB_ModelSpecAssumptions!$E$23,InputDataB_ModelSpecAssumptions!$E$22,P20+(InputDataB_ModelSpecAssumptions!$E$22-$I$20)/(InputDataB_ModelSpecAssumptions!$E$23-InputDataA_GeneralAssumptions!$D$7))) | ... BW20: =IF(VLOOKUP(InputDataB_ModelSpecAssumptions!$D$20,DataSummary!$A$122:$B$125,2,FALSE())=3,BW18,IF(BW12>=InputDataB_ModelSpecAssumptions!$E$23,InputDataB_ModelSpecAssumptions!$E$22,BV20+(InputDataB_ModelSpecAssumptions!$E$22-$I$20)/(InputDataB_ModelSpecAssumptions!$E$23-InputDataA_GeneralAssumptions!$D$7)))
B21: Choice of future value of user defined Output Target: | C21: Select from list --> | D21: Automatic | G21: Used in "scenario" simulation | H21: =H20 | I21: =IF(VLOOKUP(InputDataB_ModelSpecAssumptions!$D$21,DataSummary!$A$111:$B$112,2,FALSE())=1,InputDataB_ModelSpecAssumptions!I19,InputDataB_ModelSpecAssumptions!I20) | J21: =IF(VLOOKUP(InputDataB_ModelSpecAssumptions!$D$21,DataSummary!$A$111:$B$112,2,FALSE())=1,InputDataB_ModelSpecAssumptions!J19,InputDataB_ModelSpecAssumptions!J20) | K21: =IF(VLOOKUP(InputDataB_ModelSpecAssumptions!$D$21,DataSummary!$A$111:$B$112,2,FALSE())=1,InputDataB_ModelSpecAssumptions!K19,InputDataB_ModelSpecAssumptions!K20) | L21: =IF(VLOOKUP(InputDataB_ModelSpecAssumptions!$D$21,DataSummary!$A$111:$B$112,2,FALSE())=1,InputDataB_ModelSpecAssumptions!L19,InputDataB_ModelSpecAssumptions!L20) | M21: =IF(VLOOKUP(InputDataB_ModelSpecAssumptions!$D$21,DataSummary!$A$111:$B$112,2,FALSE())=1,InputDataB_ModelSpecAssumptions!M19,InputDataB_ModelSpecAssumptions!M20) | N21: =IF(VLOOKUP(InputDataB_ModelSpecAssumptions!$D$21,DataSummary!$A$111:$B$112,2,FALSE())=1,InputDataB_ModelSpecAssumptions!N19,InputDataB_ModelSpecAssumptions!N20) | O21: =IF(VLOOKUP(InputDataB_ModelSpecAssumptions!$D$21,DataSummary!$A$111:$B$112,2,FALSE())=1,InputDataB_ModelSpecAssumptions!O19,InputDataB_ModelSpecAssumptions!O20) | P21: =IF(VLOOKUP(InputDataB_ModelSpecAssumptions!$D$21,DataSummary!$A$111:$B$112,2,FALSE())=1,InputDataB_ModelSpecAssumptions!P19,InputDataB_ModelSpecAssumptions!P20) | ... BW21: =IF(VLOOKUP(InputDataB_ModelSpecAssumptions!$D$21,DataSummary!$A$111:$B$112,2,FALSE())=1,InputDataB_ModelSpecAssumptions!BW19,InputDataB_ModelSpecAssumptions!BW20)
B22: Target Value for user defined Output Variable --> | C22: =IF(DataSummary!B133=1,"(e.g. 0.01)",IF(DataSummary!B133=2,"(e.g. 0.01)","Real US$")) | D22: =D15 | E22: =D22
B23: Reach Target by year --> | C23: (YYYY) | D23: 2030 | E23: =D23
B25: Model 3: Defining path for Gross National Savings (Ratio to GDP) | F25: =D30 | G25: Gross National Savings Ratio to GDP | H25: Chart | I25: =InputDataA_GeneralAssumptions!$D$7 | J25: =I25+1 | K25: =J25+1 | L25: =K25+1 | M25: =L25+1 | N25: =M25+1 | O25: =N25+1 | P25: =O25+1 | Q25: =P25+1 | ... BW25: =BV25+1
B26: Initial Gross National Savings Ratio (user defined) --> | C26: =DataSummary!D295 | F26: =DataSummary!N4 | G26: "Manual" [user defined year by year] | H26: (e.g. 0.40) | I26: =InputDataB_ModelSpecAssumptions!D28 | J26: 0.4 | K26: 0.4 | L26: 0.36461538 | M26: 0.36615385 | N26: 0.36769231 | O26: 0.36923077 | P26: 0.37076923 | Q26: 0.37230769 | R26: 0.37384615 | S26: 0.37538462 | T26: 0.37692308 | U26: 0.37846154 | V26: 0.38 | W26: 0.38153846 | X26: 0.38307692 | Y26: 0.38461538 | Z26: 0.38615385 | AA26: 0.38769231 | AB26: 0.38923077 | AC26: 0.39076923 | AD26: 0.39230769 | AE26: 0.39384615 | AF26: 0.39538462 | AG26: 0.39692308 | AH26: 0.39846154 | AI26: 0.4 | AJ26: 0.4 | AK26: 0.4 | AL26: 0.4 | AM26: 0.4 | AN26: 0.8 | AO26: 0.9 | AP26: 0.4 | AQ26: 0.4 | AR26: 0.4 | AS26: 0.4 | AT26: =AS26 | AU26: =AT26 | AV26: =AU26 | AW26: =AV26 | AX26: =AW26 | AY26: =AX26 | AZ26: =AY26 | BA26: =AZ26 | ... BW26: =BV26
B27: ="Initial Gross National Savings Ratio, pre-loaded from "&DataSummary!D301&" --> " | C27: WDI 15yr ave | D27: =IF(ISNUMBER(DataSummary!B301)=TRUE(),DataSummary!B301,".") | G27: "Automatic" [reach target by year] | H27: =H26 | I27: =D28 | J27: =IF(Submodel3!F4>InputDataB_ModelSpecAssumptions!$D$32,InputDataB_ModelSpecAssumptions!$D$31,I27+(InputDataB_ModelSpecAssumptions!$D$31-$I27)/(InputDataB_ModelSpecAssumptions!$D$32-InputDataA_GeneralAssumptions!$D$7)) | K27: =IF(Submodel3!G4>InputDataB_ModelSpecAssumptions!$D$32,InputDataB_ModelSpecAssumptions!$D$31,J27+(InputDataB_ModelSpecAssumptions!$D$31-$I27)/(InputDataB_ModelSpecAssumptions!$D$32-InputDataA_GeneralAssumptions!$D$7)) | L27: =IF(Submodel3!H4>InputDataB_ModelSpecAssumptions!$D$32,InputDataB_ModelSpecAssumptions!$D$31,K27+(InputDataB_ModelSpecAssumptions!$D$31-$I27)/(InputDataB_ModelSpecAssumptions!$D$32-InputDataA_GeneralAssumptions!$D$7)) | M27: =IF(Submodel3!I4>InputDataB_ModelSpecAssumptions!$D$32,InputDataB_ModelSpecAssumptions!$D$31,L27+(InputDataB_ModelSpecAssumptions!$D$31-$I27)/(InputDataB_ModelSpecAssumptions!$D$32-InputDataA_GeneralAssumptions!$D$7)) | N27: =IF(Submodel3!J4>InputDataB_ModelSpecAssumptions!$D$32,InputDataB_ModelSpecAssumptions!$D$31,M27+(InputDataB_ModelSpecAssumptions!$D$31-$I27)/(InputDataB_ModelSpecAssumptions!$D$32-InputDataA_GeneralAssumptions!$D$7)) | O27: =IF(Submodel3!K4>InputDataB_ModelSpecAssumptions!$D$32,InputDataB_ModelSpecAssumptions!$D$31,N27+(InputDataB_ModelSpecAssumptions!$D$31-$I27)/(InputDataB_ModelSpecAssumptions!$D$32-InputDataA_GeneralAssumptions!$D$7)) | P27: =IF(Submodel3!L4>InputDataB_ModelSpecAssumptions!$D$32,InputDataB_ModelSpecAssumptions!$D$31,O27+(InputDataB_ModelSpecAssumptions!$D$31-$I27)/(InputDataB_ModelSpecAssumptions!$D$32-InputDataA_GeneralAssumptions!$D$7)) | Q27: =IF(Submodel3!M4>InputDataB_ModelSpecAssumptions!$D$32,InputDataB_ModelSpecAssumptions!$D$31,P27+(InputDataB_ModelSpecAssumptions!$D$31-$I27)/(InputDataB_ModelSpecAssumptions!$D$32-InputDataA_GeneralAssumptions!$D$7)) | ... BW27: =IF(Submodel3!BS4>InputDataB_ModelSpecAssumptions!$D$32,InputDataB_ModelSpecAssumptions!$D$31,BV27+(InputDataB_ModelSpecAssumptions!$D$31-$I27)/(InputDataB_ModelSpecAssumptions!$D$32-InputDataA_GeneralAssumptions!$D$7))
B28: Initial GNS/Y is (if cell D24:E24 is blank uses pre-loaded) --> | C28: (e.g. 0.40) | D28: =IF(ISBLANK(D26)=TRUE(),D27,D26) | E28: =IF(ISBLANK(E26)=TRUE(),D27,E26) | G28: Used in "baseline" simulation | H28: (e.g. 0.40) | I28: =IF(VLOOKUP(InputDataB_ModelSpecAssumptions!$D$30,DataSummary!$A$111:$B$112,2,FALSE())=1,I26,I27) | J28: =IF(VLOOKUP(InputDataB_ModelSpecAssumptions!$D$30,DataSummary!$A$111:$B$112,2,FALSE())=1,J26,J27) | K28: =IF(VLOOKUP(InputDataB_ModelSpecAssumptions!$D$30,DataSummary!$A$111:$B$112,2,FALSE())=1,K26,K27) | L28: =IF(VLOOKUP(InputDataB_ModelSpecAssumptions!$D$30,DataSummary!$A$111:$B$112,2,FALSE())=1,L26,L27) | M28: =IF(VLOOKUP(InputDataB_ModelSpecAssumptions!$D$30,DataSummary!$A$111:$B$112,2,FALSE())=1,M26,M27) | N28: =IF(VLOOKUP(InputDataB_ModelSpecAssumptions!$D$30,DataSummary!$A$111:$B$112,2,FALSE())=1,N26,N27) | O28: =IF(VLOOKUP(InputDataB_ModelSpecAssumptions!$D$30,DataSummary!$A$111:$B$112,2,FALSE())=1,O26,O27) | P28: =IF(VLOOKUP(InputDataB_ModelSpecAssumptions!$D$30,DataSummary!$A$111:$B$112,2,FALSE())=1,P26,P27) | ... BW28: =IF(VLOOKUP(InputDataB_ModelSpecAssumptions!$D$30,DataSummary!$A$111:$B$112,2,FALSE())=1,BW26,BW27)
B30: Choice for future Gross National Savings Ratio to GDP: | C30: Select from list --> | D30: Automatic | F30: =DataSummary!N5 | G30: "Manual" [user defined year by year] | H30: =H28 | I30: =InputDataB_ModelSpecAssumptions!D28 | J30: 0.5 | K30: 0.5 | L30: 0.5 | M30: 0.36615385 | N30: 0.36769231 | O30: 0.36923077 | P30: 0.37076923 | Q30: 0.37230769 | R30: 0.37384615 | S30: 0.37538462 | T30: 0.37692308 | U30: 0.37846154 | V30: 0.38 | W30: 0.38153846 | X30: 0.38307692 | Y30: 0.38461538 | Z30: 0.38615385 | AA30: 0.38769231 | AB30: 0.38923077 | AC30: 0.39076923 | AD30: 0.39230769 | AE30: 0.39384615 | AF30: 0.39538462 | AG30: 0.39692308 | AH30: 0.39846154 | AI30: 0.4 | AJ30: 0.4 | AK30: 0.4 | AL30: 0.4 | AM30: 0.4 | AN30: 0.4 | AO30: 0.4 | AP30: 0.4 | AQ30: 0.4 | AR30: 0.4 | AS30: 0.4 | AT30: 0.4 | AU30: 0.4 | AV30: 0.4 | AW30: 0.4 | AX30: 0.4 | AY30: 0.4 | AZ30: 0.4 | BA30: 0.4 | BB30: 0.4 | BC30: 0.4 | BD30: 0.4 | BE30: 0.4 | BF30: 0.4 | BG30: 0.4 | BH30: 0.4 | BI30: 0.4 | BJ30: 0.4 | BK30: 0.4 | BL30: 0.4 | BM30: 0.4 | BN30: 0.4 | BO30: 0.4 | BP30: 0.4 | BQ30: 0.4 | BR30: 0.4 | BS30: 0.4 | BT30: 0.4 | BU30: 0.4 | BV30: 0.4 | BW30: 0.4
B31: Target GNS / GDP --> | C31: (e.g. 0.40) | D31: =D28 | E31: =E28 | G31: "Automatic" [reach target by year] | H31: (e.g. 0.40) | I31: =E28 | J31: =IF(Submodel3s!F4>InputDataB_ModelSpecAssumptions!$E$32,InputDataB_ModelSpecAssumptions!$E$31,I31+(InputDataB_ModelSpecAssumptions!$E$31-$I31)/(InputDataB_ModelSpecAssumptions!$E$32-InputDataA_GeneralAssumptions!$D$7)) | K31: =IF(Submodel3s!G4>InputDataB_ModelSpecAssumptions!$E$32,InputDataB_ModelSpecAssumptions!$E$31,J31+(InputDataB_ModelSpecAssumptions!$E$31-$I31)/(InputDataB_ModelSpecAssumptions!$E$32-InputDataA_GeneralAssumptions!$D$7)) | L31: =IF(Submodel3s!H4>InputDataB_ModelSpecAssumptions!$E$32,InputDataB_ModelSpecAssumptions!$E$31,K31+(InputDataB_ModelSpecAssumptions!$E$31-$I31)/(InputDataB_ModelSpecAssumptions!$E$32-InputDataA_GeneralAssumptions!$D$7)) | M31: =IF(Submodel3s!I4>InputDataB_ModelSpecAssumptions!$E$32,InputDataB_ModelSpecAssumptions!$E$31,L31+(InputDataB_ModelSpecAssumptions!$E$31-$I31)/(InputDataB_ModelSpecAssumptions!$E$32-InputDataA_GeneralAssumptions!$D$7)) | N31: =IF(Submodel3s!J4>InputDataB_ModelSpecAssumptions!$E$32,InputDataB_ModelSpecAssumptions!$E$31,M31+(InputDataB_ModelSpecAssumptions!$E$31-$I31)/(InputDataB_ModelSpecAssumptions!$E$32-InputDataA_GeneralAssumptions!$D$7)) | O31: =IF(Submodel3s!K4>InputDataB_ModelSpecAssumptions!$E$32,InputDataB_ModelSpecAssumptions!$E$31,N31+(InputDataB_ModelSpecAssumptions!$E$31-$I31)/(InputDataB_ModelSpecAssumptions!$E$32-InputDataA_GeneralAssumptions!$D$7)) | P31: =IF(Submodel3s!L4>InputDataB_ModelSpecAssumptions!$E$32,InputDataB_ModelSpecAssumptions!$E$31,O31+(InputDataB_ModelSpecAssumptions!$E$31-$I31)/(InputDataB_ModelSpecAssumptions!$E$32-InputDataA_GeneralAssumptions!$D$7)) | Q31: =IF(Submodel3s!M4>InputDataB_ModelSpecAssumptions!$E$32,InputDataB_ModelSpecAssumptions!$E$31,P31+(InputDataB_ModelSpecAssumptions!$E$31-$I31)/(InputDataB_ModelSpecAssumptions!$E$32-InputDataA_GeneralAssumptions!$D$7)) | ... BW31: =IF(Submodel3s!BS4>InputDataB_ModelSpecAssumptions!$E$32,InputDataB_ModelSpecAssumptions!$E$31,BV31+(InputDataB_ModelSpecAssumptions!$E$31-$I31)/(InputDataB_ModelSpecAssumptions!$E$32-InputDataA_GeneralAssumptions!$D$7))
B32: Reach target GNS/GDP by year --> | C32: (YYYY) | D32: 2030 | E32: =D32 | G32: Used in "scenario" simulation | H32: =H31 | I32: =IF(VLOOKUP(InputDataB_ModelSpecAssumptions!$D$30,DataSummary!$A$111:$B$112,2,FALSE())=1,I30,I31) | J32: =IF(VLOOKUP(InputDataB_ModelSpecAssumptions!$D$30,DataSummary!$A$111:$B$112,2,FALSE())=1,J30,J31) | K32: =IF(VLOOKUP(InputDataB_ModelSpecAssumptions!$D$30,DataSummary!$A$111:$B$112,2,FALSE())=1,K30,K31) | L32: =IF(VLOOKUP(InputDataB_ModelSpecAssumptions!$D$30,DataSummary!$A$111:$B$112,2,FALSE())=1,L30,L31) | M32: =IF(VLOOKUP(InputDataB_ModelSpecAssumptions!$D$30,DataSummary!$A$111:$B$112,2,FALSE())=1,M30,M31) | N32: =IF(VLOOKUP(InputDataB_ModelSpecAssumptions!$D$30,DataSummary!$A$111:$B$112,2,FALSE())=1,N30,N31) | O32: =IF(VLOOKUP(InputDataB_ModelSpecAssumptions!$D$30,DataSummary!$A$111:$B$112,2,FALSE())=1,O30,O31) | P32: =IF(VLOOKUP(InputDataB_ModelSpecAssumptions!$D$30,DataSummary!$A$111:$B$112,2,FALSE())=1,P30,P31) | ... BW32: =IF(VLOOKUP(InputDataB_ModelSpecAssumptions!$D$30,DataSummary!$A$111:$B$112,2,FALSE())=1,BW30,BW31)

Sheet GraphsB
A1: Model 1: Growth given Investment | E1: Back
A2: Input | G2: Output | M2: Diagnostic: Effectiveness of investment | R2: State Variable: K/Y ratio | W2: Poverty and Income Distribution | AB2: Headline GDP Growth | AG2: Real GDP PC Level | AL2: Shared Prosperity: Growth rate of incomes of bottom 40%
A17: Model 2: Investment given growth | E17: Back
A18: Input | G18: Output | M18: Diagnostic: Effectiveness of investment | R18: State Variable: K/Y ratio | W18: Poverty and Income Distribution | AB18: Real GDP PC Level (regardless of target) | AG18: Real GDP PC Growth Rate (regardless of target) | AL18: Real GDP Headline Growth Rate (regardless of target) | AQ18: Shared Prosperity: Growth Rate of income of bottom 40% (regardless of target)
A33: Model 3: Growth Given Savings | E33: Back
A34: Input | G34: Output | M34: Implied investment to GDP ratio | R34: Diagnostic: Effectiveness of investment | W34: State Variable: K/Y ratio | AB34: Poverty and Income Distribution | AG34: Headline GDP Growth | AL34: Real GDP PC Level | AQ34: Shared Prosperity: Growth Rate of incomes bottom 40%

Sheet data
B1: 1 | C1: 1 | D1: =C1+1 | E1: =D1+1 | F1: =E1+1 | G1: =F1+1 | H1: =G1+1 | I1: =H1+1 | J1: =I1+1 | K1: =J1+1 | ... TO1: =TN1+1 | TP1: =TN1+1 | TQ1: =TP1+1 | TR1: =TQ1+1 | TS1: =TR1+1 | TT1: =TS1+1 | TU1: =TT1+1 | TV1: =TU1+1 | TW1: =TV1+1 | TX1: =TW1+1 | ... YD1: =YC1+1
A2: Variable Name | B2: Country Name | C2: wb_code | D2: Depreciation Rate | F2: Depreciation Rate | H2: Depreciation Rate | J2: Source of Labsh | K2: Labor Share | L2: Labor Share | N2: Labor Share | P2: Labor Share | R2: Labor Share | V2: Labor Share | W2: Labor Share | Y2: Labor Share | AA2: Labor Share | AC2: Labor Share | AG2: Labor Share | AH2: Labor Share | AJ2: Labor Share | AL2: Labor Share | AN2: Labor Share | AQ2: =AQ22 | AR2: =AR22 | AS2: =AS22 | AT2: ky9 | AV2: =AV22 | AX2: =AX22 | BA2: Source | BB2: HC Growth | BC2: HC Growth | BD2: HC Growth | BE2: HC Growth | BF2: HC Growth | BI2: HC Growth | BJ2: HC Growth | BK2: HC Growth | BL2: HC Growth | BM2: HC Growth | BP2: HC Growth | BQ2: HC Growth | BR2: HC Growth | BS2: HC Growth | BT2: HC Growth | BV2: Years of Schooling | BW2: Years of Schooling | BX2: Years of Schooling | BY2: Years of Schooling | BZ2: Years of Schooling | CC2: Years of Schooling | CD2: Years of Schooling | CE2: Years of Schooling | CF2: Years of Schooling | CG2: Years of Schooling | CK2: UN Avg years | CO2: =CO22 | CP2: =CP22 | CQ2: =CQ22 | CR2: =CR22 | CS2: =CS22 | CT2: =CT22 | CV2: =CV22 | CW2: TFP Growth | CX2: TFP Growth | CY2: TFP Growth | CZ2: TFP Growth | DA2: TFP Growth | DC2: =DC22 | DD2: TFP Growth | DE2: TFP Growth | DF2: TFP Growth | DG2: TFP Growth | DH2: TFP Growth | DL2: Labor Market Participation | DP2: Participation rate, male | DT2: Participation rate, female | DW2: CAB/Y | DX2: CAB/Y | DY2: CAB/Y | DZ2: CAB/Y | EA2: CAB/Y | ED2: CAB/Y | EE2: CAB/Y | EF2: CAB/Y | EG2: CAB/Y | EH2: CAB/Y | EK2: Debt/Y | EO2: FDI/Y | EP2: FDI/Y | EQ2: FDI/Y | ER2: FDI/Y | ES2: FDI/Y | FD2: Total Population | FE2: =FE21 | FF2: =FF21 | FG2: =FG21 | FH2: =FH21 | FI2: =FI21 | FJ2: =FJ21 | FK2: =FK21 | FL2: =FL21 | ... HC2: =HC21 | HG2: Population Growth | IU2: Share of Male Pop | IV2: =IV21 | IW2: =IW21 | IX2: =IX21 | IY2: =IY21 | IZ2: =IZ21 | JA2: =JA21 | JB2: =JB21 | JC2: =JC21 | ... KE2: =KE21 | KH2: WATP 15-64 | KI2: =KI21 | KJ2: =KJ21 | KK2: =KK21 | KL2: =KL21 | KM2: =KM21 | KN2: =KN21 | KO2: =KO21 | KP2: =KP21 | ... LR2: =LR21 | LT2: WATP 15-59 | LU2: =LU5 | LV2: =LV5 | LW2: =LW5 | LX2: =LX5 | LY2: =LY5 | LZ2: =LZ5 | MA2: =MA5 | MB2: =MB5 | ... ND2: =ND5 | NG2: WATP 20-64 | NH2: =NH5 | NI2: =NI5 | NJ2: =NJ5 | NK2: =NK5 | NL2: =NL5 | NM2: =NM5 | NN2: =NN5 | NO2: =NO5 | ... OQ2: =OQ5 | OS2: Labor force participation rate, total (% of total population ages 15-64) (modeled ILO estimate) | PQ2: Growth Rate of Participation | PU2: headcountpoverty | PV2: Data from | PW2: Gini | PX2: Data from | PZ2: Gini | QA2: Data from | QD2: PH_190 | QE2: Data from | QH2: PH_320 | QI2: Data from | QL2: PH_550 | QM2: Data from | QP2: PH_NPL | QQ2: Data from | QU2: I/Y | QV2: I/Y | QW2: I/Y | QX2: I/Y | QY2: I/Y | RB2: I/Y | RC2: I/Y | RD2: I/Y | RE2: I/Y | RF2: I/Y | RJ2: GDP Growth | RK2: GDP Growth | RL2: GDP Growth | RM2: GDP Growth | RN2: GDP Growth | RR2: GDP Growth | RS2: GDP Growth | RT2: GDP Growth | RU2: GDP Growth | RV2: GDP Growth | SA2: GDP PC Growth | SB2: GDP PC Growth | SC2: GDP PC Growth | SD2: GDP PC Growth | SE2: GDP PC Growth | SJ2: GDP PC Growth | SK2: GDP PC Growth | SL2: GDP PC Growth | SM2: GDP PC Growth | SN2: GDP PC Growth | SQ2: GNI PC Level | ST2: GDP PC level | SW2: GDP PC level | TA2: S/Y | TB2: S/Y | TC2: S/Y | TD2: S/Y | TE2: S/Y | TJ2: S/Y | TK2: S/Y | TL2: S/Y | TM2: S/Y | TN2: S/Y
B3: =InputDataA_GeneralAssumptions!B3 | C3: =VLOOKUP(B3,$B$23:$CS$241,2,FALSE()) | D3: =IF(ISNUMBER(VLOOKUP($C$3,$C$23:$UW$241,D1,FALSE()))=TRUE(),VLOOKUP($C$3,$C$23:$UW$241,D1,FALSE()),".") | E3: =VLOOKUP($C$3,$C$23:$UW$241,E1,FALSE()) | F3: =IF(ISNUMBER(VLOOKUP($C$3,$C$23:$UW$241,F1,FALSE()))=TRUE(),VLOOKUP($C$3,$C$23:$UW$241,F1,FALSE()),".") | G3: =VLOOKUP($C$3,$C$23:$UW$241,G1,FALSE()) | H3: =IF(ISNUMBER(VLOOKUP($C$3,$C$23:$UW$241,H1,FALSE()))=TRUE(),VLOOKUP($C$3,$C$23:$UW$241,H1,FALSE()),".") | I3: =VLOOKUP($C$3,$C$23:$UW$241,I1,FALSE()) | J3: =VLOOKUP($C$3,$C$23:$UW$241,J1,FALSE()) | K3: =IF(ISNUMBER(VLOOKUP($C$3,$C$23:$UW$241,K1,FALSE()))=TRUE(),VLOOKUP($C$3,$C$23:$UW$241,K1,FALSE()),".") | L3: =IF(ISNUMBER(VLOOKUP($C$3,$C$23:$UW$241,L1,FALSE()))=TRUE(),VLOOKUP($C$3,$C$23:$UW$241,L1,FALSE()),".") | M3: =VLOOKUP($C$3,$C$23:$UW$241,M1,FALSE()) | N3: =IF(ISNUMBER(VLOOKUP($C$3,$C$23:$UW$241,N1,FALSE()))=TRUE(),VLOOKUP($C$3,$C$23:$UW$241,N1,FALSE()),".") | O3: =VLOOKUP($C$3,$C$23:$UW$241,O1,FALSE()) | P3: =IF(ISNUMBER(VLOOKUP($C$3,$C$23:$UW$241,P1,FALSE()))=TRUE(),VLOOKUP($C$3,$C$23:$UW$241,P1,FALSE()),".") | Q3: =VLOOKUP($C$3,$C$23:$UW$241,Q1,FALSE()) | R3: =IF(ISNUMBER(VLOOKUP($C$3,$C$23:$UW$241,R1,FALSE()))=TRUE(),VLOOKUP($C$3,$C$23:$UW$241,R1,FALSE()),".") | S3: =VLOOKUP($C$3,$C$23:$UW$241,S1,FALSE()) | U3: =VLOOKUP($C$3,$C$23:$UW$241,U1,FALSE()) | V3: =VLOOKUP($C$3,$C$23:$UW$241,V1,FALSE()) | W3: =VLOOKUP($C$3,$C$23:$UW$241,W1,FALSE()) | X3: =VLOOKUP($C$3,$C$23:$UW$241,X1,FALSE()) | Y3: =VLOOKUP($C$3,$C$23:$UW$241,Y1,FALSE()) | Z3: =VLOOKUP($C$3,$C$23:$UW$241,Z1,FALSE()) | AA3: =VLOOKUP($C$3,$C$23:$UW$241,AA1,FALSE()) | AB3: =VLOOKUP($C$3,$C$23:$UW$241,AB1,FALSE()) | ... AF3: =VLOOKUP($C$3,$C$23:$UW$241,AF1,FALSE()) | AG3: =IF(ISNUMBER(VLOOKUP($C$3,$C$23:$UW$241,AG1,FALSE()))=TRUE(),VLOOKUP($C$3,$C$23:$UW$241,AG1,FALSE()),".") | AH3: =IF(ISNUMBER(VLOOKUP($C$3,$C$23:$UW$241,AH1,FALSE()))=TRUE(),VLOOKUP($C$3,$C$23:$UW$241,AH1,FALSE()),".") | AI3: =VLOOKUP($C$3,$C$23:$UW$241,AI1,FALSE()) | AJ3: =IF(ISNUMBER(VLOOKUP($C$3,$C$23:$UW$241,AJ1,FALSE()))=TRUE(),VLOOKUP($C$3,$C$23:$UW$241,AJ1,FALSE()),".") | AK3: =VLOOKUP($C$3,$C$23:$UW$241,AK1,FALSE()) | AL3: =IF(ISNUMBER(VLOOKUP($C$3,$C$23:$UW$241,AL1,FALSE()))=TRUE(),VLOOKUP($C$3,$C$23:$UW$241,AL1,FALSE()),".") | AM3: =VLOOKUP($C$3,$C$23:$UW$241,AM1,FALSE()) | AN3: =IF(ISNUMBER(VLOOKUP($C$3,$C$23:$UW$241,AN1,FALSE()))=TRUE(),VLOOKUP($C$3,$C$23:$UW$241,AN1,FALSE()),".") | AO3: =VLOOKUP($C$3,$C$23:$UW$241,AO1,FALSE()) | AP3: =VLOOKUP($C$3,$C$23:$UW$241,AP1,FALSE()) | AQ3: =VLOOKUP($C$3,$C$23:$UW$241,AQ1,FALSE()) | AR3: =IF(ISNUMBER(VLOOKUP($C$3,$C$23:$UW$241,AR1,FALSE()))=TRUE(),VLOOKUP($C$3,$C$23:$UW$241,AR1,FALSE()),".") | AS3: =VLOOKUP($C$3,$C$23:$UW$241,AS1,FALSE()) | AT3: =VLOOKUP($C$3,$C$23:$UW$241,AT1,FALSE()) | AU3: =VLOOKUP($C$3,$C$23:$UW$241,AU1,FALSE()) | AV3: =VLOOKUP($C$3,$C$23:$UW$241,AV1,FALSE()) | AW3: =VLOOKUP($C$3,$C$23:$UW$241,AW1,FALSE()) | AX3: =VLOOKUP($C$3,$C$23:$UW$241,AX1,FALSE()) | AZ3: =VLOOKUP($C$3,$C$23:$UW$241,AZ1,FALSE()) | BB3: =IF(ISNUMBER(VLOOKUP($C$3,$C$23:$UW$241,BB1,FALSE()))=TRUE(),VLOOKUP($C$3,$C$23:$UW$241,BB1,FALSE()),".") | BC3: =IF(ISNUMBER(VLOOKUP($C$3,$C$23:$UW$241,BC1,FALSE()))=TRUE(),VLOOKUP($C$3,$C$23:$UW$241,BC1,FALSE()),".") | BD3: =IF(ISNUMBER(VLOOKUP($C$3,$C$23:$UW$241,BD1,FALSE()))=TRUE(),VLOOKUP($C$3,$C$23:$UW$241,BD1,FALSE()),".") | BE3: =IF(ISNUMBER(VLOOKUP($C$3,$C$23:$UW$241,BE1,FALSE()))=TRUE(),VLOOKUP($C$3,$C$23:$UW$241,BE1,FALSE()),".") | BF3: =IF(ISNUMBER(VLOOKUP($C$3,$C$23:$UW$241,BF1,FALSE()))=TRUE(),VLOOKUP($C$3,$C$23:$UW$241,BF1,FALSE()),".") | BH3: =IF(ISNUMBER(VLOOKUP($C$3,$C$23:$UW$241,BH1,FALSE()))=TRUE(),VLOOKUP($C$3,$C$23:$UW$241,BH1,FALSE()),".") | BI3: =IF(ISNUMBER(VLOOKUP($C$3,$C$23:$UW$241,BI1,FALSE()))=TRUE(),VLOOKUP($C$3,$C$23:$UW$241,BI1,FALSE()),".") | BJ3: =IF(ISNUMBER(VLOOKUP($C$3,$C$23:$UW$241,BJ1,FALSE()))=TRUE(),VLOOKUP($C$3,$C$23:$UW$241,BJ1,FALSE()),".") | BK3: =IF(ISNUMBER(VLOOKUP($C$3,$C$23:$UW$241,BK1,FALSE()))=TRUE(),VLOOKUP($C$3,$C$23:$UW$241,BK1,FALSE()),".") | BL3: =IF(ISNUMBER(VLOOKUP($C$3,$C$23:$UW$241,BL1,FALSE()))=TRUE(),VLOOKUP($C$3,$C$23:$UW$241,BL1,FALSE()),".") | BM3: =IF(ISNUMBER(VLOOKUP($C$3,$C$23:$UW$241,BM1,FALSE()))=TRUE(),VLOOKUP($C$3,$C$23:$UW$241,BM1,FALSE()),".") | BO3: =IF(ISNUMBER(VLOOKUP($C$3,$C$23:$UW$241,BO1,FALSE()))=TRUE(),VLOOKUP($C$3,$C$23:$UW$241,BO1,FALSE()),".") | BP3: =IF(ISNUMBER(VLOOKUP($C$3,$C$23:$UW$241,BP1,FALSE()))=TRUE(),VLOOKUP($C$3,$C$23:$UW$241,BP1,FALSE()),".") | BQ3: =IF(ISNUMBER(VLOOKUP($C$3,$C$23:$UW$241,BQ1,FALSE()))=TRUE(),VLOOKUP($C$3,$C$23:$UW$241,BQ1,FALSE()),".") | BR3: =IF(ISNUMBER(VLOOKUP($C$3,$C$23:$UW$241,BR1,FALSE()))=TRUE(),VLOOKUP($C$3,$C$23:$UW$241,BR1,FALSE()),".") | BS3: =IF(ISNUMBER(VLOOKUP($C$3,$C$23:$UW$241,BS1,FALSE()))=TRUE(),VLOOKUP($C$3,$C$23:$UW$241,BS1,FALSE()),".") | BT3: =IF(ISNUMBER(VLOOKUP($C$3,$C$23:$UW$241,BT1,FALSE()))=TRUE(),VLOOKUP($C$3,$C$23:$UW$241,BT1,FALSE()),".") | BV3: =IF(ISNUMBER(VLOOKUP($C$3,$C$23:$UW$241,BV1,FALSE()))=TRUE(),VLOOKUP($C$3,$C$23:$UW$241,BV1,FALSE()),".") | BW3: =IF(ISNUMBER(VLOOKUP($C$3,$C$23:$UW$241,BW1,FALSE()))=TRUE(),VLOOKUP($C$3,$C$23:$UW$241,BW1,FALSE()),".") | BX3: =IF(ISNUMBER(VLOOKUP($C$3,$C$23:$UW$241,BX1,FALSE()))=TRUE(),VLOOKUP($C$3,$C$23:$UW$241,BX1,FALSE()),".") | BY3: =IF(ISNUMBER(VLOOKUP($C$3,$C$23:$UW$241,BY1,FALSE()))=TRUE(),VLOOKUP($C$3,$C$23:$UW$241,BY1,FALSE()),".") | BZ3: =IF(ISNUMBER(VLOOKUP($C$3,$C$23:$UW$241,BZ1,FALSE()))=TRUE(),VLOOKUP($C$3,$C$23:$UW$241,BZ1,FALSE()),".") | CA3: =VLOOKUP($C$3,$C$23:$UW$241,CA1,FALSE()) | CC3: =IF(ISNUMBER(VLOOKUP($C$3,$C$23:$UW$241,CC1,FALSE()))=TRUE(),VLOOKUP($C$3,$C$23:$UW$241,CC1,FALSE()),".") | CD3: =IF(ISNUMBER(VLOOKUP($C$3,$C$23:$UW$241,CD1,FALSE()))=TRUE(),VLOOKUP($C$3,$C$23:$UW$241,CD1,FALSE()),".") | CE3: =IF(ISNUMBER(VLOOKUP($C$3,$C$23:$UW$241,CE1,FALSE()))=TRUE(),VLOOKUP($C$3,$C$23:$UW$241,CE1,FALSE()),".") | CF3: =IF(ISNUMBER(VLOOKUP($C$3,$C$23:$UW$241,CF1,FALSE()))=TRUE(),VLOOKUP($C$3,$C$23:$UW$241,CF1,FALSE()),".") | CG3: =IF(ISNUMBER(VLOOKUP($C$3,$C$23:$UW$241,CG1,FALSE()))=TRUE(),VLOOKUP($C$3,$C$23:$UW$241,CG1,FALSE()),".") | CH3: =VLOOKUP($C$3,$C$23:$UW$241,CH1,FALSE()) | CK3: =IF(ISNUMBER(VLOOKUP($C$3,$C$23:$UW$241,CK1,FALSE()))=TRUE(),VLOOKUP($C$3,$C$23:$UW$241,CK1,FALSE()),".") | CL3: =VLOOKUP($C$3,$C$23:$UW$241,CL1,FALSE()) | CO3: =VLOOKUP($C$3,$C$23:$UW$241,CO1,FALSE()) | CP3: =IF(ISNUMBER(VLOOKUP($C$3,$C$23:$UW$241,CP1,FALSE()))=TRUE(),VLOOKUP($C$3,$C$23:$UW$241,CP1,FALSE()),".") | CQ3: =IF(ISNUMBER(VLOOKUP($C$3,$C$23:$UW$241,CQ1,FALSE()))=TRUE(),VLOOKUP($C$3,$C$23:$UW$241,CQ1,FALSE()),".") | CR3: =IF(ISNUMBER(VLOOKUP($C$3,$C$23:$UW$241,CR1,FALSE()))=TRUE(),VLOOKUP($C$3,$C$23:$UW$241,CR1,FALSE()),".") | CS3: =IF(ISNUMBER(VLOOKUP($C$3,$C$23:$UW$241,CS1,FALSE()))=TRUE(),VLOOKUP($C$3,$C$23:$UW$241,CS1,FALSE()),".") | CT3: =IF(ISNUMBER(VLOOKUP($C$3,$C$23:$UW$241,CT1,FALSE()))=TRUE(),VLOOKUP($C$3,$C$23:$UW$241,CT1,FALSE()),".") | CW3: =IF(ISNUMBER(VLOOKUP($C$3,$C$23:$UW$241,CW1,FALSE()))=TRUE(),VLOOKUP($C$3,$C$23:$UW$241,CW1,FALSE()),".") | CX3: =IF(ISNUMBER(VLOOKUP($C$3,$C$23:$UW$241,CX1,FALSE()))=TRUE(),VLOOKUP($C$3,$C$23:$UW$241,CX1,FALSE()),".") | CY3: =IF(ISNUMBER(VLOOKUP($C$3,$C$23:$UW$241,CY1,FALSE()))=TRUE(),VLOOKUP($C$3,$C$23:$UW$241,CY1,FALSE()),".") | CZ3: =IF(ISNUMBER(VLOOKUP($C$3,$C$23:$UW$241,CZ1,FALSE()))=TRUE(),VLOOKUP($C$3,$C$23:$UW$241,CZ1,FALSE()),".") | DA3: =IF(ISNUMBER(VLOOKUP($C$3,$C$23:$UW$241,DA1,FALSE()))=TRUE(),VLOOKUP($C$3,$C$23:$UW$241,DA1,FALSE()),".") | DD3: =IF(ISNUMBER(VLOOKUP($C$3,$C$23:$UW$241,DD1,FALSE()))=TRUE(),VLOOKUP($C$3,$C$23:$UW$241,DD1,FALSE()),".") | DE3: =IF(ISNUMBER(VLOOKUP($C$3,$C$23:$UW$241,DE1,FALSE()))=TRUE(),VLOOKUP($C$3,$C$23:$UW$241,DE1,FALSE()),".") | DF3: =IF(ISNUMBER(VLOOKUP($C$3,$C$23:$UW$241,DF1,FALSE()))=TRUE(),VLOOKUP($C$3,$C$23:$UW$241,DF1,FALSE()),".") | DG3: =IF(ISNUMBER(VLOOKUP($C$3,$C$23:$UW$241,DG1,FALSE()))=TRUE(),VLOOKUP($C$3,$C$23:$UW$241,DG1,FALSE()),".") | DH3: =IF(ISNUMBER(VLOOKUP($C$3,$C$23:$UW$241,DH1,FALSE()))=TRUE(),VLOOKUP($C$3,$C$23:$UW$241,DH1,FALSE()),".") | DL3: =IF(ISNUMBER(VLOOKUP($C$3,$C$23:$UW$241,DL1,FALSE()))=TRUE(),VLOOKUP($C$3,$C$23:$UW$241,DL1,FALSE()),".") | DM3: =VLOOKUP($C$3,$C$23:$UW$241,DM1,FALSE()) | DP3: =IF(ISNUMBER(VLOOKUP($C$3,$C$23:$UW$241,DP1,FALSE()))=TRUE(),VLOOKUP($C$3,$C$23:$UW$241,DP1,FALSE()),".") | DQ3: =VLOOKUP($C$3,$C$23:$UW$241,DQ1,FALSE()) | DT3: =IF(ISNUMBER(VLOOKUP($C$3,$C$23:$UW$241,DT1,FALSE()))=TRUE(),VLOOKUP($C$3,$C$23:$UW$241,DT1,FALSE()),".") | DU3: =VLOOKUP($C$3,$C$23:$UW$241,DU1,FALSE()) | DW3: =IF(ISNUMBER(VLOOKUP($C$3,$C$23:$UW$241,DW1,FALSE()))=TRUE(),VLOOKUP($C$3,$C$23:$UW$241,DW1,FALSE()),".") | DX3: =IF(ISNUMBER(VLOOKUP($C$3,$C$23:$UW$241,DX1,FALSE()))=TRUE(),VLOOKUP($C$3,$C$23:$UW$241,DX1,FALSE()),".") | DY3: =IF(ISNUMBER(VLOOKUP($C$3,$C$23:$UW$241,DY1,FALSE()))=TRUE(),VLOOKUP($C$3,$C$23:$UW$241,DY1,FALSE()),".") | DZ3: =IF(ISNUMBER(VLOOKUP($C$3,$C$23:$UW$241,DZ1,FALSE()))=TRUE(),VLOOKUP($C$3,$C$23:$UW$241,DZ1,FALSE()),".") | EA3: =IF(ISNUMBER(VLOOKUP($C$3,$C$23:$UW$241,EA1,FALSE()))=TRUE(),VLOOKUP($C$3,$C$23:$UW$241,EA1,FALSE()),".") | EB3: =VLOOKUP($C$3,$C$23:$UW$241,EB1,FALSE()) | ED3: =IF(ISNUMBER(VLOOKUP($C$3,$C$23:$UW$241,ED1,FALSE()))=TRUE(),VLOOKUP($C$3,$C$23:$UW$241,ED1,FALSE()),".") | EE3: =IF(ISNUMBER(VLOOKUP($C$3,$C$23:$UW$241,EE1,FALSE()))=TRUE(),VLOOKUP($C$3,$C$23:$UW$241,EE1,FALSE()),".") | EF3: =IF(ISNUMBER(VLOOKUP($C$3,$C$23:$UW$241,EF1,FALSE()))=TRUE(),VLOOKUP($C$3,$C$23:$UW$241,EF1,FALSE()),".") | EG3: =IF(ISNUMBER(VLOOKUP($C$3,$C$23:$UW$241,EG1,FALSE()))=TRUE(),VLOOKUP($C$3,$C$23:$UW$241,EG1,FALSE()),".") | EH3: =IF(ISNUMBER(VLOOKUP($C$3,$C$23:$UW$241,EH1,FALSE()))=TRUE(),VLOOKUP($C$3,$C$23:$UW$241,EH1,FALSE()),".") | EI3: =VLOOKUP($C$3,$C$23:$UW$241,EI1,FALSE()) | EK3: =IF(ISNUMBER(VLOOKUP($C$3,$C$23:$UW$241,EK1,FALSE()))=TRUE(),VLOOKUP($C$3,$C$23:$UW$241,EK1,FALSE()),".") | EL3: =VLOOKUP($C$3,$C$23:$UW$241,EL1,FALSE()) | EO3: =IF(ISNUMBER(VLOOKUP($C$3,$C$23:$UW$241,EO1,FALSE()))=TRUE(),VLOOKUP($C$3,$C$23:$UW$241,EO1,FALSE()),".") | EP3: =IF(ISNUMBER(VLOOKUP($C$3,$C$23:$UW$241,EP1,FALSE()))=TRUE(),VLOOKUP($C$3,$C$23:$UW$241,EP1,FALSE()),".") | EQ3: =IF(ISNUMBER(VLOOKUP($C$3,$C$23:$UW$241,EQ1,FALSE()))=TRUE(),VLOOKUP($C$3,$C$23:$UW$241,EQ1,FALSE()),".") | ER3: =IF(ISNUMBER(VLOOKUP($C$3,$C$23:$UW$241,ER1,FALSE()))=TRUE(),VLOOKUP($C$3,$C$23:$UW$241,ER1,FALSE()),".") | ES3: =IF(ISNUMBER(VLOOKUP($C$3,$C$23:$UW$241,ES1,FALSE()))=TRUE(),VLOOKUP($C$3,$C$23:$UW$241,ES1,FALSE()),".") | ET3: =VLOOKUP($C$3,$C$23:$UW$241,ET1,FALSE()) | FE3: =IF(ISNUMBER(VLOOKUP($C$3,$C$23:$UW$241,FE1,FALSE()))=TRUE(),VLOOKUP($C$3,$C$23:$UW$241,FE1,FALSE()),".") | FF3: =IF(ISNUMBER(VLOOKUP($C$3,$C$23:$UW$241,FF1,FALSE()))=TRUE(),VLOOKUP($C$3,$C$23:$UW$241,FF1,FALSE()),".") | FG3: =IF(ISNUMBER(VLOOKUP($C$3,$C$23:$UW$241,FG1,FALSE()))=TRUE(),VLOOKUP($C$3,$C$23:$UW$241,FG1,FALSE()),".") | FH3: =IF(ISNUMBER(VLOOKUP($C$3,$C$23:$UW$241,FH1,FALSE()))=TRUE(),VLOOKUP($C$3,$C$23:$UW$241,FH1,FALSE()),".") | FI3: =IF(ISNUMBER(VLOOKUP($C$3,$C$23:$UW$241,FI1,FALSE()))=TRUE(),VLOOKUP($C$3,$C$23:$UW$241,FI1,FALSE()),".") | FJ3: =IF(ISNUMBER(VLOOKUP($C$3,$C$23:$UW$241,FJ1,FALSE()))=TRUE(),VLOOKUP($C$3,$C$23:$UW$241,FJ1,FALSE()),".") | FK3: =IF(ISNUMBER(VLOOKUP($C$3,$C$23:$UW$241,FK1,FALSE()))=TRUE(),VLOOKUP($C$3,$C$23:$UW$241,FK1,FALSE()),".") | FL3: =IF(ISNUMBER(VLOOKUP($C$3,$C$23:$UW$241,FL1,FALSE()))=TRUE(),VLOOKUP($C$3,$C$23:$UW$241,FL1,FALSE()),".") | ... HC3: =IF(ISNUMBER(VLOOKUP($C$3,$C$23:$UW$241,HC1,FALSE()))=TRUE(),VLOOKUP($C$3,$C$23:$UW$241,HC1,FALSE()),".") | HG3: =IF(ISNUMBER(VLOOKUP($C$3,$C$23:$UW$241,HG1,FALSE()))=TRUE(),VLOOKUP($C$3,$C$23:$UW$241,HG1,FALSE()),".") | HH3: =IF(ISNUMBER(VLOOKUP($C$3,$C$23:$UW$241,HH1,FALSE()))=TRUE(),VLOOKUP($C$3,$C$23:$UW$241,HH1,FALSE()),".") | HI3: =IF(ISNUMBER(VLOOKUP($C$3,$C$23:$UW$241,HI1,FALSE()))=TRUE(),VLOOKUP($C$3,$C$23:$UW$241,HI1,FALSE()),".") | HJ3: =IF(ISNUMBER(VLOOKUP($C$3,$C$23:$UW$241,HJ1,FALSE()))=TRUE(),VLOOKUP($C$3,$C$23:$UW$241,HJ1,FALSE()),".") | HK3: =IF(ISNUMBER(VLOOKUP($C$3,$C$23:$UW$241,HK1,FALSE()))=TRUE(),VLOOKUP($C$3,$C$23:$UW$241,HK1,FALSE()),".") | HL3: =IF(ISNUMBER(VLOOKUP($C$3,$C$23:$UW$241,HL1,FALSE()))=TRUE(),VLOOKUP($C$3,$C$23:$UW$241,HL1,FALSE()),".") | HM3: =IF(ISNUMBER(VLOOKUP($C$3,$C$23:$UW$241,HM1,FALSE()))=TRUE(),VLOOKUP($C$3,$C$23:$UW$241,HM1,FALSE()),".") | HN3: =IF(ISNUMBER(VLOOKUP($C$3,$C$23:$UW$241,HN1,FALSE()))=TRUE(),VLOOKUP($C$3,$C$23:$UW$241,HN1,FALSE()),".") | ... IO3: =IF(ISNUMBER(VLOOKUP($C$3,$C$23:$UW$241,IO1,FALSE()))=TRUE(),VLOOKUP($C$3,$C$23:$UW$241,IO1,FALSE()),".") | IP3: =VLOOKUP($C$3,$C$23:$UW$241,IP1,FALSE()) | IU3: =VLOOKUP($C$3,$C$23:$UW$241,IU1,FALSE()) | IV3: =IF(ISNUMBER(VLOOKUP($C$3,$C$23:$UW$241,IV1,FALSE()))=TRUE(),VLOOKUP($C$3,$C$23:$UW$241,IV1,FALSE()),".") | IW3: =IF(ISNUMBER(VLOOKUP($C$3,$C$23:$UW$241,IW1,FALSE()))=TRUE(),VLOOKUP($C$3,$C$23:$UW$241,IW1,FALSE()),".") | IX3: =IF(ISNUMBER(VLOOKUP($C$3,$C$23:$UW$241,IX1,FALSE()))=TRUE(),VLOOKUP($C$3,$C$23:$UW$241,IX1,FALSE()),".") | IY3: =IF(ISNUMBER(VLOOKUP($C$3,$C$23:$UW$241,IY1,FALSE()))=TRUE(),VLOOKUP($C$3,$C$23:$UW$241,IY1,FALSE()),".") | IZ3: =IF(ISNUMBER(VLOOKUP($C$3,$C$23:$UW$241,IZ1,FALSE()))=TRUE(),VLOOKUP($C$3,$C$23:$UW$241,IZ1,FALSE()),".") | JA3: =IF(ISNUMBER(VLOOKUP($C$3,$C$23:$UW$241,JA1,FALSE()))=TRUE(),VLOOKUP($C$3,$C$23:$UW$241,JA1,FALSE()),".") | JB3: =IF(ISNUMBER(VLOOKUP($C$3,$C$23:$UW$241,JB1,FALSE()))=TRUE(),VLOOKUP($C$3,$C$23:$UW$241,JB1,FALSE()),".") | JC3: =IF(ISNUMBER(VLOOKUP($C$3,$C$23:$UW$241,JC1,FALSE()))=TRUE(),VLOOKUP($C$3,$C$23:$UW$241,JC1,FALSE()),".") | ... KE3: =IF(ISNUMBER(VLOOKUP($C$3,$C$23:$UW$241,KE1,FALSE()))=TRUE(),VLOOKUP($C$3,$C$23:$UW$241,KE1,FALSE()),".") | KH3: =VLOOKUP($C$3,$C$23:$UW$241,KH1,FALSE()) | KI3: =IF(ISNUMBER(VLOOKUP($C$3,$C$23:$UW$241,KI1,FALSE()))=TRUE(),VLOOKUP($C$3,$C$23:$UW$241,KI1,FALSE()),".") | KJ3: =IF(ISNUMBER(VLOOKUP($C$3,$C$23:$UW$241,KJ1,FALSE()))=TRUE(),VLOOKUP($C$3,$C$23:$UW$241,KJ1,FALSE()),".") | KK3: =IF(ISNUMBER(VLOOKUP($C$3,$C$23:$UW$241,KK1,FALSE()))=TRUE(),VLOOKUP($C$3,$C$23:$UW$241,KK1,FALSE()),".") | KL3: =IF(ISNUMBER(VLOOKUP($C$3,$C$23:$UW$241,KL1,FALSE()))=TRUE(),VLOOKUP($C$3,$C$23:$UW$241,KL1,FALSE()),".") | KM3: =IF(ISNUMBER(VLOOKUP($C$3,$C$23:$UW$241,KM1,FALSE()))=TRUE(),VLOOKUP($C$3,$C$23:$UW$241,KM1,FALSE()),".") | KN3: =IF(ISNUMBER(VLOOKUP($C$3,$C$23:$UW$241,KN1,FALSE()))=TRUE(),VLOOKUP($C$3,$C$23:$UW$241,KN1,FALSE()),".") | KO3: =IF(ISNUMBER(VLOOKUP($C$3,$C$23:$UW$241,KO1,FALSE()))=TRUE(),VLOOKUP($C$3,$C$23:$UW$241,KO1,FALSE()),".") | KP3: =IF(ISNUMBER(VLOOKUP($C$3,$C$23:$UW$241,KP1,FALSE()))=TRUE(),VLOOKUP($C$3,$C$23:$UW$241,KP1,FALSE()),".") | ... LR3: =IF(ISNUMBER(VLOOKUP($C$3,$C$23:$UW$241,LR1,FALSE()))=TRUE(),VLOOKUP($C$3,$C$23:$UW$241,LR1,FALSE()),".") | LT3: =VLOOKUP($C$3,$C$23:$UW$241,LT1,FALSE()) | LU3: =IF(ISNUMBER(VLOOKUP($C$3,$C$23:$UW$241,LU1,FALSE()))=TRUE(),VLOOKUP($C$3,$C$23:$UW$241,LU1,FALSE()),".") | LV3: =IF(ISNUMBER(VLOOKUP($C$3,$C$23:$UW$241,LV1,FALSE()))=TRUE(),VLOOKUP($C$3,$C$23:$UW$241,LV1,FALSE()),".") | LW3: =IF(ISNUMBER(VLOOKUP($C$3,$C$23:$UW$241,LW1,FALSE()))=TRUE(),VLOOKUP($C$3,$C$23:$UW$241,LW1,FALSE()),".") | LX3: =IF(ISNUMBER(VLOOKUP($C$3,$C$23:$UW$241,LX1,FALSE()))=TRUE(),VLOOKUP($C$3,$C$23:$UW$241,LX1,FALSE()),".") | LY3: =IF(ISNUMBER(VLOOKUP($C$3,$C$23:$UW$241,LY1,FALSE()))=TRUE(),VLOOKUP($C$3,$C$23:$UW$241,LY1,FALSE()),".") | LZ3: =IF(ISNUMBER(VLOOKUP($C$3,$C$23:$UW$241,LZ1,FALSE()))=TRUE(),VLOOKUP($C$3,$C$23:$UW$241,LZ1,FALSE()),".") | MA3: =IF(ISNUMBER(VLOOKUP($C$3,$C$23:$UW$241,MA1,FALSE()))=TRUE(),VLOOKUP($C$3,$C$23:$UW$241,MA1,FALSE()),".") | MB3: =IF(ISNUMBER(VLOOKUP($C$3,$C$23:$UW$241,MB1,FALSE()))=TRUE(),VLOOKUP($C$3,$C$23:$UW$241,MB1,FALSE()),".") | ... ND3: =IF(ISNUMBER(VLOOKUP($C$3,$C$23:$UW$241,ND1,FALSE()))=TRUE(),VLOOKUP($C$3,$C$23:$UW$241,ND1,FALSE()),".") | NG3: =VLOOKUP($C$3,$C$23:$UW$241,NG1,FALSE()) | NH3: =IF(ISNUMBER(VLOOKUP($C$3,$C$23:$UW$241,NH1,FALSE()))=TRUE(),VLOOKUP($C$3,$C$23:$UW$241,NH1,FALSE()),".") | NI3: =IF(ISNUMBER(VLOOKUP($C$3,$C$23:$UW$241,NI1,FALSE()))=TRUE(),VLOOKUP($C$3,$C$23:$UW$241,NI1,FALSE()),".") | NJ3: =IF(ISNUMBER(VLOOKUP($C$3,$C$23:$UW$241,NJ1,FALSE()))=TRUE(),VLOOKUP($C$3,$C$23:$UW$241,NJ1,FALSE()),".") | NK3: =IF(ISNUMBER(VLOOKUP($C$3,$C$23:$UW$241,NK1,FALSE()))=TRUE(),VLOOKUP($C$3,$C$23:$UW$241,NK1,FALSE()),".") | NL3: =IF(ISNUMBER(VLOOKUP($C$3,$C$23:$UW$241,NL1,FALSE()))=TRUE(),VLOOKUP($C$3,$C$23:$UW$241,NL1,FALSE()),".") | NM3: =IF(ISNUMBER(VLOOKUP($C$3,$C$23:$UW$241,NM1,FALSE()))=TRUE(),VLOOKUP($C$3,$C$23:$UW$241,NM1,FALSE()),".") | NN3: =IF(ISNUMBER(VLOOKUP($C$3,$C$23:$UW$241,NN1,FALSE()))=TRUE(),VLOOKUP($C$3,$C$23:$UW$241,NN1,FALSE()),".") | NO3: =IF(ISNUMBER(VLOOKUP($C$3,$C$23:$UW$241,NO1,FALSE()))=TRUE(),VLOOKUP($C$3,$C$23:$UW$241,NO1,FALSE()),".") | ... PM3: =IF(ISNUMBER(VLOOKUP($C$3,$C$23:$UW$241,PM1,FALSE()))=TRUE(),VLOOKUP($C$3,$C$23:$UW$241,PM1,FALSE()),".") | PQ3: =IF(ISNUMBER(VLOOKUP($C$3,$C$23:$UW$241,PQ1,FALSE()))=TRUE(),VLOOKUP($C$3,$C$23:$UW$241,PQ1,FALSE()),".") | PU3: =IF(ISNUMBER(VLOOKUP($C$3,$C$23:$UW$241,PU1,FALSE()))=TRUE(),VLOOKUP($C$3,$C$23:$UW$241,PU1,FALSE()),".") | PV3: =IF(ISNUMBER(VLOOKUP($C$3,$C$23:$UW$241,PV1,FALSE()))=TRUE(),VLOOKUP($C$3,$C$23:$UW$241,PV1,FALSE()),".") | PW3: =IF(ISNUMBER(VLOOKUP($C$3,$C$23:$UW$241,PW1,FALSE()))=TRUE(),VLOOKUP($C$3,$C$23:$UW$241,PW1,FALSE()),".") | PX3: =IF(ISNUMBER(VLOOKUP($C$3,$C$23:$UW$241,PX1,FALSE()))=TRUE(),VLOOKUP($C$3,$C$23:$UW$241,PX1,FALSE()),".") | PZ3: =IF(ISNUMBER(VLOOKUP($C$3,$C$23:$UW$241,PZ1,FALSE()))=TRUE(),VLOOKUP($C$3,$C$23:$UW$241,PZ1,FALSE()),".") | QA3: =IF(ISNUMBER(VLOOKUP($C$3,$C$23:$UW$241,QA1,FALSE()))=TRUE(),VLOOKUP($C$3,$C$23:$UW$241,QA1,FALSE()),".") | QB3: =VLOOKUP($C$3,$C$23:$UW$241,QB1,FALSE()) | QD3: =IF(ISNUMBER(VLOOKUP($C$3,$C$23:$UW$241,QD1,FALSE()))=TRUE(),VLOOKUP($C$3,$C$23:$UW$241,QD1,FALSE()),".") | QE3: =IF(ISNUMBER(VLOOKUP($C$3,$C$23:$UW$241,QE1,FALSE()))=TRUE(),VLOOKUP($C$3,$C$23:$UW$241,QE1,FALSE()),".") | QF3: =VLOOKUP($C$3,$C$23:$UW$241,QF1,FALSE()) | QH3: =IF(ISNUMBER(VLOOKUP($C$3,$C$23:$UW$241,QH1,FALSE()))=TRUE(),VLOOKUP($C$3,$C$23:$UW$241,QH1,FALSE()),".") | QI3: =IF(ISNUMBER(VLOOKUP($C$3,$C$23:$UW$241,QI1,FALSE()))=TRUE(),VLOOKUP($C$3,$C$23:$UW$241,QI1,FALSE()),".") | QJ3: =VLOOKUP($C$3,$C$23:$UW$241,QJ1,FALSE()) | QL3: =IF(ISNUMBER(VLOOKUP($C$3,$C$23:$UW$241,QL1,FALSE()))=TRUE(),VLOOKUP($C$3,$C$23:$UW$241,QL1,FALSE()),".") | QM3: =VLOOKUP($C$3,$C$23:$UW$241,QM1,FALSE()) | QN3: =VLOOKUP($C$3,$C$23:$UW$241,QN1,FALSE()) | QP3: =IF(ISNUMBER(VLOOKUP($C$3,$C$23:$UW$241,QP1,FALSE()))=TRUE(),VLOOKUP($C$3,$C$23:$UW$241,QP1,FALSE()),".") | QQ3: =IF(ISNUMBER(VLOOKUP($C$3,$C$23:$UW$241,QQ1,FALSE()))=TRUE(),VLOOKUP($C$3,$C$23:$UW$241,QQ1,FALSE()),".") | QR3: =VLOOKUP($C$3,$C$23:$UW$241,QR1,FALSE()) | QT3: =VLOOKUP($C$3,$C$23:$UW$241,QT1,FALSE()) | QU3: =IF(ISNUMBER(VLOOKUP($C$3,$C$23:$UW$241,QU1,FALSE()))=TRUE(),VLOOKUP($C$3,$C$23:$UW$241,QU1,FALSE()),".") | QV3: =IF(ISNUMBER(VLOOKUP($C$3,$C$23:$UW$241,QV1,FALSE()))=TRUE(),VLOOKUP($C$3,$C$23:$UW$241,QV1,FALSE()),".") | QW3: =IF(ISNUMBER(VLOOKUP($C$3,$C$23:$UW$241,QW1,FALSE()))=TRUE(),VLOOKUP($C$3,$C$23:$UW$241,QW1,FALSE()),".") | QX3: =IF(ISNUMBER(VLOOKUP($C$3,$C$23:$UW$241,QX1,FALSE()))=TRUE(),VLOOKUP($C$3,$C$23:$UW$241,QX1,FALSE()),".") | QY3: =IF(ISNUMBER(VLOOKUP($C$3,$C$23:$UW$241,QY1,FALSE()))=TRUE(),VLOOKUP($C$3,$C$23:$UW$241,QY1,FALSE()),".") | RB3: =IF(ISNUMBER(VLOOKUP($C$3,$C$23:$UW$241,RB1,FALSE()))=TRUE(),VLOOKUP($C$3,$C$23:$UW$241,RB1,FALSE()),".") | RC3: =IF(ISNUMBER(VLOOKUP($C$3,$C$23:$UW$241,RC1,FALSE()))=TRUE(),VLOOKUP($C$3,$C$23:$UW$241,RC1,FALSE()),".") | RD3: =IF(ISNUMBER(VLOOKUP($C$3,$C$23:$UW$241,RD1,FALSE()))=TRUE(),VLOOKUP($C$3,$C$23:$UW$241,RD1,FALSE()),".") | RE3: =IF(ISNUMBER(VLOOKUP($C$3,$C$23:$UW$241,RE1,FALSE()))=TRUE(),VLOOKUP($C$3,$C$23:$UW$241,RE1,FALSE()),".") | RF3: =VLOOKUP($C$3,$C$23:$UW$241,RF1,FALSE()) | RG3: =VLOOKUP($C$3,$C$23:$UW$241,RG1,FALSE()) | RJ3: =IF(ISNUMBER(VLOOKUP($C$3,$C$23:$UW$241,RJ1,FALSE()))=TRUE(),VLOOKUP($C$3,$C$23:$UW$241,RJ1,FALSE()),".") | RK3: =IF(ISNUMBER(VLOOKUP($C$3,$C$23:$UW$241,RK1,FALSE()))=TRUE(),VLOOKUP($C$3,$C$23:$UW$241,RK1,FALSE()),".") | RL3: =IF(ISNUMBER(VLOOKUP($C$3,$C$23:$UW$241,RL1,FALSE()))=TRUE(),VLOOKUP($C$3,$C$23:$UW$241,RL1,FALSE()),".") | RM3: =IF(ISNUMBER(VLOOKUP($C$3,$C$23:$UW$241,RM1,FALSE()))=TRUE(),VLOOKUP($C$3,$C$23:$UW$241,RM1,FALSE()),".") | RN3: =IF(ISNUMBER(VLOOKUP($C$3,$C$23:$UW$241,RN1,FALSE()))=TRUE(),VLOOKUP($C$3,$C$23:$UW$241,RN1,FALSE()),".") | RO3: =VLOOKUP($C$3,$C$23:$UW$241,RO1,FALSE()) | RR3: =IF(ISNUMBER(VLOOKUP($C$3,$C$23:$UW$241,RR1,FALSE()))=TRUE(),VLOOKUP($C$3,$C$23:$UW$241,RR1,FALSE()),".") | RS3: =IF(ISNUMBER(VLOOKUP($C$3,$C$23:$UW$241,RS1,FALSE()))=TRUE(),VLOOKUP($C$3,$C$23:$UW$241,RS1,FALSE()),".") | RT3: =IF(ISNUMBER(VLOOKUP($C$3,$C$23:$UW$241,RT1,FALSE()))=TRUE(),VLOOKUP($C$3,$C$23:$UW$241,RT1,FALSE()),".") | RU3: =IF(ISNUMBER(VLOOKUP($C$3,$C$23:$UW$241,RU1,FALSE()))=TRUE(),VLOOKUP($C$3,$C$23:$UW$241,RU1,FALSE()),".") | RV3: =IF(ISNUMBER(VLOOKUP($C$3,$C$23:$UW$241,RV1,FALSE()))=TRUE(),VLOOKUP($C$3,$C$23:$UW$241,RV1,FALSE()),".") | RW3: =VLOOKUP($C$3,$C$23:$UW$241,RW1,FALSE()) | SA3: =IF(ISNUMBER(VLOOKUP($C$3,$C$23:$UW$241,SA1,FALSE()))=TRUE(),VLOOKUP($C$3,$C$23:$UW$241,SA1,FALSE()),".") | SB3: =IF(ISNUMBER(VLOOKUP($C$3,$C$23:$UW$241,SB1,FALSE()))=TRUE(),VLOOKUP($C$3,$C$23:$UW$241,SB1,FALSE()),".") | SC3: =IF(ISNUMBER(VLOOKUP($C$3,$C$23:$UW$241,SC1,FALSE()))=TRUE(),VLOOKUP($C$3,$C$23:$UW$241,SC1,FALSE()),".") | SD3: =IF(ISNUMBER(VLOOKUP($C$3,$C$23:$UW$241,SD1,FALSE()))=TRUE(),VLOOKUP($C$3,$C$23:$UW$241,SD1,FALSE()),".") | SE3: =VLOOKUP($C$3,$C$23:$UW$241,SE1,FALSE()) | SF3: =VLOOKUP($C$3,$C$23:$UW$241,SF1,FALSE()) | SJ3: =IF(ISNUMBER(VLOOKUP($C$3,$C$23:$UW$241,SJ1,FALSE()))=TRUE(),VLOOKUP($C$3,$C$23:$UW$241,SJ1,FALSE()),".") | SK3: =IF(ISNUMBER(VLOOKUP($C$3,$C$23:$UW$241,SK1,FALSE()))=TRUE(),VLOOKUP($C$3,$C$23:$UW$241,SK1,FALSE()),".") | SL3: =IF(ISNUMBER(VLOOKUP($C$3,$C$23:$UW$241,SL1,FALSE()))=TRUE(),VLOOKUP($C$3,$C$23:$UW$241,SL1,FALSE()),".") | SM3: =IF(ISNUMBER(VLOOKUP($C$3,$C$23:$UW$241,SM1,FALSE()))=TRUE(),VLOOKUP($C$3,$C$23:$UW$241,SM1,FALSE()),".") | SN3: =IF(ISNUMBER(VLOOKUP($C$3,$C$23:$UW$241,SN1,FALSE()))=TRUE(),VLOOKUP($C$3,$C$23:$UW$241,SN1,FALSE()),".") | SO3: =VLOOKUP($C$3,$C$23:$UW$241,SO1,FALSE()) | SQ3: =IF(ISNUMBER(VLOOKUP($C$3,$C$23:$UW$241,SQ1,FALSE()))=TRUE(),VLOOKUP($C$3,$C$23:$UW$241,SQ1,FALSE()),".") | SR3: =VLOOKUP($C$3,$C$23:$UW$241,SR1,FALSE()) | ST3: =IF(ISNUMBER(VLOOKUP($C$3,$C$23:$UW$241,ST1,FALSE()))=TRUE(),VLOOKUP($C$3,$C$23:$UW$241,ST1,FALSE()),".") | SU3: =VLOOKUP($C$3,$C$23:$UW$241,SU1,FALSE()) | SW3: =IF(ISNUMBER(VLOOKUP($C$3,$C$23:$UW$241,SW1,FALSE()))=TRUE(),VLOOKUP($C$3,$C$23:$UW$241,SW1,FALSE()),".") | SX3: =VLOOKUP($C$3,$C$23:$UW$241,SX1,FALSE()) | TA3: =IF(ISNUMBER(VLOOKUP($C$3,$C$23:$UW$241,TA1,FALSE()))=TRUE(),VLOOKUP($C$3,$C$23:$UW$241,TA1,FALSE()),".") | TB3: =IF(ISNUMBER(VLOOKUP($C$3,$C$23:$UW$241,TB1,FALSE()))=TRUE(),VLOOKUP($C$3,$C$23:$UW$241,TB1,FALSE()),".") | TC3: =IF(ISNUMBER(VLOOKUP($C$3,$C$23:$UW$241,TC1,FALSE()))=TRUE(),VLOOKUP($C$3,$C$23:$UW$241,TC1,FALSE()),".") | TD3: =IF(ISNUMBER(VLOOKUP($C$3,$C$23:$UW$241,TD1,FALSE()))=TRUE(),VLOOKUP($C$3,$C$23:$UW$241,TD1,FALSE()),".") | TE3: =IF(ISNUMBER(VLOOKUP($C$3,$C$23:$UW$241,TE1,FALSE()))=TRUE(),VLOOKUP($C$3,$C$23:$UW$241,TE1,FALSE()),".") | TF3: =VLOOKUP($C$3,$C$23:$UW$241,TF1,FALSE()) | TJ3: =IF(ISNUMBER(VLOOKUP($C$3,$C$23:$UW$241,TJ1,FALSE()))=TRUE(),VLOOKUP($C$3,$C$23:$UW$241,TJ1,FALSE()),".") | TK3: =IF(ISNUMBER(VLOOKUP($C$3,$C$23:$UW$241,TK1,FALSE()))=TRUE(),VLOOKUP($C$3,$C$23:$UW$241,TK1,FALSE()),".") | TL3: =IF(ISNUMBER(VLOOKUP($C$3,$C$23:$UW$241,TL1,FALSE()))=TRUE(),VLOOKUP($C$3,$C$23:$UW$241,TL1,FALSE()),".") | TM3: =IF(ISNUMBER(VLOOKUP($C$3,$C$23:$UW$241,TM1,FALSE()))=TRUE(),VLOOKUP($C$3,$C$23:$UW$241,TM1,FALSE()),".") | TN3: =IF(ISNUMBER(VLOOKUP($C$3,$C$23:$UW$241,TN1,FALSE()))=TRUE(),VLOOKUP($C$3,$C$23:$UW$241,TN1,FALSE()),".") | TO3: =VLOOKUP($C$3,$C$23:$UW$241,TO1,FALSE())
A4: Source | D4: PWT 8.1 | F4: PWT 9.0 | H4: PWT 9.1 | K4: PWT 8.1 | L4: PWT 8.1 | N4: PWT 8.1 | P4: PWT 8.1 | R4: PWT 8.1 | V4: PWT 9 | W4: PWT 9 | Y4: PWT 9 | AA4: PWT 9 | AC4: PWT 9 | AG4: PWT 9.1 | AH4: PWT 9.1 | AJ4: PWT 9.1 | AL4: PWT 9.1 | AN4: PWT 9.1 | AQ4: =VLOOKUP($C$3,$C$23:$UW$241,AQ1,FALSE()) | AR4: PWT 8.1 | AS4: PWT 9 | AT4: PWT 9.0 | AV4: PWT 9.1 | AX4: =VLOOKUP($C$3,$C$23:$UW$241,AX1,FALSE()) | BA4: =VLOOKUP($C$3,$C$23:$UW$241,BA1,FALSE()) | BB4: PWT 8.1 | BC4: PWT 8.1 | BD4: PWT 8.1 | BE4: PWT 8.1 | BF4: PWT 8.1 | BH4: =VLOOKUP($C$3,$C$23:$UW$241,BH1,FALSE()) | BI4: PWT 9 | BJ4: PWT 9 | BK4: PWT 9 | BL4: PWT 9 | BM4: PWT 9 | BO4: =VLOOKUP($C$3,$C$23:$UW$241,BO1,FALSE()) | BP4: PWT 9.1 | BQ4: PWT 9.1 | BR4: PWT 9.1 | BS4: PWT 9.1 | BT4: PWT 9.1 | BV4: PWT 9 | BW4: PWT 9 | BX4: PWT 9 | BY4: PWT 9 | BZ4: PWT 9 | CC4: PWT 9.1 | CD4: PWT 9.1 | CE4: PWT 9.1 | CF4: PWT 9.1 | CG4: PWT 9.1 | CP4: PWT 8.1 | CQ4: PWT 8.1 | CR4: PWT 8.1 | CS4: PWT 8.1 | CT4: PWT 8.1 | CV4: =VLOOKUP($C$3,$C$23:$UW$241,CV1,FALSE()) | CW4: PWT 9 | CX4: PWT 9 | CY4: PWT 9 | CZ4: PWT 9 | DA4: PWT 9 | DC4: =VLOOKUP($C$3,$C$23:$UW$241,DC1,FALSE()) | DD4: PWT 9.1 | DE4: PWT 9.1 | DF4: PWT 9.1 | DG4: PWT 9.1 | DH4: PWT 9.1 | DW4: MFMOD | ED4: WDI | PU4: Povcalnet | PW4: Povcalnet | PZ4: WDI | QD4: WDI | QH4: WDI | QL4: WDI | QP4: WDI | QV4: MFMOD | RC4: WDI | RJ4: MFMOD | RR4: WDI | SA4: MFMOD | SJ4: WDI | TA4: MFMOD | TJ4: WDI
A5: Year / Years used to calculate number | AX5: MFMOD | BB5: 1991-2010 | BC5: 1996-2010 | BD5: 2001-2010 | BE5: 2006-2010 | BF5: 2010 | BI5: 1995-2014 | BJ5: 2000-2014 | BK5: 2005-2014 | BL5: 2010-2014 | BM5: 2014 | BP5: 1998-2017 | BQ5: 2003-2017 | BR5: 2008-2017 | BS5: 2013-2017 | BT5: 2017 | BV5: 1994 | BW5: 1999 | BX5: 2004 | BY5: 2009 | BZ5: 2014 | CC5: 2001 | CD5: 2005 | CE5: 2009 | CF5: 2013 | CG5: 2017 | CK5: 2017 | CP5: 1991-2010 | CQ5: 1996-2010 | CR5: 2001-2010 | CS5: 2006-2010 | CT5: 2010 | CW5: 1995-2014 | CX5: 2000-2014 | CY5: 2005-2014 | CZ5: 2010-2014 | DA5: 2014 | DD5: 1998-2017 | DE5: 2003-2017 | DF5: 2008-2017 | DG5: 2013-2017 | DH5: 2017 | DW5: 2000-2019 | DX5: 2005-2019 | DY5: 2010-2019 | DZ5: 2015-2019 | EA5: 2019 | ED5: 2000-2019 | EE5: 2005-2019 | EF5: 2010-2019 | EG5: 2015-2019 | EH5: 2019 | EO5: 2000-2019 | EP5: 2005-2019 | EQ5: 2010-2019 | ER5: 2015-2019 | ES5: 2019 | HG5: =HG21 | HH5: =HH21 | HI5: =HI21 | HJ5: =HJ21 | HK5: =HK21 | HL5: =HL21 | HM5: =HM21 | HN5: =HN21 | ... IO5: =IO21 | LU5: =LU21 | LV5: =LV21 | LW5: =LW21 | LX5: =LX21 | LY5: =LY21 | LZ5: =LZ21 | MA5: =MA21 | MB5: =MB21 | ... ND5: =ND21 | NG5: =NG21 | NH5: =NH21 | NI5: =NI21 | NJ5: =NJ21 | NK5: =NK21 | NL5: =NL21 | NM5: =NM21 | NN5: =NN21 | ... OQ5: =OQ21 | OT5: =OT21 | OU5: =OU21 | OV5: =OV21 | OW5: =OW21 | OX5: =OX21 | OY5: =OY21 | OZ5: =OZ21 | PA5: =PA21 | ... PM5: =PM21 | QU5: 2000-2019 | QV5: 2005-2019 | QW5: 2010-2019 | QX5: 2015-2019 | QY5: 2019 | RB5: 2000-2019 | RC5: 2005-2019 | RD5: 2010-2019 | RE5: 2015-2019 | RF5: 2019 | RJ5: 2000-2019 | RK5: 2005-2019 | RL5: 2010-2019 | RM5: 2015-2019 | RN5: 2019 | RR5: 2000-2019 | RS5: 2005-2019 | RT5: 2010-2019 | RU5: 2015-2019 | RV5: 2019 | SA5: 2000-2019 | SB5: 2005-2019 | SC5: 2010-2019 | SD5: 2015-2019 | SE5: 2019 | SJ5: 2000-2019 | SK5: 2005-2019 | SL5: 2010-2019 | SM5: 2015-2019 | SN5: 2019 | SQ5: 2019 | ST5: 2019 | SW5: 2019 | TA5: 2000-2019 | TB5: 2005-2019 | TC5: 2010-2019 | TD5: 2015-2019 | TE5: 2019 | TJ5: 2000-2019 | TK5: 2005-2019 | TL5: 2010-2019 | TM5: 2015-2019 | TN5: 2019
A6: Last Year in dataset | D6: 2011 | F6: 2014 | H6: 2017 | K6: 2010 | L6: 2010 | N6: 2010 | P6: 2010 | R6: 2010 | V6: 2014 | W6: 2014 | Y6: 2014 | AA6: 2014 | AC6: 2014 | AG6: 2017 | AH6: 2017 | AJ6: 2017 | AL6: 2017 | AN6: 2017 | AR6: 2011 | AS6: 2014 | AT6: 2014 | AV6: 2017 | AX6: 2019 | BB6: 2010 | BC6: 2010 | BD6: 2010 | BE6: 2010 | BF6: 2010 | BI6: 2014 | BJ6: 2014 | BK6: 2014 | BL6: 2014 | BM6: 2014 | BP6: 2017 | BQ6: 2017 | BR6: 2017 | BS6: 2017 | BT6: 2017 | BV6: 2014 | BW6: 2014 | BX6: 2014 | BY6: 2014 | BZ6: 2014 | CC6: 2017 | CD6: 2017 | CE6: 2017 | CF6: 2017 | CG6: 2017 | CP6: 2010 | CQ6: 2010 | CR6: 2010 | CS6: 2010 | CT6: 2010 | CW6: 2014 | CX6: 2014 | CY6: 2014 | CZ6: 2014 | DA6: 2014 | DD6: 2017 | DE6: 2017 | DF6: 2017 | DG6: 2017 | DH6: 2017 | DL6: 2019 | DP6: 2019 | DT6: 2018 | EA6: 2019 | EK6: 2019 | EO6: 2019 | EP6: 2019 | EQ6: 2019 | ER6: 2019 | ES6: 2019 | PQ6: 2019
A7: Comment | K7: LaborShare | L7: LaborShare1 | N7: LaborShare2 | P7: LaborShare3 | R7: LaborShare4 | V7: LaborShare | W7: LaborShare1 | Y7: LaborShare2 | AA7: LaborShare3 | AC7: LaborShare4 | EK7: External debt stocks, total (DOD, current US$) / GDP | FE7: the values corresponding to future years are estimated by demographers
FE21: 2000 | FF21: 2001 | FG21: 2002 | FH21: 2003 | FI21: 2004 | FJ21: 2005 | FK21: 2006 | FL21: 2007 | FM21: 2008 | FN21: 2009 | FO21: 2010 | FP21: 2011 | FQ21: 2012 | FR21: 2013 | FS21: 2014 | FT21: 2015 | FU21: 2016 | FV21: 2017 | FW21: 2018 | FX21: 2019 | FY21: 2020 | FZ21: 2021 | GA21: 2022 | GB21: 2023 | GC21: 2024 | GD21: 2025 | GE21: 2026 | GF21: 2027 | GG21: 2028 | GH21: 2029 | GI21: 2030 | GJ21: 2031 | GK21: 2032 | GL21: 2033 | GM21: 2034 | GN21: 2035 | GO21: 2036 | GP21: 2037 | GQ21: 2038 | GR21: 2039 | GS21: 2040 | GT21: 2041 | GU21: 2042 | GV21: 2043 | GW21: 2044 | GX21: 2045 | GY21: 2046 | GZ21: 2047 | HA21: 2048 | HB21: 2049 | HC21: 2050 | HG21: 2016 | HH21: 2017 | HI21: 2018 | HJ21: 2019 | HK21: 2020 | HL21: 2021 | HM21: 2022 | HN21: 2023 | HO21: 2024 | HP21: 2025 | HQ21: 2026 | HR21: 2027 | HS21: 2028 | HT21: 2029 | HU21: 2030 | HV21: 2031 | HW21: 2032 | HX21: 2033 | HY21: 2034 | HZ21: 2035 | IA21: 2036 | IB21: 2037 | IC21: 2038 | ID21: 2039 | IE21: 2040 | IF21: 2041 | IG21: 2042 | IH21: 2043 | II21: 2044 | IJ21: 2045 | IK21: 2046 | IL21: 2047 | IM21: 2048 | IN21: 2049 | IO21: 2050 | IV21: 2015 | IW21: 2016 | IX21: 2017 | IY21: 2018 | IZ21: 2019 | JA21: 2020 | JB21: 2021 | JC21: 2022 | JD21: 2023 | JE21: 2024 | JF21: 2025 | JG21: 2026 | JH21: 2027 | JI21: 2028 | JJ21: 2029 | JK21: 2030 | JL21: 2031 | JM21: 2032 | JN21: 2033 | JO21: 2034 | JP21: 2035 | JQ21: 2036 | JR21: 2037 | JS21: 2038 | JT21: 2039 | JU21: 2040 | JV21: 2041 | JW21: 2042 | JX21: 2043 | JY21: 2044 | JZ21: 2045 | KA21: 2046 | KB21: 2047 | KC21: 2048 | KD21: 2049 | KE21: 2050 | KI21: 2015 | KJ21: 2016 | KK21: 2017 | KL21: 2018 | KM21: 2019 | KN21: 2020 | KO21: 2021 | KP21: 2022 | KQ21: 2023 | KR21: 2024 | KS21: 2025 | KT21: 2026 | KU21: 2027 | KV21: 2028 | KW21: 2029 | KX21: 2030 | KY21: 2031 | KZ21: 2032 | LA21: 2033 | LB21: 2034 | LC21: 2035 | LD21: 2036 | LE21: 2037 | LF21: 2038 | LG21: 2039 | LH21: 2040 | LI21: 2041 | LJ21: 2042 | LK21: 2043 | LL21: 2044 | LM21: 2045 | LN21: 2046 | LO21: 2047 | LP21: 2048 | LQ21: 2049 | LR21: 2050 | LU21: 2015 | LV21: =LU21+1 | LW21: =LV21+1 | LX21: =LW21+1 | LY21: =LX21+1 | LZ21: =LY21+1 | MA21: =LZ21+1 | MB21: =MA21+1 | MC21: =MB21+1 | ... ND21: =NC21+1 | NH21: 2015 | NI21: =NH21+1 | NJ21: =NI21+1 | NK21: =NJ21+1 | NL21: =NK21+1 | NM21: =NL21+1 | NN21: =NM21+1 | NO21: =NN21+1 | NP21: =NO21+1 | ... OQ21: =OP21+1 | OT21: 2000 | OU21: =OT21+1 | OV21: =OU21+1 | OW21: =OV21+1 | OX21: =OW21+1 | OY21: =OX21+1 | OZ21: =OY21+1 | PA21: =OZ21+1 | PB21: =PA21+1 | ... PM21: =PL21+1
A23: income_group | B23: country | C23: countrycode | D23: delta81 | E23: data_delta81 | F23: delta9 | G23: data_delta90 | H23: delta91 | I23: data_delta91 | J23: data_labsh81 | K23: labsh81 | L23: lab_sh1_81 | M23: data_lab_sh1_81 | N23: lab_sh2_81 | O23: data_lab_sh2_81 | P23: lab_sh3_81 | Q23: data_lab_sh3_81 | R23: lab_sh4_81 | S23: data_lab_sh4_81 | T23: blank11 | U23: data_labsh90 | V23: labsh_9 | W23: lab_sh1_9 | X23: data_lab_sh1_9 | Y23: lab_sh2_9 | Z23: data_lab_sh2_9 | AA23: lab_sh3_9 | AB23: data_lab_sh3_9 | AC23: lab_sh4_9 | AD23: data_lab_sh4_9 | AE23: blank17 | AF23: data_labsh91 | AG23: labsh_91 | AH23: lab_sh1_91 | AI23: data_lab_sh1_91 | AJ23: lab_sh2_91 | AK23: data_lab_sh2_91 | AL23: lab_sh3_91 | AM23: data_lab_sh3_91 | AN23: lab_sh4_91 | AO23: data_lab_sh4_91 | AP23: blank18 | AQ23: data_typeky8 | AR23: ky8 | AS23: data_typeky9 | AT23: ky9 | AU23: data_typeky91 | AV23: ky91 | AW23: blank20 | AX23: ky_mfmod19 | AY23: data_mfmod_ky | AZ23: blank22 | BA23: data_typehc81 | BB23: avg_hc81_growth20 | BC23: avg_hc81_growth15 | BD23: avg_hc81_growth10 | BE23: avg_hc81_growth05 | BF23: avg_hc81_growth00 | BG23: blank27 | BH23: data_typehc9 | BI23: avg_hc9_growth20 | BJ23: avg_hc9_growth15 | BK23: avg_hc9_growth10 | BL23: avg_hc9_growth05 | BM23: avg_hc9_growth00 | BN23: blank34 | BO23: data_typehc91 | BP23: avg_hc91_growth20 | BQ23: avg_hc91_growth15 | BR23: avg_hc91_growth10 | BS23: avg_hc91_growth05 | BT23: avg_hc91_growth00 | BU23: blank35 | BV23: yr_sch1994 | BW23: yr_sch1999 | BX23: yr_sch2004 | BY23: yr_sch2009 | BZ23: yr_sch2014 | CA23: data_pwt90_schooling | CB23: blank36 | CC23: yr_sch1997 | CD23: yr_sch2002 | CE23: yr_sch2007 | CF23: yr_sch2012 | CG23: yr_sch2017 | CH23: data_pwt91_schooling | CI23: blank40 | CJ23: blank41 | CK23: UNDP_edu_2017 | CL23: data_un | CM23: blank43 | CN23: blank44 | CO23: data_typetfp81 | CP23: avg_tfp81_growth20 | CQ23: avg_tfp81_growth15 | CR23: avg_tfp81_growth10 | CS23: avg_tfp81_growth05 | CT23: avg_tfp81_growth00 | CU23: blank48 | CV23: data_typetfp9 | CW23: avg_tfp9_growth20 | CX23: avg_tfp9_growth15 | CY23: avg_tfp9_growth10 | CZ23: avg_tfp9_growth05 | DA23: avg_tfp9_growth00 | DB23: blank49 | DC23: data_typetfp91 | DD23: avg_tfp91_growth20 | DE23: avg_tfp91_growth15 | DF23: avg_tfp91_growth10 | DG23: avg_tfp91_growth05 | DH23: avg_tfp91_growth00 | DI23: blank55 | DJ23: blank56 | DK23: blank57 | DL23: lab_market_part | DM23: data_lab_market_participation | DN23: blank60 | DO23: blank61 | DP23: lab_market_part_male | DQ23: data_lab_male_market_part | DR23: blank63 | DS23: blank64 | DT23: lab_market_part_female | DU23: data_lab_female_market_part | DV23: blank66 | DW23: avg_cab_growth20 | DX23: avg_cab_growth15 | DY23: avg_cab_growth10 | DZ23: avg_cab_growth05 | EA23: avg_cab_growth00 | EB23: data_cab_mfmod | EC23: blank72 | ED23: avg_cabwdi_growth20 | EE23: avg_cabwdi_growth15 | EF23: avg_cabwdi_growth10 | EG23: avg_cabwdi_growth05 | EH23: avg_cabwdi_growth00 | EI23: data_cab_wdi | EJ23: blank78 | EK23: debt_y | EL23: data_debt_wdi | EM23: blank80 | EN23: black81 | EO23: avg_fdiwdi_growth20 | EP23: avg_fdiwdi_growth15 | EQ23: avg_fdiwdi_growth10 | ER23: avg_fdiwdi_growth05 | ES23: avg_fdiwdi_growth00 | ET23: data_wdi_fdi | EU23: blank86 | EV23: blank87 | EW23: blank88 | EX23: blank89 | EY23: blank90 | EZ23: blank91 | FA23: blank92 | FB23: blank93 | FC23: blank94 | FD23: blank95 | FE23: pop2000 | FF23: pop2001 | FG23: pop2002 | FH23: pop2003 | FI23: pop2004 | FJ23: pop2005 | FK23: pop2006 | FL23: pop2007 | FM23: pop2008 | FN23: pop2009 | FO23: pop2010 | FP23: pop2011 | FQ23: pop2012 | FR23: pop2013 | FS23: pop2014 | FT23: pop2015 | FU23: pop2016 | FV23: pop2017 | FW23: pop2018 | FX23: pop2019 | FY23: pop2020 | FZ23: pop2021 | GA23: pop2022 | GB23: pop2023 | GC23: pop2024 | GD23: pop2025 | GE23: pop2026 | GF23: pop2027 | GG23: pop2028 | GH23: pop2029 | GI23: pop2030 | GJ23: pop2031 | GK23: pop2032 | GL23: pop2033 | GM23: pop2034 | GN23: pop2035 | GO23: pop2036 | GP23: pop2037 | GQ23: pop2038 | GR23: pop2039 | GS23: pop2040 | GT23: pop2041 | GU23: pop2042 | GV23: pop2043 | GW23: pop2044 | GX23: pop2045 | GY23: pop2046 | GZ23: pop2047 | HA23: pop2048 | HB23: pop2049 | HC23: pop2050 | HD23: blank147 | HE23: blank148 | HF23: blank149 | HG23: pop_g2016 | HH23: pop_g2017 | HI23: pop_g2018 | HJ23: pop_g2019 | HK23: pop_g2020 | HL23: pop_g2021 | HM23: pop_g2022 | HN23: pop_g2023 | HO23: pop_g2024 | HP23: pop_g2025 | HQ23: pop_g2026 | HR23: pop_g2027 | HS23: pop_g2028 | HT23: pop_g2029 | HU23: pop_g2030 | HV23: pop_g2031 | HW23: pop_g2032 | HX23: pop_g2033 | HY23: pop_g2034 | HZ23: pop_g2035 | IA23: pop_g2036 | IB23: pop_g2037 | IC23: pop_g2038 | ID23: pop_g2039 | IE23: pop_g2040 | IF23: pop_g2041 | IG23: pop_g2042 | IH23: pop_g2043 | II23: pop_g2044 | IJ23: pop_g2045 | IK23: pop_g2046 | IL23: pop_g2047 | IM23: pop_g2048 | IN23: pop_g2049 | IO23: pop_g2050 | IP23: data_pop_growth | IQ23: blank184 | IR23: blank185 | IS23: blank186 | IT23: blank187 | IU23: data_type | IV23: pop_m2015 | IW23: pop_m2016 | IX23: pop_m2017 | IY23: pop_m2018 | IZ23: pop_m2019 | JA23: pop_m2020 | JB23: pop_m2021 | JC23: pop_m2022 | JD23: pop_m2023 | JE23: pop_m2024 | JF23: pop_m2025 | JG23: pop_m2026 | JH23: pop_m2027 | JI23: pop_m2028 | JJ23: pop_m2029 | JK23: pop_m2030 | JL23: pop_m2031 | JM23: pop_m2032 | JN23: pop_m2033 | JO23: pop_m2034 | JP23: pop_m2035 | JQ23: pop_m2036 | JR23: pop_m2037 | JS23: pop_m2038 | JT23: pop_m2039 | JU23: pop_m2040 | JV23: pop_m2041 | JW23: pop_m2042 | JX23: pop_m2043 | JY23: pop_m2044 | JZ23: pop_m2045 | KA23: pop_m2046 | KB23: pop_m2047 | KC23: pop_m2048 | KD23: pop_m2049 | KE23: pop_m2050 | KF23: blank224 | KG23: blank225 | KH23: watp_1564 | KI23: watp_1564_2015 | KJ23: watp_1564_2016 | KK23: watp_1564_2017 | KL23: watp_1564_2018 | KM23: watp_1564_2019 | KN23: watp_1564_2020 | KO23: watp_1564_2021 | KP23: watp_1564_2022 | KQ23: watp_1564_2023 | KR23: watp_1564_2024 | KS23: watp_1564_2025 | KT23: watp_1564_2026 | KU23: watp_1564_2027 | KV23: watp_1564_2028 | KW23: watp_1564_2029 | KX23: watp_1564_2030 | KY23: watp_1564_2031 | KZ23: watp_1564_2032 | LA23: watp_1564_2033 | LB23: watp_1564_2034 | LC23: watp_1564_2035 | LD23: watp_1564_2036 | LE23: watp_1564_2037 | LF23: watp_1564_2038 | LG23: watp_1564_2039 | LH23: watp_1564_2040 | LI23: watp_1564_2041 | LJ23: watp_1564_2042 | LK23: watp_1564_2043 | LL23: watp_1564_2044 | LM23: watp_1564_2045 | LN23: watp_1564_2046 | LO23: watp_1564_2047 | LP23: watp_1564_2048 | LQ23: watp_1564_2049 | LR23: watp_1564_2050 | LS23: blank263 | LT23: watp_1559 | LU23: watp_1559_2015 | LV23: watp_1559_2016 | LW23: watp_1559_2017 | LX23: watp_1559_2018 | LY23: watp_1559_2019 | LZ23: watp_1559_2020 | MA23: watp_1559_2021 | MB23: watp_1559_2022 | MC23: watp_1559_2023 | MD23: watp_1559_2024 | ME23: watp_1559_2025 | MF23: watp_1559_2026 | MG23: watp_1559_2027 | MH23: watp_1559_2028 | MI23: watp_1559_2029 | MJ23: watp_1559_2030 | MK23: watp_1559_2031 | ML23: watp_1559_2032 | MM23: watp_1559_2033 | MN23: watp_1559_2034 | MO23: watp_1559_2035 | MP23: watp_1559_2036 | MQ23: watp_1559_2037 | MR23: watp_1559_2038 | MS23: watp_1559_2039 | MT23: watp_1559_2040 | MU23: watp_1559_2041 | MV23: watp_1559_2042 | MW23: watp_1559_2043 | MX23: watp_1559_2044 | MY23: watp_1559_2045 | MZ23: watp_1559_2046 | NA23: watp_1559_2047 | NB23: watp_1559_2048 | NC23: watp_1559_2049 | ND23: watp_1559_2050 | NE23: blank999 | NF23: blank900 | NG23: watp_2064 | NH23: watp_2064_2015 | NI23: watp_2064_2016 | NJ23: watp_2064_2017 | NK23: watp_2064_2018 | NL23: watp_2064_2019 | NM23: watp_2064_2020 | NN23: watp_2064_2021 | NO23: watp_2064_2022 | NP23: watp_2064_2023 | NQ23: watp_2064_2024 | NR23: watp_2064_2025 | NS23: watp_2064_2026 | NT23: watp_2064_2027 | NU23: watp_2064_2028 | NV23: watp_2064_2029 | NW23: watp_2064_2030 | NX23: watp_2064_2031 | NY23: watp_2064_2032 | NZ23: watp_2064_2033 | OA23: watp_2064_2034 | OB23: watp_2064_2035 | OC23: watp_2064_2036 | OD23: watp_2064_2037 | OE23: watp_2064_2038 | OF23: watp_2064_2039 | OG23: watp_2064_2040 | OH23: watp_2064_2041 | OI23: watp_2064_2042 | OJ23: watp_2064_2043 | OK23: watp_2064_2044 | OL23: watp_2064_2045 | OM23: watp_2064_2046 | ON23: watp_2064_2047 | OO23: watp_2064_2048 | OP23: watp_2064_2049 | OQ23: watp_2064_2050 | OR23: blank299 | OS23: blank300 | OT23: lab_market_part2001 | OU23: lab_market_part2002 | OV23: lab_market_part2003 | OW23: lab_market_part2004 | OX23: lab_market_part2005 | OY23: lab_market_part2006 | OZ23: lab_market_part2007 | PA23: lab_market_part2008 | PB23: lab_market_part2009 | PC23: lab_market_part2010 | PD23: lab_market_part2011 | PE23: lab_market_part2012 | PF23: lab_market_part2013 | PG23: lab_market_part2014 | PH23: lab_market_part2015 | PI23: lab_market_part2016 | PJ23: lab_market_part2017 | PK23: lab_market_part2018 | PL23: lab_market_part2019 | PM23: blank320 | PN23: blank321 | PO23: blank322 | PP23: blank323 | PQ23: lab_growth | PR23: blank327 | PS23: blank328 | PT23: blank329 | PU23: blank330 | PV23: blank331 | PW23: blank332 | PX23: blank333 | PY23: blank334 | PZ23: gini | QA23: yeargini | QB23: data_wdi_gini | QC23: blank337 | QD23: poverty190 | QE23: yearp190 | QF23: data_wdi_p190 | QG23: blank340 | QH23: poverty320 | QI23: yearp320 | QJ23: data_wdi_p320 | QK23: blank343 | QL23: poverty550 | QM23: yearp550 | QN23: data_wdi_p550 | QO23: blank346 | QP23: povertynl | QQ23: yearpnl | QR23: data_wdi_pnl | QS23: blank349 | QT23: data_type_iy | QU23: avg_iy_growth20 | QV23: avg_iy_growth15 | QW23: avg_iy_growth10 | QX23: avg_iy_growth05 | QY23: avg_iy_growth00 | QZ23: blank356 | RA23: blank357 | RB23: avg_iywdi_growth20 | RC23: avg_iywdi_growth15 | RD23: avg_iywdi_growth10 | RE23: avg_iywdi_growth05 | RF23: avg_iywdi_growth00 | RG23: data_wdi_iy | RH23: blank363 | RI23: blank364 | RJ23: avg_gdp_growth20 | RK23: avg_gdp_growth15 | RL23: avg_gdp_growth10 | RM23: avg_gdp_growth05 | RN23: avg_gdp_growth00 | RO23: data_gdpgrowth_mf | RP23: blank370 | RQ23: blank371 | RR23: avg_gdpwdi_growth20 | RS23: avg_gdpwdi_growth15 | RT23: avg_gdpwdi_growth10 | RU23: avg_gdpwdi_growth05 | RV23: avg_gdpwdi_growth00 | RW23: data_wdi_gdpgr | RX23: blank377 | RY23: blank378 | RZ23: blank379 | SA23: avg_gdppc_growth20 | SB23: avg_gdppc_growth15 | SC23: avg_gdppc_growth10 | SD23: avg_gdppc_growth05 | SE23: avg_gdppc_growth00 | SF23: data_mf_gdppcgr | SG23: blank384 | SH23: blank385 | SI23: blank386 | SJ23: avg_gdppcwdi_growth20 | SK23: avg_gdppcwdi_growth15 | SL23: avg_gdppcwdi_growth10 | SM23: avg_gdppcwdi_growth05 | SN23: avg_gdppcwdi_growth00 | SO23: data_wdi_gdppcgr | SP23: blank391 | SQ23: gni_cpc_wdi18 | SR23: data_wdi_cpc | SS23: blank393 | ST23: gdppclevel2019 | SU23: data_mf_pclevel | SV23: blank395 | SW23: gdp_pc_wdi18 | SX23: data_wdi_pclevel | SY23: blank397 | SZ23: blank398 | TA23: avg_sy_growth20 | TB23: avg_sy_growth15 | TC23: avg_sy_growth10 | TD23: avg_sy_growth05 | TE23: avg_sy_growth00 | TF23: data_mf_sav | TG23: blank404 | TH23: blank405 | TI23: blank406 | TJ23: avg_sywdi_growth20 | TK23: avg_sywdi_growth15 | TL23: avg_sywdi_growth10 | TM23: avg_sywdi_growth05 | TN23: avg_sywdi_growth00 | TO23: data_wdi_sav
A24: Low income | B24: Afghanistan | C24: AFG | D24: 0.037789278 | E24: Interpolated | F24: 0.052902717 | G24: Interpolated | H24: 0.050320797 | I24: Interpolated | J24: Interpolated | K24: 0.58587915 | M24: No Data | O24: No Data | Q24: No Data | S24: No Data | U24: Interpolated | V24: 0.5313772 | X24: No Data | Z24: No Data | AB24: No Data | AD24: No Data | AF24: Interpolated | AG24: 0.51387328 | AI24: No Data | AK24: No Data | AM24: No Data | AO24: No Data | AQ24: Interpolated | AR24: 1.9280254 | AS24: Interpolated | AT24: 2.4131117 | AU24: Interpolated | AV24: 3.0145073 | AX24: 1.3657937 | AY24: MFMOD | BA24: Interpolated | BB24: 0.0091786236 | BC24: 0.0094486196 | BD24: 0.010329174 | BE24: 0.0094340341 | BF24: 0.0094340146 | BH24: Interpolated | BI24: 0.0082585905 | BJ24: 0.0082279164 | BK24: 0.0082744975 | BL24: 0.0092336768 | BM24: 0.00971328 | BO24: Interpolated | BP24: 0.0085397651 | BQ24: 0.0084343608 | BR24: 0.008993879 | BS24: 0.0097132465 | BT24: 0.0090504047 | CA24: No data | CH24: No data | CK24: 3.8 | CL24: United Nations | CO24: Interpolated | CP24: 0.0017731205 | CQ24: 0.0078073801 | CR24: 0.010499698 | CS24: 0.016782781 | CT24: 0.010616176 | CV24: Interpolated | CW24: 0.0079624997 | CX24: 0.0096666664 | CY24: 0.010895001 | CZ24: 0.0032500003 | DA24: 0.0024999999 | DC24: Interpolated | DD24: 0.00096504414 | DE24: -0.0033170865 | DF24: 0.00098316453 | DG24: -0.0074484642 | DH24: -0.0052168672 | DL24: 0.50463001 | DM24: WDI & ILO | DP24: 0.76541 | DQ24: WDI & ILO | DT24: 0.22566999 | DU24: WDI & ILO | DW24: 0.043925125 | DX24: 0.046637956 | DY24: 0.023411587 | DZ24: 0.014434728 | EA24: -0.0010287374 | EB24: MFMOD | ED24: -0.14876875 | EE24: -0.14876875 | EF24: -0.17839639 | EG24: -0.19164461 | EH24: -0.19657588 | EI24: WDI | EK24: 0.13797478 | EL24: WDI | EO24: 0.011860433 | EP24: 0.010173302 | EQ24: 0.0046392917 | ER24: 0.0048285541 | ES24: 0.0012132304 | ET24: WDI | FE24: 20779953 | FF24: 21606988 | FG24: 22600770 | FH24: 23680871 | FI24: 24726684 | FJ24: 25654277 | FK24: 26433049 | FL24: 27100536 | FM24: 27722276 | FN24: 28394813 | FO24: 29185507 | FP24: 30117413 | FQ24: 31161376 | FR24: 32269589 | FS24: 33370794 | FT24: 34413603 | FU24: 35383128 | FV24: 36296400 | FW24: 37172386 | FX24: 38041754 | FY24: 38928000 | FZ24: 39835000 | GA24: 40754000 | GB24: 41681000 | GC24: 42609000 | GD24: 43532000 | GE24: 44449000 | GF24: 45364000 | GG24: 46275000 | GH24: 47185000 | GI24: 48094000 | GJ24: 49000000 | GK24: 49904000 | GL24: 50804000 | GM24: 51699000 | GN24: 52587000 | GO24: 53469000 | GP24: 54343000 | GQ24: 55209000 | GR24: 56065000 | GS24: 56912000 | GT24: 57748000 | GU24: 58574000 | GV24: 59387000 | GW24: 60188000 | GX24: 60974000 | GY24: 61746000 | GZ24: 62503000 | HA24: 63245000 | HB24: 63972000 | HC24: 64683000 | HG24: 0.027783174 | HH24: 0.025483467 | HI24: 0.023847612 | HJ24: 0.023118172 | HK24: 0.023029439 | HL24: 0.023032136 | HM24: 0.022808071 | HN24: 0.022491395 | HO24: 0.022020109 | HP24: 0.021430802 | HQ24: 0.020846164 | HR24: 0.020376375 | HS24: 0.01988302 | HT24: 0.019474188 | HU24: 0.019081384 | HV24: 0.018662868 | HW24: 0.018280862 | HX24: 0.017873932 | HY24: 0.017463347 | HZ24: 0.017030502 | IA24: 0.016633106 | IB24: 0.016213764 | IC24: 0.015810173 | ID24: 0.015385749 | IE24: 0.014994483 | IF24: 0.014582502 | IG24: 0.014202195 | IH24: 0.013784435 | II24: 0.01339765 | IJ24: 0.012974547 | IK24: 0.012581652 | IL24: 0.012185359 | IM24: 0.011801518 | IN24: 0.011429414 | IO24: 0.011052928 | IP24: UN & WDI | IU24: UN & WDI | IV24: 0.51392951 | IW24: 0.51400332 | IX24: 0.51388384 | IY24: 0.51364153 | IZ24: 0.51337605 | JA24: 0.5131548 | JB24: 0.5129851 | JC24: 0.51284155 | JD24: 0.51271587 | JE24: 0.5125932 | JF24: 0.51246383 | JG24: 0.51232889 | JH24: 0.51219399 | JI24: 0.51205873 | JJ24: 0.51192297 | JK24: 0.51178644 | JL24: 0.51164877 | JM24: 0.5115099 | JN24: 0.51136939 | JO24: 0.51122707 | JP24: 0.51108268 | JQ24: 0.51093598 | JR24: 0.51078668 | JS24: 0.51063488 | JT24: 0.51048012 | JU24: 0.51032229 | JV24: 0.51016106 | JW24: 0.50999657 | JX24: 0.50982835 | JY24: 0.50965636 | JZ24: 0.50948034 | KA24: 0.50930028 | KB24: 0.50911605 | KC24: 0.50892739 | KD24: 0.50873443 | KE24: 0.50853681 | KH24: UN & WDI | KI24: 0.526443 | KJ24: 0.53207964 | KK24: 0.53763223 | KL24: 0.54324901 | KM24: 0.54911935 | KN24: 0.55528152 | KO24: 0.5611397 | KP24: 0.56725723 | KQ24: 0.57349873 | KR24: 0.57959586 | KS24: 0.58540845 | KT24: 0.59076697 | KU24: 0.595891 | KV24: 0.60086441 | KW24: 0.60572213 | KX24: 0.61049193 | KY24: 0.61506122 | KZ24: 0.61950946 | LA24: 0.62390757 | LB24: 0.62821329 | LC24: 0.63243765 | LD24: 0.63640612 | LE24: 0.64030325 | LF24: 0.6441341 | LG24: 0.64787298 | LH24: 0.65147948 | LI24: 0.65479326 | LJ24: 0.65800524 | LK24: 0.66113794 | LL24: 0.66415232 | LM24: 0.66708761 | LN24: 0.66975999 | LO24: 0.67233574 | LP24: 0.67483598 | LQ24: 0.67724943 | LR24: 0.6795603 | LT24: UN & WDI | LU24: 0.51147068 | LV24: 0.51707017 | LW24: 0.5225144 | LX24: 0.52796274 | LY24: 0.53362226 | LZ24: 0.53953451 | MA24: 0.54522407 | MB24: 0.55113608 | MC24: 0.55711234 | MD24: 0.56293273 | ME24: 0.5684554 | MF24: 0.57357872 | MG24: 0.57841021 | MH24: 0.5830794 | MI24: 0.5875808 | MJ24: 0.59194493 | MK24: 0.5962041 | ML24: 0.60029256 | MM24: 0.60428315 | MN24: 0.60807753 | MO24: 0.61174816 | MP24: 0.6151976 | MQ24: 0.61851573 | MR24: 0.62169212 | MS24: 0.62473917 | MT24: 0.62760049 | MU24: 0.63029021 | MV24: 0.63282341 | MW24: 0.63522321 | MX24: 0.63750249 | MY24: 0.63969886 | MZ24: 0.64179057 | NA24: 0.64377707 | NB24: 0.64561623 | NC24: 0.64726758 | ND24: 0.64864028 | NG24: UN & WDI | NH24: 0.40839198 | NI24: 0.41349882 | NJ24: 0.41887262 | NK24: 0.42448413 | NL24: 0.43032426 | NM24: 0.43634403 | NN24: 0.44239989 | NO24: 0.44861853 | NP24: 0.45502746 | NQ24: 0.46147528 | NR24: 0.46797758 | NS24: 0.47456637 | NT24: 0.48119655 | NU24: 0.48777959 | NV24: 0.49416128 | NW24: 0.5002287 | NX24: 0.50618368 | NY24: 0.51186275 | NZ24: 0.51736087 | OA24: 0.52267933 | OB24: 0.52786809 | OC24: 0.53296304 | OD24: 0.53795338 | OE24: 0.54282814 | OF24: 0.54752517 | OG24: 0.55208039 | OH24: 0.55648679 | OI24: 0.56077784 | OJ24: 0.56495529 | OK24: 0.56895059 | OL24: 0.57281792 | OM24: 0.57652318 | ON24: 0.58011615 | OO24: 0.58358765 | OP24: 0.58691305 | OQ24: 0.59012413 | OT24: 0.48943001 | OU24: 0.49178001 | OV24: 0.49424 | OW24: 0.49644001 | OX24: 0.49824001 | OY24: 0.49594002 | OZ24: 0.49344002 | PA24: 0.49104 | PB24: 0.48910999 | PC24: 0.48786999 | PD24: 0.48993 | PE24: 0.49273998 | PF24: 0.49455002 | PG24: 0.49652 | PH24: 0.49859001 | PI24: 0.50032001 | PJ24: 0.50207001 | PK24: 0.50412998 | PL24: 0.50463001 | PQ24: 0.0009913767 | QB24: No data | QF24: No data | QJ24: No data | QN24: No data | QP24: 0.545 | QQ24: 2016 | QR24: WDI | QT24: MFMOD | QU24: 0.15253091 | QV24: 0.15661439 | QW24: 0.15121758 | QX24: 0.16410014 | QY24: 0.14494574 | RF24: 0.21277934 | RG24: Interpolated | RJ24: 0.058445759 | RK24: 0.068676934 | RL24: 0.053301055 | RM24: 0.022427293 | RN24: 0.038370386 | RO24: MFMOD | RR24: 0.063063279 | RS24: 0.064893052 | RT24: 0.04529348 | RU24: 0.022615718 | RV24: 0.038370386 | RW24: WDI | SA24: 0.027817037 | SB24: 0.039968856 | SC24: 0.024076141 | SD24: -0.0037689067 | SE24: 0.01523409 | SF24: MFMOD | SJ24: 0.032433841 | SK24: 0.036172964 | SL24: 0.016045693 | SM24: -0.0035849346 | SN24: 0.015252212 | SO24: WDI | SQ24: 530 | SR24: WDI | ST24: 506.14691 | SU24: MFMOD | SW24: 573.28755 | SX24: WDI | TA24: 0.20657794 | TB24: 0.20325235 | TC24: 0.17462917 | TD24: 0.17853488 | TE24: 0.14391701 | TF24: MFMOD | TN24: 0.16032274 | TO24: Interpolated
